Workbook
Name 使用画面ID: 'プルダウンメニュー (SE用)'!$F$2:$F$34
Name SEステータス: 'プルダウンメニュー (SE用)'!$A$2:$A$8
Name BGM発注: 'プルダウンメニュー (SE用)'!$B$2:$B$7
Name 使用画面: 'プルダウンメニュー (SE用)'!$E$2:$E$34

Sheet ID割り振りルール
A2: ■ID設定ルールについて
C3: 番号以外も指定可能になった ※万が一作品IDなどで被りが生まれるなどイレギュラーがありましたら、別途ルール追加いただいて問題ございません。 ただし、関係各所への共有を忘れないこと！！
C4: カテゴリー | D4: ID付与ルール | E4: 最大ID桁数
C5: 作品 | D5: 作品のローマ字表記の先頭3文字からとったものとする。 小文字表記。 例）『SPY×FAMILY』ならspyとなる。 | E5: 3桁
C6: キャラ | D6: キャラクターIDは接頭語(chara)+作品ID3桁+5桁のIDで管理する。 敵キャラの場合は接頭語がenemyとなる。 例）アーニャの場合、chara_spy_00001、2体目（別のアーニャ）はchara_spy_00002となる。 同じ作品のロイドは、chara_spy_00100となる。1IPの1キャラにつき99番のIDを割り振れる。 敵キャラも同様のルール 同時期かつ同名キャラに関して、別IDを取得する 例）極楽蝶（遠） enemy_jig_00401 極楽蝶（近） enemy_jig_00402 | E6: 15桁
C7: アバターアイコン | D7: キャラと同じルール。 接頭語がcharaからiconになったのみ。 例）スパイファミリーのキャラで00001のアーニャのアイコンの場合は、下記となる。 unit_icon_chara_spy_00001 もしエネミーのアバターアイコンを配布など割り振りが必要な場合は、charaの箇所をenemyに変更してIDを採番する。 | E7: 25桁
C8: クエスト | D8: 接頭語(quest)+クエストの難易度+クエストカテゴリー+作品ID3桁+5桁のIDで管理する。 クエストの難易度設定がないものに関しては、nullとなる。クエストカテゴリーは、メインクエスト、特集祭などのイベントなどがある。 例）メインクエストのノーマルの難易度のダンダダンのクエストの場合は、下記となる。 quest_main_normal_dan_00001 | E8: 32桁
C9: アイテム | D9: 接頭語(各カテゴリー)+作品ID3桁+5桁のIDで管理する。 それぞれカテゴリー別で接頭語が決まっているので注意すること。 例）プリズムであれば、下記となる。 prism_glo_00001 | E9: 19桁
C10: 図鑑 | D10: 接頭語(book)+作品ID3桁+5桁のIDで管理する。 例）スパイファミリーの図鑑の場合は、下記となる。 book_spy_00001 | E10: 14桁
C11: エンブレム | D11: 接頭語(emblem)+エンブレムカテゴリー+作品ID3桁+5桁のIDで管理する。 例）ダンダダンの特集祭で入手できるエンブレムの場合は、下記となる。 emblem_event_spy_00001 | E11: 24桁
C12: 背景 | D12: 接頭語(background)+作品ID3桁+5桁のIDで管理する。 作品毎の背景で最大99999番まで割り振ることが可能。 また、汎用背景に関しては、作品IDをgloとして管理する。 例）スパイファミリーの背景の場合は、下記となる。 background_spy_00001 | E12: 20桁
C13: コンテンツ | D13: 接頭語(contents)+コンテンツカテゴリー+作品ID3桁+5桁のIDで管理する。 コンテンツカテゴリーには、event、training、duel、raid、limitedがある。 例）ラーメン赤猫の大特集祭の場合は、下記となる。 contents_event_aha_00001 | E13: 24桁
C14: BGM | D14: BGMは画面遷移図の大分類の管理番号+サウンド数で管理する。 例）タイトル画面であれば下記となる SBG_011_001 | E14: 11桁
C15: キャラアイコン | D15: キャラの頭にさらに接頭語を追加します。 接頭語がcharaの頭にpicon or eiconをつけるのみ。 例）スパイファミリーのキャラで00001のアーニャのアイコンの場合は、下記となる。 picon_chara_spy_00001、eicon_chara_spy_00001 敵onlyのキャラはeiconのみで良い eicon_enemy_spy_00001 | E15: 21桁
C16: ゲート | D16: ゲートIDは接頭語(outpost)+作品ID3桁+5桁のIDで管理する。 敵キャラの場合は接頭語がenemyとなる。 例）姫+エクスの場合、outpost_gom_00001、2個目（別の姫）はoutpost_gom_00002となる。 同じ作品について別キャラであっても実装順に連番とする。エクスのみを実装したい場合outpost_gom_00003となる。最大で99999番のID割り振りが可能。 敵ゲートは、enemy_gom_00001から連番で使用するので、99999番のID割り振りが可能。 | E16: 17桁

Sheet 作品
A1: 作品_ID | B1: 作品バナーID | C1: 作品ロゴID | D1: 作品名 | E1: 連載曜日 | F1: サブタイトル | G1: サブタイトルの位置 | H1: タイトル合成 | I1: display_order | J1: 設定ID | K1: left1 | L1: left2 | M1: left3 | N1: メインサムネ1画像AssetKey | O1: メインサムネ2画像AssetKey | P1: メインサムネ3画像AssetKey | Q1: メインサムネ3画像AssetKey | R1: BGMジャンル(通常) | S1: BGMジャンル(ボス) | T1: デプロイ | U1: リリース監状況
A2: spy | B2: =CONCATENATE("series_banner_",A2) -> series_banner_spy | C2: series_logo_spy | D2: SPY×FAMILY | E2: 月曜日 | F2: - | H2: =if(G2="",D2,if(G2="後ろ",D2&" "&F2,F2&" "&D2)) -> SPY×FAMILY | I2: 001 | J2: spy | K2: =left(J2,1) -> s | L2: =left(J2,2) -> sp | M2: =left(J2,3) -> spy | N2: ="quest_image_"&A2&"_"&"01" -> quest_image_spy_01 | R2: 日常・ギャグ | S2: 強敵/ボス登場時2 （高難度）
A3: aka | B3: =CONCATENATE("series_banner_",A3) -> series_banner_aka | C3: series_logo_aka | D3: ラーメン赤猫 | E3: 月曜日 | F3: - | H3: =if(G3="",D3,if(G3="後ろ",D3&" "&F3,F3&" "&D3)) -> ラーメン赤猫 | I3: 002 | J3: akaneko | K3: =left(J3,1) -> a | L3: =left(J3,2) -> ak | M3: =left(J3,3) -> aka | N3: ="quest_image_"&A3&"_"&"01" -> quest_image_aka_01 | R3: バトル系2 | S3: 強敵/ボス登場時2 （高難度）
A4: rik | B4: =CONCATENATE("series_banner_",A4) -> series_banner_rik | C4: series_logo_rik | D4: トマトイプーのリコピン | E4: 月曜日 | F4: - | H4: =if(G4="",D4,if(G4="後ろ",D4&" "&F4,F4&" "&D4)) -> トマトイプーのリコピン | I4: 003 | J4: rikopin | K4: =left(J4,1) -> r | L4: =left(J4,2) -> ri | M4: =left(J4,3) -> rik | N4: ="quest_image_"&A4&"_"&"01" -> quest_image_rik_01 | R4: 日常・ギャグ | S4: 強敵/ボス登場時2 （高難度）
A5: dan | B5: =CONCATENATE("series_banner_",A5) -> series_banner_dan | C5: series_logo_dan | D5: ダンダダン | E5: 火曜日 | F5: - | H5: =if(G5="",D5,if(G5="後ろ",D5&" "&F5,F5&" "&D5)) -> ダンダダン | I5: 004 | J5: dan | K5: =left(J5,1) -> d | L5: =left(J5,2) -> da | M5: =left(J5,3) -> dan | N5: ="quest_image_"&A5&"_"&"01" -> quest_image_dan_01 | R5: バトル系1 | S5: 強敵/ボスバトル1
A6: gom | B6: =CONCATENATE("series_banner_",A6) -> series_banner_gom | C6: series_logo_gom | D6: 姫様“拷問”の時間です | E6: 火曜日 | F6: - | H6: =if(G6="",D6,if(G6="後ろ",D6&" "&F6,F6&" "&D6)) -> 姫様“拷問”の時間です | I6: 005 | J6: gomon | K6: =left(J6,1) -> g | L6: =left(J6,2) -> go | M6: =left(J6,3) -> gom | N6: ="quest_image_"&A6&"_"&"01" -> quest_image_gom_01 | R6: バトル系2 | S6: 強敵/ボス登場時2 （高難度）
A7: chi | B7: =CONCATENATE("series_banner_",A7) -> series_banner_chi | C7: series_logo_chi | D7: チェンソーマン | E7: 水曜日 | F7: - | H7: =if(G7="",D7,if(G7="後ろ",D7&" "&F7,F7&" "&D7)) -> チェンソーマン | I7: 006 | J7: chienso | K7: =left(J7,1) -> c | L7: =left(J7,2) -> ch | M7: =left(J7,3) -> chi | N7: ="quest_image_"&A7&"_"&"01" -> quest_image_chi_01 | R7: バトル系1 | S7: 強敵/ボスバトル1
A8: mag | B8: =CONCATENATE("series_banner_",A8) -> series_banner_mag | C8: series_logo_mag | D8: 株式会社マジルミエ | E8: 水曜日 | F8: - | H8: =if(G8="",D8,if(G8="後ろ",D8&" "&F8,F8&" "&D8)) -> 株式会社マジルミエ | I8: 007 | J8: magirumie | K8: =left(J8,1) -> m | L8: =left(J8,2) -> ma | M8: mag | N8: ="quest_image_"&A8&"_"&"01" -> quest_image_mag_01 | R8: バトル系1 | S8: 強敵/ボスバトル1
A9: dos | B9: =CONCATENATE("series_banner_",A9) -> series_banner_dos | C9: series_logo_dos | D9: 道産子ギャルはなまらめんこい | E9: 水曜日 | F9: - | H9: =if(G9="",D9,if(G9="後ろ",D9&" "&F9,F9&" "&D9)) -> 道産子ギャルはなまらめんこい | I9: 008 | J9: dosanko | K9: =left(J9,1) -> d | L9: =left(J9,2) -> do | M9: =left(J9,3) -> dos | N9: ="quest_image_"&A9&"_"&"01" -> quest_image_dos_01 | R9: ラブコメ2 | S9: 強敵/ボス登場時2 （高難度）
A10: bat | B10: =CONCATENATE("series_banner_",A10) -> series_banner_bat | C10: series_logo_bat | D10: 忘却バッテリー | E10: 木曜日 | F10: - | H10: =if(G10="",D10,if(G10="後ろ",D10&" "&F10,F10&" "&D10)) -> 忘却バッテリー | I10: 009 | J10: batteri | K10: =left(J10,1) -> b | L10: =left(J10,2) -> ba | M10: =left(J10,3) -> bat | N10: ="quest_image_"&A10&"_"&"01" -> quest_image_bat_01 | R10: バトル系1 | S10: 強敵/ボス登場時2 （高難度）
A11: kai | B11: =CONCATENATE("series_banner_",A11) -> series_banner_kai | C11: series_logo_kai | D11: 怪獣８号 | E11: 金曜日 | F11: - | H11: =if(G11="",D11,if(G11="後ろ",D11&" "&F11,F11&" "&D11)) -> 怪獣８号 | I11: 010 | J11: kaiju | K11: =left(J11,1) -> k | L11: =left(J11,2) -> ka | M11: =left(J11,3) -> kai | N11: ="quest_image_"&A11&"_"&"01" -> quest_image_kai_01 | R11: バトル系1 | S11: 強敵/ボスバトル1
A12: yuw | B12: =CONCATENATE("series_banner_",A12) -> series_banner_yuw | C12: series_logo_yuw | D12: 2.5次元の誘惑 | E12: 土曜日 | F12: - | H12: =if(G12="",D12,if(G12="後ろ",D12&" "&F12,F12&" "&D12)) -> 2.5次元の誘惑 | I12: 011 | J12: yuwaku | K12: =left(J12,1) -> y | L12: =left(J12,2) -> yu | M12: =left(J12,3) -> yuw | N12: ="quest_image_"&A12&"_"&"01" -> quest_image_yuw_01 | R12: バトル系2 | S12: 強敵/ボス登場時2 （高難度）
A13: sur | B13: =CONCATENATE("series_banner_",A13) -> series_banner_sur | C13: series_logo_sur | D13: 魔都精兵のスレイブ | E13: 土曜日 | F13: - | H13: =if(G13="",D13,if(G13="後ろ",D13&" "&F13,F13&" "&D13)) -> 魔都精兵のスレイブ | I13: 012 | J13: sureibu | K13: =left(J13,1) -> s | L13: =left(J13,2) -> su | M13: =left(J13,3) -> sur | N13: ="quest_image_"&A13&"_"&"01" -> quest_image_sur_01 | R13: バトル系1 | S13: 強敵/ボスバトル1
A14: ron | B14: =CONCATENATE("series_banner_",A14) -> series_banner_ron | C14: series_logo_ron | D14: 鴨乃橋ロンの禁断推理 | E14: 日曜日 | F14: - | H14: =if(G14="",D14,if(G14="後ろ",D14&" "&F14,F14&" "&D14)) -> 鴨乃橋ロンの禁断推理 | I14: 013 | J14: ron | K14: =left(J14,1) -> r | L14: =left(J14,2) -> ro | M14: =left(J14,3) -> ron | N14: ="quest_image_"&A14&"_"&"01" -> quest_image_ron_01 | R14: シリアス | S14: 強敵/ボス登場時2 （高難度）
A15: aha | B15: =CONCATENATE("series_banner_",A15) -> series_banner_aha | C15: series_logo_aha | D15: 阿波連さんははかれない | E15: - | F15: - | H15: =if(G15="",D15,if(G15="後ろ",D15&" "&F15,F15&" "&D15)) -> 阿波連さんははかれない | I15: 014 | J15: aharen | K15: =left(J15,1) -> a | L15: =left(J15,2) -> ah | M15: =left(J15,3) -> aha | N15: ="quest_image_"&A15&"_"&"01" -> quest_image_aha_01 | R15: バトル系2 | S15: 強敵/ボス登場時2 （高難度）
A16: sum | B16: =CONCATENATE("series_banner_",A16) -> series_banner_sum | C16: series_logo_sum | D16: サマータイムレンダ | E16: - | F16: - | H16: =if(G16="",D16,if(G16="後ろ",D16&" "&F16,F16&" "&D16)) -> サマータイムレンダ | I16: 015 | J16: summer | K16: =left(J16,1) -> s | L16: =left(J16,2) -> su | M16: =left(J16,3) -> sum | N16: ="quest_image_"&A16&"_"&"01" -> quest_image_sum_01 | R16: シリアス | S16: 強敵/ボスバトル1
A17: jig | B17: =CONCATENATE("series_banner_",A17) -> series_banner_jig | C17: series_logo_jig | D17: 地獄楽 | E17: - | F17: - | H17: =if(G17="",D17,if(G17="後ろ",D17&" "&F17,F17&" "&D17)) -> 地獄楽 | I17: 016 | J17: jigoku | K17: =left(J17,1) -> j | L17: =left(J17,2) -> ji | M17: =left(J17,3) -> jig | N17: ="quest_image_"&A17&"_"&"01" -> quest_image_jig_01 | R17: シリアス | S17: 強敵/ボスバトル1
A18: tak | B18: =CONCATENATE("series_banner_",A18) -> series_banner_tak | C18: series_logo_tak | D18: タコピーの原罪 | E18: - | F18: - | H18: =if(G18="",D18,if(G18="後ろ",D18&" "&F18,F18&" "&D18)) -> タコピーの原罪 | I18: 017 | J18: takopi | K18: =left(J18,1) -> t | L18: =left(J18,2) -> ta | M18: =left(J18,3) -> tak | N18: ="quest_image_"&A18&"_"&"01" -> quest_image_tak_01 | R18: 日常・ギャグ | S18: 強敵/ボス登場時2 （高難度）
A19: osh | B19: =CONCATENATE("series_banner_",A19) -> series_banner_osh | C19: series_logo_tak | D19: 【推しの子】 | E19: - | F19: - | H19: =if(G19="",D19,if(G19="後ろ",D19&" "&F19,F19&" "&D19)) -> 【推しの子】 | I19: 018 | J19: oshinoko | K19: =left(J19,1) -> o | L19: =left(J19,2) -> os | M19: =left(J19,3) -> osh | N19: ="quest_image_"&A19&"_"&"01" -> quest_image_osh_01 | R19: ラブコメ2 | S19: 強敵/ボス登場時2 （高難度）
A20: you | B20: =CONCATENATE("series_banner_",A20) -> series_banner_you | C20: series_logo_tak | D20: 幼稚園WARS | E20: 木曜日 | F20: - | H20: =if(G20="",D20,if(G20="後ろ",D20&" "&F20,F20&" "&D20)) -> 幼稚園WARS | I20: 019 | J20: youchien | K20: =left(J20,1) -> y | L20: =left(J20,2) -> yo | M20: =left(J20,3) -> you | N20: ="quest_image_"&A20&"_"&"01" -> quest_image_you_01 | R20: バトル系2 | S20: 強敵/ボスバトル1
A21: kim | B21: =CONCATENATE("series_banner_",A21) -> series_banner_kim | C21: series_logo_tak | D21: 君のことが大大大大大好きな100人の彼女 | E21: 木曜日 | H21: =if(G21="",D21,if(G21="後ろ",D21&" "&F21,F21&" "&D21)) -> 君のことが大大大大大好きな100人の彼女 | I21: 020 | J21: kimino | K21: k | L21: ki | M21: kim | N21: ="quest_image_"&A21&"_"&"01" -> quest_image_kim_01 | R21: ラブコメ2 | S21: 強敵/ボス登場時2 （高難度）
A22: hut | B22: =CONCATENATE("series_banner_",A22) -> series_banner_hut | C22: series_logo_hut | D22: ふつうの軽音部 | E22: 日曜日 | F22: - | H22: ふつうの軽音部 | I22: 021 | J22: hutuu | K22: h | L22: hu | M22: hut | N22: ="quest_image_"&A22&"_"&"01" -> quest_image_hut_01 | R22: 日常・ギャグ | S22: 強敵/ボスバトル1
A23: rur | B23: =CONCATENATE("series_banner_",A23) -> series_banner_rur | C23: series_logo_rur | D23: ルリドラゴン | E23: - | F23: - | H23: ルリドラゴン | I23: 022 | J23: rurid | K23: r | L23: ru | M23: rur | N23: ="quest_image_"&A23&"_"&"01" -> quest_image_rur_01 | R23: 日常・ギャグ | S23: 強敵/ボスバトル1
A24: hyp | B24: =CONCATENATE("series_banner_",A24) -> series_banner_hyp | C24: series_logo_hyp | D24: ハイパーインフレーション | E24: - | F24: - | H24: ハイパーインフレーション | I24: 023 | J24: hyper | K24: h | L24: hy | M24: hyp | N24: ="quest_image_"&A24&"_"&"01" -> quest_image_hyp_01 | R24: シリアス | S24: 強敵/ボスバトル1
A25: gam | B25: =CONCATENATE("series_banner_",A25) -> series_banner_gam | C25: series_logo_gam | D25: ゲーミングお嬢様 | H25: ゲーミングお嬢様 | I25: 024 | J25: gamin | K25: g | L25: ga | M25: gam | N25: ="quest_image_"&A25&"_"&"01" -> quest_image_gam_01
A26: ara | B26: =CONCATENATE("series_banner_",A26) -> series_banner_ara | C26: series_logo_ara | D26: アラガネの子 | H26: アラガネの子 | I26: 025 | J26: aragane | K26: a | L26: ar | M26: ara | N26: ="quest_image_"&A26&"_"&"01" -> quest_image_ara_01
A27: aya | B27: =CONCATENATE("series_banner_",A27) -> series_banner_aya | C27: =CONCATENATE("series_logo_",A27) -> series_logo_aya | D27: あやかしトライアングル | H27: あやかしトライアングル | I27: 026 | J27: ayakasi | K27: a | L27: ay | M27: aya | N27: ="quest_image_"&A27&"_"&"01" -> quest_image_aya_01
A28: mar | B28: =CONCATENATE("series_banner_",A28) -> series_banner_mar | C28: =CONCATENATE("series_logo_",A28) -> series_logo_mar | D28: マリッジトキシン | H28: マリッジトキシン | I28: 027 | J28: marriage | K28: m | L28: ma | M28: mar | N28: ="quest_image_"&A28&"_"&"01" -> quest_image_mar_01
A29: sib | B29: =CONCATENATE("series_banner_",A29) -> series_banner_sib | C29: =CONCATENATE("series_logo_",A29) -> series_logo_sib | D29: シバつき物件 | H29: シバつき物件 | I29: 028 | J29: siba | K29: s | L29: si | M29: sib | N29: ="quest_image_"&A29&"_"&"01" -> quest_image_sib_01
A30: nek | B30: =CONCATENATE("series_banner_",A30) -> series_banner_nek | C30: =CONCATENATE("series_logo_",A30) -> series_logo_nek | D30: 猫田びより | H30: 猫田びより | I30: 029 | J30: neko | K30: n | L30: ne | M30: nek | N30: ="quest_image_"&A30&"_"&"01" -> quest_image_nek_01
A31: mad | B31: =CONCATENATE("series_banner_",A31) -> series_banner_mad | C31: =CONCATENATE("series_logo_",A31) -> series_logo_mad | D31: MAD | H31: MAD | I31: 030 | J31: mad | K31: m | L31: ma | M31: mad | N31: ="quest_image_"&A31&"_"&"01" -> quest_image_mad_01
A32: syu | B32: =CONCATENATE("series_banner_",A32) -> series_banner_syu | C32: =CONCATENATE("series_logo_",A32) -> series_logo_syu | D32: 終末のハーレム | H32: 終末のハーレム | I32: 031 | J32: syuumatu | K32: s | L32: sy | M32: syu | N32: ="quest_image_"&A32&"_"&"01" -> quest_image_syu_01
A33: aft | B33: =CONCATENATE("series_banner_",A33) -> series_banner_aft | C33: =CONCATENATE("series_logo_",A33) -> series_logo_aft | D33: 終末のハーレム After World | H33: 終末のハーレム After World | I33: 032 | J33: after | K33: a | L33: af | M33: aft | N33: ="quest_image_"&A33&"_"&"01" -> quest_image_aft_01
A34: fan | B34: =CONCATENATE("series_banner_",A34) -> series_banner_fan | C34: =CONCATENATE("series_logo_",A34) -> series_logo_fan | D34: 終末のハーレム ファンタジア | H34: 終末のハーレム ファンタジア | I34: 033 | J34: fantasia | K34: f | L34: fa | M34: fan | N34: ="quest_image_"&A34&"_"&"01" -> quest_image_fan_01
A35: kut | B35: =CONCATENATE("series_banner_",A35) -> series_banner_kut | C35: =CONCATENATE("series_logo_",A35) -> series_logo_kut | D35: 口が裂けても君には | H35: 口が裂けても君には | I35: 034 | J35: kuti | K35: k | L35: ku | M35: kut | N35: ="quest_image_"&A35&"_"&"01" -> quest_image_kut_01
A36: san | B36: =CONCATENATE("series_banner_",A36) -> series_banner_san | C36: =CONCATENATE("series_logo_",A36) -> series_logo_san | D36: サンキューピッチ | H36: サンキューピッチ | I36: 035 | J36: sankyuu | K36: s | L36: sa | M36: san | N36: ="quest_image_"&A36&"_"&"01" -> quest_image_san_01
A37: kus | B37: =CONCATENATE("series_banner_",A37) -> series_banner_kus | C37: =CONCATENATE("series_logo_",A37) -> series_logo_kus | D37: クソ女に幸あれ | H37: クソ女に幸あれ | I37: 036 | J37: kuso | K37: k | L37: ku | M37: kus | N37: ="quest_image_"&A37&"_"&"01" -> quest_image_kus_01
A38: han | B38: =CONCATENATE("series_banner_",A38) -> series_banner_han | C38: =CONCATENATE("series_logo_",A38) -> series_logo_han | D38: 半人前の恋人 | H38: 半人前の恋人 | I38: 037 | J38: hanninmae | K38: h | L38: ha | M38: han | N38: ="quest_image_"&A38&"_"&"01" -> quest_image_han_01
... A41: kaw | B41: =CONCATENATE("series_banner_",A41) -> series_banner_kaw | C41: =CONCATENATE("series_logo_",A41) -> series_logo_kaw | D41: カワイスギクライシス | H41: カワイスギクライシス | I41: 040 | J41: kawaisugi | K41: k | L41: ka | M41: kaw | N41: ="quest_image_"&A41&"_"&"01" -> quest_image_kaw_01
A42: c8m | B42: =CONCATENATE("series_banner_",A42) -> series_banner_c8m | C42: =CONCATENATE("series_logo_",A42) -> series_logo_c8m | D42: ちえりの恋は8メートル
A43: glo | B43: =CONCATENATE("series_banner_",A43) -> series_banner_glo | C43: series_logo_glo | D43: GLOW | E43: - | F43: - | H43: =if(G43="",D43,if(G43="後ろ",D43&" "&F43,F43&" "&D43)) -> GLOW | I43: 999 | J43: glow | K43: =left(J43,1) -> g | L43: =left(J43,2) -> gl | M43: =left(J43,3) -> glo | N43: ="quest_image_"&A43&"_"&"01" -> quest_image_glo_01 | R43: （高難易度）バトル1 | S43: 強敵/ボスバトル1
D45: ※連載中のものは上記の曜日の区分を優先とし月曜〜順に表示され、中身の順としてはこちらの順にゲーム内では表示する。 ※既に連鎖機終了しているものは日曜日連載作品の後ろに来るようになり、記載順は作品名のあいうえお順とする。

Sheet キャラpng素材
A1: 作品ID | B1: 作品名 | C1: 立ち絵png_ID | D1: キャラ名（仮） | E1: キャラ名（監修FIX） | F1: valid_start_date | G1: valid_end_date | H1: デプロイ | I1: 補足
A2: spy | B2: SPY×FAMILY | C2: unit_stand_image_spy_00001 | D2: アーニャ・フォージャー | F2: 45658 | G2: 390812.5
A3: spy | B3: SPY×FAMILY | C3: unit_stand_image_spy_00002 | D3: イーデン校の生徒 アーニャ | F3: 45658 | G3: 390812.5
A4: spy | B4: SPY×FAMILY | C4: unit_stand_image_spy_00101 | D4: ロイド・フォージャー | F4: 45658 | G4: 390812.5
A5: spy | B5: SPY×FAMILY | C5: unit_stand_image_spy_00201 | D5: ヨル・フォージャー | F5: 45658 | G5: 390812.5
A6: spy | B6: SPY×FAMILY | C6: unit_stand_image_spy_00301 | D6: ダミアン・デズモンド | F6: 45658 | G6: 390812.5
A7: spy | B7: SPY×FAMILY | C7: unit_stand_image_spy_00401 | D7: フランキー・フランクリン | F7: 45658 | G7: 390812.5
A8: aka | B8: ラーメン赤猫 | C8: unit_stand_image_aka_00001 | D8: 佐々木 | F8: 45658 | G8: 390812.5
A9: aka | B9: ラーメン赤猫 | C9: unit_stand_image_aka_00101 | D9: 文蔵 | F9: 45658 | G9: 390812.5
A10: rik | B10: トマトイプーのリコピン | C10: unit_stand_image_rik_00001 | D10: リコピン | F10: 45658 | G10: 390812.5
A11: rik | B11: トマトイプーのリコピン | C11: unit_stand_image_rik_00101 | D11: 甘戸 めめ | F11: 45658 | G11: 390812.5
A12: rik | B12: トマトイプーのリコピン | C12: unit_stand_image_rik_00201 | D12: チアミン | F12: 45658 | G12: 390812.5
A13: dan | B13: ダンダダン | C13: unit_stand_image_dan_00001 | D13: オカルン （制服着用） | F13: 45658 | G13: 390812.5
... A51: sum | B51: サマータイムレンダ | C51: unit_stand_image_sum_00201 | D51: 小舟 澪 | F51: 45658 | G51: 390812.5

Sheet ゲート
A1: 作品ID | B1: 作品名 | C1: ゲート_ID | D1: asset_key | E1: ゲート名（管理用） | F1: ゲート位置 | G1: 制作番号 | H1: valid_start_date | I1: valid_end_date | J1: デプロイ | K1: 補足
A2: gom | B2: 姫様“拷問”の時間です | C2: =CONCATENATE("outpost_",A2,"_",F2,"_",text(G2,"0000")) -> outpost_gom_ally_0001 | D2: =CONCATENATE(A2,"_",F2,"_",text(G2,"0000")) -> gom_ally_0001 | E2: 姫+エクス | F2: ally | G2: 1
A3: gom | B3: 姫様“拷問”の時間です | C3: =CONCATENATE("outpost_",A3,"_",F3,"_",text(G3,"0000")) -> outpost_gom_enemy_0001 | D3: =CONCATENATE(A3,"_",F3,"_",text(G3,"0000")) -> gom_enemy_0001 | E3: トーチャー（ピック）+アイアンメイデン | F3: enemy | G3: 1
A4: gom | B4: 姫様“拷問”の時間です | C4: =CONCATENATE("outpost_",A4,"_",F4,"_",text(G4,"0000")) -> outpost_gom_enemy_0002 | D4: =CONCATENATE(A4,"_",F4,"_",text(G4,"0000")) -> gom_enemy_0002 | E4: トーチャー（ゴリラ） | F4: enemy | G4: 2
A5: gom | B5: 姫様“拷問”の時間です | C5: =CONCATENATE("outpost_",A5,"_",F5,"_",text(G5,"0000")) -> outpost_gom_enemy_0003 | D5: =CONCATENATE(A5,"_",F5,"_",text(G5,"0000")) -> gom_enemy_0003 | E5: クロル | F5: enemy | G5: 3
A6: kim | B6: {=iferror(INDEX('作品'!D:D,MATCH(A6,'作品'!A:A,0),0),"error")} -> 君のことが大大大大大好きな100人の彼女 | C6: =CONCATENATE("outpost_",A6,"_",F6,"_",text(G6,"0000")) -> outpost_kim_enemy_0001 | D6: =CONCATENATE(A6,"_",F6,"_",text(G6,"0000")) -> kim_enemy_0001 | E6: 愛城恋太郎 | F6: enemy | G6: 1
A7: glo | B7: GLOW | C7: =CONCATENATE("outpost_",A7,"_",F7,"_",text(G7,"0000")) -> outpost_glo_enemy_0001 | D7: =CONCATENATE(A7,"_",F7,"_",text(G7,"0000")) -> glo_enemy_0001 | E7: 宝箱 | F7: enemy | G7: 1
A8: sample | B8: サンプル1 | C8: =CONCATENATE("outpost_",A8,"_",F8,"_",text(G8,"0000")) -> outpost_sample_ally_0001 | D8: =CONCATENATE(A8,"_",F8,"_",text(G8,"0000")) -> sample_ally_0001 | E8: ID発行イメージサンプル | F8: ally | G8: 1 | K8: 命名規則： outpost_作品ID_ゲート位置_制作番号4桁
A9: sample | B9: サンプル2 | C9: =CONCATENATE("outpost_",A9,"_",F9,"_",text(G9,"0000")) -> outpost_sample_ally_0002 | D9: =CONCATENATE(A9,"_",F9,"_",text(G9,"0000")) -> sample_ally_0002 | E9: ID発行イメージサンプル | F9: ally | G9: 2
A10: sample | B10: サンプル3 | C10: =CONCATENATE("outpost_",A10,"_",F10,"_",text(G10,"0000")) -> outpost_sample_enemy_0001 | D10: =CONCATENATE(A10,"_",F10,"_",text(G10,"0000")) -> sample_enemy_0001 | E10: ID発行イメージサンプル | F10: enemy | G10: 1

Sheet 原画のかけら原画
A1: 作品_ID | B1: 作品名 | C1: 接頭語（カテゴリー） | D1: アイテム_ID | E1: assetKey | F1: drop_ID | G1: アイテム名 | H1: レアリティ | I1: 最大所持数 | J1: フレーバーテキスト | K1: アイテム備考 | L1: start_date | M1: リリースキー
A2: 原画のかけら1枚原画完成ダイアログ用（524*524）ID 解像度高い方
A3: spy | B3: {=iferror(INDEX('作品'!D:D,MATCH(A3,'作品'!A:A,0),0),"error")} -> SPY×FAMILY | C3: artwork | D3: =$C$15&"_"&$A3&"_"&TEXT(countif($A3:A$3,A3),"0000") -> artwork_spy_0001 | E3: =D3 -> artwork_spy_0001 | G3: 秘密の家族 | H3: - | I3: 1 | J3: 父はスパイ、母は殺し屋、娘は超能力者！？ 全員が秘密を抱えた家族生活が始まる！ | K3: ノーマル | L3: 45924.625 | M3: 202509010
A4: spy | B4: {=iferror(INDEX('作品'!D:D,MATCH(A4,'作品'!A:A,0),0),"error")} -> SPY×FAMILY | C4: artwork | D4: =$C$15&"_"&$A4&"_"&TEXT(countif($A$3:A4,A4),"0000") -> artwork_spy_0002 | E4: =D4 -> artwork_spy_0002 | G4: 素敵な家族 | H4: - | I4: 1 | J4: 共通認識を深めるために出かけた3人は、 協力してひったくりを捕まえる。 | K4: ハード | L4: 45924.625 | M4: 202509010
A5: spy | B5: {=iferror(INDEX('作品'!D:D,MATCH(A5,'作品'!A:A,0),0),"error")} -> SPY×FAMILY | C5: artwork | D5: =$C$15&"_"&$A5&"_"&TEXT(countif($A$3:A5,A5),"0000") -> artwork_spy_0003 | E5: =D5 -> artwork_spy_0003 | G5: 明るい未来に！！ | H5: - | I5: 1 | J5: イーデンでの面接試験の後、 落ち込むロイドを励ますために お茶で乾杯！ | K5: Ex | L5: 45924.625 | M5: 202509010
A7: gom | B7: {=iferror(INDEX('作品'!D:D,MATCH(A7,'作品'!A:A,0),0),"error")} -> 姫様“拷問”の時間です | C7: artwork | D7: =$C$15&"_"&$A7&"_"&TEXT(countif($A$3:A7,A7),"0000") -> artwork_gom_0001 | E7: =D7 -> artwork_gom_0001 | G7: 決して屈しない! | H7: - | I7: 1 | J7: 国王軍第三騎士団”騎士団長”にして王女の姫様は、魔王軍からの”拷問”に抵抗する! | K7: ノーマル | L7: 45924.625 | M7: 202509010
A8: gom | B8: {=iferror(INDEX('作品'!D:D,MATCH(A8,'作品'!A:A,0),0),"error")} -> 姫様“拷問”の時間です | C8: artwork | D8: =$C$15&"_"&$A8&"_"&TEXT(countif($A$3:A8,A8),"0000") -> artwork_gom_0002 | E8: =D8 -> artwork_gom_0002 | G8: 姫様”拷問”の時間です | H8: - | I8: 1 | J8: 魔王軍 最高位拷問官のトーチャーは、どのような拷問をするのか・・・ | K8: ハード | L8: 45924.625 | M8: 202509010
A9: gom | B9: {=iferror(INDEX('作品'!D:D,MATCH(A9,'作品'!A:A,0),0),"error")} -> 姫様“拷問”の時間です | C9: artwork | D9: =$C$15&"_"&$A9&"_"&TEXT(countif($A$3:A9,A9),"0000") -> artwork_gom_0003 | E9: =D9 -> artwork_gom_0003 | G9: 姫様と最高位拷問官 | H9: - | I9: 1 | J9: 拷問が終われば、立場を気にせずにパーティーだ! | K9: Ex | L9: 45924.625 | M9: 202509010
A11: aka | B11: {=iferror(INDEX('作品'!D:D,MATCH(A11,'作品'!A:A,0),0),"error")} -> ラーメン赤猫 | C11: artwork | D11: =$C$15&"_"&$A11&"_"&TEXT(countif($A$3:A11,A11),"0000") -> artwork_aka_0001 | E11: =D11 -> artwork_aka_0001 | G11: 新メニューの試食 | H11: - | I11: 1 | J11: 早起きした珠子に試食を頼む文蔵。​ もしかして、新メニュー！？ | K11: ノーマル | L11: 45924.625 | M11: 202509010
A12: aka | B12: {=iferror(INDEX('作品'!D:D,MATCH(A12,'作品'!A:A,0),0),"error")} -> ラーメン赤猫 | C12: artwork | D12: =$C$15&"_"&$A12&"_"&TEXT(countif($A$3:A12,A12),"0000") -> artwork_aka_0002 | E12: =D12 -> artwork_aka_0002 | G12: 話は聞かせてもらった！ | H12: - | I12: 1 | J12: 新メニュー開発に挑戦する文蔵。​ ラーメン赤猫のみんなで新メニュー開発だ！ | K12: ハード | L12: 45924.625 | M12: 202509010
A13: aka | B13: {=iferror(INDEX('作品'!D:D,MATCH(A13,'作品'!A:A,0),0),"error")} -> ラーメン赤猫 | C13: artwork | D13: =$C$15&"_"&$A13&"_"&TEXT(countif($A$3:A13,A13),"0000") -> artwork_aka_0003 | E13: =D13 -> artwork_aka_0003 | G13: みんなでお昼寝 | H13: - | I13: 1 | J13: 昼営業と夜営業の間の休憩時間。​ 至福のお昼寝タイム！ | K13: Ex | L13: 45924.625 | M13: 202509010
A15: dan | B15: {=iferror(INDEX('作品'!D:D,MATCH(A15,'作品'!A:A,0),0),"error")} -> ダンダダン | C15: artwork | D15: =$C$15&"_"&$A15&"_"&TEXT(countif($A$3:A15,A15),"0000") -> artwork_dan_0001 | E15: =D15 -> artwork_dan_0001 | G15: オカルトの話しよーぜ | H15: - | I15: 1 | J15: 度重なる危機を乗り越え、 なんだか友達になれそうな二人。 | K15: ノーマル | L15: 45924.625 | M15: 202509010
A16: dan | B16: {=iferror(INDEX('作品'!D:D,MATCH(A16,'作品'!A:A,0),0),"error")} -> ダンダダン | C16: artwork | D16: =$C$15&"_"&$A16&"_"&TEXT(countif($A$3:A16,A16),"0000") -> artwork_dan_0002 | E16: =D16 -> artwork_dan_0002 | G16: ターボババアをぶっ飛ばそう | H16: - | I16: 1 | J16: オカルンの呪いを解くために、トンネルで再びターボババアと対峙する。 | K16: ハード | L16: 45924.625 | M16: 202509010
A17: dan | B17: {=iferror(INDEX('作品'!D:D,MATCH(A17,'作品'!A:A,0),0),"error")} -> ダンダダン | C17: artwork | D17: =$C$15&"_"&$A17&"_"&TEXT(countif($A$3:A17,A17),"0000") -> artwork_dan_0003 | E17: =D17 -> artwork_dan_0003 | G17: 力が溢れてくるぜ・・・!! | H17: - | I17: 1 | J17: ターボババアの呪いを解放した「オカルン」。超スピードで移動できるが、ネガティブになってしまう。 | K17: Ex | L17: 45924.625 | M17: 202509010
A19: jig | B19: {=iferror(INDEX('作品'!D:D,MATCH(A19,'作品'!A:A,0),0),"error")} -> 地獄楽 | C19: artwork | D19: =$C$15&"_"&$A19&"_"&TEXT(countif($A$3:A19,A19),"0000") -> artwork_jig_0001 | E19: =D19 -> artwork_jig_0001 | G19: 必ず生きて帰る 君のために・・・!! | H19: - | I19: 1 | J19: 帰りを待つ愛する人のために、決意する。 | K19: ノーマル | L19: 45924.625 | M19: 202509010
... A29: chi | B29: {=iferror(INDEX('作品'!D:D,MATCH(A29,'作品'!A:A,0),0),"error")} -> チェンソーマン | C29: artwork | D29: =$C$15&"_"&$A29&"_"&TEXT(countif($A$3:A29,A29),"0000") -> artwork_chi_0003 | E29: =D29 -> artwork_chi_0003 | G29: 公安対魔特異４課 | H29: - | I29: 1 | J29: 公安に悪魔の駆除要請。​ 公安対魔特異４課６人、全員集合！​ | K29: Ex | L29: 45924.625 | M29: 202509010
H30: - | I30: 1 | J30: -
A31: kai | B31: {=iferror(INDEX('作品'!D:D,MATCH(A31,'作品'!A:A,0),0),"error")} -> 怪獣８号 | C31: artwork | D31: =$C$15&"_"&$A31&"_"&TEXT(countif($A$3:A31,A31),"0000") -> artwork_kai_0001 | E31: =D31 -> artwork_kai_0001 | G31: 戦力解放！！ | H31: - | I31: 1 | J31: 怪獣襲来！ 解放戦力１％になった、 今までとは違うカフカを見せてやる！ | K31: ノーマル | L31: 45924.625 | M31: 202509010
A32: kai | B32: {=iferror(INDEX('作品'!D:D,MATCH(A32,'作品'!A:A,0),0),"error")} -> 怪獣８号 | C32: artwork | D32: =$C$15&"_"&$A32&"_"&TEXT(countif($A$3:A32,A32),"0000") -> artwork_kai_0002 | E32: =D32 -> artwork_kai_0002 | G32: 取るべき行動 | H32: - | I32: 1 | J32: 防衛隊員選別試験二次最終審査開始！ 攻撃能力の低いカフカとレノの取るべき行動は…！？ | K32: ハード | L32: 45924.625 | M32: 202509010
A33: kai | B33: {=iferror(INDEX('作品'!D:D,MATCH(A33,'作品'!A:A,0),0),"error")} -> 怪獣８号 | C33: artwork | D33: =$C$15&"_"&$A33&"_"&TEXT(countif($A$3:A33,A33),"0000") -> artwork_kai_0003 | E33: =D33 -> artwork_kai_0003 | G33: あとは俺に任せろ | H33: - | I33: 1 | J33: 防衛隊入隊試験中に現れた謎の大怪獣。 他の受験者を避難させる為に足止めをするキコルの前に、 怪獣8号が現れる…！！ | K33: Ex | L33: 45924.625 | M33: 202509010
H34: - | J34: -
A35: sur | B35: {=iferror(INDEX('作品'!D:D,MATCH(A35,'作品'!A:A,0),0),"error")} -> 魔都精兵のスレイブ | C35: artwork | D35: =$C$15&"_"&$A35&"_"&TEXT(countif($A$3:A35,A35),"0000") -> artwork_sur_0001 | E35: =D35 -> artwork_sur_0001 | G35: お前を私の奴隷にする | H35: - | I35: 1 | J35: 魔都に迷い込んだ和倉 優希を助けた 魔防隊七番組組長、羽前 京香は、 突然奴隷にすると言い出し…！？ | K35: ノーマル | L35: 45924.625 | M35: 202509010
A36: sur | B36: {=iferror(INDEX('作品'!D:D,MATCH(A36,'作品'!A:A,0),0),"error")} -> 魔都精兵のスレイブ | C36: artwork | D36: =$C$15&"_"&$A36&"_"&TEXT(countif($A$3:A36,A36),"0000") -> artwork_sur_0002 | E36: =D36 -> artwork_sur_0002 | G36: 無窮の鎖 | H36: - | I36: 1 | J36: 無窮の鎖となった優希は、 驚異的な力を発揮する！ | K36: ハード | L36: 45924.625 | M36: 202509010
A37: sur | B37: {=iferror(INDEX('作品'!D:D,MATCH(A37,'作品'!A:A,0),0),"error")} -> 魔都精兵のスレイブ | C37: artwork | D37: =$C$15&"_"&$A37&"_"&TEXT(countif($A$3:A37,A37),"0000") -> artwork_sur_0003 | E37: =D37 -> artwork_sur_0003 | G37: 魔都精兵七番隊 | H37: - | I37: 1 | J37: 京香の奴隷となった優希は、 七番隊組寮の管理人となる！ | K37: Ex | L37: 45924.625 | M37: 202509010
H38: - | I38: 1 | J38: -
A39: rik | B39: {=iferror(INDEX('作品'!D:D,MATCH(A39,'作品'!A:A,0),0),"error")} -> トマトイプーのリコピン | C39: artwork | D39: =$C$15&"_"&$A39&"_"&TEXT(countif($A$3:A39,A39),"0000") -> artwork_rik_0001 | E39: =D39 -> artwork_rik_0001 | G39: フワフワ乗り物の雲 | H39: - | I39: 1 | J39: リコピンのパパが設計をしたフワフワ乗り物の雲！ 他にも食べられる雲やインテリア雲があるぞ！ | K39: ノーマル | L39: 45924.625 | M39: 202509010
A40: rik | B40: {=iferror(INDEX('作品'!D:D,MATCH(A40,'作品'!A:A,0),0),"error")} -> トマトイプーのリコピン | C40: artwork | D40: =$C$15&"_"&$A40&"_"&TEXT(countif($A$3:A40,A40),"0000") -> artwork_rik_0002 | E40: =D40 -> artwork_rik_0002 | G40: めめちゃんの世界へようこそ | H40: - | I40: 1 | J40: めめちゃんの世界に来てしまったリコピン！ 洗濯をしたり、不燃ごみをまとめたり…！？ | K40: ハード | L40: 45924.625 | M40: 202509010
A41: rik | B41: {=iferror(INDEX('作品'!D:D,MATCH(A41,'作品'!A:A,0),0),"error")} -> トマトイプーのリコピン | C41: artwork | D41: =$C$15&"_"&$A41&"_"&TEXT(countif($A$3:A41,A41),"0000") -> artwork_rik_0003 | E41: =D41 -> artwork_rik_0003 | G41: はじめましてぼくリコピン | H41: - | I41: 1 | J41: リコピンはトマトの苗から生まれたトイプードル！ トマトイプーの3さいの男の子なんだよ！ | K41: Ex | L41: 45924.625 | M41: 202509010
H42: - | I42: 1 | J42: -
A43: mag | B43: {=iferror(INDEX('作品'!D:D,MATCH(A43,'作品'!A:A,0),0),"error")} -> 株式会社マジルミエ | C43: artwork | D43: =$C$15&"_"&$A43&"_"&TEXT(countif($A$3:A43,A43),"0000") -> artwork_mag_0001 | E43: =D43 -> artwork_mag_0001 | G43: 初めての変身 | H43: - | I43: 1 | J43: 魔法少女としての初仕事！​ 出動前に変身だ！ | K43: ノーマル | L43: 45924.625 | M43: 202509010
A44: mag | B44: {=iferror(INDEX('作品'!D:D,MATCH(A44,'作品'!A:A,0),0),"error")} -> 株式会社マジルミエ | C44: artwork | D44: =$C$15&"_"&$A44&"_"&TEXT(countif($A$3:A44,A44),"0000") -> artwork_mag_0002 | E44: =D44 -> artwork_mag_0002 | G44: 業務完了！ | H44: - | I44: 1 | J44: 面接中に現れた怪異に対応すべく現れた​ 魔法少女・越谷 仁美。 | K44: ハード | L44: 45924.625 | M44: 202509010
A45: mag | B45: {=iferror(INDEX('作品'!D:D,MATCH(A45,'作品'!A:A,0),0),"error")} -> 株式会社マジルミエ | C45: artwork | D45: =$C$15&"_"&$A45&"_"&TEXT(countif($A$3:A45,A45),"0000") -> artwork_mag_0003 | E45: =D45 -> artwork_mag_0003 | G45: 飛ばすよ！ | H45: - | I45: 1 | J45: 初めての仕事、初めてのホーキ、初めての魔法！ 初めてでももう立派な魔法少女。 | K45: Ex | L45: 45924.625 | M45: 202509010
H46: - | I46: 1 | J46: -
A47: sum | B47: {=iferror(INDEX('作品'!D:D,MATCH(A47,'作品'!A:A,0),0),"error")} -> サマータイムレンダ | C47: artwork | D47: =$C$15&"_"&$A47&"_"&TEXT(countif($A$3:A47,A47),"0000") -> artwork_sum_0001 | E47: =D47 -> artwork_sum_0001 | G47: 言うてる場合かっ！！！ | H47: - | I47: 1 | J47: 見つからないように人混みの中を駆け抜ける 慎平と潮。 | K47: ノーマル | L47: 45924.625 | M47: 202509010
A48: sum | B48: {=iferror(INDEX('作品'!D:D,MATCH(A48,'作品'!A:A,0),0),"error")} -> サマータイムレンダ | C48: artwork | D48: =$C$15&"_"&$A48&"_"&TEXT(countif($A$3:A48,A48),"0000") -> artwork_sum_0002 | E48: =D48 -> artwork_sum_0002 | G48: ちゃんと見つけてよ | H48: - | I48: 1 | J48: 夏祭りの人混みで潮を見かけたような気がして 向かった先の浜辺には潮の姿が…！？ | K48: ハード | L48: 45924.625 | M48: 202509010
A49: sum | B49: {=iferror(INDEX('作品'!D:D,MATCH(A49,'作品'!A:A,0),0),"error")} -> サマータイムレンダ | C49: artwork | D49: =$C$15&"_"&$A49&"_"&TEXT(countif($A$3:A49,A49),"0000") -> artwork_sum_0003 | E49: =D49 -> artwork_sum_0003 | G49: 言おうと思てたことあんねん | H49: - | I49: 1 | J49: 浜辺で再会した、死んだはずの幼馴染潮。 彼女は、慎平に再会できたら 言おうと思っていたことがあるという。 | K49: Ex | L49: 45924.625 | M49: 202509010
H50: -
A51: glo | B51: {=iferror(INDEX('作品'!D:D,MATCH(A51,'作品'!A:A,0),0),"error")} -> GLOW | C51: artwork | D51: artwork_tutorial_0001 | E51: =D51 -> artwork_tutorial_0001 | G51: 希望のコマ | H51: - | I51: 1 | K51: チュートリアル初期設定。最初から持ち物に所持。 | L51: 45924.625 | M51: 202509010 ※チュートリアル使用
A52: glo | B52: {=iferror(INDEX('作品'!D:D,MATCH(A52,'作品'!A:A,0),0),"error")} -> GLOW | C52: artwork | D52: =$C$15&"_"&$A52&"_"&TEXT(countif($A$3:A52,A52),"0000") -> artwork_glo_0002 | E52: =D52 -> artwork_glo_0002 | G52: ジャンプラバースファントム侵攻 | H52: - | I52: 1 | J52: 侵略されたジャンプラバースの画像 | K52: エネミー専用のゲート原画 | L52: 45924.625 | M52: 202509010 ※チュートリアル使用
A54: osh | B54: {=iferror(INDEX('作品'!D:D,MATCH(A54,'作品'!A:A,0),0),"error")} -> 【推しの子】 | C54: artwork | D54: =$C$15&"_"&$A54&"_"&TEXT(countif($A$3:A54,A54),"0000") -> artwork_osh_0001 | E54: =D54 -> artwork_osh_0001 | G54: 激バズ！本能のヲタ芸！ | H54: - | I54: 1 | J54: 推しへの愛が高まりすぎた双子の赤ちゃんが ヲタ芸を打つという異常事態に思わずアイドルも個レス！ | K54: ノーマル | L54: 45658 | M54: 202512020
A55: osh | B55: {=iferror(INDEX('作品'!D:D,MATCH(A55,'作品'!A:A,0),0),"error")} -> 【推しの子】 | C55: artwork | D55: =$C$15&"_"&$A55&"_"&TEXT(countif($A$3:A55,A55),"0000") -> artwork_osh_0002 | E55: =D55 -> artwork_osh_0002 | G55: やっと言えた | H55: - | I55: 1 | J55: この言葉は絶対 嘘じゃない | K55: ハード | L55: 45658 | M55: 202512020
A56: osh | B56: {=iferror(INDEX('作品'!D:D,MATCH(A56,'作品'!A:A,0),0),"error")} -> 【推しの子】 | C56: artwork | D56: =$C$15&"_"&$A56&"_"&TEXT(countif($A$3:A56,A56),"0000") -> artwork_osh_0003 | E56: =D56 -> artwork_osh_0003 | G56: いってきます | H56: - | I56: 1 | J56: かくして幼少期(プロローグ)は終わり それぞれの想いを胸に、新たな物語の幕が上がる | K56: Ex | L56: 45658 | M56: 202512020
A58: 原画のかけら イベント用
A60: kai | B60: {=iferror(INDEX('作品'!D:D,MATCH(A60,'作品'!A:A,0),0),"error")} -> 怪獣８号 | C60: artwork_event | D60: =C60&"_"&$A60&"_"&TEXT(countif($A$60:A60,A60),"0000") -> artwork_event_kai_0001 | E60: =D60 -> artwork_event_kai_0001 | G60: ぶち抜くから歯食いしばれ | H60: - | I60: 1 | J60: 傷付いた仲間を想い、怪獣９号へ怒りをむき出しに。怒りを乗せたその拳で怪獣９号の討伐へ挑む。 | K60: イベントクエスト | L60: 45922 | M60: 202509010
A61: kai | B61: {=iferror(INDEX('作品'!D:D,MATCH(A61,'作品'!A:A,0),0),"error")} -> 怪獣８号 | C61: artwork_event | D61: =C61&"_"&$A61&"_"&TEXT(countif($A$60:A61,A61),"0000") -> artwork_event_kai_0002 | E61: =D61 -> artwork_event_kai_0002 | G61: うん ずっと待ってる | H61: - | I61: 1 | J61: 四ノ宮 功との戦いで怪獣８号に変身した日比野 カフカ。激闘の中で荒ぶる怪獣の本能に身を蝕まれ暴走するも、亜白 ミナとの約束が彼を再び人へと引き戻した。 | K61: イベントクエスト | L61: 45922 | M61: 202509010
A62: spy | B62: {=iferror(INDEX('作品'!D:D,MATCH(A62,'作品'!A:A,0),0),"error")} -> SPY×FAMILY | C62: artwork_event | D62: =C62&"_"&$A62&"_"&TEXT(countif($A$60:A62,A62),"0000") -> artwork_event_spy_0001 | E62: =D62 -> artwork_event_spy_0001 | G62: うそつきのちち | H62: - | I62: 1 | J62: 2人の家への帰り路、娘を守るために奮闘した父はすごくかっこいい！ | K62: イベントクエスト | L62: 45936 | M62: 202510010
A63: spy | B63: {=iferror(INDEX('作品'!D:D,MATCH(A63,'作品'!A:A,0),0),"error")} -> SPY×FAMILY | C63: artwork_event | D63: =C63&"_"&$A63&"_"&TEXT(countif($A$60:A63,A63),"0000") -> artwork_event_spy_0002 | E63: =D63 -> artwork_event_spy_0002 | G63: オトナの余裕 | H63: - | I63: 1 | J63: ちょっとした意地悪くらいなら笑って流せるのがカッコイイお姉さん。 | K63: イベントクエスト | L63: 45936 | M63: 202510010
A64: dan | B64: {=iferror(INDEX('作品'!D:D,MATCH(A64,'作品'!A:A,0),0),"error")} -> ダンダダン | C64: artwork_event | D64: =C64&"_"&$A64&"_"&TEXT(countif($A$60:A64,A64),"0000") -> artwork_event_dan_0001 | E64: =D64 -> artwork_event_dan_0001 | G64: 逃げろ!! | H64: - | I64: 1 | J64: 招き猫の中に乗り移ってしまったターボババア。 とにかく逃げろ!! | K64: イベントクエスト | L64: 45952.625 | M64: 202510020
A65: dan | B65: {=iferror(INDEX('作品'!D:D,MATCH(A65,'作品'!A:A,0),0),"error")} -> ダンダダン | C65: artwork_event | D65: =C65&"_"&$A65&"_"&TEXT(countif($A$60:A65,A65),"0000") -> artwork_event_dan_0002 | E65: =D65 -> artwork_event_dan_0002 | G65: お⺟さん 愛してる | H65: - | I65: 1 | J65: アイラに炎(オーラ)を託して消えゆくアクロバティックさらさら。 宇宙で⼀番幸せだった記憶は絶対に消えない。 | K65: イベントクエスト | L65: 45952.625 | M65: 202510020
A66: mag | B66: {=iferror(INDEX('作品'!D:D,MATCH(A66,'作品'!A:A,0),0),"error")} -> 株式会社マジルミエ | C66: artwork_event | D66: =C66&"_"&$A66&"_"&TEXT(countif($A$60:A66,A66),"0000") -> artwork_event_mag_0001 | E66: =D66 -> artwork_event_mag_0001 | G66: 上司です | H66: - | I66: 1 | J66: 株式会社マジルミエの社長を務める重本 浩司は魔法少女に魂を捧げており、その覚悟は私生活にも表れている。 日々、衣装の手入れやスキンケアを欠かすことなく、自身が思い描く理想の魔法少女像を追い求めている。 | K66: イベントクエスト | L66: 45967.625 | M66: 202511010
A67: mag | B67: {=iferror(INDEX('作品'!D:D,MATCH(A67,'作品'!A:A,0),0),"error")} -> 株式会社マジルミエ | C67: artwork_event | D67: =C67&"_"&$A67&"_"&TEXT(countif($A$60:A67,A67),"0000") -> artwork_event_mag_0002 | E67: =D67 -> artwork_event_mag_0002 | G67: 一人とチーム | H67: - | I67: 1 | J67: これまでは一人で考え、選択し、責任を負う仕事をしてきた槇野 あかね。マジルミエで桜木 カナや越谷 仁美、そしてエンジニアと共に業務をこなす中で、「チームで仕事をすること」を身につけ、連携し対応できるようになった。 | K67: イベントクエスト | L67: 45967.625 | M67: 202511010
A68: yuw | B68: {=iferror(INDEX('作品'!D:D,MATCH(A68,'作品'!A:A,0),0),"error")} -> 2.5次元の誘惑 | C68: artwork_event | D68: =C68&"_"&$A68&"_"&TEXT(countif($A$60:A68,A68),"0000") -> artwork_event_yuw_0001 | E68: =D68 -> artwork_event_yuw_0001 | G68: 負けられないのよっ!!! | H68: - | I68: 1 | J68: コスプレの神様がいるのなら、自分の力で振り向かせる！誰にも負けないくらいコスプレを楽しんでやるんだから！ | K68: イベントクエスト | L68: 45986.625 | M68: 202511020
A69: yuw | B69: {=iferror(INDEX('作品'!D:D,MATCH(A69,'作品'!A:A,0),0),"error")} -> 2.5次元の誘惑 | C69: artwork_event | D69: =C69&"_"&$A69&"_"&TEXT(countif($A$60:A69,A69),"0000") -> artwork_event_yuw_0002 | E69: =D69 -> artwork_event_yuw_0002 | G69: 私たちは本気だ | H69: - | I69: 1 | J69: 隣を見れば仲間がいる、恋焦がれた漫画の次元を全力で作っている 幸せです… | K69: イベントクエスト | L69: 45986.625 | M69: 202511020
A70: sur | B70: {=iferror(INDEX('作品'!D:D,MATCH(A70,'作品'!A:A,0),0),"error")} -> 魔都精兵のスレイブ | C70: artwork_event | D70: =C70&"_"&$A70&"_"&TEXT(countif($A$60:A70,A70),"0000") -> artwork_event_sur_0001 | E70: =D70 -> artwork_event_sur_0001 | G70: 六番組長の出雲 天花です | H70: - | I70: 1 | J70: 初めて会う未来のお義姉さんへ、心よりご挨拶を。 | K70: イベントクエスト | M70: 202512010
A71: sur | B71: {=iferror(INDEX('作品'!D:D,MATCH(A71,'作品'!A:A,0),0),"error")} -> 魔都精兵のスレイブ | C71: artwork_event | D71: =C71&"_"&$A71&"_"&TEXT(countif($A$60:A71,A71),"0000") -> artwork_event_sur_0002 | E71: =D71 -> artwork_event_sur_0002 | G71: お前の姉じゃない | H71: - | I71: 1 | J71: 魔防隊は敵。協力するつもりは無い。そのうえ「お義姉さん」などと勝手に呼ぶ女など、しばき倒す他にない。 | K71: イベントクエスト | M71: 202512010
A72: osh | B72: {=iferror(INDEX('作品'!D:D,MATCH(A72,'作品'!A:A,0),0),"error")} -> 【推しの子】 | C72: artwork_event | D72: =C72&"_"&$A72&"_"&TEXT(countif($A$60:A72,A72),"0000") -> artwork_event_osh_0001 | E72: =D72 -> artwork_event_osh_0001 | G72: 絶対ママみたいになるんだ！ | H72: - | I72: 1 | J72: 幼い頃から夢に見た、アイというアイドルの輝きを追って。厳しさや辛さも覚悟のうえ。ついに、芸能界へ一歩踏み出す。 | K72: イベントクエスト | L72: 45658 | M72: 202512020
A73: osh | B73: {=iferror(INDEX('作品'!D:D,MATCH(A73,'作品'!A:A,0),0),"error")} -> 【推しの子】 | C73: artwork_event | D73: =C73&"_"&$A73&"_"&TEXT(countif($A$60:A73,A73),"0000") -> artwork_event_osh_0002 | E73: =D73 -> artwork_event_osh_0002 | G73: 覆面筋トレ系ユーチューバー | H73: - | I73: 1 | J73: 苺プロダクションの稼ぎ頭！大先輩の背中はデカい… | K73: イベントクエスト | L73: 45658 | M73: 202512020
A74: jig | B74: {=iferror(INDEX('作品'!D:D,MATCH(A74,'作品'!A:A,0),0),"error")} -> 地獄楽 | C74: artwork_event | D74: =C74&"_"&$A74&"_"&TEXT(countif($A$60:A74,A74),"0000") -> artwork_event_jig_0001 | E74: =D74 -> artwork_event_jig_0001 | G74: 必ず生きて帰る | H74: - | I74: 1 | J74: 死罪となった“がらんの画眉丸“は、死を目前に妻の言葉を思い出す。 「人の心は、そんなに簡単に死なないわ」。里に残した妻がかけてくれた言葉だ。 妻との「普通の暮らし」を手に入れるため、画眉丸は謎多き島・神仙郷へ向かう。 そして心に強く誓う「必ず生きて帰る」と。 | K74: イベントクエスト | L74: 45673.625 | M74: 202601010
A75: jig | B75: {=iferror(INDEX('作品'!D:D,MATCH(A75,'作品'!A:A,0),0),"error")} -> 地獄楽 | C75: artwork_event | D75: =C75&"_"&$A75&"_"&TEXT(countif($A$60:A75,A75),"0000") -> artwork_event_jig_0002 | E75: =D75 -> artwork_event_jig_0002 | G75: 兄は弟の道標だ！！ | H75: - | I75: 1 | J75: 立場こそ死罪人と首切り役人だが、亜左弔兵衛と山田浅ェ門桐馬は、紛れもなく兄弟である。 二人は、壮絶な幼少期を生き抜いてきた。 親を失い路頭に迷う日々に、泣きじゃくる弟へ兄は言った。 「何が正しいかわからねぇなら、オレだけを信じろ！」 その言葉が示すように、二人の絆は成長した今も昔も変わらない。 兄は弟を導き、弟は兄を信じ続けている。 | K75: イベントクエスト | L75: 45673.625 | M75: 202601010
A76: you | B76: {=iferror(INDEX('作品'!D:D,MATCH(A76,'作品'!A:A,0),0),"error")} -> 幼稚園WARS | C76: artwork_event | D76: =C76&"_"&$A76&"_"&TEXT(countif($A$60:A76,A76),"0000") -> artwork_event_you_0001 | E76: =D76 -> artwork_event_you_0001 | G76: これで貸しはチャラだ | H76: - | I76: 1 | J76: 未作成攫われたダグを助けにきたリタ。 殺し屋たちがブラック幼稚園に向かわないように 全員やっつける！ | K76: イベントクエスト | L76: 45690.625 | M76: 202602010
A77: you | B77: {=iferror(INDEX('作品'!D:D,MATCH(A77,'作品'!A:A,0),0),"error")} -> 幼稚園WARS | C77: artwork_event | D77: =C77&"_"&$A77&"_"&TEXT(countif($A$60:A77,A77),"0000") -> artwork_event_you_0002 | E77: =D77 -> artwork_event_you_0002 | G77: 兄と妹 | H77: - | I77: 1 | J77: 世界で一番大切な人。 お互いに罪を償って、また再会しよう。 | K77: イベントクエスト | L77: 45690.625 | M77: 202602010
A78: kim | B78: {=iferror(INDEX('作品'!D:D,MATCH(A78,'作品'!A:A,0),0),"error")} -> 君のことが大大大大大好きな100人の彼女 | C78: artwork_event | D78: =C78&"_"&$A78&"_"&TEXT(countif($A$60:A78,A78),"0000") -> artwork_event_kim_0001 | E78: =D78 -> artwork_event_kim_0001 | G78: キスゾンビ | H78: - | I78: 1 | J78: 彼女たちがキスを求めるキスゾンビに！愛の力でキスバイオハザードを生き残れ！ | K78: イベントクエスト | L78: 45704.625
A79: kim | B79: {=iferror(INDEX('作品'!D:D,MATCH(A79,'作品'!A:A,0),0),"error")} -> 君のことが大大大大大好きな100人の彼女 | C79: artwork_event | D79: =C79&"_"&$A79&"_"&TEXT(countif($A$60:A79,A79),"0000") -> artwork_event_kim_0002 | E79: =D79 -> artwork_event_kim_0002 | G79: 運命の出会い | H79: - | I79: 1 | J79: 一目見た瞬間、全身に走った衝撃。この二人が愛城 恋太郎の"運命の人"…!? | K79: イベントクエスト | L79: 45704.625
A80: hut | B80: {=iferror(INDEX('作品'!D:D,MATCH(A80,'作品'!A:A,0),0),"error")} -> ふつうの軽音部 | C80: artwork_event | D80: =C80&"_"&$A80&"_"&TEXT(countif($A$60:A80,A80),"0000") -> artwork_event_hut_0001 | E80: =D80 -> artwork_event_hut_0001 | G80: もっと自由にわがままに | H80: - | I80: 1 | K80: イベントクエスト | L80: 45718.625
A81: hut | B81: {=iferror(INDEX('作品'!D:D,MATCH(A81,'作品'!A:A,0),0),"error")} -> ふつうの軽音部 | C81: artwork_event | D81: =C81&"_"&$A81&"_"&TEXT(countif($A$60:A81,A81),"0000") -> artwork_event_hut_0002 | E81: =D81 -> artwork_event_hut_0002 | G81: いつか私たちの演奏で | H81: - | I81: 1 | K81: イベントクエスト | L81: 45718.625
A82: aya | B82: {=iferror(INDEX('作品'!D:D,MATCH(A82,'作品'!A:A,0),0),"error")} -> あやかしトライアングル | C82: artwork_event | D82: =C82&"_"&$A82&"_"&TEXT(countif($A$60:A82,A82),"0000") -> artwork_event_aya_0001 | E82: =D82 -> artwork_event_aya_0001 | G82: オモカゲ | H82: - | I82: 1 | K82: イベントクエスト | L82: 45764.625
A83: aya | B83: {=iferror(INDEX('作品'!D:D,MATCH(A83,'作品'!A:A,0),0),"error")} -> あやかしトライアングル | C83: artwork_event | D83: =C83&"_"&$A83&"_"&TEXT(countif($A$60:A83,A83),"0000") -> artwork_event_aya_0002 | E83: =D83 -> artwork_event_aya_0002 | G83: 覚醒の兆し | H83: - | I83: 1 | K83: イベントクエスト | L83: 45764.625
A85: 原画のかけらID ※アイテムIDは100番台→ノーマル、200番台→ハード、300番台→ベリーハード、400番台→イベントとしておく（α3）
A86: spy | B86: {=iferror(INDEX('作品'!D:D,MATCH(A86,'作品'!A:A,0),0),"error")} -> SPY×FAMILY | C86: artwork_fragment | D86: =C86&"_"&A86&"_"&TEXT(countif($A$86:A86,A86),"00100") -> artwork_fragment_spy_00101 | F86: spy_a_0001 | G86: 秘密の家族のかけら1 | H86: N | I86: 1
A87: spy | B87: {=iferror(INDEX('作品'!D:D,MATCH(A87,'作品'!A:A,0),0),"error")} -> SPY×FAMILY | C87: artwork_fragment | D87: =C87&"_"&A87&"_"&TEXT(countif($A$86:A87,A87),"00100") -> artwork_fragment_spy_00102 | F87: spy_a_0001 | G87: 秘密の家族のかけら2 | H87: N | I87: 1
A88: spy | B88: {=iferror(INDEX('作品'!D:D,MATCH(A88,'作品'!A:A,0),0),"error")} -> SPY×FAMILY | C88: artwork_fragment | D88: =C88&"_"&A88&"_"&TEXT(countif($A$86:A88,A88),"00100") -> artwork_fragment_spy_00103 | F88: spy_a_0002 | G88: 秘密の家族のかけら3 | H88: N | I88: 1
A89: spy | B89: {=iferror(INDEX('作品'!D:D,MATCH(A89,'作品'!A:A,0),0),"error")} -> SPY×FAMILY | C89: artwork_fragment | D89: =C89&"_"&A89&"_"&TEXT(countif($A$86:A89,A89),"00100") -> artwork_fragment_spy_00104 | F89: spy_a_0002 | G89: 秘密の家族のかけら4 | H89: N | I89: 1
A90: spy | B90: {=iferror(INDEX('作品'!D:D,MATCH(A90,'作品'!A:A,0),0),"error")} -> SPY×FAMILY | C90: artwork_fragment | D90: =C90&"_"&A90&"_"&TEXT(countif($A$86:A90,A90),"00100") -> artwork_fragment_spy_00105 | F90: spy_a_0003 | G90: 秘密の家族のかけら5 | H90: N | I90: 1
A91: spy | B91: {=iferror(INDEX('作品'!D:D,MATCH(A91,'作品'!A:A,0),0),"error")} -> SPY×FAMILY | C91: artwork_fragment | D91: =C91&"_"&A91&"_"&TEXT(countif($A$86:A91,A91),"00100") -> artwork_fragment_spy_00106 | F91: spy_a_0003 | G91: 秘密の家族のかけら6 | H91: N | I91: 1
A92: spy | B92: {=iferror(INDEX('作品'!D:D,MATCH(A92,'作品'!A:A,0),0),"error")} -> SPY×FAMILY | C92: artwork_fragment | D92: =C92&"_"&A92&"_"&TEXT(countif($A$86:A92,A92),"00100") -> artwork_fragment_spy_00107 | F92: spy_a_0004 | G92: 秘密の家族のかけら7 | H92: N | I92: 1
A93: spy | B93: {=iferror(INDEX('作品'!D:D,MATCH(A93,'作品'!A:A,0),0),"error")} -> SPY×FAMILY | C93: artwork_fragment | D93: =C93&"_"&A93&"_"&TEXT(countif($A$86:A93,A93),"00100") -> artwork_fragment_spy_00108 | F93: spy_a_0004 | G93: 秘密の家族のかけら8 | H93: N | I93: 1
A94: spy | B94: {=iferror(INDEX('作品'!D:D,MATCH(A94,'作品'!A:A,0),0),"error")} -> SPY×FAMILY | C94: artwork_fragment | D94: =C94&"_"&A94&"_"&TEXT(countif($A$86:A94,A94),"00100") -> artwork_fragment_spy_00109 | F94: spy_a_0005 | G94: 秘密の家族のかけら9 | H94: N | I94: 1
A95: spy | B95: {=iferror(INDEX('作品'!D:D,MATCH(A95,'作品'!A:A,0),0),"error")} -> SPY×FAMILY | C95: artwork_fragment | D95: =C95&"_"&A95&"_"&TEXT(countif($A$86:A95,A95),"00100") -> artwork_fragment_spy_00110 | F95: spy_a_0005 | G95: 秘密の家族のかけら10 | H95: N | I95: 1
A96: spy | B96: {=iferror(INDEX('作品'!D:D,MATCH(A96,'作品'!A:A,0),0),"error")} -> SPY×FAMILY | C96: artwork_fragment | D96: =C96&"_"&A96&"_"&TEXT(countif($A$86:A96,A96),"00100") -> artwork_fragment_spy_00111 | F96: spy_a_0006 | G96: 秘密の家族のかけら11 | H96: N | I96: 1
A97: spy | B97: {=iferror(INDEX('作品'!D:D,MATCH(A97,'作品'!A:A,0),0),"error")} -> SPY×FAMILY | C97: artwork_fragment | D97: =C97&"_"&A97&"_"&TEXT(countif($A$86:A97,A97),"00100") -> artwork_fragment_spy_00112 | F97: spy_a_0006 | G97: 秘密の家族のかけら12 | H97: N | I97: 1
A98: spy | B98: {=iferror(INDEX('作品'!D:D,MATCH(A98,'作品'!A:A,0),0),"error")} -> SPY×FAMILY | C98: artwork_fragment | D98: =C98&"_"&A98&"_"&TEXT(countif($A$86:A86,A98),"00200") -> artwork_fragment_spy_00201 | F98: spy_b_0001 | G98: 素敵な家族のかけら1 | H98: N | I98: 1
A99: spy | B99: {=iferror(INDEX('作品'!D:D,MATCH(A99,'作品'!A:A,0),0),"error")} -> SPY×FAMILY | C99: artwork_fragment | D99: =C99&"_"&A99&"_"&TEXT(countif($A$86:A87,A99),"00200") -> artwork_fragment_spy_00202 | F99: spy_b_0001 | G99: 素敵な家族のかけら2 | H99: N | I99: 1
A100: spy | B100: {=iferror(INDEX('作品'!D:D,MATCH(A100,'作品'!A:A,0),0),"error")} -> SPY×FAMILY | C100: artwork_fragment | D100: =C100&"_"&A100&"_"&TEXT(countif($A$86:A88,A100),"00200") -> artwork_fragment_spy_00203 | F100: spy_b_0002 | G100: 素敵な家族のかけら3 | H100: N | I100: 1
A101: spy | B101: {=iferror(INDEX('作品'!D:D,MATCH(A101,'作品'!A:A,0),0),"error")} -> SPY×FAMILY | C101: artwork_fragment | D101: =C101&"_"&A101&"_"&TEXT(countif($A$86:A89,A101),"00200") -> artwork_fragment_spy_00204 | F101: spy_b_0002 | G101: 素敵な家族のかけら4 | H101: N | I101: 1
A102: spy | B102: {=iferror(INDEX('作品'!D:D,MATCH(A102,'作品'!A:A,0),0),"error")} -> SPY×FAMILY | C102: artwork_fragment | D102: =C102&"_"&A102&"_"&TEXT(countif($A$86:A90,A102),"00200") -> artwork_fragment_spy_00205 | F102: spy_b_0003 | G102: 素敵な家族のかけら5 | H102: N | I102: 1
A103: spy | B103: {=iferror(INDEX('作品'!D:D,MATCH(A103,'作品'!A:A,0),0),"error")} -> SPY×FAMILY | C103: artwork_fragment | D103: =C103&"_"&A103&"_"&TEXT(countif($A$86:A91,A103),"00200") -> artwork_fragment_spy_00206 | F103: spy_b_0003 | G103: 素敵な家族のかけら6 | H103: N | I103: 1
A104: spy | B104: {=iferror(INDEX('作品'!D:D,MATCH(A104,'作品'!A:A,0),0),"error")} -> SPY×FAMILY | C104: artwork_fragment | D104: =C104&"_"&A104&"_"&TEXT(countif($A$86:A92,A104),"00200") -> artwork_fragment_spy_00207 | F104: spy_b_0004 | G104: 素敵な家族のかけら7 | H104: N | I104: 1
A105: spy | B105: {=iferror(INDEX('作品'!D:D,MATCH(A105,'作品'!A:A,0),0),"error")} -> SPY×FAMILY | C105: artwork_fragment | D105: =C105&"_"&A105&"_"&TEXT(countif($A$86:A93,A105),"00200") -> artwork_fragment_spy_00208 | F105: spy_b_0004 | G105: 素敵な家族のかけら8 | H105: N | I105: 1
A106: spy | B106: {=iferror(INDEX('作品'!D:D,MATCH(A106,'作品'!A:A,0),0),"error")} -> SPY×FAMILY | C106: artwork_fragment | D106: =C106&"_"&A106&"_"&TEXT(countif($A$86:A94,A106),"00200") -> artwork_fragment_spy_00209 | F106: spy_b_0005 | G106: 素敵な家族のかけら9 | H106: N | I106: 1
A107: spy | B107: {=iferror(INDEX('作品'!D:D,MATCH(A107,'作品'!A:A,0),0),"error")} -> SPY×FAMILY | C107: artwork_fragment | D107: =C107&"_"&A107&"_"&TEXT(countif($A$86:A95,A107),"00200") -> artwork_fragment_spy_00210 | F107: spy_b_0005 | G107: 素敵な家族のかけら10 | H107: N | I107: 1
A108: spy | B108: {=iferror(INDEX('作品'!D:D,MATCH(A108,'作品'!A:A,0),0),"error")} -> SPY×FAMILY | C108: artwork_fragment | D108: =C108&"_"&A108&"_"&TEXT(countif($A$86:A96,A108),"00200") -> artwork_fragment_spy_00211 | F108: spy_b_0006 | G108: 素敵な家族のかけら11 | H108: N | I108: 1
A109: spy | B109: {=iferror(INDEX('作品'!D:D,MATCH(A109,'作品'!A:A,0),0),"error")} -> SPY×FAMILY | C109: artwork_fragment | D109: =C109&"_"&A109&"_"&TEXT(countif($A$86:A97,A109),"00200") -> artwork_fragment_spy_00212 | F109: spy_b_0006 | G109: 素敵な家族のかけら12 | H109: N | I109: 1
A110: spy | B110: {=iferror(INDEX('作品'!D:D,MATCH(A110,'作品'!A:A,0),0),"error")} -> SPY×FAMILY | C110: artwork_fragment | D110: =C110&"_"&A110&"_"&TEXT(countif($A$110:A110,A110),"00300") -> artwork_fragment_spy_00301 | F110: spy_c_0001 | G110: 明るい未来に！！のかけら1 | H110: N | I110: 1
A111: spy | B111: {=iferror(INDEX('作品'!D:D,MATCH(A111,'作品'!A:A,0),0),"error")} -> SPY×FAMILY | C111: artwork_fragment | D111: =C111&"_"&A111&"_"&TEXT(countif($A$110:A111,A111),"00300") -> artwork_fragment_spy_00302 | F111: spy_c_0001 | G111: 明るい未来に！！のかけら2 | H111: N | I111: 1
A112: spy | B112: {=iferror(INDEX('作品'!D:D,MATCH(A112,'作品'!A:A,0),0),"error")} -> SPY×FAMILY | C112: artwork_fragment | D112: =C112&"_"&A112&"_"&TEXT(countif($A$110:A112,A112),"00300") -> artwork_fragment_spy_00303 | F112: spy_c_0002 | G112: 明るい未来に！！のかけら3 | H112: N | I112: 1
A113: spy | B113: {=iferror(INDEX('作品'!D:D,MATCH(A113,'作品'!A:A,0),0),"error")} -> SPY×FAMILY | C113: artwork_fragment | D113: =C113&"_"&A113&"_"&TEXT(countif($A$110:A113,A113),"00300") -> artwork_fragment_spy_00304 | F113: spy_c_0002 | G113: 明るい未来に！！のかけら4 | H113: N | I113: 1
A114: spy | B114: {=iferror(INDEX('作品'!D:D,MATCH(A114,'作品'!A:A,0),0),"error")} -> SPY×FAMILY | C114: artwork_fragment | D114: =C114&"_"&A114&"_"&TEXT(countif($A$110:A114,A114),"00300") -> artwork_fragment_spy_00305 | F114: spy_c_0003 | G114: 明るい未来に！！のかけら5 | H114: N | I114: 1
A115: spy | B115: {=iferror(INDEX('作品'!D:D,MATCH(A115,'作品'!A:A,0),0),"error")} -> SPY×FAMILY | C115: artwork_fragment | D115: =C115&"_"&A115&"_"&TEXT(countif($A$110:A115,A115),"00300") -> artwork_fragment_spy_00306 | F115: spy_c_0003 | G115: 明るい未来に！！のかけら6 | H115: N | I115: 1
A116: spy | B116: {=iferror(INDEX('作品'!D:D,MATCH(A116,'作品'!A:A,0),0),"error")} -> SPY×FAMILY | C116: artwork_fragment | D116: =C116&"_"&A116&"_"&TEXT(countif($A$110:A116,A116),"00300") -> artwork_fragment_spy_00307 | F116: spy_c_0004 | G116: 明るい未来に！！のかけら7 | H116: N | I116: 1
A117: spy | B117: {=iferror(INDEX('作品'!D:D,MATCH(A117,'作品'!A:A,0),0),"error")} -> SPY×FAMILY | C117: artwork_fragment | D117: =C117&"_"&A117&"_"&TEXT(countif($A$110:A117,A117),"00300") -> artwork_fragment_spy_00308 | F117: spy_c_0004 | G117: 明るい未来に！！のかけら8 | H117: N | I117: 1
...

Sheet キャラ
A1: 作品ID | B1: 作品名 | C1: 識別ID | D1: キャラ_ID | E1: キャラ名（仮） | F1: キャラ名（監修FIX） | G1: 必殺ワザ名（監修FIX） | H1: レアリティ | I1: ラベル | J1: 属性 | K1: キャラ立ち位置 | L1: ロール | M1: 通常攻撃モーション | N1: 攻撃射程 | O1: 必殺ワザモーション | P1: 必殺ワザ発動有無 | Q1: 通常攻撃モーション | R1: 通常攻撃発生 | S1: 必殺攻撃モーション | T1: 必殺攻撃発生 | U1: valid_start_date | V1: valid_end_date | W1: catch_copy_image_filename | X1: ノーマル敵専用アイコン_ID | Y1: BOSS専用アイコン_ID | Z1: 通常攻撃Asset | AA1: 必殺ワザAsset | AB1: デプロイ | AC1: プランナー監修状況 | AD1: 全て監修状況 | AE1: 補足 | AF1: 発注依頼書状況 | AG1: リリースキー
A2: spy | B2: {=iferror(INDEX('作品'!D:D,MATCH(A2,'作品'!A:A,0),0),"error")} -> SPY×FAMILY | C2: 00001 | D2: =K2&"_"&A2&"_"&C2 -> chara_spy_00001 | E2: わくわく アーニャ | F2: わくわく アーニャ | G2: せいふくのアーニャかわいい？ | H2: UR | I2: PremiumUR | J2: 無 | K2: chara | L2: スペシャル | M2: - | N2: ー | O2: - | P2: =RIGHT(D2,5) -> 00001 | Q2: - | R2: - | S2: 3.44 | T2: 0 | U2: 45922.458 | V2: 390812.5 | W2: ="catchcopy_character_"&text(D2,"000000")&".png" -> catchcopy_character_chara_spy_00001.png | X2: ="enemy_icon_"&K2&"_"&A2&"_"&C2 -> enemy_icon_chara_spy_00001 | Y2: ="boss_icon_"&K2&"_"&A2&"_"&C2 -> boss_icon_chara_spy_00001 | AA2: chara_spy_00001_special | AB2: リリース時 | AC2: 監修通過 | AE2: ▼フレーバーなど下記のシートに記載 GLOW_キャラ名称＆キャラセリフ資料 | AF2: 未 | AG2: 202509010_リリース
A3: spy | B3: {=iferror(INDEX('作品'!D:D,MATCH(A3,'作品'!A:A,0),0),"error")} -> SPY×FAMILY | C3: 00002 | D3: =K3&"_"&A3&"_"&C3 -> chara_spy_00002 | F3: 選定中 | G3: （未FIX）アーニャがんばるます！ | H3: SSR | I3: DropSSR | J3: 無 | K3: chara | L3: スペシャル | M3: - | N3: ー | O3: - | P3: =RIGHT(D3,5) -> 00002 | Q3: - | R3: - | S3: 2.4 | T3: stop無:1.03 | U3: 実装未定 | V3: 390812.5 | W3: ="catchcopy_character_"&text(D3,"000000")&".png" -> catchcopy_character_chara_spy_00002.png | X3: ="enemy_icon_"&K3&"_"&A3&"_"&C3 -> enemy_icon_chara_spy_00002 | Y3: ="boss_icon_"&K3&"_"&A3&"_"&C3 -> boss_icon_chara_spy_00002 | AB3: 1周年 | AC3: 監修中 | AG3: 999999999_リリースキー未定
A4: spy | B4: {=iferror(INDEX('作品'!D:D,MATCH(A4,'作品'!A:A,0),0),"error")} -> SPY×FAMILY | C4: 00101 | D4: =K4&"_"&A4&"_"&C4 -> chara_spy_00101 | E4: <黄昏> ロイド | F4: <黄昏> ロイド | G4: 終わりにしよう | H4: UR | I4: PremiumUR | J4: 黄 | K4: chara | L4: アタック | M4: shageki_1 | N4: Long | O4: shageki_1 | P4: =RIGHT(D4,5) -> 00101 | Q4: 1.64 | R4: 0.83 | S4: 2.50 | T4: 1.33 | U4: 45922.458 | V4: 390812.5 | W4: ="catchcopy_character_"&text(D4,"000000")&".png" -> catchcopy_character_chara_spy_00101.png | X4: ="enemy_icon_"&K4&"_"&A4&"_"&C4 -> enemy_icon_chara_spy_00101 | Y4: ="boss_icon_"&K4&"_"&A4&"_"&C4 -> boss_icon_chara_spy_00101 | Z4: chara_spy_00101_normal | AA4: chara_spy_00101_special | AB4: リリース時 | AC4: 監修通過 | AE4: ▼フレーバーなど下記のシートに記載 GLOW_キャラ名称＆キャラセリフ資料 | AF4: 未 | AG4: 202509010_リリース
A5: spy | B5: {=iferror(INDEX('作品'!D:D,MATCH(A5,'作品'!A:A,0),0),"error")} -> SPY×FAMILY | C5: 00201 | D5: =K5&"_"&A5&"_"&C5 -> chara_spy_00201 | E5: <いばら姫> ヨル | F5: <いばら姫> ヨル | G5: この手が血で汚れても構わない | H5: UR | I5: PremiumUR | J5: 赤 | K5: chara | L5: アタック | M5: zangeki_1 | N5: Middle | O5: dageki_1 | P5: =RIGHT(D5,5) -> 00201 | Q5: 1.42 | R5: stop無:1回目 0.61 | S5: 2.50 | T5: stop有:1回目 0.73 | U5: 45922.458 | V5: 390812.5 | W5: ="catchcopy_character_"&text(D5,"000000")&".png" -> catchcopy_character_chara_spy_00201.png | X5: ="enemy_icon_"&K5&"_"&A5&"_"&C5 -> enemy_icon_chara_spy_00201 | Y5: ="boss_icon_"&K5&"_"&A5&"_"&C5 -> boss_icon_chara_spy_00201 | Z5: chara_spy_00201_normal | AA5: chara_spy_00201_special | AB5: リリース時 | AC5: 監修通過 | AE5: ▼フレーバーなど下記のシートに記載 GLOW_キャラ名称＆キャラセリフ資料 | AF5: 未 | AG5: 202509010_リリース
A6: spy | B6: {=iferror(INDEX('作品'!D:D,MATCH(A6,'作品'!A:A,0),0),"error")} -> SPY×FAMILY | C6: 00301 | D6: =K6&"_"&A6&"_"&C6 -> chara_spy_00301 | E6: ダミアン・デズモンド | F6: ダミアン・デズモンド | G6: いい気になるなよ | H6: SR | I6: DropSR | J6: 無 | K6: chara | L6: スペシャル | M6: - | N6: ー | O6: - | P6: =RIGHT(D6,5) -> 00301 | Q6: - | R6: - | S6: 2.10 | T6: 0 | U6: 45936.625 | V6: 390812.5 | W6: ="catchcopy_character_"&text(D6,"000000")&".png" -> catchcopy_character_chara_spy_00301.png | X6: ="enemy_icon_"&K6&"_"&A6&"_"&C6 -> enemy_icon_chara_spy_00301 | Y6: ="boss_icon_"&K6&"_"&A6&"_"&C6 -> boss_icon_chara_spy_00301 | AA6: chara_spy_00301_special | AB6: SPY×FAMILYいいジャン祭 | AC6: 監修通過 | AE6: ▼フレーバーなど下記のシートに記載 GLOW_キャラ名称＆キャラセリフ資料 | AF6: 未 | AG6: 202510010_SPY×FAMILY
A7: spy | B7: {=iferror(INDEX('作品'!D:D,MATCH(A7,'作品'!A:A,0),0),"error")} -> SPY×FAMILY | C7: 00401 | D7: =K7&"_"&A7&"_"&C7 -> chara_spy_00401 | E7: フランキー・フランクリン | F7: フランキー・フランクリン | G7: 超人外骨格！！ | H7: SR | I7: DropSR | J7: 緑 | K7: chara | L7: ディフェンス | M7: dageki_2 | N7: Short | O7: dageki_2 | P7: =RIGHT(D7,5) -> 00401 | Q7: 1.20 | R7: 0.50 | S7: 2.75 | T7: 1.34 | U7: 45936.625 | V7: 390812.5 | W7: ="catchcopy_character_"&text(D7,"000000")&".png" -> catchcopy_character_chara_spy_00401.png | X7: ="enemy_icon_"&K7&"_"&A7&"_"&C7 -> enemy_icon_chara_spy_00401 | Y7: ="boss_icon_"&K7&"_"&A7&"_"&C7 -> boss_icon_chara_spy_00401 | Z7: chara_spy_00401_normal | AA7: chara_spy_00401_special | AB7: リリース時 | AC7: 監修通過 | AE7: ▼フレーバーなど下記のシートに記載 GLOW_キャラ名称＆キャラセリフ資料 | AF7: 未 | AG7: 202509010_リリース
A8: spy | B8: {=iferror(INDEX('作品'!D:D,MATCH(A8,'作品'!A:A,0),0),"error")} -> SPY×FAMILY | C8: 00501 | D8: =K8&"_"&A8&"_"&C8 -> chara_spy_00501 | E8: ユーリ・ブライア | F8: 姉を想う盲愛 ユーリ・ブライア | G8: 姉さぁーーーん♡ | H8: UR | I8: PremiumUR | J8: 青 | K8: chara | L8: ディフェンス | M8: dageki_1 | N8: Short | O8: - | P8: =RIGHT(D8,5) -> 00501 | Q8: 1.13 | R8: stop有:1回目 0.33 | S8: 2.33 | T8: stop無:1回目 1.17 | U8: 45936.625 | V8: 390812.5 | W8: ="catchcopy_character_"&text(D8,"000000")&".png" -> catchcopy_character_chara_spy_00501.png | X8: ="enemy_icon_"&K8&"_"&A8&"_"&C8 -> enemy_icon_chara_spy_00501 | Y8: ="boss_icon_"&K8&"_"&A8&"_"&C8 -> boss_icon_chara_spy_00501 | AA8: chara_spy_00501_special | AB8: SPY×FAMILYいいジャン祭 | AC8: 監修通過 | AE8: ▼フレーバーなど下記のシートに記載 GLOW_キャラ名称＆キャラセリフ資料 | AF8: 未 | AG8: 202510010_SPY×FAMILY
A9: aka | B9: {=iferror(INDEX('作品'!D:D,MATCH(A9,'作品'!A:A,0),0),"error")} -> ラーメン赤猫 | C9: 00001 | D9: =K9&"_"&A9&"_"&C9 -> chara_aka_00001 | E9: 佐々木 | F9: 佐々木 | G9: ハチワレの猫の佐々木さん | H9: R | I9: PremiumR | J9: 赤 | K9: chara | L9: ディフェンス | M9: dageki_1 | N9: Short | O9: zangeki_1 | P9: =RIGHT(D9,5) -> 00001 | Q9: 1.70 | R9: 0.66 | T9: 1.33 | U9: 45922.458 | V9: 390812.5 | W9: ="catchcopy_character_"&text(D9,"000000")&".png" -> catchcopy_character_chara_aka_00001.png | X9: ="enemy_icon_"&K9&"_"&A9&"_"&C9 -> enemy_icon_chara_aka_00001 | Y9: ="boss_icon_"&K9&"_"&A9&"_"&C9 -> boss_icon_chara_aka_00001 | AA9: chara_aka_00001_special | AB9: リリース時 | AC9: 監修通過 | AE9: ▼フレーバーなど下記のシートに記載 GLOW_キャラ名称＆キャラセリフ資料 | AF9: 未 | AG9: 202509010_リリース
A10: aka | B10: {=iferror(INDEX('作品'!D:D,MATCH(A10,'作品'!A:A,0),0),"error")} -> ラーメン赤猫 | C10: 00101 | D10: =K10&"_"&A10&"_"&C10 -> chara_aka_00101 | E10: 文蔵 | F10: 文蔵 | G10: ラーメン赤猫の職人 | H10: R | I10: PremiumR | J10: 赤 | K10: chara | L10: テクニカル | M10: dageki_1 | N10: Short | O10: zangeki_1 | P10: =RIGHT(D10,5) -> 00101 | Q10: 1.50 | R10: stop無:1回目 0.54 | S10: 4.50 | T10: stop無:1回目 1.37 stop無:2回目 1.63 stop有:3回目 2.67 | U10: 45922.458 | V10: 390812.5 | W10: ="catchcopy_character_"&text(D10,"000000")&".png" -> catchcopy_character_chara_aka_00101.png | X10: ="enemy_icon_"&K10&"_"&A10&"_"&C10 -> enemy_icon_chara_aka_00101 | Y10: ="boss_icon_"&K10&"_"&A10&"_"&C10 -> boss_icon_chara_aka_00101 | Z10: chara_aka_00101_normal | AA10: chara_aka_00101_special | AB10: リリース時 | AC10: 監修通過 | AE10: ▼フレーバーなど下記のシートに記載 GLOW_キャラ名称＆キャラセリフ資料 | AF10: 未 | AG10: 202509010_リリース
A11: aka | B11: {=iferror(INDEX('作品'!D:D,MATCH(A11,'作品'!A:A,0),0),"error")} -> ラーメン赤猫 | C11: 00201 | D11: =K11&"_"&A11&"_"&C11 -> chara_aka_00201 | E11: ハナ | F11: ハナ | G11: ハナのほっこり接客術 | H11: SR | I11: DropSR | J11: 赤 | K11: chara | L11: サポート | Q11: 1.37 | R11: stop有:1回目 0.63 | S11: 2.73 | T11: stop無:1回目 0.6 | U11: 2026年5月中旬のアニマル祭りで実装予定 | V11: 390812.5 | W11: ="catchcopy_character_"&text(D11,"000000")&".png" -> catchcopy_character_chara_aka_00201.png | X11: ="enemy_icon_"&K11&"_"&A11&"_"&C11 -> enemy_icon_chara_aka_00201 | Y11: ="boss_icon_"&K11&"_"&A11&"_"&C11 -> boss_icon_chara_aka_00201 | Z11: chara_aka_00101_normal | AA11: chara_aka_00101_special | AB11: 2026年5月中旬のアニマル祭りで実装予定 | AC11: 監修中 | AE11: ▼フレーバーなど下記のシートに記載 GLOW_キャラ名称＆キャラセリフ資料 | AG11: プラン確認
A12: aka | B12: {=iferror(INDEX('作品'!D:D,MATCH(A12,'作品'!A:A,0),0),"error")} -> ラーメン赤猫 | C12: 00301 | D12: =K12&"_"&A12&"_"&C12 -> chara_aka_00301 | E12: サブ | F12: サブ | H12: SR | I12: DropSR | J12: 緑 | K12: chara | L12: アタック | M12: dageki_1 | O12: shageki_1 | Q12: 1.33 | R12: stop有:1回目 0.55 | S12: 2.53 | T12: stop無:1回目 0.76 stop無:2回目 0.91 stop有:3回目 1.4 | U12: 2026年5月中旬のアニマル祭りで実装予定 | V12: 390812.5 | W12: ="catchcopy_character_"&text(D12,"000000")&".png" -> catchcopy_character_chara_aka_00301.png | X12: ="enemy_icon_"&K12&"_"&A12&"_"&C12 -> enemy_icon_chara_aka_00301 | Y12: ="boss_icon_"&K12&"_"&A12&"_"&C12 -> boss_icon_chara_aka_00301 | Z12: chara_aka_00101_normal | AA12: chara_aka_00101_special | AB12: 2026年5月中旬のアニマル祭りで実装予定 | AC12: 監修中 | AE12: ▼フレーバーなど下記のシートに記載 GLOW_キャラ名称＆キャラセリフ資料 | AG12: プラン確認
A13: rik | B13: {=iferror(INDEX('作品'!D:D,MATCH(A13,'作品'!A:A,0),0),"error")} -> トマトイプーのリコピン | C13: 00001 | D13: =K13&"_"&A13&"_"&C13 -> chara_rik_00001 | E13: リコピン | F13: リコピン | G13: トマト果汁は健康の証 | H13: R | I13: PremiumR | J13: 赤 | K13: chara | L13: アタック | M13: dageki_2 | N13: Short | O13: dageki_2 | P13: =RIGHT(D13,5) -> 00001 | Q13: 1.64 | R13: 0.93 | S13: 4.01 | T13: 1回目：0.83 2回目：1.84 3回目：2.67 | U13: 45922.458 | V13: 390812.5 | W13: ="catchcopy_character_"&text(D13,"000000")&".png" -> catchcopy_character_chara_rik_00001.png | X13: ="enemy_icon_"&K13&"_"&A13&"_"&C13 -> enemy_icon_chara_rik_00001 | Y13: ="boss_icon_"&K13&"_"&A13&"_"&C13 -> boss_icon_chara_rik_00001 | Z13: chara_rik_00001_normal | AA13: chara_rik_00001_special | AB13: リリース時 | AC13: 監修通過 | AE13: ▼フレーバーなど下記のシートに記載 GLOW_キャラ名称＆キャラセリフ資料 | AF13: 未 | AG13: 202509010_リリース
A14: rik | B14: {=iferror(INDEX('作品'!D:D,MATCH(A14,'作品'!A:A,0),0),"error")} -> トマトイプーのリコピン | C14: 00101 | D14: =K14&"_"&A14&"_"&C14 -> chara_rik_00101 | E14: 甘戸 めめ | F14: 甘戸 めめ | G14: モンブランケーキ | H14: R | I14: DropR | J14: 赤 | K14: chara | L14: サポート | M14: dageki_2 | N14: Middle | O14: - | P14: =RIGHT(D14,5) -> 00101 | Q14: 1.57 | R14: 0.87 | S14: 2.67 | T14: stop無:1.00 | U14: 45922.458 | V14: 390812.5 | W14: ="catchcopy_character_"&text(D14,"000000")&".png" -> catchcopy_character_chara_rik_00101.png | X14: ="enemy_icon_"&K14&"_"&A14&"_"&C14 -> enemy_icon_chara_rik_00101 | Y14: ="boss_icon_"&K14&"_"&A14&"_"&C14 -> boss_icon_chara_rik_00101 | Z14: chara_rik_00101_normal | AA14: chara_rik_00101_special | AB14: リリース時 | AC14: 監修通過 | AE14: ▼フレーバーなど下記のシートに記載 GLOW_キャラ名称＆キャラセリフ資料 | AF14: 未 | AG14: 202509010_リリース
A15: dan | B15: {=iferror(INDEX('作品'!D:D,MATCH(A15,'作品'!A:A,0),0),"error")} -> ダンダダン | C15: 00001 | D15: =K15&"_"&A15&"_"&C15 -> chara_dan_00001 | E15: オカルン | F15: オカルン | G15: 友達ができたからだ！ | H15: R | I15: PremiumR | J15: 赤 | K15: chara | L15: ディフェンス | M15: dageki_1 | N15: Short | O15: - | P15: =RIGHT(D15,5) -> 00001 | Q15: 1.43 | R15: 0.53 | S15: 4.00 | T15: 1.66 | U15: 45922.458 | V15: 390812.5 | W15: ="catchcopy_character_"&text(D15,"000000")&".png" -> catchcopy_character_chara_dan_00001.png | X15: ="enemy_icon_"&K15&"_"&A15&"_"&C15 -> enemy_icon_chara_dan_00001 | Y15: ="boss_icon_"&K15&"_"&A15&"_"&C15 -> boss_icon_chara_dan_00001 | Z15: chara_dan_00001_normal | AA15: chara_dan_00001_special | AB15: リリース時 | AC15: 監修通過 | AE15: ▼フレーバーなど下記のシートに記載 GLOW_キャラ名称＆キャラセリフ資料 | AF15: α3 | AG15: 202509010_リリース
A16: dan | B16: {=iferror(INDEX('作品'!D:D,MATCH(A16,'作品'!A:A,0),0),"error")} -> ダンダダン | C16: 00002 | D16: =K16&"_"&A16&"_"&C16 -> chara_dan_00002 | E16: ターボババアの霊力 オカルン | F16: ターボババアの霊力 オカルン | G16: 萎えるぜ | H16: UR | I16: PremiumUR | J16: 青 | K16: chara | L16: アタック | M16: dageki_1 | N16: Middle | O16: dageki_1 | P16: =RIGHT(D16,5) -> 00002 | Q16: 1.84 | R16: stop有:1回目 0.66 stop有:2回目 1.27 | S16: 5.21 | T16: stop有:1回目：1.78 stop有:2回目：3.34 stop無:3回目 3.76 stop無:4回目 3.92 stop無:5回目 4.09 stop無:6回目 4.26 stop無:7回目 4.42 | U16: 45922.458 | V16: 390812.5 | W16: ="catchcopy_character_"&text(D16,"000000")&".png" -> catchcopy_character_chara_dan_00002.png | X16: ="enemy_icon_"&K16&"_"&A16&"_"&C16 -> enemy_icon_chara_dan_00002 | Y16: ="boss_icon_"&K16&"_"&A16&"_"&C16 -> boss_icon_chara_dan_00002 | AA16: chara_dan_00002_special | AB16: リリース時 | AC16: 監修通過 | AE16: ▼フレーバーなど下記のシートに記載 GLOW_キャラ名称＆キャラセリフ資料 | AF16: α3 | AG16: 202509010_リリース
A17: dan | B17: {=iferror(INDEX('作品'!D:D,MATCH(A17,'作品'!A:A,0),0),"error")} -> ダンダダン | C17: 00101 | D17: =K17&"_"&A17&"_"&C17 -> chara_dan_00101 | E17: モモ | F17: モモ | G17: おっしゃあ いけえ!! | H17: SSR | I17: PremiumSSR | J17: 赤 | K17: chara | L17: アタック | M17: dageki_1 | N17: Middle | O17: dageki_1 | P17: =RIGHT(D17,5) -> 00101 | Q17: 1.00 | R17: 0.50 | S17: 2.00 | T17: 1.00 | U17: 45922.458 | V17: 390812.5 | W17: ="catchcopy_character_"&text(D17,"000000")&".png" -> catchcopy_character_chara_dan_00101.png | X17: ="enemy_icon_"&K17&"_"&A17&"_"&C17 -> enemy_icon_chara_dan_00101 | Y17: ="boss_icon_"&K17&"_"&A17&"_"&C17 -> boss_icon_chara_dan_00101 | Z17: chara_dan_00101_normal | AA17: chara_dan_00101_special | AB17: リリース時 | AC17: 監修通過 | AE17: ▼フレーバーなど下記のシートに記載 GLOW_キャラ名称＆キャラセリフ資料 | AF17: 作成済み | AG17: 202509010_リリース
A18: dan | B18: {=iferror(INDEX('作品'!D:D,MATCH(A18,'作品'!A:A,0),0),"error")} -> ダンダダン | C18: 00201 | D18: =K18&"_"&A18&"_"&C18 -> chara_dan_00201 | E18: アイラ | F18: アイラ | G18: 私って美女すぎる | H18: SR | I18: DropSR | J18: 青 | K18: chara | L18: サポート | M18: dageki_2 | N18: Short | O18: - | P18: =RIGHT(D18,5) -> 00201 | Q18: 1.5 | R18: stop有:1回目 0.43 | S18: 2.50 | T18: stop無:1回目：1.33 | U18: 45952.625 | V18: 390812.5 | W18: ="catchcopy_character_"&text(D18,"000000")&".png" -> catchcopy_character_chara_dan_00201.png | X18: ="enemy_icon_"&K18&"_"&A18&"_"&C18 -> enemy_icon_chara_dan_00201 | Y18: ="boss_icon_"&K18&"_"&A18&"_"&C18 -> boss_icon_chara_dan_00201 | Z18: chara_dan_00201_normal | AA18: chara_dan_00201_special | AB18: ダンダダンいいジャン祭 | AC18: 監修通過 | AE18: ▼フレーバーなど下記のシートに記載 GLOW_キャラ名称＆キャラセリフ資料 | AF18: 未 | AG18: 202510020_ダンダダン
A19: dan | B19: {=iferror(INDEX('作品'!D:D,MATCH(A19,'作品'!A:A,0),0),"error")} -> ダンダダン | C19: 00202 | D19: =K19&"_"&A19&"_"&C19 -> chara_dan_00202 | E19: アクさらの愛 アイラ | F19: アクさらの愛 アイラ | G19: お放しなさい!! | H19: UR | I19: PremiumUR | J19: 緑 | K19: chara | L19: アタック | M19: dageki_1 | N19: Middle | O19: dageki_1 | P19: =RIGHT(D19,5) -> 00202 | Q19: 1.37 | R19: 0.45 | S19: 2.44 | T19: stop無:1回目:0.30 stop無:2回目:0.65 stop有:3回目:1.05 | U19: 45952.625 | V19: 390812.5 | W19: ="catchcopy_character_"&text(D19,"000000")&".png" -> catchcopy_character_chara_dan_00202.png | X19: ="enemy_icon_"&K19&"_"&A19&"_"&C19 -> enemy_icon_chara_dan_00202 | Y19: ="boss_icon_"&K19&"_"&A19&"_"&C19 -> boss_icon_chara_dan_00202 | Z19: chara_dan_00202_normal | AA19: chara_dan_00202_special | AB19: ダンダダンいいジャン祭 | AC19: 監修通過 | AE19: ▼フレーバーなど下記のシートに記載 GLOW_キャラ名称＆キャラセリフ資料 | AF19: 未 | AG19: 202510020_ダンダダン
A20: dan | B20: {=iferror(INDEX('作品'!D:D,MATCH(A20,'作品'!A:A,0),0),"error")} -> ダンダダン | C20: 00301 | D20: =K20&"_"&A20&"_"&C20 -> chara_dan_00301 | E20: 招き猫 ターボババア | F20: 招き猫 ターボババア | G20: クソだらあ!! | H20: SR | I20: DropSR | J20: 黄 | K20: chara | L20: ディフェンス | M20: dageki_1 | N20: Short | O20: - | P20: =RIGHT(D20,5) -> 00301 | Q20: 1.60 | R20: stop無:1回目 0.38 stop無:2回目 0.83 stop無:3回目 1.16 | S20: 1.83 | T20: stop無:1回目：0.30 | U20: 45952.625 | V20: 390812.5 | W20: ="catchcopy_character_"&text(D20,"000000")&".png" -> catchcopy_character_chara_dan_00301.png | X20: ="enemy_icon_"&K20&"_"&A20&"_"&C20 -> enemy_icon_chara_dan_00301 | Y20: ="boss_icon_"&K20&"_"&A20&"_"&C20 -> boss_icon_chara_dan_00301 | Z20: chara_dan_00301_normal | AA20: chara_dan_00301_special | AB20: ダンダダンいいジャン祭 | AC20: 監修通過 | AE20: ▼フレーバーなど下記のシートに記載 GLOW_キャラ名称＆キャラセリフ資料 | AF20: 未 | AG20: 202510020_ダンダダン
A21: dan | B21: {=iferror(INDEX('作品'!D:D,MATCH(A21,'作品'!A:A,0),0),"error")} -> ダンダダン | C21: 00501 | D21: =K21&"_"&A21&"_"&C21 -> chara_dan_00501 | E21: 坂田 金太 | F21: 選定中 | H21: SSR | I21: DropSSR | J21: 青 | K21: chara | L21: ディフェンス | M21: dageki_2 | N21: Short | O21: dageki_1 | Q21: 1.6 | R21: 0.92 | S21: 2.67 | T21: stop有:1.05 | U21: 実装未定 | V21: 390812.5 | W21: ="catchcopy_character_"&text(D21,"000000")&".png" -> catchcopy_character_chara_dan_00501.png | X21: ="enemy_icon_"&K21&"_"&A21&"_"&C21 -> enemy_icon_chara_dan_00501 | Y21: ="boss_icon_"&K21&"_"&A21&"_"&C21 -> boss_icon_chara_dan_00501 | AB21: 不明：メダルガシャ追加時 | AF21: 未 | AG21: 999999999_リリースキー未定
A22: dan | B22: {=iferror(INDEX('作品'!D:D,MATCH(A22,'作品'!A:A,0),0),"error")} -> ダンダダン | C22: 00601 | D22: =K22&"_"&A22&"_"&C22 -> chara_dan_00601 | E22: 星子 | F22: 選定中 | H22: UR | I22: PremiumUR | J22: 黄 | K22: chara | L22: サポート | M22: dageki_1 | N22: Short | O22: - | Q22: 1.37 | R22: stop有:0.50 | S22: 2.5 | T22: stop無:1.57 | U22: ハーフアニバ想定 | V22: 390812.5 | W22: ="catchcopy_character_"&text(D22,"000000")&".png" -> catchcopy_character_chara_dan_00601.png | X22: ="enemy_icon_"&K22&"_"&A22&"_"&C22 -> enemy_icon_chara_dan_00601 | Y22: ="boss_icon_"&K22&"_"&A22&"_"&C22 -> boss_icon_chara_dan_00601 | AB22: ハーフアニバーサリー | AF22: 未 | AG22: 999999999_リリースキー未定
A23: gom | B23: {=iferror(INDEX('作品'!D:D,MATCH(A23,'作品'!A:A,0),0),"error")} -> 姫様“拷問”の時間です | C23: 00001 | D23: =K23&"_"&A23&"_"&C23 -> chara_gom_00001 | E23: 囚われの王女 姫様 | F23: 囚われの王女 姫様 | G23: 決して屈しない！ | H23: UR | I23: PremiumUR | J23: 緑 | K23: chara | L23: ディフェンス | M23: dageki_1 | N23: Short | O23: - | P23: =RIGHT(D23,5) -> 00001 | Q23: 1.30 | R23: stop有:1回目 0.50 | S23: 4.00 | T23: stop無:1回目 2.3 | U23: 45922.458 | V23: 390812.5 | W23: ="catchcopy_character_"&text(D23,"000000")&".png" -> catchcopy_character_chara_gom_00001.png | X23: ="enemy_icon_"&K23&"_"&A23&"_"&C23 -> enemy_icon_chara_gom_00001 | Y23: ="boss_icon_"&K23&"_"&A23&"_"&C23 -> boss_icon_chara_gom_00001 | Z23: chara_gom_00001_normal | AA23: chara_gom_00001_special | AB23: リリース時 | AC23: 監修通過 | AE23: ▼フレーバーなど下記のシートに記載 GLOW_キャラ名称＆キャラセリフ資料 | AF23: 作成済み | AG23: 202509010_リリース
A24: gom | B24: {=iferror(INDEX('作品'!D:D,MATCH(A24,'作品'!A:A,0),0),"error")} -> 姫様“拷問”の時間です | C24: 00101 | D24: =K24&"_"&A24&"_"&C24 -> chara_gom_00101 | E24: トーチャー・トルチュール | F24: トーチャー・トルチュール | G24: “拷問”の時間です | H24: SR | I24: PremiumSR | J24: 黄 | K24: chara | L24: テクニカル | M24: dageki_2 | N24: Short | O24: dageki_1 | P24: =RIGHT(D24,5) -> 00101 | Q24: 1.34 | R24: stop無:1回目 0.43 | S24: 4.84 | T24: stop無:1回目 3.00 | U24: 45922.458 | V24: 390812.5 | W24: ="catchcopy_character_"&text(D24,"000000")&".png" -> catchcopy_character_chara_gom_00101.png | X24: ="enemy_icon_"&K24&"_"&A24&"_"&C24 -> enemy_icon_chara_gom_00101 | Y24: ="boss_icon_"&K24&"_"&A24&"_"&C24 -> boss_icon_chara_gom_00101 | Z24: chara_gom_00101_normal | AA24: chara_gom_00101_special | AB24: リリース時 | AC24: 監修通過 | AE24: ▼フレーバーなど下記のシートに記載 GLOW_キャラ名称＆キャラセリフ資料 | AF24: α3 | AG24: 202509010_リリース
A25: gom | B25: {=iferror(INDEX('作品'!D:D,MATCH(A25,'作品'!A:A,0),0),"error")} -> 姫様“拷問”の時間です | C25: 00201 | D25: =K25&"_"&A25&"_"&C25 -> chara_gom_00201 | E25: クロル | F25: クロル | G25: ワンちゃん大量作戦だ☆ | H25: R | I25: DropR | J25: 黄 | K25: chara | L25: アタック | M25: dageki_1 | N25: Long | O25: dageki_1 | P25: =RIGHT(D25,5) -> 00201 | Q25: 1.43 | R25: stop無:1回目 0.40 stop無:2回目 0.60 stop無:3回目 0.80 | S25: 5.00 | T25: stop無:1回目 2.10 stop無:2回目 2.30 stop無:3回目 2.50 stop無:4回目 2.70 stop無:5回目 2.90 stop無:6回目 3.20 stop無:7回目 3.40 stop無:8回目 3.60 stop無:9回目 3.80 | U25: 45922.458 | V25: 390812.5 | W25: ="catchcopy_character_"&text(D25,"000000")&".png" -> catchcopy_character_chara_gom_00201.png | X25: ="enemy_icon_"&K25&"_"&A25&"_"&C25 -> enemy_icon_chara_gom_00201 | Y25: ="boss_icon_"&K25&"_"&A25&"_"&C25 -> boss_icon_chara_gom_00201 | Z25: chara_gom_00201_normal | AA25: chara_gom_00201_special | AB25: リリース時 | AC25: 監修通過 | AE25: ▼フレーバーなど下記のシートに記載 GLOW_キャラ名称＆キャラセリフ資料 | AF25: 未 | AG25: 202509010_リリース
A26: gom | B26: {=iferror(INDEX('作品'!D:D,MATCH(A26,'作品'!A:A,0),0),"error")} -> 姫様“拷問”の時間です | C26: 00301 | D26: =K26&"_"&A26&"_"&C26 -> chara_gom_00301 | E26: 魔王 ゴッドサンダー | F26: 選定中 | H26: UR | I26: PremiumUR | J26: 赤 | K26: chara | L26: アタック | Q26: 1.37 | R26: stop有: 0.55 | S26: 2.67 | T26: stop有: 1.5 | U26: (仮)2026/03/01 15:00:00 | V26: 390812.5 | X26: ="enemy_icon_"&K26&"_"&A26&"_"&C26 -> enemy_icon_chara_gom_00301 | Y26: ="boss_icon_"&K26&"_"&A26&"_"&C26 -> boss_icon_chara_gom_00301 | AB26: 姫様“拷問”の時間ですいいジャン祭 | AG26: 999999999_リリースキー未定
A27: gom | B27: {=iferror(INDEX('作品'!D:D,MATCH(A27,'作品'!A:A,0),0),"error")} -> 姫様“拷問”の時間です | C27: 00401 | D27: =K27&"_"&A27&"_"&C27 -> chara_gom_00401 | E27: マオマオちゃん | F27: 選定中 | H27: SSR | I27: PremiumSSR | J27: 無 | K27: chara | L27: スペシャル | M27: - | Q27: - | R27: - | S27: 2.5 | T27: stop無: 1 | U27: (仮)2026/03/01 15:00:00 | V27: 390812.5 | X27: ="enemy_icon_"&K27&"_"&A27&"_"&C27 -> enemy_icon_chara_gom_00401 | Y27: ="boss_icon_"&K27&"_"&A27&"_"&C27 -> boss_icon_chara_gom_00401 | AB27: 姫様“拷問”の時間ですいいジャン祭 | AG27: 999999999_リリースキー未定
A28: gom | B28: {=iferror(INDEX('作品'!D:D,MATCH(A28,'作品'!A:A,0),0),"error")} -> 姫様“拷問”の時間です | C28: 00501 | D28: =K28&"_"&A28&"_"&C28 -> chara_gom_00501 | E28: 陽鬼 | F28: 選定中 | H28: SR | I28: DropSR | J28: 緑 | K28: chara | L28: アタック | M28: shageki_1 | N28: Long | O28: shageki_1 | P28: Long | Q28: 1.37 | R28: stop有: 0.51 | S28: 2.67 | T28: stop無:1回目 0.5 stop無:2回目 1.3 stop有:3回目 2.08 | U28: (仮)2026/03/01 15:00:00 | V28: 390812.5 | X28: ="enemy_icon_"&K28&"_"&A28&"_"&C28 -> enemy_icon_chara_gom_00501 | Y28: ="boss_icon_"&K28&"_"&A28&"_"&C28 -> boss_icon_chara_gom_00501 | AB28: 姫様“拷問”の時間ですいいジャン祭 | AG28: 999999999_リリースキー未定
A29: gom | B29: {=iferror(INDEX('作品'!D:D,MATCH(A29,'作品'!A:A,0),0),"error")} -> 姫様“拷問”の時間です | C29: 00601 | D29: =K29&"_"&A29&"_"&C29 -> chara_gom_00601 | E29: 陰鬼 | F29: 選定中 | H29: SR | I29: DropSR | J29: 赤 | K29: chara | L29: テクニカル | M29: dageki_2 | N29: Short | O29: dageki_2 | P29: Short | Q29: 1.37 | R29: stop有: 0.33 | S29: 2.33 | T29: stop無:1回目 0.46 stop無:2回目 0.61 stop無:3回目 0.81 stop有:4回目 1.01 | U29: (仮)2026/03/01 15:00:00 | V29: 390812.5 | X29: ="enemy_icon_"&K29&"_"&A29&"_"&C29 -> enemy_icon_chara_gom_00601 | Y29: ="boss_icon_"&K29&"_"&A29&"_"&C29 -> boss_icon_chara_gom_00601 | AB29: 姫様“拷問”の時間ですいいジャン祭 | AG29: 999999999_リリースキー未定
A30: gom | B30: {=iferror(INDEX('作品'!D:D,MATCH(A30,'作品'!A:A,0),0),"error")} -> 姫様“拷問”の時間です | C30: 00701 | D30: =K30&"_"&A30&"_"&C30 -> chara_gom_00701 | E30: カナッジ | F30: 選定中 | H30: SR | I30: DropSR | J30: 青 | K30: chara | L30: ディフェンス | Q30: 1.57 | R30: stop有: 0.42 | S30: 2.27 | T30: stop無: 0.92 | U30: 実装未定 | V30: 390812.5 | X30: ="enemy_icon_"&K30&"_"&A30&"_"&C30 -> enemy_icon_chara_gom_00701 | Y30: ="boss_icon_"&K30&"_"&A30&"_"&C30 -> boss_icon_chara_gom_00701 | AB30: 姫様“拷問”の時間ですいいジャン祭 | AG30: 999999999_リリースキー未定
A31: chi | B31: {=iferror(INDEX('作品'!D:D,MATCH(A31,'作品'!A:A,0),0),"error")} -> チェンソーマン | C31: 00001 | D31: =K31&"_"&A31&"_"&C31 -> chara_chi_00001 | E31: デンジ | F31: デンジ | G31: 股間！しか！狙わねえ！ | H31: R | I31: PremiumR | J31: 緑 | K31: chara | L31: アタック | M31: zangeki_1 | N31: Short | O31: dageki_1 | P31: =RIGHT(D31,5) -> 00001 | Q31: 1.40 | R31: 0.53 | S31: 3.37 | T31: 1.57 | U31: 45922.458 | V31: 390812.5 | W31: ="catchcopy_character_"&text(D31,"000000")&".png" -> catchcopy_character_chara_chi_00001.png | X31: ="enemy_icon_"&K31&"_"&A31&"_"&C31 -> enemy_icon_chara_chi_00001 | Y31: ="boss_icon_"&K31&"_"&A31&"_"&C31 -> boss_icon_chara_chi_00001 | Z31: chara_chi_00001_normal | AA31: chara_chi_00001_special | AB31: リリース時 | AC31: 監修通過 | AE31: ▼フレーバーなど下記のシートに記載 GLOW_キャラ名称＆キャラセリフ資料 必殺技発動前に必殺技名を吹き出しにて表示をする | AF31: 未 | AG31: 202509010_リリース
A32: chi | B32: {=iferror(INDEX('作品'!D:D,MATCH(A32,'作品'!A:A,0),0),"error")} -> チェンソーマン | C32: 00002 | D32: =K32&"_"&A32&"_"&C32 -> chara_chi_00002 | E32: 悪魔が恐れる悪魔 チェンソーマン | F32: 悪魔が恐れる悪魔 チェンソーマン | G32: ぶっ殺さねえとなあ！ | H32: UR | I32: PremiumUR | J32: 黄 | K32: chara | L32: テクニカル | M32: zangeki_1 | N32: Short | O32: zangeki_1 | P32: =RIGHT(D32,5) -> 00002 | Q32: 1.07 | R32: stop無:1回目 0.66 | S32: 3.74 | T32: stop無:1回目 0.53 stop無:2回目 0.70 stop無:3回目 0.90 stop無:4回目 1.03 stop無:5回目 1.23 stop有:6回目 2.62 | U32: 45922.458 | V32: 390812.5 | W32: ="catchcopy_character_"&text(D32,"000000")&".png" -> catchcopy_character_chara_chi_00002.png | X32: ="enemy_icon_"&K32&"_"&A32&"_"&C32 -> enemy_icon_chara_chi_00002 | Y32: ="boss_icon_"&K32&"_"&A32&"_"&C32 -> boss_icon_chara_chi_00002 | Z32: chara_chi_00002_normal | AA32: chara_chi_00002_special | AB32: リリース時 | AC32: 監修通過 | AE32: ▼フレーバーなど下記のシートに記載 GLOW_キャラ名称＆キャラセリフ資料 | AF32: 未 | AG32: 202509010_リリース
A33: chi | B33: {=iferror(INDEX('作品'!D:D,MATCH(A33,'作品'!A:A,0),0),"error")} -> チェンソーマン | C33: 00201 | D33: =K33&"_"&A33&"_"&C33 -> chara_chi_00201 | E33: 早川 アキ | F33: 早川 アキ | G33: 狐の悪魔 | H33: SSR | I33: PremiumSSR | J33: 緑 | K33: chara | L33: アタック | M33: dageki_1 | N33: Short | O33: dageki_2 | P33: =RIGHT(D33,5) -> 00201 | Q33: 1.60 | R33: 0.84 | S33: 2.44 | T33: 1.64 | U33: 45922.458 | V33: 390812.5 | W33: ="catchcopy_character_"&text(D33,"000000")&".png" -> catchcopy_character_chara_chi_00201.png | X33: ="enemy_icon_"&K33&"_"&A33&"_"&C33 -> enemy_icon_chara_chi_00201 | Y33: ="boss_icon_"&K33&"_"&A33&"_"&C33 -> boss_icon_chara_chi_00201 | Z33: chara_chi_00201_normal | AA33: chara_chi_00201_special | AB33: リリース時 | AC33: 監修通過 | AE33: ▼フレーバーなど下記のシートに記載 GLOW_キャラ名称＆キャラセリフ資料 | AF33: 未 | AG33: 202509010_リリース
A34: chi | B34: {=iferror(INDEX('作品'!D:D,MATCH(A34,'作品'!A:A,0),0),"error")} -> チェンソーマン | C34: 00301 | D34: =K34&"_"&A34&"_"&C34 -> chara_chi_00301 | E34: パワー | F34: パワー | G34: 血の匂いじゃ！ | H34: SSR | I34: PremiumSSR | J34: 青 | K34: chara | L34: アタック | M34: dageki_1 | N34: Middle | O34: dageki_1 | P34: 00201 | Q34: 1.50 | R34: 0.58 | S34: 2.67 | T34: 1.00 | U34: 45922.458 | V34: 390812.5 | W34: catchcopy_character_chara_chi_00201.png | X34: ="enemy_icon_"&K34&"_"&A34&"_"&C34 -> enemy_icon_chara_chi_00301 | Y34: ="boss_icon_"&K34&"_"&A34&"_"&C34 -> boss_icon_chara_chi_00301 | Z34: chara_chi_00301_normal | AA34: chara_chi_00301_special | AB34: リリース時 | AC34: 監修通過 | AE34: ▼フレーバーなど下記のシートに記載 GLOW_キャラ名称＆キャラセリフ資料 | AF34: 未 | AG34: 202509010_リリース
A35: chi | B35: {=iferror(INDEX('作品'!D:D,MATCH(A35,'作品'!A:A,0),0),"error")} -> チェンソーマン | C35: 00401 | D35: =K35&"_"&A35&"_"&C35 -> chara_chi_00401 | E35: マキマ | F35: 選定中 | H35: UR | I35: PremiumUR | J35: 調整中 | K35: chara | L35: 調整中 | Q35: - | R35: - | S35: 2.5 | T35: 0 | U35: 実装未定 | V35: 390812.5 | X35: ="enemy_icon_"&K35&"_"&A35&"_"&C35 -> enemy_icon_chara_chi_00401 | Y35: ="boss_icon_"&K35&"_"&A35&"_"&C35 -> boss_icon_chara_chi_00401 | AB35: チェンソーマンいいジャン祭 | AG35: 999999999_リリースキー未定
A36: chi | B36: {=iferror(INDEX('作品'!D:D,MATCH(A36,'作品'!A:A,0),0),"error")} -> チェンソーマン | C36: 00501 | D36: =K36&"_"&A36&"_"&C36 -> chara_chi_00501 | E36: 姫野 | F36: 選定中 | H36: SSR | I36: PremiumSSR | J36: 調整中 | K36: chara | L36: 調整中 | Q36: 1.17 | R36: .5 | S36: 1.87 | T36: stop有:1 | U36: 実装未定 | V36: 390812.5 | X36: ="enemy_icon_"&K36&"_"&A36&"_"&C36 -> enemy_icon_chara_chi_00501 | Y36: ="boss_icon_"&K36&"_"&A36&"_"&C36 -> boss_icon_chara_chi_00501 | AB36: チェンソーマンいいジャン祭 | AG36: 999999999_リリースキー未定
A37: chi | B37: {=iferror(INDEX('作品'!D:D,MATCH(A37,'作品'!A:A,0),0),"error")} -> チェンソーマン | C37: 00601 | D37: =K37&"_"&A37&"_"&C37 -> chara_chi_00601 | E37: 小紅 | F37: 選定中 | H37: SR | I37: DropSR | J37: 調整中 | K37: chara | L37: 調整中 | Q37: 1.30 | R37: stop有:1回目 0.36 | S37: 2.07 | T37: stop有:1回目 1.20 | U37: 実装未定 | V37: 390812.5 | X37: ="enemy_icon_"&K37&"_"&A37&"_"&C37 -> enemy_icon_chara_chi_00601 | Y37: ="boss_icon_"&K37&"_"&A37&"_"&C37 -> boss_icon_chara_chi_00601 | AB37: チェンソーマンいいジャン祭 | AG37: 999999999_リリースキー未定
A38: chi | B38: {=iferror(INDEX('作品'!D:D,MATCH(A38,'作品'!A:A,0),0),"error")} -> チェンソーマン | C38: 00701 | D38: =K38&"_"&A38&"_"&C38 -> chara_chi_00701 | E38: 沢渡 アカネ | F38: 選定中 | H38: SR | I38: DropSR | J38: 調整中 | K38: chara | L38: 調整中 | Q38: 1.2 | R38: 0.27 | S38: 2.27 | T38: stop有:0.86 | U38: 実装未定 | V38: 390812.5 | X38: ="enemy_icon_"&K38&"_"&A38&"_"&C38 -> enemy_icon_chara_chi_00701 | Y38: ="boss_icon_"&K38&"_"&A38&"_"&C38 -> boss_icon_chara_chi_00701 | AB38: チェンソーマンいいジャン祭 | AG38: 999999999_リリースキー未定
A39: chi | B39: {=iferror(INDEX('作品'!D:D,MATCH(A39,'作品'!A:A,0),0),"error")} -> チェンソーマン | C39: 00801 | D39: =K39&"_"&A39&"_"&C39 -> chara_chi_00801 | E39: サムライソード | F39: 選定中 | H39: SR | I39: DropSR | J39: 調整中 | K39: chara | L39: 調整中 | Q39: 1.37 | R39: stop有:1回目0.58 | S39: 2.07 | T39: stop有:1回目0.91 | U39: 実装未定 | V39: 390812.5 | X39: ="enemy_icon_"&K39&"_"&A39&"_"&C39 -> enemy_icon_chara_chi_00801 | Y39: ="boss_icon_"&K39&"_"&A39&"_"&C39 -> boss_icon_chara_chi_00801 | AB39: チェンソーマンいいジャン祭 | AG39: 999999999_リリースキー未定
A40: chi | B40: {=iferror(INDEX('作品'!D:D,MATCH(A40,'作品'!A:A,0),0),"error")} -> チェンソーマン | C40: 00901 | D40: =K40&"_"&A40&"_"&C40 -> chara_chi_00901 | E40: レゼ | F40: 選定中 | H40: UR | K40: chara
A41: bat | B41: {=iferror(INDEX('作品'!D:D,MATCH(A41,'作品'!A:A,0),0),"error")} -> 忘却バッテリー | C41: 00001 | D41: =K41&"_"&A41&"_"&C41 -> chara_bat_00001 | E41: 清峰 葉流火 | F41: 清峰 葉流火 | G41: 負ける気なんて毛頭ない | H41: SR | I41: PremiumSR | J41: 赤 | K41: chara | L41: アタック | M41: dageki_1 | N41: Long | O41: dageki_2 | P41: =RIGHT(D41,5) -> 00001 | Q41: 1.97 | R41: 0.70 | S41: 2.07 | T41: 0.96 | U41: 45922.458 | V41: 390812.5 | W41: ="catchcopy_character_"&text(D41,"000000")&".png" -> catchcopy_character_chara_bat_00001.png | X41: ="enemy_icon_"&K41&"_"&A41&"_"&C41 -> enemy_icon_chara_bat_00001 | Y41: ="boss_icon_"&K41&"_"&A41&"_"&C41 -> boss_icon_chara_bat_00001 | Z41: chara_bat_00001_normal | AA41: chara_bat_00001_special | AB41: リリース時 | AC41: 監修通過 | AE41: ▼フレーバーなど下記のシートに記載 GLOW_キャラ名称＆キャラセリフ資料 | AF41: 未 | AG41: 202509010_リリース
A42: bat | B42: {=iferror(INDEX('作品'!D:D,MATCH(A42,'作品'!A:A,0),0),"error")} -> 忘却バッテリー | C42: 00101 | D42: =K42&"_"&A42&"_"&C42 -> chara_bat_00101 | E42: 要 圭 | F42: 要 圭 | G42: 天才捕手 要圭 | H42: SR | I42: PremiumSR | J42: 赤 | K42: chara | L42: ディフェンス | M42: dageki_1 | N42: Middle | O42: - | P42: =RIGHT(D42,5) -> 00101 | R42: 0.75 | S42: 3.00 | T42: 1.20 | U42: 45922.458 | V42: 390812.5 | W42: ="catchcopy_character_"&text(D42,"000000")&".png" -> catchcopy_character_chara_bat_00101.png | X42: ="enemy_icon_"&K42&"_"&A42&"_"&C42 -> enemy_icon_chara_bat_00101 | Y42: ="boss_icon_"&K42&"_"&A42&"_"&C42 -> boss_icon_chara_bat_00101 | Z42: chara_bat_00101_normal | AA42: chara_bat_00101_special | AB42: リリース時 | AC42: 監修通過 | AE42: ▼フレーバーなど下記のシートに記載 GLOW_キャラ名称＆キャラセリフ資料 | AF42: 未 | AG42: 202509010_リリース
A43: bat | B43: {=iferror(INDEX('作品'!D:D,MATCH(A43,'作品'!A:A,0),0),"error")} -> 忘却バッテリー | C43: 00102 | D43: =K43&"_"&A43&"_"&C43 -> chara_bat_00102 | E43: 智将 要 圭 | F43: 選定中 | H43: UR | I43: PremiumUR | J43: 無 | K43: chara | L43: スペシャル | AG43: プラン確認
A44: bat | B44: {=iferror(INDEX('作品'!D:D,MATCH(A44,'作品'!A:A,0),0),"error")} -> 忘却バッテリー | C44: 00201 | D44: =K44&"_"&A44&"_"&C44 -> chara_bat_00201 | E44: 千早 瞬平 | F44: 選定中 | H44: SR | I44: DropSR | J44: 緑 | K44: chara | AG44: プラン確認
A45: bat | B45: {=iferror(INDEX('作品'!D:D,MATCH(A45,'作品'!A:A,0),0),"error")} -> 忘却バッテリー | C45: 00301 | D45: =K45&"_"&A45&"_"&C45 -> chara_bat_00301 | E45: 藤堂 葵 | F45: 選定中 | H45: SR | I45: DropSR | J45: 青 | K45: chara | AG45: プラン確認
A46: kai | B46: {=iferror(INDEX('作品'!D:D,MATCH(A46,'作品'!A:A,0),0),"error")} -> 怪獣８号 | C46: 00001 | D46: =K46&"_"&A46&"_"&C46 -> chara_kai_00001 | E46: 日比野 カフカ | F46: 日比野 カフカ | G46: 部分変身!! | H46: R | I46: PremiumR | J46: 黄 | K46: chara | L46: アタック | M46: dageki_1 | N46: Short | O46: - | P46: =RIGHT(D46,5) -> 00001 | Q46: 1.83 | R46: 1.00 | S46: 2.33 | T46: 1.33 | U46: 45922.458 | V46: 390812.5 | W46: ="catchcopy_character_"&text(D46,"000000")&".png" -> catchcopy_character_chara_kai_00001.png | X46: ="enemy_icon_"&K46&"_"&A46&"_"&C46 -> enemy_icon_chara_kai_00001 | Y46: ="boss_icon_"&K46&"_"&A46&"_"&C46 -> boss_icon_chara_kai_00001 | AA46: chara_kai_00001_special | AB46: リリース時 | AC46: 監修通過 | AE46: ▼フレーバーなど下記のシートに記載 GLOW_キャラ名称＆キャラセリフ資料 | AF46: 未 | AG46: 202509010_リリース
A47: kai | B47: {=iferror(INDEX('作品'!D:D,MATCH(A47,'作品'!A:A,0),0),"error")} -> 怪獣８号 | C47: 00002 | D47: =K47&"_"&A47&"_"&C47 -> chara_kai_00002 | E47: 隠された英雄の姿 怪獣８号 | F47: 隠された英雄の姿 怪獣８号 | G47: あとは俺に任せろ | H47: UR | I47: PremiumUR | J47: 緑 | K47: chara | L47: アタック | M47: dageki_1 | N47: Short | O47: dageki_2 | P47: =RIGHT(D47,5) -> 00002 | Q47: 1.50 | R47: stop無:1回目 0.54 | S47: 2.40 | T47: stop有:1回目 1.00 stop無:2回目 1.37 stop無:3回目 1.54 stop無:4回目 1.70 stop無:5回目 1.87 stop無:6回目 2.04 | U47: 45922.458 | V47: 390812.5 | W47: ="catchcopy_character_"&text(D47,"000000")&".png" -> catchcopy_character_chara_kai_00002.png | X47: ="enemy_icon_"&K47&"_"&A47&"_"&C47 -> enemy_icon_chara_kai_00002 | Y47: ="boss_icon_"&K47&"_"&A47&"_"&C47 -> boss_icon_chara_kai_00002 | Z47: chara_kai_00002_normal | AA47: chara_kai_00002_special | AB47: リリース時 | AC47: 監修通過 | AE47: ▼フレーバーなど下記のシートに記載 GLOW_キャラ名称＆キャラセリフ資料 | AF47: 未 | AG47: 202509010_リリース
A48: kai | B48: {=iferror(INDEX('作品'!D:D,MATCH(A48,'作品'!A:A,0),0),"error")} -> 怪獣８号 | C48: 00003 | D48: =K48&"_"&A48&"_"&C48 -> chara_kai_00003 | E48: ドレスアップ怪獣８号 | H48: UR | K48: chara
A49: kai | B49: {=iferror(INDEX('作品'!D:D,MATCH(A49,'作品'!A:A,0),0),"error")} -> 怪獣８号 | C49: 00101 | D49: =K49&"_"&A49&"_"&C49 -> chara_kai_00101 | E49: 市川 レノ | F49: 市川 レノ | G49: 仲間のために体張れる男だ!! | H49: SR | I49: PremiumSR | J49: 青 | K49: chara | L49: テクニカル | M49: shageki_1 | N49: Long | O49: shageki_1 | P49: =RIGHT(D49,5) -> 00101 | Q49: 1.40 | R49: stop無:1回目 0.91 | S49: 3.17 | T49: stop無:1回目 1.05 stop無:2回目 1.33 stop無:3回目 1.76 | U49: 45922.458 | V49: 390812.5 | W49: ="catchcopy_character_"&text(D49,"000000")&".png" -> catchcopy_character_chara_kai_00101.png | X49: ="enemy_icon_"&K49&"_"&A49&"_"&C49 -> enemy_icon_chara_kai_00101 | Y49: ="boss_icon_"&K49&"_"&A49&"_"&C49 -> boss_icon_chara_kai_00101 | Z49: chara_kai_00101_normal | AA49: chara_kai_00101_special | AB49: リリース時 | AC49: 監修通過 | AE49: ▼フレーバーなど下記のシートに記載 GLOW_キャラ名称＆キャラセリフ資料 | AF49: 未 | AG49: 202509010_リリース
A50: kai | B50: {=iferror(INDEX('作品'!D:D,MATCH(A50,'作品'!A:A,0),0),"error")} -> 怪獣８号 | C50: 00102 | D50: =K50&"_"&A50&"_"&C50 -> chara_kai_00102 | E50: 識別怪獣兵器6 市川 レノ | F50: 識別怪獣兵器6 市川 レノ | H50: SSR | I50: PremiumSSR | J50: 黄 | K50: chara | L50: テクニカル | U50: 2026/07/上旬 | V50: 390812.5 | W50: ="catchcopy_character_"&text(D50,"000000")&".png" -> catchcopy_character_chara_kai_00102.png | X50: ="enemy_icon_"&K50&"_"&A50&"_"&C50 -> enemy_icon_chara_kai_00102 | Y50: ="boss_icon_"&K50&"_"&A50&"_"&C50 -> boss_icon_chara_kai_00102 | AB50: 怪獣８号 2回目 いいジャン祭 | AG50: プラン確認
A51: kai | B51: {=iferror(INDEX('作品'!D:D,MATCH(A51,'作品'!A:A,0),0),"error")} -> 怪獣８号 | C51: 00201 | D51: =K51&"_"&A51&"_"&C51 -> chara_kai_00201 | E51: 第三部隊隊長 亜白 ミナ | F51: 第三部隊隊長 亜白 ミナ | G51: 解放戦力 96% | H51: UR | I51: PremiumUR | J51: 青 | K51: chara | L51: アタック | M51: shageki_1 | N51: Long | O51: shageki_1 | P51: =RIGHT(D51,5) -> 00201 | Q51: 1.50 | R51: 0.75 | S51: 4.41 | T51: stop無:1回目 1.42 stop無:2回目 1.85 stop無:3回目 2.29 stop無:4回目 2.73 stop有:5回目 3.17 | U51: 45922.458 | V51: 390812.5 | W51: ="catchcopy_character_"&text(D51,"000000")&".png" -> catchcopy_character_chara_kai_00201.png | X51: ="enemy_icon_"&K51&"_"&A51&"_"&C51 -> enemy_icon_chara_kai_00201 | Y51: ="boss_icon_"&K51&"_"&A51&"_"&C51 -> boss_icon_chara_kai_00201 | Z51: chara_kai_00201_normal | AA51: chara_kai_00201_special | AB51: 怪獣８号いいジャン祭 | AC51: 監修通過 | AE51: ▼フレーバーなど下記のシートに記載 GLOW_キャラ名称＆キャラセリフ資料 | AF51: 未 | AG51: 202509010_怪獣8号
A52: kai | B52: {=iferror(INDEX('作品'!D:D,MATCH(A52,'作品'!A:A,0),0),"error")} -> 怪獣８号 | C52: 00202 | D52: =K52&"_"&A52&"_"&C52 -> chara_kai_00202 | E52: 超大型キラー 亜白 ミナ | F52: 選定中 | H52: UR | K52: chara
A53: kai | B53: {=iferror(INDEX('作品'!D:D,MATCH(A53,'作品'!A:A,0),0),"error")} -> 怪獣８号 | C53: 00301 | D53: =K53&"_"&A53&"_"&C53 -> chara_kai_00301 | E53: 四ノ宮 キコル | F53: 四ノ宮 キコル | G53: 隊式斧術1式 落雷 | H53: SSR | I53: PremiumSSR | J53: 黄 | K53: chara | L53: ディフェンス | M53: zangeki_1 | N53: Short | O53: zangeki_1 | P53: =RIGHT(D53,5) -> 00301 | Q53: 2.04 | R53: 0.70 | S53: 3.34 | T53: 1.07 | U53: 45922.458 | V53: 390812.5 | W53: ="catchcopy_character_"&text(D53,"000000")&".png" -> catchcopy_character_chara_kai_00301.png | X53: ="enemy_icon_"&K53&"_"&A53&"_"&C53 -> enemy_icon_chara_kai_00301 | Y53: ="boss_icon_"&K53&"_"&A53&"_"&C53 -> boss_icon_chara_kai_00301 | Z53: chara_kai_00301_normal | AA53: chara_kai_00301_special | AB53: リリース時 | AC53: 監修通過 | AE53: ▼フレーバーなど下記のシートに記載 GLOW_キャラ名称＆キャラセリフ資料 | AF53: 未 | AG53: 202509010_リリース
A54: kai | B54: {=iferror(INDEX('作品'!D:D,MATCH(A54,'作品'!A:A,0),0),"error")} -> 怪獣８号 | C54: 00302 | D54: =K54&"_"&A54&"_"&C54 -> chara_kai_00302 | E54: 識別怪獣兵器4 四ノ宮 キコル | F54: 選定中 | H54: UR | K54: chara
A55: kai | B55: {=iferror(INDEX('作品'!D:D,MATCH(A55,'作品'!A:A,0),0),"error")} -> 怪獣８号 | C55: 00401 | D55: =K55&"_"&A55&"_"&C55 -> chara_kai_00401 | E55: 保科 宗四郎 | F55: 保科 宗四郎 | G55: 6式 八重討ち | H55: SSR | I55: PremiumSSR | J55: 青 | K55: chara | L55: アタック | M55: zangeki_1 | N55: Short | O55: zangeki_1 | Q55: 1.27 | R55: stop有:1回目 0.43 | S55: 2.67 | T55: stop無:1回目 0.25 stop無:2回目 0.91 stop無:3回目 1.05 stop無:4回目 1.15 stop有:5回目 1.66 | U55: 45922.458 | V55: 390812.5 | X55: ="enemy_icon_"&K55&"_"&A55&"_"&C55 -> enemy_icon_chara_kai_00401 | Y55: ="boss_icon_"&K55&"_"&A55&"_"&C55 -> boss_icon_chara_kai_00401 | Z55: chara_kai_00401_normal | AA55: chara_kai_00401_special | AB55: 怪獣８号いいジャン祭 | AC55: 監修通過 | AE55: ▼フレーバーなど下記のシートに記載 GLOW_キャラ名称＆キャラセリフ資料 | AG55: 202509010_怪獣8号
A56: kai | B56: {=iferror(INDEX('作品'!D:D,MATCH(A56,'作品'!A:A,0),0),"error")} -> 怪獣８号 | C56: 00501 | D56: =K56&"_"&A56&"_"&C56 -> chara_kai_00501 | E56: 四ノ宮 功 | F56: 四ノ宮 功 | G56: 隊式格闘術2式 発破 | H56: SR | I56: DropSR | J56: 黄 | K56: chara | L56: アタック | M56: dageki_1 | N56: Short | O56: dageki_1 | Q56: 1.97 | R56: 1.10 | S56: 2.67 | T56: 1.62 | U56: 45922.458 | V56: 390812.5 | X56: ="enemy_icon_"&K56&"_"&A56&"_"&C56 -> enemy_icon_chara_kai_00501 | Y56: ="boss_icon_"&K56&"_"&A56&"_"&C56 -> boss_icon_chara_kai_00501 | Z56: chara_kai_00501_normal | AA56: chara_kai_00501_special | AB56: 怪獣８号いいジャン祭 | AC56: 監修通過 | AE56: ▼フレーバーなど下記のシートに記載 GLOW_キャラ名称＆キャラセリフ資料 | AG56: 202509010_怪獣8号
A57: kai | B57: {=iferror(INDEX('作品'!D:D,MATCH(A57,'作品'!A:A,0),0),"error")} -> 怪獣８号 | C57: 00601 | D57: =K57&"_"&A57&"_"&C57 -> chara_kai_00601 | E57: 古橋 伊春 | F57: 古橋 伊春 | G57: 俺がお前を守るんだ バカヤロー | H57: SR | I57: DropSR | J57: 緑 | K57: chara | L57: ディフェンス | M57: shageki_1 | N57: Middle | O57: - | Q57: 1.37 | R57: stop有:1回目 0.71 | S57: 1.83 | T57: stop無:1回目 0.93 | U57: 45922.458 | V57: 390812.5 | X57: ="enemy_icon_"&K57&"_"&A57&"_"&C57 -> enemy_icon_chara_kai_00601 | Y57: ="boss_icon_"&K57&"_"&A57&"_"&C57 -> boss_icon_chara_kai_00601 | Z57: chara_kai_00601_normal | AA57: chara_kai_00601_special | AB57: 怪獣８号いいジャン祭 | AC57: 監修通過 | AE57: ▼フレーバーなど下記のシートに記載 GLOW_キャラ名称＆キャラセリフ資料 | AG57: 202509010_怪獣8号
A58: kai | B58: {=iferror(INDEX('作品'!D:D,MATCH(A58,'作品'!A:A,0),0),"error")} -> 怪獣８号 | C58: 00701 | D58: =K58&"_"&A58&"_"&C58 -> chara_kai_00701 | E58: 識別怪獣兵器1 鳴海 弦 | F58: 識別怪獣兵器1 鳴海 弦 | H58: UR | I58: PremiumUR | J58: 黄 | K58: chara | L58: アタック | U58: 2026/07/上旬 | V58: 390812.5 | W58: ="catchcopy_character_"&text(D58,"000000")&".png" -> catchcopy_character_chara_kai_00701.png | X58: ="enemy_icon_"&K58&"_"&A58&"_"&C58 -> enemy_icon_chara_kai_00701 | Y58: ="boss_icon_"&K58&"_"&A58&"_"&C58 -> boss_icon_chara_kai_00701 | AB58: 怪獣８号 2回目 いいジャン祭 | AG58: プラン確認
A59: kai | B59: {=iferror(INDEX('作品'!D:D,MATCH(A59,'作品'!A:A,0),0),"error")} -> 怪獣８号 | C59: 00801 | D59: =K59&"_"&A59&"_"&C59 -> chara_kai_00801 | E59: 東雲 りん | F59: 選定中 | H59: SR | I59: DropSR | K59: chara | L59: ディフェンス | U59: 2026/07/上旬 | V59: 390812.5 | W59: ="catchcopy_character_"&text(D59,"000000")&".png" -> catchcopy_character_chara_kai_00801.png | X59: ="enemy_icon_"&K59&"_"&A59&"_"&C59 -> enemy_icon_chara_kai_00801 | Y59: ="boss_icon_"&K59&"_"&A59&"_"&C59 -> boss_icon_chara_kai_00801 | AB59: 怪獣８号 2回目 いいジャン祭 | AG59: プラン確認
A60: kai | B60: {=iferror(INDEX('作品'!D:D,MATCH(A60,'作品'!A:A,0),0),"error")} -> 怪獣８号 | C60: 00901 | D60: =K60&"_"&A60&"_"&C60 -> chara_kai_00901 | E60: 四ノ宮ヒカリ | F60: 選定中 | H60: SR | I60: DropSR | K60: chara | L60: スペシャル | U60: 2026/07/上旬 | V60: 390812.5 | W60: ="catchcopy_character_"&text(D60,"000000")&".png" -> catchcopy_character_chara_kai_00901.png | X60: ="enemy_icon_"&K60&"_"&A60&"_"&C60 -> enemy_icon_chara_kai_00901 | Y60: ="boss_icon_"&K60&"_"&A60&"_"&C60 -> boss_icon_chara_kai_00901 | AB60: 怪獣８号 2回目 いいジャン祭 | AG60: プラン確認
A61: kai | B61: {=iferror(INDEX('作品'!D:D,MATCH(A61,'作品'!A:A,0),0),"error")} -> 怪獣８号 | C61: 01001 | D61: =K61&"_"&A61&"_"&C61 -> chara_kai_01001 | E61: 怪獣15号 | F61: 選定中 | H61: SR | K61: chara
A62: yuw | B62: {=iferror(INDEX('作品'!D:D,MATCH(A62,'作品'!A:A,0),0),"error")} -> 2.5次元の誘惑 | C62: 00001 | D62: =K62&"_"&A62&"_"&C62 -> chara_yuw_00001 | E62: リリエルに捧ぐ愛 天乃 リリサ | F62: リリエルに捧ぐ愛 天乃 リリサ | G62: リリエル爆破!! | H62: UR | I62: PremiumUR | J62: 黄 | K62: chara | L62: アタック | M62: dageki_2 | N62: Middle | O62: - | P62: =RIGHT(D62,5) -> 00001 | Q62: 1.54 | R62: 0.50 | S62: 3.67 | T62: 2.44 | U62: 45922.458 | V62: 390812.5 | W62: ="catchcopy_character_"&text(D62,"000000")&".png" -> catchcopy_character_chara_yuw_00001.png | X62: ="enemy_icon_"&K62&"_"&A62&"_"&C62 -> enemy_icon_chara_yuw_00001 | Y62: ="boss_icon_"&K62&"_"&A62&"_"&C62 -> boss_icon_chara_yuw_00001 | Z62: chara_yuw_00001_normal | AA62: chara_yuw_00001_special | AB62: リリース時 | AC62: 監修通過 | AE62: ▼フレーバーなど下記のシートに記載 GLOW_キャラ名称＆キャラセリフ資料 | AF62: 未 | AG62: 202509010_リリース
A63: yuw | B63: {=iferror(INDEX('作品'!D:D,MATCH(A63,'作品'!A:A,0),0),"error")} -> 2.5次元の誘惑 | C63: 00002 | D63: =K63&"_"&A63&"_"&C63 -> chara_yuw_00002 | E63: 天乃 リリサ(クリスマス) | F63: 選定中 | H63: UR | I63: PremiumUR | J63: 緑 | K63: chara | L63: サポート | U63: 実装未定 | V63: 390812.5 | X63: ="enemy_icon_"&K63&"_"&A63&"_"&C63 -> enemy_icon_chara_yuw_00002 | Y63: ="boss_icon_"&K63&"_"&A63&"_"&C63 -> boss_icon_chara_yuw_00002 | AB63: 不明 | AG63: 999999999_リリースキー未定
A64: yuw | B64: {=iferror(INDEX('作品'!D:D,MATCH(A64,'作品'!A:A,0),0),"error")} -> 2.5次元の誘惑 | C64: 00101 | D64: =K64&"_"&A64&"_"&C64 -> chara_yuw_00101 | E64: コスプレに託す乙女心 橘 美花莉 | F64: コスプレに託す乙女心 橘 美花莉 | G64: 私を見てよ！ | H64: UR | I64: PremiumUR | J64: 緑 | K64: chara | L64: テクニカル | M64: dageki_1 | N64: Short | O64: - | P64: =RIGHT(D64,5) -> 00101 | Q64: 1.50 | R64: stop無:1回目 0.45 stop無:2回目 0.55 stop無:3回目 0.67 stop無:4回目 0.77 stop無:5回目 0.90 stop無:6回目 0.95 | S64: 3.50 | T64: stop無: 1回目 3.20 | U64: 45922.458 | V64: 390812.5 | W64: ="catchcopy_character_"&text(D64,"000000")&".png" -> catchcopy_character_chara_yuw_00101.png | X64: ="enemy_icon_"&K64&"_"&A64&"_"&C64 -> enemy_icon_chara_yuw_00101 | Y64: ="boss_icon_"&K64&"_"&A64&"_"&C64 -> boss_icon_chara_yuw_00101 | Z64: chara_yuw_00101_normal | AA64: chara_yuw_00101_special | AB64: リリース時 | AC64: 監修通過 | AE64: ▼フレーバーなど下記のシートに記載 GLOW_キャラ名称＆キャラセリフ資料 | AF64: 未 | AG64: 202509010_リリース
A65: yuw | B65: {=iferror(INDEX('作品'!D:D,MATCH(A65,'作品'!A:A,0),0),"error")} -> 2.5次元の誘惑 | C65: 00102 | D65: =K65&"_"&A65&"_"&C65 -> chara_yuw_00102 | E65: クリスマス 橘 美花莉 | F65: 愛届ける聖夜のサンタ 橘 美花莉 | G65: プレゼントは私だよ〜♡ | H65: UR | I65: FestivalUR | J65: 緑 | K65: chara | L65: サポート | M65: dageki_1 | N65: Short | O65: - | Q65: 1.67 | R65: stop有:1回目 0.50 | S65: 3.5 | T65: stop無: 1回目 2.00 | U65: 46013.5 | V65: 390812.5 | W65: ="catchcopy_character_"&text(D65,"000000")&".png" -> catchcopy_character_chara_yuw_00102.png | X65: ="enemy_icon_"&K65&"_"&A65&"_"&C65 -> enemy_icon_chara_yuw_00102 | Y65: ="boss_icon_"&K65&"_"&A65&"_"&C65 -> boss_icon_chara_yuw_00102 | Z65: chara_yuw_00101_normal | AA65: chara_yuw_00101_special | AB65: 2025年 クリスマス限定ガシャ | AC65: 監修通過 | AE65: ▼フレーバーなど下記のシートに記載 GLOW_キャラ名称＆キャラセリフ資料 | AF65: 未 | AG65: 202512015_クリスマス
A66: yuw | B66: {=iferror(INDEX('作品'!D:D,MATCH(A66,'作品'!A:A,0),0),"error")} -> 2.5次元の誘惑 | C66: 00201 | D66: =K66&"_"&A66&"_"&C66 -> chara_yuw_00201 | E66: 羽生 まゆり | F66: 羽生 まゆり | G66: 先生がもう一肌脱ぐしかないわね | H66: SSR | I66: PremiumSSR | J66: 青 | K66: chara | L66: テクニカル | M66: dageki_2 | N66: Short | O66: dageki_1 | P66: =RIGHT(D66,5) -> 00201 | Q66: 1.06 | R66: 0.34 | S66: 4.67 | T66: 3.50 | U66: 45986.625 | V66: 390812.5 | W66: ="catchcopy_character_"&text(D66,"000000")&".png" -> catchcopy_character_chara_yuw_00201.png | X66: ="enemy_icon_"&K66&"_"&A66&"_"&C66 -> enemy_icon_chara_yuw_00201 | Y66: ="boss_icon_"&K66&"_"&A66&"_"&C66 -> boss_icon_chara_yuw_00201 | AB66: 2.5次元の誘惑いいジャン祭 | AC66: 監修通過 | AE66: ▼フレーバーなど下記のシートに記載 GLOW_キャラ名称＆キャラセリフ資料 | AF66: 未 | AG66: 202511020_【クリスマス】2.5次元の誘惑
A67: yuw | B67: {=iferror(INDEX('作品'!D:D,MATCH(A67,'作品'!A:A,0),0),"error")} -> 2.5次元の誘惑 | C67: 00301 | D67: =K67&"_"&A67&"_"&C67 -> chara_yuw_00301 | E67: 勇気を纏うコスプレ 乃愛 | F67: 勇気を纏うコスプレ 乃愛 | G67: 命に換えてもお守りします | H67: UR | I67: PremiumUR | J67: 青 | K67: chara | L67: サポート | M67: dageki_2 | N67: Short | O67: - | P67: =RIGHT(D67,5) -> 00301 | Q67: 1.57 | R67: stop無:1回目 0.50 stop無:2回目 1.00 | S67: 3.50 | T67: stop無: 1回目 3.20 | U67: 45986.625 | V67: 390812.5 | W67: ="catchcopy_character_"&text(D67,"000000")&".png" -> catchcopy_character_chara_yuw_00301.png | X67: ="enemy_icon_"&K67&"_"&A67&"_"&C67 -> enemy_icon_chara_yuw_00301 | Y67: ="boss_icon_"&K67&"_"&A67&"_"&C67 -> boss_icon_chara_yuw_00301 | Z67: chara_yuw_00301_normal | AA67: chara_yuw_00301_special | AB67: 2.5次元の誘惑いいジャン祭 | AC67: 監修通過 | AE67: ▼フレーバーなど下記のシートに記載 GLOW_キャラ名称＆キャラセリフ資料 | AF67: 未 | AG67: 202511020_【クリスマス】2.5次元の誘惑
A68: yuw | B68: {=iferror(INDEX('作品'!D:D,MATCH(A68,'作品'!A:A,0),0),"error")} -> 2.5次元の誘惑 | C68: 00401 | D68: =K68&"_"&A68&"_"&C68 -> chara_yuw_00401 | E68: 伝えたいウチの想い 喜咲 アリア | F68: 伝えたいウチの想い 喜咲 アリア | G68: アタシに任せてよ!! | H68: UR | I68: PremiumUR | J68: 赤 | K68: chara | L68: ディフェンス | M68: dageki_2 | N68: Short | O68: zangeki_1 | P68: =RIGHT(D68,5) -> 00401 | Q68: 1.17 | R68: 0.34 | S68: 2.67 | T68: 1.64 | U68: 45986.625 | V68: 390812.5 | W68: ="catchcopy_character_"&text(D68,"000000")&".png" -> catchcopy_character_chara_yuw_00401.png | X68: ="enemy_icon_"&K68&"_"&A68&"_"&C68 -> enemy_icon_chara_yuw_00401 | Y68: ="boss_icon_"&K68&"_"&A68&"_"&C68 -> boss_icon_chara_yuw_00401 | AB68: 2.5次元の誘惑いいジャン祭 | AC68: 監修通過 | AE68: ▼フレーバーなど下記のシートに記載 GLOW_キャラ名称＆キャラセリフ資料 | AF68: 未 | AG68: 202511020_【クリスマス】2.5次元の誘惑
A69: yuw | B69: {=iferror(INDEX('作品'!D:D,MATCH(A69,'作品'!A:A,0),0),"error")} -> 2.5次元の誘惑 | C69: 00501 | D69: =K69&"_"&A69&"_"&C69 -> chara_yuw_00501 | E69: 753♡ | F69: 753♡ | G69: どっちがコスプレを愛してる？ | H69: SR | I69: DropSR | J69: 赤 | K69: chara | L69: サポート | M69: dageki_2 | N69: Short | O69: - | P69: =RIGHT(D69,5) -> 00501 | Q69: 1.24 | R69: stop有:1回目 0.43 | S69: 2.17 | T69: stop無: 1回目 1.50 | U69: 45986.625 | V69: 390812.5 | W69: ="catchcopy_character_"&text(D69,"000000")&".png" -> catchcopy_character_chara_yuw_00501.png | X69: ="enemy_icon_"&K69&"_"&A69&"_"&C69 -> enemy_icon_chara_yuw_00501 | Y69: ="boss_icon_"&K69&"_"&A69&"_"&C69 -> boss_icon_chara_yuw_00501 | Z69: chara_yuw_00501_normal | AA69: chara_yuw_00501_special | AB69: 2.5次元の誘惑いいジャン祭 | AC69: 監修通過 | AE69: ▼フレーバーなど下記のシートに記載 GLOW_キャラ名称＆キャラセリフ資料 | AF69: 未 | AG69: 202511020_【クリスマス】2.5次元の誘惑
A70: yuw | B70: {=iferror(INDEX('作品'!D:D,MATCH(A70,'作品'!A:A,0),0),"error")} -> 2.5次元の誘惑 | C70: 00502 | D70: =K70&"_"&A70&"_"&C70 -> chara_yuw_00502 | E70: 753♡(魔女コスプレ) | F70: 選定中 | H70: UR | I70: PremiumUR | J70: 黄 | K70: chara | L70: テクニカル | U70: 実装未定 | V70: 390812.5 | X70: ="enemy_icon_"&K70&"_"&A70&"_"&C70 -> enemy_icon_chara_yuw_00502 | Y70: ="boss_icon_"&K70&"_"&A70&"_"&C70 -> boss_icon_chara_yuw_00502 | AB70: 不明 | AE70: ▼フレーバーなど下記のシートに記載 GLOW_キャラ名称＆キャラセリフ資料 | AG70: 999999999_リリースキー未定
A71: yuw | B71: {=iferror(INDEX('作品'!D:D,MATCH(A71,'作品'!A:A,0),0),"error")} -> 2.5次元の誘惑 | C71: 00601 | D71: =K71&"_"&A71&"_"&C71 -> chara_yuw_00601 | E71: 奥村 正宗 | F71: 奥村 正宗 | G71: 事実だけ言ってやる!! | H71: SR | I71: DropSR | J71: 黄 | K71: chara | L71: ディフェンス | M71: dageki_1 | N71: Short | O71: - | P71: =RIGHT(D71,5) -> 00601 | Q71: 1.20 | R71: 0.67 | S71: 1.84 | T71: stop無: 1回目 0.68 | U71: 45986.625 | V71: 390812.5 | W71: ="catchcopy_character_"&text(D71,"000000")&".png" -> catchcopy_character_chara_yuw_00601.png | X71: ="enemy_icon_"&K71&"_"&A71&"_"&C71 -> enemy_icon_chara_yuw_00601 | Y71: ="boss_icon_"&K71&"_"&A71&"_"&C71 -> boss_icon_chara_yuw_00601 | Z71: chara_yuw_00601_normal | AA71: chara_yuw_00601_special | AB71: 2.5次元の誘惑いいジャン祭 | AC71: 監修通過 | AE71: ▼フレーバーなど下記のシートに記載 GLOW_キャラ名称＆キャラセリフ資料 | AF71: 未 | AG71: 202511020_【クリスマス】2.5次元の誘惑
A72: sur | B72: {=iferror(INDEX('作品'!D:D,MATCH(A72,'作品'!A:A,0),0),"error")} -> 魔都精兵のスレイブ | C72: 00001 | D72: =K72&"_"&A72&"_"&C72 -> chara_sur_00001 | E72: 和倉 優希 | F72: 和倉 優希 | G72: 張り切っちゃうぜ！ | H72: R | I72: PremiumR | J72: 緑 | K72: chara | L72: サポート | M72: dageki_2 | N72: Short | O72: - | P72: =RIGHT(D72,5) -> 00001 | Q72: 1.17 | R72: stop有:1回目 0.30 | S72: 2.80 | T72: stop無:1回目 2.00 | U72: 45922.458 | V72: 390812.5 | W72: ="catchcopy_character_"&text(D72,"000000")&".png" -> catchcopy_character_chara_sur_00001.png | X72: ="enemy_icon_"&K72&"_"&A72&"_"&C72 -> enemy_icon_chara_sur_00001 | Y72: ="boss_icon_"&K72&"_"&A72&"_"&C72 -> boss_icon_chara_sur_00001 | AA72: chara_sur_00001_special | AB72: リリース時 | AC72: 監修通過 | AE72: ▼フレーバーなど下記のシートに記載 GLOW_キャラ名称＆キャラセリフ資料 | AF72: 未 | AG72: 202509010_リリース
A73: sur | B73: {=iferror(INDEX('作品'!D:D,MATCH(A73,'作品'!A:A,0),0),"error")} -> 魔都精兵のスレイブ | C73: 00101 | D73: =K73&"_"&A73&"_"&C73 -> chara_sur_00101 | E73: 誇り高き魔都の剣姫 羽前京香 | F73: 誇り高き魔都の剣姫 羽前 京香 | G73: 乱れ山桜 | H73: UR | I73: PremiumUR | J73: 緑 | K73: chara | L73: アタック | M73: zangeki_1 | N73: Middle | O73: zangeki_1 | P73: =RIGHT(D73,5) -> 00101 | Q73: 1.40 | R73: stop無:1回目 0.33 | S73: 2.67 | T73: stop無:1回目 0.40 stop無:2回目 0.60 stop無:3回目 0.80 stop無:4回目 0.90 stop無:5回目 1.03 stop有:6回目 1.57 | U73: 45922.458 | V73: 390812.5 | W73: ="catchcopy_character_"&text(D73,"000000")&".png" -> catchcopy_character_chara_sur_00101.png | X73: ="enemy_icon_"&K73&"_"&A73&"_"&C73 -> enemy_icon_chara_sur_00101 | Y73: ="boss_icon_"&K73&"_"&A73&"_"&C73 -> boss_icon_chara_sur_00101 | Z73: chara_sur_00101_normal | AA73: chara_sur_00101_special | AB73: リリース時 | AC73: 監修通過 | AE73: ▼フレーバーなど下記のシートに記載 GLOW_キャラ名称＆キャラセリフ資料 | AF73: 未 | AG73: 202509010_リリース
A74: sur | B74: {=iferror(INDEX('作品'!D:D,MATCH(A74,'作品'!A:A,0),0),"error")} -> 魔都精兵のスレイブ | C74: 00201 | D74: =K74&"_"&A74&"_"&C74 -> chara_sur_00201 | E74: 東 日万凛 | F74: 東 日万凛 | G74: 武装小町 | H74: SR | I74: PremiumSR | J74: 青 | K74: chara | L74: アタック | M74: shageki_1 | N74: Short | O74: shageki_1 | P74: =RIGHT(D74,5) -> 00201 | Q74: 1.47 | R74: stop無:1回目 0.37 | S74: 2.67 | T74: stop無:1回目 0.74 stop無:2回目 0.92 stop無:3回目 1.1 stop無:4回目 1.28 stop無:5回目 1.45 stop無:6回目 1.65 stop有:7回目 1.84 | U74: 45922.458 | V74: 390812.5 | W74: ="catchcopy_character_"&text(D74,"000000")&".png" -> catchcopy_character_chara_sur_00201.png | X74: ="enemy_icon_"&K74&"_"&A74&"_"&C74 -> enemy_icon_chara_sur_00201 | Y74: ="boss_icon_"&K74&"_"&A74&"_"&C74 -> boss_icon_chara_sur_00201 | AA74: chara_sur_00101_special | AB74: リリース時 | AC74: 監修通過 | AE74: ▼フレーバーなど下記のシートに記載 GLOW_キャラ名称＆キャラセリフ資料 | AF74: 未 | AG74: 202509010_リリース
A75: sur | B75: {=iferror(INDEX('作品'!D:D,MATCH(A75,'作品'!A:A,0),0),"error")} -> 魔都精兵のスレイブ | C75: 00301 | D75: =K75&"_"&A75&"_"&C75 -> chara_sur_00301 | E75: 駿河 朱々 | F75: 駿河 朱々 | G75: 玉体革命 | H75: SR | I75: PremiumSR | J75: 黄 | K75: chara | L75: ディフェンス | M75: dageki_1 | N75: Short | O75: dageki_2 | P75: =RIGHT(D75,5) -> 00301 | Q75: 1.56 | R75: 0.66 | S75: 1.91 | T75: 0.73 | U75: 45922.458 | V75: 390812.5 | W75: ="catchcopy_character_"&text(D75,"000000")&".png" -> catchcopy_character_chara_sur_00301.png | X75: ="enemy_icon_"&K75&"_"&A75&"_"&C75 -> enemy_icon_chara_sur_00301 | Y75: ="boss_icon_"&K75&"_"&A75&"_"&C75 -> boss_icon_chara_sur_00301 | Z75: chara_sur_00301_normal | AA75: chara_sur_00301_special | AB75: リリース時 | AC75: 監修通過 | AE75: ▼フレーバーなど下記のシートに記載 GLOW_キャラ名称＆キャラセリフ資料 | AF75: 未 | AG75: 202509010_リリース
A76: sur | B76: {=iferror(INDEX('作品'!D:D,MATCH(A76,'作品'!A:A,0),0),"error")} -> 魔都精兵のスレイブ | C76: 00401 | D76: =K76&"_"&A76&"_"&C76 -> chara_sur_00401 | E76: 大川村 寧 | F76: 大川村 寧 | G76: きっと見つける | H76: SR | I76: DropSR | J76: 無 | K76: chara | L76: スペシャル | M76: - | N76: ー | O76: - | P76: =RIGHT(D76,5) -> 00401 | Q76: - | R76: - | S76: 2.50 | T76: 0 | U76: 45922.458 | V76: 390812.5 | W76: ="catchcopy_character_"&text(D76,"000000")&".png" -> catchcopy_character_chara_sur_00401.png | X76: ="enemy_icon_"&K76&"_"&A76&"_"&C76 -> enemy_icon_chara_sur_00401 | Y76: ="boss_icon_"&K76&"_"&A76&"_"&C76 -> boss_icon_chara_sur_00401 | AA76: chara_sur_00401_special | AB76: リリース時 | AC76: 監修通過 | AE76: ▼フレーバーなど下記のシートに記載 GLOW_キャラ名称＆キャラセリフ資料 | AF76: 未 | AG76: 202509010_リリース
A77: sur | B77: {=iferror(INDEX('作品'!D:D,MATCH(A77,'作品'!A:A,0),0),"error")} -> 魔都精兵のスレイブ | C77: 00501 | D77: =K77&"_"&A77&"_"&C77 -> chara_sur_00501 | E77: 出雲 天花 | F77: 空間を操る六番組組長 出雲 天花 | G77: 天御鳥命 | H77: UR | I77: PremiumUR | J77: 黄 | K77: chara | L77: テクニカル | M77: dageki_1 | N77: Long | O77: dageki_1 | P77: =RIGHT(D77,5) -> 00501 | Q77: 1.71 | R77: stop有:1回目 0.93 | S77: 2.67 | T77: stop有:1回目 1.53 | U77: 45999.5 | V77: 390812.5 | W77: ="catchcopy_character_"&text(D77,"000000")&".png" -> catchcopy_character_chara_sur_00501.png | X77: ="enemy_icon_"&K77&"_"&A77&"_"&C77 -> enemy_icon_chara_sur_00501 | Y77: ="boss_icon_"&K77&"_"&A77&"_"&C77 -> boss_icon_chara_sur_00501 | AB77: 魔都精兵のスレイブいいジャン祭 | AC77: 監修通過 | AF77: 未 | AG77: 202512010_魔都精兵のスレイブ
A78: sur | B78: {=iferror(INDEX('作品'!D:D,MATCH(A78,'作品'!A:A,0),0),"error")} -> 魔都精兵のスレイブ | C78: 00601 | D78: =K78&"_"&A78&"_"&C78 -> chara_sur_00601 | E78: 東 八千穂 | F78: 東 八千穂 | G78: 東の辰刻 | H78: SSR | I78: PremiumSSR | J78: 赤 | K78: chara | L78: テクニカル | M78: shageki_1 | N78: Middle | O78: dageki_1 | P78: =RIGHT(D78,5) -> 00601 | Q78: 1.64 | R78: stop有:1回目 0.75 | S78: 3.34 | T78: stop有:1回目 1.2 | U78: 45999.5 | V78: 390812.5 | W78: ="catchcopy_character_"&text(D78,"000000")&".png" -> catchcopy_character_chara_sur_00601.png | X78: ="enemy_icon_"&K78&"_"&A78&"_"&C78 -> enemy_icon_chara_sur_00601 | Y78: ="boss_icon_"&K78&"_"&A78&"_"&C78 -> boss_icon_chara_sur_00601 | AB78: 魔都精兵のスレイブいいジャン祭 | AC78: 監修通過 | AF78: 未 | AG78: 202512010_魔都精兵のスレイブ
A79: sur | B79: {=iferror(INDEX('作品'!D:D,MATCH(A79,'作品'!A:A,0),0),"error")} -> 魔都精兵のスレイブ | C79: 00701 | D79: =K79&"_"&A79&"_"&C79 -> chara_sur_00701 | E79: 和倉 青羽 | F79: 和倉 青羽 | G79: 弟について喋ってるでしょ | H79: SR | I79: DropSR | J79: 青 | K79: chara | L79: アタック | M79: dageki_1 | N79: Short | O79: dageki_1 | P79: =RIGHT(D79,5) -> 00701 | Q79: 1.07 | R79: 0.28 | S79: 2.01 | T79: stop無:1回目 0.67 stop無:2回目 0.84 stop無:3回目 1 stop有:4回目 1.25 | U79: 45999.625 | V79: 390812.5 | W79: ="catchcopy_character_"&text(D79,"000000")&".png" -> catchcopy_character_chara_sur_00701.png | X79: ="enemy_icon_"&K79&"_"&A79&"_"&C79 -> enemy_icon_chara_sur_00701 | Y79: ="boss_icon_"&K79&"_"&A79&"_"&C79 -> boss_icon_chara_sur_00701 | AB79: 魔都精兵のスレイブいいジャン祭 | AC79: 監修通過 | AF79: 未 | AG79: 202512010_魔都精兵のスレイブ
A80: sur | B80: {=iferror(INDEX('作品'!D:D,MATCH(A80,'作品'!A:A,0),0),"error")} -> 魔都精兵のスレイブ | C80: 00801 | D80: =K80&"_"&A80&"_"&C80 -> chara_sur_00801 | E80: 和倉優希（変身） | F80: 無窮の鎖 和倉 優希 | G80: 隷架拳 | H80: SR | I80: DropSR | J80: 黄 | K80: chara | L80: ディフェンス | M80: dageki_1 | N80: Short | O80: dageki_1 | P80: =RIGHT(D80,5) -> 00801 | Q80: 1.24 | R80: stop有:1回目 0.66 | S80: 2.01 | T80: stop有:1回目 1.06 | U80: 45999.625 | V80: 390812.5 | W80: ="catchcopy_character_"&text(D80,"000000")&".png" -> catchcopy_character_chara_sur_00801.png | X80: ="enemy_icon_"&K80&"_"&A80&"_"&C80 -> enemy_icon_chara_sur_00801 | Y80: ="boss_icon_"&K80&"_"&A80&"_"&C80 -> boss_icon_chara_sur_00801 | AB80: 魔都精兵のスレイブいいジャン祭 | AC80: 監修通過 | AF80: 未 | AG80: 202512010_魔都精兵のスレイブ
A81: sur | B81: {=iferror(INDEX('作品'!D:D,MATCH(A81,'作品'!A:A,0),0),"error")} -> 魔都精兵のスレイブ | C81: 00901 | D81: =K81&"_"&A81&"_"&C81 -> chara_sur_00901 | E81: 山城 恋 | F81: 万物を統べる総組長 山城 恋 | G81: 万物を総該した無限宇宙の全一 | H81: UR | I81: PremiumUR | J81: 青 | K81: chara | L81: アタック | N81: Middle | Q81: 1.17 | R81: stop有 : 0.43 | S81: 2.92 | T81: stop有 : 1.31 | U81: 実装未定 | V81: 390812.5 | W81: ="catchcopy_character_"&text(D81,"000000")&".png" -> catchcopy_character_chara_sur_00901.png | X81: ="enemy_icon_"&K81&"_"&A81&"_"&C81 -> enemy_icon_chara_sur_00901 | Y81: ="boss_icon_"&K81&"_"&A81&"_"&C81 -> boss_icon_chara_sur_00901 | AB81: ストックキャラ | AG81: 999999999_リリースキー未定
A82: ron | B82: {=iferror(INDEX('作品'!D:D,MATCH(A82,'作品'!A:A,0),0),"error")} -> 鴨乃橋ロンの禁断推理 | C82: 00001 | D82: =K82&"_"&A82&"_"&C82 -> chara_ron_00001 | E82: 鴨乃橋 ロン | F82: 鴨乃橋 ロン | G82: 今からそれを証明してみせる | H82: SSR | I82: PremiumSSR | J82: 青 | K82: chara | L82: テクニカル | M82: dageki_2 | N82: Middle | O82: dageki_1 | P82: =RIGHT(D82,5) -> 00001 | Q82: 1.67 | R82: stop有:1回目 0.92 | S82: 2.74 | T82: stop有:1回目 1.17 stop無:2回目 1.50 stop無:3回目 1.67 stop無:4回目 1.84 stop無:5回目 1.97 | U82: 45922.458 | V82: 390812.5 | W82: ="catchcopy_character_"&text(D82,"000000")&".png" -> catchcopy_character_chara_ron_00001.png | X82: ="enemy_icon_"&K82&"_"&A82&"_"&C82 -> enemy_icon_chara_ron_00001 | Y82: ="boss_icon_"&K82&"_"&A82&"_"&C82 -> boss_icon_chara_ron_00001 | Z82: chara_ron_00001_normal | AA82: chara_ron_00001_special | AB82: リリース時 | AC82: 監修通過 | AE82: ▼フレーバーなど下記のシートに記載 GLOW_キャラ名称＆キャラセリフ資料 | AF82: 未 | AG82: 202509010_リリース
A83: ron | B83: {=iferror(INDEX('作品'!D:D,MATCH(A83,'作品'!A:A,0),0),"error")} -> 鴨乃橋ロンの禁断推理 | C83: 00101 | D83: =K83&"_"&A83&"_"&C83 -> chara_ron_00101 | E83: 一色 都々丸 | F83: 一色 都々丸 | G83: ピュアでマヌケな名探偵 | H83: R | I83: PremiumR | J83: 青 | K83: chara | L83: ディフェンス | M83: dageki_2 | N83: Middle | O83: dageki_1 | P83: =RIGHT(D83,5) -> 00101 | Q83: 1.67 | R83: 0.70 | S83: 2.67 | T83: 1.44 | U83: 45922.458 | V83: 390812.5 | W83: ="catchcopy_character_"&text(D83,"000000")&".png" -> catchcopy_character_chara_ron_00101.png | X83: ="enemy_icon_"&K83&"_"&A83&"_"&C83 -> enemy_icon_chara_ron_00101 | Y83: ="boss_icon_"&K83&"_"&A83&"_"&C83 -> boss_icon_chara_ron_00101 | Z83: chara_ron_00101_normal | AA83: chara_ron_00101_special | AB83: リリース時 | AC83: 監修通過 | AE83: ▼フレーバーなど下記のシートに記載 GLOW_キャラ名称＆キャラセリフ資料 | AF83: 未 | AG83: 202509010_リリース
A84: aha | B84: {=iferror(INDEX('作品'!D:D,MATCH(A84,'作品'!A:A,0),0),"error")} -> 阿波連さんははかれない | C84: 00001 | D84: =K84&"_"&A84&"_"&C84 -> chara_aha_00001 | E84: ライドウ | F84: ライドウ | G84: 公園は皆のものだから | H84: SR | I84: PremiumSR | J84: 黄 | K84: chara | L84: ディフェンス | M84: dageki_2 | N84: Short | O84: dageki_1 | P84: =RIGHT(D84,5) -> 00001 | Q84: 1.60 | R84: 0.67 | S84: 2.67 | T84: 1.05 | U84: 45922.458 | V84: 390812.5 | W84: ="catchcopy_character_"&text(D84,"000000")&".png" -> catchcopy_character_chara_aha_00001.png | X84: ="enemy_icon_"&K84&"_"&A84&"_"&C84 -> enemy_icon_chara_aha_00001 | Y84: ="boss_icon_"&K84&"_"&A84&"_"&C84 -> boss_icon_chara_aha_00001 | AA84: chara_aha_00001_special | AB84: リリース時 | AC84: 監修通過 | AE84: ▼フレーバーなど下記のシートに記載 GLOW_キャラ名称＆キャラセリフ資料 | AF84: 未 | AG84: 202509010_リリース
A85: aha | B85: {=iferror(INDEX('作品'!D:D,MATCH(A85,'作品'!A:A,0),0),"error")} -> 阿波連さんははかれない | C85: 00101 | D85: =K85&"_"&A85&"_"&C85 -> chara_aha_00101 | E85: 阿波連 れいな | F85: 阿波連 れいな | G85: さっきはありがとう | H85: SSR | I85: PremiumSSR | J85: 黄 | K85: chara | L85: サポート | M85: dageki_1 | N85: Short | O85: - | P85: =RIGHT(D85,5) -> 00101 | Q85: 1.27 | R85: stop有:1回目 0.46 | S85: 3.17 | T85: stop無:1回目 2.00 | U85: 45922.458 | V85: 390812.5 | W85: ="catchcopy_character_"&text(D85,"000000")&".png" -> catchcopy_character_chara_aha_00101.png | X85: ="enemy_icon_"&K85&"_"&A85&"_"&C85 -> enemy_icon_chara_aha_00101 | Y85: ="boss_icon_"&K85&"_"&A85&"_"&C85 -> boss_icon_chara_aha_00101 | Z85: chara_aha_00101_normal | AA85: chara_aha_00101_special | AB85: リリース時 | AC85: 監修通過 | AE85: ▼フレーバーなど下記のシートに記載 GLOW_キャラ名称＆キャラセリフ資料 | AF85: 未 | AG85: 202509010_リリース
A86: tak | B86: {=iferror(INDEX('作品'!D:D,MATCH(A86,'作品'!A:A,0),0),"error")} -> タコピーの原罪 | C86: 00001 | D86: =K86&"_"&A86&"_"&C86 -> chara_tak_00001 | E86: ハッピー星からの使者 タコピー | F86: ハッピー星からの使者 タコピー | G86: 笑ってもらえるように | H86: UR | I86: PremiumUR | J86: 黄 | K86: chara | L86: ディフェンス | M86: dageki_1 | N86: Short | O86: - | P86: =RIGHT(D86,5) -> 00001 | Q86: 1.00 | R86: 0.44 | S86: 3.34 | T86: 0.75 | U86: 45922.458 | V86: 390812.5 | W86: ="catchcopy_character_"&text(D86,"000000")&".png" -> catchcopy_character_chara_tak_00001.png | X86: ="enemy_icon_"&K86&"_"&A86&"_"&C86 -> enemy_icon_chara_tak_00001 | Y86: ="boss_icon_"&K86&"_"&A86&"_"&C86 -> boss_icon_chara_tak_00001 | Z86: chara_tak_00001_normal | AA86: chara_tak_00001_special | AB86: リリース時 | AC86: 監修通過 | AE86: ▼フレーバーなど下記のシートに記載 GLOW_キャラ名称＆キャラセリフ資料 | AF86: 未 | AG86: 202509010_リリース
A87: tak | B87: {=iferror(INDEX('作品'!D:D,MATCH(A87,'作品'!A:A,0),0),"error")} -> タコピーの原罪 | C87: 00101 | D87: =K87&"_"&A87&"_"&C87 -> chara_tak_00101 | E87: 久世 しずか＆タコピー | F87: 選定中 | H87: UR | I87: PremiumUR | J87: 無 | K87: chara
A88: tak | B88: {=iferror(INDEX('作品'!D:D,MATCH(A88,'作品'!A:A,0),0),"error")} -> タコピーの原罪 | C88: 00201 | D88: =K88&"_"&A88&"_"&C88 -> chara_tak_00201 | E88: 雲母坂 まりな | F88: 選定中 | H88: SR | I88: DropSR | J88: 緑 | K88: chara
A89: jig | B89: {=iferror(INDEX('作品'!D:D,MATCH(A89,'作品'!A:A,0),0),"error")} -> 地獄楽 | C89: 00001 | D89: =K89&"_"&A89&"_"&C89 -> chara_jig_00001 | E89: がらんの画眉丸 | F89: がらんの画眉丸 | G89: 忍法 火法師 | H89: UR | I89: PremiumUR | J89: 赤 | K89: chara | L89: テクニカル | M89: dageki_1 | N89: Short | O89: dageki_1 | P89: =RIGHT(D89,5) -> 00001 | Q89: 1.17 | R89: stop有:1回目0.20 | S89: 2.30 | T89: stop有:1回目 0.08 stop有:2回目 0.90 stop有:3回目 1.50 | U89: 45922.458 | V89: 390812.5 | W89: ="catchcopy_character_"&text(D89,"000000")&".png" -> catchcopy_character_chara_jig_00001.png | X89: ="enemy_icon_"&K89&"_"&A89&"_"&C89 -> enemy_icon_chara_jig_00001 | Y89: ="boss_icon_"&K89&"_"&A89&"_"&C89 -> boss_icon_chara_jig_00001 | Z89: chara_jig_00001_normal | AA89: chara_jig_00001_special | AB89: リリース時 | AC89: 監修通過 | AE89: ▼フレーバーなど下記のシートに記載 GLOW_キャラ名称＆キャラセリフ資料 | AF89: α3 | AG89: 202509010_リリース
A90: jig | B90: {=iferror(INDEX('作品'!D:D,MATCH(A90,'作品'!A:A,0),0),"error")} -> 地獄楽 | C90: 00101 | D90: =K90&"_"&A90&"_"&C90 -> chara_jig_00101 | E90: 山田浅ェ門 佐切 | F90: 山田浅ェ門 佐切 | G90: 試一刀流 具足割 | H90: SSR | I90: PremiumSSR | J90: 赤 | K90: chara | L90: アタック | M90: zangeki_1 | N90: Short | O90: zangeki_1 | P90: =RIGHT(D90,5) -> 00101 | Q90: 1.5 | R90: 0.50 | S90: 2.50 | T90: 1.20 | U90: 45922.458 | V90: 390812.5 | W90: ="catchcopy_character_"&text(D90,"000000")&".png" -> catchcopy_character_chara_jig_00101.png | X90: ="enemy_icon_"&K90&"_"&A90&"_"&C90 -> enemy_icon_chara_jig_00101 | Y90: ="boss_icon_"&K90&"_"&A90&"_"&C90 -> boss_icon_chara_jig_00101 | Z90: chara_jig_00101_normal | AA90: chara_jig_00101_special | AB90: リリース時 | AC90: 監修通過 | AE90: ▼フレーバーなど下記のシートに記載 GLOW_キャラ名称＆キャラセリフ資料 | AF90: 作成済み | AG90: 202509010_リリース
A91: jig | B91: {=iferror(INDEX('作品'!D:D,MATCH(A91,'作品'!A:A,0),0),"error")} -> 地獄楽 | C91: 00201 | D91: =K91&"_"&A91&"_"&C91 -> chara_jig_00201 | E91: 杠 | F91: 杠 | G91: 忍法 線斬行 | H91: SSR | I91: DropSSR | J91: 緑 | K91: chara | L91: テクニカル | M91: shageki_1 | N91: Middle | O91: shageki_1 | P91: =RIGHT(D91,5) -> 00201 | Q91: 1.67 | R91: stop有:1回目 1 | S91: 2.56 | T91: stop有:1回目1.66 | U91: 45922.458 | V91: 390812.5 | W91: ="catchcopy_character_"&text(D91,"000000")&".png" -> catchcopy_character_chara_jig_00201.png | X91: ="enemy_icon_"&K91&"_"&A91&"_"&C91 -> enemy_icon_chara_jig_00201 | Y91: ="boss_icon_"&K91&"_"&A91&"_"&C91 -> boss_icon_chara_jig_00201 | Z91: chara_jig_00201_normal | AA91: chara_jig_00201_special | AB91: リリース時 | AC91: 監修通過 | AE91: ▼フレーバーなど下記のシートに記載 GLOW_キャラ名称＆キャラセリフ資料 | AF91: 作成済み | AG91: 202509010_リリース
A92: jig | B92: {=iferror(INDEX('作品'!D:D,MATCH(A92,'作品'!A:A,0),0),"error")} -> 地獄楽 | C92: 00301 | D92: =K92&"_"&A92&"_"&C92 -> chara_jig_00301 | E92: 山田浅ェ門 仙汰 | F92: 山田浅ェ門 仙汰 | G92: 僕を通して貰わないと | H92: SR | I92: PremiumSR | J92: 緑 | K92: chara | L92: ディフェンス | M92: zangeki_1 | N92: Short | O92: zangeki_1 | P92: =RIGHT(D92,5) -> 00301 | Q92: 1.80 | R92: stop有0.50 | S92: 2.34 | T92: stop無:1回目：0.35 stop無:2回目：0.50 stop無:3回目 0.62 stop無:4回目 0.78 stop有:5回目 1.00 | U92: 45922.458 | V92: 390812.5 | W92: ="catchcopy_character_"&text(D92,"000000")&".png" -> catchcopy_character_chara_jig_00301.png | X92: ="enemy_icon_"&K92&"_"&A92&"_"&C92 -> enemy_icon_chara_jig_00301 | Y92: ="boss_icon_"&K92&"_"&A92&"_"&C92 -> boss_icon_chara_jig_00301 | AA92: chara_jig_00301_special | AB92: リリース時 | AC92: 監修通過 | AE92: ▼フレーバーなど下記のシートに記載 GLOW_キャラ名称＆キャラセリフ資料 | AF92: 作成済み | AG92: 202509010_リリース
A93: jig | B93: {=iferror(INDEX('作品'!D:D,MATCH(A93,'作品'!A:A,0),0),"error")} -> 地獄楽 | C93: 00401 | D93: =K93&"_"&A93&"_"&C93 -> chara_jig_00401 | E93: 賊王 亜左 弔兵衛 | F93: 賊王 亜左 弔兵衛 | G93: オレの神もオレだ!! | H93: UR | I93: PremiumUR | J93: 無 | K93: chara | L93: テクニカル | M93: zangeki_1 | N93: Short | O93: zangeki_1 | P93: =RIGHT(D93,5) -> 00401 | Q93: 1.67 | R93: stop有:1回目0.50 | S93: 2.67 | T93: stop有:1回目1.57 | U93: 46038.625 | V93: 390812.5 | W93: ="catchcopy_character_"&text(D93,"000000")&".png" -> catchcopy_character_chara_jig_00401.png | X93: ="enemy_icon_"&K93&"_"&A93&"_"&C93 -> enemy_icon_chara_jig_00401 | Y93: ="boss_icon_"&K93&"_"&A93&"_"&C93 -> boss_icon_chara_jig_00401 | AB93: 地獄楽いいジャン祭 | AC93: 監修通過 | AF93: 作成済み | AG93: 202601010_地獄楽
A94: jig | B94: {=iferror(INDEX('作品'!D:D,MATCH(A94,'作品'!A:A,0),0),"error")} -> 地獄楽 | C94: 00501 | D94: =K94&"_"&A94&"_"&C94 -> chara_jig_00501 | E94: 山田浅ェ門 桐馬 | F94: 山田浅ェ門 桐馬 | G94: 兄さんは強いんだ | H94: SSR | I94: PremiumSSR | J94: 緑 | K94: chara | L94: サポート | M94: zangeki_1 | N94: Short | O94: - | P94: =RIGHT(D94,5) -> 00501 | Q94: 1.6 | R94: stop有:1回目0.4 | S94: 3.33 | T94: stop無:1.67 | U94: 46038.625 | V94: 390812.5 | W94: ="catchcopy_character_"&text(D94,"000000")&".png" -> catchcopy_character_chara_jig_00501.png | X94: ="enemy_icon_"&K94&"_"&A94&"_"&C94 -> enemy_icon_chara_jig_00501 | Y94: ="boss_icon_"&K94&"_"&A94&"_"&C94 -> boss_icon_chara_jig_00501 | AB94: 地獄楽いいジャン祭 | AC94: 監修通過 | AF94: 作成済み | AG94: 202601010_地獄楽
A95: jig | B95: {=iferror(INDEX('作品'!D:D,MATCH(A95,'作品'!A:A,0),0),"error")} -> 地獄楽 | C95: 00601 | D95: =K95&"_"&A95&"_"&C95 -> chara_jig_00601 | E95: 民谷 巌鉄斎 | F95: 民谷 巌鉄斎 | G95: 真の不老不死だ!! | H95: SR | I95: DropSR | J95: 青 | K95: chara | L95: ディフェンス | M95: zangeki_1 | N95: Short | O95: zangeki_1 | P95: =RIGHT(D95,5) -> 00601 | Q95: 1.67 | R95: stop有:1回目0.6 | S95: 2.67 | T95: stop有:1.5 | U95: 46038.625 | V95: 390812.5 | W95: ="catchcopy_character_"&text(D95,"000000")&".png" -> catchcopy_character_chara_jig_00601.png | X95: ="enemy_icon_"&K95&"_"&A95&"_"&C95 -> enemy_icon_chara_jig_00601 | Y95: ="boss_icon_"&K95&"_"&A95&"_"&C95 -> boss_icon_chara_jig_00601 | AB95: 地獄楽いいジャン祭 | AC95: 監修通過 | AF95: 作成済み | AG95: 202601010_地獄楽
A96: jig | B96: {=iferror(INDEX('作品'!D:D,MATCH(A96,'作品'!A:A,0),0),"error")} -> 地獄楽 | C96: 00701 | D96: =K96&"_"&A96&"_"&C96 -> chara_jig_00701 | E96: メイ | F96: メイ | G96: 強イモ弱イモ ゼンブダイジ | H96: SR | I96: DropSR | J96: 無 | K96: chara | L96: スペシャル | M96: - | N96: ー | O96: - | P96: =RIGHT(D96,5) -> 00701 | Q96: - | R96: - | S96: 2.4 | T96: 0 | U96: 46038.625 | V96: 390812.5 | W96: ="catchcopy_character_"&text(D96,"000000")&".png" -> catchcopy_character_chara_jig_00701.png | X96: ="enemy_icon_"&K96&"_"&A96&"_"&C96 -> enemy_icon_chara_jig_00701 | Y96: ="boss_icon_"&K96&"_"&A96&"_"&C96 -> boss_icon_chara_jig_00701 | AB96: 地獄楽いいジャン祭 | AC96: 監修通過 | AF96: 作成済み | AG96: 202601010_地獄楽
A97: mag | B97: {=iferror(INDEX('作品'!D:D,MATCH(A97,'作品'!A:A,0),0),"error")} -> 株式会社マジルミエ | C97: 00001 | D97: =K97&"_"&A97&"_"&C97 -> chara_mag_00001 | E97: 新人魔法少女 桜木 カナ | F97: 新人魔法少女 桜木 カナ | G97: 私は役に立てる | H97: UR | I97: PremiumUR | J97: 青 | K97: chara | L97: アタック | M97: shageki_1 | N97: Long | O97: shageki_1 | P97: =RIGHT(D97,5) -> 00001 | Q97: 1.77 | R97: stop有:1回目 0.92 | S97: 2.33 | T97: stop無:1回目 0.75 stop無:2回目 0.92 stop無:3回目 1.08 stop無:4回目 1.25 stop無:5回目 1.42 stop無:6回目 1.58 | U97: 45922.458 | V97: 390812.5 | W97: ="catchcopy_character_"&text(D97,"000000")&".png" -> catchcopy_character_chara_mag_00001.png | X97: ="enemy_icon_"&K97&"_"&A97&"_"&C97 -> enemy_icon_chara_mag_00001 | Y97: ="boss_icon_"&K97&"_"&A97&"_"&C97 -> boss_icon_chara_mag_00001 | Z97: chara_mag_00001_normal | AA97: chara_mag_00001_special | AB97: リリース時 | AC97: 監修通過 | AE97: ▼フレーバーなど下記のシートに記載 GLOW_キャラ名称＆キャラセリフ資料 | AF97: 未 | AG97: 202509010_リリース
A98: mag | B98: {=iferror(INDEX('作品'!D:D,MATCH(A98,'作品'!A:A,0),0),"error")} -> 株式会社マジルミエ | C98: 00101 | D98: =K98&"_"&A98&"_"&C98 -> chara_mag_00101 | E98: 越谷 仁美 | F98: 越谷 仁美 | G98: まずァ一発！ | H98: SR | I98: PremiumSR | J98: 黄 | K98: chara | L98: アタック | M98: shageki_1 | N98: Middle | O98: shageki_1 | P98: =RIGHT(D98,5) -> 00101 | Q98: 1.90 | R98: 0.84 | S98: 2.67 | T98: 1.50 | U98: 45922.458 | V98: 390812.5 | W98: ="catchcopy_character_"&text(D98,"000000")&".png" -> catchcopy_character_chara_mag_00101.png | X98: ="enemy_icon_"&K98&"_"&A98&"_"&C98 -> enemy_icon_chara_mag_00101 | Y98: ="boss_icon_"&K98&"_"&A98&"_"&C98 -> boss_icon_chara_mag_00101 | Z98: chara_mag_00101_normal | AA98: chara_mag_00101_special | AB98: リリース時 | AC98: 監修通過 | AE98: ▼フレーバーなど下記のシートに記載 GLOW_キャラ名称＆キャラセリフ資料 | AF98: 未 | AG98: 202509010_リリース
A99: mag | B99: {=iferror(INDEX('作品'!D:D,MATCH(A99,'作品'!A:A,0),0),"error")} -> 株式会社マジルミエ | C99: 00201 | D99: =K99&"_"&A99&"_"&C99 -> chara_mag_00201 | E99: 土刃 メイ | F99: 絶対効率の体現者 土刃 メイ | G99: これが仕事です | H99: UR | I99: PremiumUR | J99: 赤 | K99: chara | L99: アタック | M99: shageki_1 | N99: Long | O99: dageki_1 | Q99: 1.17 | R99: stop有:1回目 0.42 | S99: 2.71 | T99: stop有:1回目 0.38 stop無:2回目 1.55 stop無:3回目 1.8 stop無:4回目 2.1 | U99: 45967.625 | V99: 390812.5 | X99: ="enemy_icon_"&K99&"_"&A99&"_"&C99 -> enemy_icon_chara_mag_00201 | Y99: ="boss_icon_"&K99&"_"&A99&"_"&C99 -> boss_icon_chara_mag_00201 | AB99: 株式会社マジルミエいいジャン祭 | AG99: 202511010_株式会社マジルミエ
A100: mag | B100: {=iferror(INDEX('作品'!D:D,MATCH(A100,'作品'!A:A,0),0),"error")} -> 株式会社マジルミエ | C100: 00301 | D100: =K100&"_"&A100&"_"&C100 -> chara_mag_00301 | E100: 葵 リリー | F100: 葵 リリー | G100: 笑って | H100: SSR | I100: PremiumSSR | J100: 緑 | K100: chara | L100: ディフェンス | M100: dageki_1 | N100: Middle | O100: - | Q100: 1.6 | R100: stop有:0.6 | S100: 2.5 | T100: stop無 1 | U100: 45967.625 | V100: 390812.5 | X100: ="enemy_icon_"&K100&"_"&A100&"_"&C100 -> enemy_icon_chara_mag_00301 | Y100: ="boss_icon_"&K100&"_"&A100&"_"&C100 -> boss_icon_chara_mag_00301 | AB100: 株式会社マジルミエいいジャン祭 | AG100: 202511010_株式会社マジルミエ
...

Sheet 敵情報アイコン
A1: 作品ID | B1: 作品名 | C1: 識別ID | D1: ノーマル敵専用アイコン_ID | E1: 強敵（BOSS）専用アイコン_ID | F1: キャラ名（仮） | G1: キャラ名（監修FIX） | H1: レアリティ | I1: キャラ立ち位置 | J1: ロール | K1: valid_start_date | L1: valid_end_date | M1: デプロイ | N1: 補足
A2: spy | B2: SPY×FAMILY | C2: 00001 | D2: ="enemy_icon_chara"&"_"&#REF!&"_"&C2 -> #REF! | E2: boss_icon_chara_spy_00001 | F2: アーニャ・フォージャー | H2: N | I2: プレイアブル＆敵キャラでも登場可 | J2: サポート | K2: 45658 | L2: 390812.5
A3: spy | B3: SPY×FAMILY | C3: 00002 | D3: enemy_icon_chara_spy_00002 | E3: boss_icon_chara_spy_00002 | F3: イーデン校の生徒 アーニャ | H3: SSR | I3: プレイアブル＆敵キャラでも登場可 | J3: サポート | K3: 45658 | L3: 390812.5
A4: spy | B4: SPY×FAMILY | C4: 00101 | D4: enemy_icon_chara_spy_00101 | E4: boss_icon_chara_spy_00101 | F4: ロイド・フォージャー | H4: SR | I4: プレイアブル＆敵キャラでも登場可 | J4: アタック | K4: 45658 | L4: 390812.5
A5: spy | B5: SPY×FAMILY | C5: 00201 | D5: enemy_icon_chara_spy_00201 | E5: boss_icon_chara_spy_00201 | F5: ヨル・フォージャー | H5: SR | I5: プレイアブル＆敵キャラでも登場可 | J5: アタック | K5: 45658 | L5: 390812.5
A6: spy | B6: SPY×FAMILY | C6: 00301 | D6: enemy_icon_chara_spy_00301 | E6: boss_icon_chara_spy_00301 | F6: ダミアン・デズモンド | H6: R | I6: プレイアブル＆敵キャラでも登場可 | J6: アタック | K6: 45658 | L6: 390812.5
A7: spy | B7: SPY×FAMILY | C7: 00401 | D7: enemy_icon_chara_spy_00401 | E7: boss_icon_chara_spy_00401 | F7: フランキー・フランクリン | H7: N | I7: プレイアブル＆敵キャラでも登場可 | J7: ディフェンス | K7: 45658 | L7: 390812.5
A8: spy | B8: SPY×FAMILY | C8: 00001 | D8: enemy_icon_enemy_spy_00001 | E8: boss_icon_enemy_spy_00001 | F8: キース・ケプラー | I8: 敵キャラonly | J8: アタック | K8: 45658 | L8: 390812.5
A9: spy | B9: SPY×FAMILY | C9: 00002 | D9: enemy_icon_enemy_spy_00002 | E9: boss_icon_enemy_spy_00002 | F9: エドガー | I9: 敵キャラonly | J9: ディフェンス | K9: 45658 | L9: 390812.5
A10: spy | B10: SPY×FAMILY | C10: 00003 | D10: enemy_icon_enemy_spy_00003 | E10: boss_icon_enemy_spy_00003 | F10: 殺し屋たち（A） | I10: 敵キャラonly | J10: アタック | K10: 45658 | L10: 390812.5
A11: spy | B11: SPY×FAMILY | C11: 00004 | D11: enemy_icon_enemy_spy_00004 | E11: boss_icon_enemy_spy_00004 | F11: 殺し屋たち（B） | I11: 敵キャラonly | J11: アタック | K11: 45658 | L11: 390812.5
A12: spy | B12: SPY×FAMILY | C12: 00005 | D12: enemy_icon_enemy_spy_00005 | E12: boss_icon_enemy_spy_00005 | F12: 学生テロリストたち | I12: 敵キャラonly | J12: アタック | K12: 45658 | L12: 390812.5
A13: spy | B13: SPY×FAMILY | C13: 00006 | D13: enemy_icon_enemy_spy_00006 | E13: boss_icon_enemy_spy_00006 | F13: 爆弾犬 | I13: 敵キャラonly | J13: アタック | K13: 45658 | L13: 390812.5
A14: aka | B14: ラーメン赤猫 | C14: 00001 | D14: enemy_icon_chara_aka_00001 | E14: boss_icon_chara_aka_00001 | F14: 佐々木 | K14: 45658 | L14: 390812.5
A15: aka | B15: ラーメン赤猫 | C15: 00101 | D15: enemy_icon_chara_aka_00101 | E15: boss_icon_chara_aka_00101 | F15: 文蔵 | K15: 45658 | L15: 390812.5
A16: rik | B16: トマトイプーのリコピン | C16: 00001 | D16: enemy_icon_chara_rik_00001 | E16: boss_icon_chara_rik_00001 | F16: リコピン | K16: 45658 | L16: 390812.5
A17: rik | B17: トマトイプーのリコピン | C17: 00101 | D17: enemy_icon_chara_rik_00101 | E17: boss_icon_chara_rik_00101 | F17: 甘戸 めめ | K17: 45658 | L17: 390812.5
A18: rik | B18: トマトイプーのリコピン | C18: 00201 | D18: enemy_icon_chara_rik_00201 | E18: boss_icon_chara_rik_00201 | F18: チアミン | K18: 45658 | L18: 390812.5
A19: dan | B19: ダンダダン | C19: 00001 | D19: enemy_icon_chara_dan_00001 | E19: boss_icon_chara_dan_00001 | F19: オカルン （制服着用） | K19: 45658 | L19: 390812.5
A20: dan | B20: ダンダダン | C20: 00002 | D20: enemy_icon_chara_dan_00002 | E20: boss_icon_chara_dan_00002 | F20: オカルン（高倉 健） （ターボババア憑依状態） | K20: 45658 | L20: 390812.5
A21: dan | B21: ダンダダン | C21: 00101 | D21: enemy_icon_chara_dan_00101 | E21: boss_icon_chara_dan_00101 | F21: 綾瀬桃 | K21: 45658 | L21: 390812.5
A22: dan | B22: ダンダダン | C22: 00201 | D22: enemy_icon_chara_dan_00201 | E22: boss_icon_chara_dan_00201 | F22: 白鳥 愛羅 | K22: 45658 | L22: 390812.5
A23: dan | B23: ダンダダン | C23: 00001 | D23: enemy_icon_enemy_dan_00001 | E23: boss_icon_enemy_dan_00001 | F23: セルポ星人 桃が最初に出会った宇宙人 | K23: 45658 | L23: 390812.5
A24: dan | B24: ダンダダン | C24: 00002 | D24: enemy_icon_enemy_dan_00002 | E24: boss_icon_enemy_dan_00002 | F24: ターボババァ | K24: 45658 | L24: 390812.5
A25: gom | B25: 姫様“拷問”の時間です | C25: 00001 | D25: enemy_icon_chara_gom_00001 | E25: boss_icon_chara_gom_00001 | F25: 姫（奴隷服） | K25: 45658 | L25: 390812.5
... A71: sum | B71: サマータイムレンダ | C71: 00201 | D71: enemy_icon_chara_sum_00201 | E71: boss_icon_chara_sum_00201 | F71: 小舟 澪 | K71: 45658 | L71: 390812.5

Sheet アイテム
A1: 作品_ID | B1: 作品名 | C1: 接頭語（カテゴリー） | D1: 識別ID | E1: アイテム_ID | F1: assetKey | G1: 画像ファイルID | H1: アイテム名 | I1: レアリティ | J1: 最大所持数 | K1: 最大表示上限数 | L1: フレーバーテキスト | M1: アイテム備考 | N1: start_date | O1: リリースキー | P1: 単価
A2: glo | B2: {=iferror(INDEX('作品'!D:D,MATCH(A2,'作品'!A:A,0),0),"error")} -> GLOW | C2: prism | D2: 00001 | E2: =C2&"_"&A2&"_"&D2 -> prism_glo_00001 | F2: =E2 -> prism_glo_00001 | G2: ="item_icon_"&F2 -> item_icon_prism_glo_00001 | H2: プリズム | I2: UR | J2: 999999999 | K2: 999999999 | L2: 未定 | N2: 2024-01-01 00:00:00 | O2: 202509010 | P2: 2
A3: glo | B3: {=iferror(INDEX('作品'!D:D,MATCH(A3,'作品'!A:A,0),0),"error")} -> GLOW | C3: coin | D3: 00001 | E3: Coin | F3: coin_glo_00001 | G3: ="item_icon_"&F3 -> item_icon_coin_glo_00001 | H3: コイン | I3: SR | J3: 999999999 | K3: 999999999 | L3: 未定 | N3: 2024-01-01 00:00:00 | O3: 202509010 | P3: 0.13
A5: glo | B5: {=iferror(INDEX('作品'!D:D,MATCH(A5,'作品'!A:A,0),0),"error")} -> GLOW | C5: stamina | D5: 00001 | E5: =C5&"_"&A5&"_"&D5 -> stamina_glo_00001 | F5: =E5 -> stamina_glo_00001 | G5: ="item_icon_"&F5 -> item_icon_stamina_glo_00001 | H5: スタミナ | I5: R | J5: 999 | K5: 999 | N5: 2024-01-01 00:00:00 | O5: 202509010 | P5: 7.56
A6: glo | B6: {=iferror(INDEX('作品'!D:D,MATCH(A6,'作品'!A:A,0),0),"error")} -> GLOW | C6: stamina_item | D6: 00001 | E6: =C6&"_"&A6&"_"&D6 -> stamina_item_glo_00001 | F6: =E6 -> stamina_item_glo_00001 | G6: ="item_icon_"&F6 -> item_icon_stamina_item_glo_00001 | H6: スタミナドリンク | I6: R | J6: 999999999 | K6: 999999999 | L6: 使用することでスタミナ最を10回復できるアイテム | N6: 2024-01-01 00:00:00 | O6: 202509010 | P6: =P5*10 -> 75.6
A7: glo | B7: {=iferror(INDEX('作品'!D:D,MATCH(A7,'作品'!A:A,0),0),"error")} -> GLOW | C7: stamina_item | D7: 00002 | E7: =C7&"_"&A7&"_"&D7 -> stamina_item_glo_00002 | F7: =E7 -> stamina_item_glo_00002 | G7: ="item_icon_"&F7 -> item_icon_stamina_item_glo_00002 | H7: スーパースタミナドリンク | I7: SR | J7: 999999999 | K7: 999999999 | L7: 使用することでスタミナ最を50回復できるアイテム | N7: 2024-01-01 00:00:00 | O7: 202509010 | P7: =P5*50 -> 378
A8: glo | B8: {=iferror(INDEX('作品'!D:D,MATCH(A8,'作品'!A:A,0),0),"error")} -> GLOW | C8: exp | D8: 00001 | E8: =C8&"_"&A8&"_"&D8 -> exp_glo_00001 | F8: =E8 -> exp_glo_00001 | G8: ="item_icon_"&F8 -> item_icon_exp_glo_00001 | H8: リーダーEXP | I8: R | J8: - | K8: - | N8: 2024-01-01 00:00:00 | O8: 202509010 | P8: -
A10: glo | B10: {=iferror(INDEX('作品'!D:D,MATCH(A10,'作品'!A:A,0),0),"error")} -> GLOW | C10: ticket | D10: 00001 | E10: =C10&"_"&A10&"_"&D10 -> ticket_glo_00001 | F10: =E10 -> ticket_glo_00001 | G10: ="item_icon_"&F10 -> item_icon_ticket_glo_00001 | H10: ノーマルガシャチケット | I10: R | J10: 999999999 | K10: 999999999 | L10: ノーマルガシャを引くことができるアイテム | M10: ノーマルガシャは実施無しに変更。 無料配布OK、コインで購入OK ※ガシャチケの配布ルールはアイテム構成図を確認すること https://wonderplanet.atlassian.net/wiki/spaces/GLOW/pages/344622597 ノーマルガシャを1回引けるガシャチケット。10枚集めると10連も可能（最大10連を上限とする） | N10: リリース無し | P10: =O10*1.3 -> 0
A11: glo | B11: {=iferror(INDEX('作品'!D:D,MATCH(A11,'作品'!A:A,0),0),"error")} -> GLOW | C11: ticket | D11: 00002 | E11: =C11&"_"&A11&"_"&D11 -> ticket_glo_00002 | F11: =E11 -> ticket_glo_00002 | G11: ="item_icon_"&F11 -> item_icon_ticket_glo_00002 | H11: スペシャルガシャチケット | I11: UR | J11: 999999999 | K11: 999999999 | L11: スペシャルガシャを引くことができるアイテム | M11: 有償/無償プリズムで引くことのできるスペシャルガシャを1回引けるガシャチケット。10枚集めると10連も可能（最大10連を上限とする）。 | N11: 2024-01-01 00:00:00 | O11: 202509010 | P11: 300
A12: glo | B12: {=iferror(INDEX('作品'!D:D,MATCH(A12,'作品'!A:A,0),0),"error")} -> GLOW | C12: ticket | D12: 00003 | E12: =C12&"_"&A12&"_"&D12 -> ticket_glo_00003 | F12: =E12 -> ticket_glo_00003 | G12: ="item_icon_"&F12 -> item_icon_ticket_glo_00003 | H12: ピックアップガシャチケット | I12: UR | J12: 999999999 | K12: 999999999 | L12: ピックアップガシャを引くことができるアイテム | M12: 有償/無償プリズムで引くことのできるピックアップガシャを1回引けるガシャチケット。10枚集めると10連も可能（最大10連を上限とする）。 | N12: 2024-01-01 00:00:00 | O12: 202509010 | P12: 300
A13: glo | B13: {=iferror(INDEX('作品'!D:D,MATCH(A13,'作品'!A:A,0),0),"error")} -> GLOW | C13: ticket | D13: 00004 | E13: =C13&"_"&A13&"_"&D13 -> ticket_glo_00004 | F13: =E13 -> ticket_glo_00004 | G13: ="item_icon_"&F13 -> item_icon_ticket_glo_00004 | H13: フェスガシャチケット | I13: UR | J13: 999999999 | K13: 999999999 | L13: フェスガシャを引くことができるアイテム | M13: 有償/無償プリズムで引くことのできるフェスプガシャを1回引けるガシャチケット。10枚集めると10連も可能（最大10連を上限とする）。 | N13: 2024-01-01 00:00:00 | O13: 202509010 | P13: 300
A14: glo | B14: {=iferror(INDEX('作品'!D:D,MATCH(A14,'作品'!A:A,0),0),"error")} -> GLOW | C14: ticket | D14: 00102 | E14: =C14&"_"&A14&"_"&D14 -> ticket_glo_00102 | F14: =E14 -> ticket_glo_00102 | G14: ="item_icon_"&F14 -> item_icon_ticket_glo_00102 | H14: R以上確定ガシャチケット | I14: R | J14: 999999999 | K14: 999999999 | L14: R以上確定ガシャを引くことができるアイテム | M14: ガシャデータ未作成 無料配布OK、コインで購入OK 1体R以上キャラ確定のガシャチケット。10枚集めると10連も可能（最大10連を上限とする）。1枚のみだと単発。 プレミアムガシャチケットと違い、天井がない。 | N14: 2024-01-01 00:00:00 | O14: 202509010 | P14: 588
A15: glo | B15: {=iferror(INDEX('作品'!D:D,MATCH(A15,'作品'!A:A,0),0),"error")} -> GLOW | C15: ticket | D15: 00104 | E15: =C15&"_"&A15&"_"&D15 -> ticket_glo_00104 | F15: =E15 -> ticket_glo_00104 | G15: ="item_icon_"&F15 -> item_icon_ticket_glo_00104 | H15: SR以上確定ガシャチケット | I15: SR | J15: 999999999 | K15: 999999999 | L15: SR以上確定ガシャを引くことができるアイテム | M15: ガシャデータ未作成 無料配布OK、コインで購入は× 1体SR以上のキャラ確定の1連ガシャチケット。10枚集めると10連も可能（最大10連を上限とする）。 ガシャID未作成。 | N15: 2024-01-01 00:00:00 | O15: 202509010 | P15: 1000
A16: glo | B16: {=iferror(INDEX('作品'!D:D,MATCH(A16,'作品'!A:A,0),0),"error")} -> GLOW | C16: ticket | D16: 00105 | E16: =C16&"_"&A16&"_"&D16 -> ticket_glo_00105 | F16: =E16 -> ticket_glo_00105 | G16: ="item_icon_"&F16 -> item_icon_ticket_glo_00105 | H16: SSR以上確定ガシャチケット | I16: SSR | J16: 999999999 | K16: 999999999 | L16: SSR以上確定ガシャを引くことができるアイテム | M16: ガシャデータ未作成 有償販売・プリズム販売・オマケのみ SSRキャラ確定の1連ガシャチケット。10枚集めると10連も可能（最大10連を上限とする）。 | N16: 2024-01-01 00:00:00 | O16: 202509010 | P16: 2000
A17: glo | B17: {=iferror(INDEX('作品'!D:D,MATCH(A17,'作品'!A:A,0),0),"error")} -> GLOW | C17: ticket | D17: 00202 | E17: =C17&"_"&A17&"_"&D17 -> ticket_glo_00202 | F17: =E17 -> ticket_glo_00202 | G17: ="item_icon_"&F17 -> item_icon_ticket_glo_00202 | H17: UR確定ガシャチケット | I17: UR | J17: 999999999 | K17: 999999999 | L17: UR以上確定ガシャを引くことができるアイテム | M17: ガシャデータ未作成 有償販売・プリズム販売・オマケのみ URキャラ確定の1連ガシャチケット。10枚集めると10連も可能（最大10連を上限とする）。 | N17: 2024-01-01 00:00:00 | O17: 202509010 | P17: 7500
A18: glo | B18: {=iferror(INDEX('作品'!D:D,MATCH(A18,'作品'!A:A,0),0),"error")} -> GLOW | C18: ticket | D18: 00203 | E18: =C18&"_"&A18&"_"&D18 -> ticket_glo_00203 | F18: =E18 -> ticket_glo_00203 | G18: ="item_icon_"&F18 -> item_icon_ticket_glo_00203 | H18: UR1体確定10連ガシャチケット | I18: UR | J18: 999999999 | K18: 999999999 | L18: UR1体確定10連ガシャを引くことができるアイテム | M18: 有償販売・プリズム販売・オマケのみ URキャラ1体確定の10連ガシャチケット。1枚(10連)ずつしか使えない。 | N18: 2024-01-01 00:00:00 | O18: 202509010 | P18: 7500
A19: glo | B19: {=iferror(INDEX('作品'!D:D,MATCH(A19,'作品'!A:A,0),0),"error")} -> GLOW | C19: ticket | D19: 00204 | E19: =C19&"_"&A19&"_"&D19 -> ticket_glo_00204 | F19: =E19 -> ticket_glo_00204 | G19: ="item_icon_"&F19 -> item_icon_ticket_glo_00204 | H19: ピックアップUR1体確定10連ガシャチケット | I19: UR | J19: 999999999 | K19: 999999999 | L19: ピックアップUR1体確定10連ガシャを引くことができるアイテム | M19: ガシャデータ未作成 有償販売・プリズム販売・オマケのみ URキャラ1体確定の10連ガシャチケット。1枚(10連)ずつしか使えない。 | N19: 2024-01-01 00:00:00 | O19: 202509010 | P19: 7500
A20: glo | B20: {=iferror(INDEX('作品'!D:D,MATCH(A20,'作品'!A:A,0),0),"error")} -> GLOW | C20: ticket | D20: 00205 | E20: =C20&"_"&A20&"_"&D20 -> ticket_glo_00205 | F20: =E20 -> ticket_glo_00205 | G20: ="item_icon_"&F20 -> item_icon_ticket_glo_00205 | H20: URキャラ1体確定10連フェスガシャチケット | I20: UR | J20: 999999999 | K20: 999999999 | L20: フェス限定URキャラ1体確定10連ガシャを引くことができるアイテム | M20: ガシャデータ未作成 有償販売・プリズム販売・オマケのみ URキャラ1体確定の10連ガシャチケット。1枚(10連)ずつしか使えない。 | N20: 2024-01-01 00:00:00 | O20: 202509010 | P20: 7500
A21: glo | B21: {=iferror(INDEX('作品'!D:D,MATCH(A21,'作品'!A:A,0),0),"error")} -> GLOW | C21: ticket | D21: 00206 | E21: =C21&"_"&A21&"_"&D21 -> ticket_glo_00206 | F21: =E21 -> ticket_glo_00206 | G21: ="item_icon_"&F21 -> item_icon_ticket_glo_00206 | H21: 『補てん』スタートダッシュガシャチケット | I21: UR | J21: 999999999 | K21: 999999999 | L21: 72時間限定スタートダッシュガシャを引くことができるアイテム | N21: 2024-01-01 00:00:00 | O21: 202509010
A22: glo | B22: {=iferror(INDEX('作品'!D:D,MATCH(A22,'作品'!A:A,0),0),"error")} -> GLOW | C22: ticket | D22: 00207 | E22: =C22&"_"&A22&"_"&D22 -> ticket_glo_00207 | F22: =E22 -> ticket_glo_00207 | G22: ="item_icon_"&F22 -> item_icon_ticket_glo_00207 | H22: 『補てん』2026年正月記念！UR1体確定ガシャチケット | I22: UR | J22: 999999999 | K22: 999999999 | L22: 2026年正月記念！UR1体確定ガシャを引くことができるアイテム | N22: 2026-01-01 00:00:00 | O22: 202512020
A23: glo | B23: {=iferror(INDEX('作品'!D:D,MATCH(A23,'作品'!A:A,0),0),"error")} -> GLOW | C23: ticket | D23: 90000 | E23: =C23&"_"&A23&"_"&D23 -> ticket_glo_90000 | F23: =E23 -> ticket_glo_90000 | G23: ="item_icon_"&F23 -> item_icon_ticket_glo_90000 | H23: プレミアムメダル | I23: UR | J23: 999999999 | K23: 999999999 | L23: プレミアムメダルガシャを引くことができるアイテム | N23: 2024-01-01 00:00:00 | O23: 202509010
A24: osh | B24: {=iferror(INDEX('作品'!D:D,MATCH(A24,'作品'!A:A,0),0),"error")} -> 【推しの子】 | C24: ticket | D24: 10000 | E24: =C24&"_"&A24&"_"&D24 -> ticket_osh_10000 | F24: =E24 -> ticket_osh_10000 | G24: ="item_icon_"&F24 -> item_icon_ticket_osh_10000 | H24: 【推しの子】SSR確定ガシャチケット | I24: SSR | J24: 999999999 | K24: 999999999 | L24: 【推しの子】SSR確定ガシャを引くことができるアイテム | M24: 推しの子イベント用 | N24: 2026-01-01 00:00:00 | O24: 202512020
A25: glo | B25: {=iferror(INDEX('作品'!D:D,MATCH(A25,'作品'!A:A,0),0),"error")} -> GLOW | C25: ticket | D25: 10001 | E25: =C25&"_"&A25&"_"&D25 -> ticket_glo_10001 | F25: =E25 -> ticket_glo_10001 | G25: ="item_icon_"&F25 -> item_icon_ticket_glo_10001 | H25: 賀正ガシャチケット Ver.2026 | I25: SSR | J25: 999999999 | K25: 999999999 | L25: 賀正ガシャ Ver.2026を引くことができるアイテム。ミッションをクリアしてたくさん集めよう！ | M25: 正月イベント用 | N25: 2026-01-01 00:00:00 | O25: 202512020
A26: kim | B26: {=iferror(INDEX('作品'!D:D,MATCH(A26,'作品'!A:A,0),0),"error")} -> 君のことが大大大大大好きな100人の彼女 | C26: ticket | D26: 00001 | E26: =C26&"_"&A26&"_"&D26 -> ticket_kim_00001 | F26: =E26 -> ticket_kim_00001 | G26: ="item_icon_"&F26 -> item_icon_ticket_kim_00001 | H26: SSR彼女確定ガシャチケット | I26: SSR | J26: 999999999 | K26: 999999999 | L26: SSR彼女確定ガシャを引くことができるアイテム | M26: 君のことが大大大大大好きな100人の彼女イベント用
A27: glo | B27: {=iferror(INDEX('作品'!D:D,MATCH(A27,'作品'!A:A,0),0),"error")} -> GLOW | C27: ticket | D27: 10002 | E27: =C27&"_"&A27&"_"&D27 -> ticket_glo_10002 | F27: =E27 -> ticket_glo_10002 | G27: ="item_icon_"&F27 -> item_icon_ticket_glo_10002 | H27: バレンタインピックアップガシャチケット | I27: SSR | J27: 999999999 | K27: 999999999 | L27: バレンタインピックアップガシャチケットを引くことができるアイテム | M27: バレンタインガシャ用 | N27: 2026-01-01 00:00:00 | O27: 202512020
A30: glo | B30: {=iferror(INDEX('作品'!D:D,MATCH(A30,'作品'!A:A,0),0),"error")} -> GLOW | C30: memory | D30: 00001 | E30: =C30&"_"&A30&"_"&D30 -> memory_glo_00001 | F30: =E30 -> memory_glo_00001 | G30: ="item_icon_"&F30 -> item_icon_memory_glo_00001 | H30: カラーメモリー・グレー | I30: UR | J30: 999999999 | K30: 999999999 | L30: 無属性キャラのLv.上限開放に使用するアイテム | N30: 2024-01-01 00:00:00 | O30: 202509010 | P30: 14.4
A31: glo | B31: {=iferror(INDEX('作品'!D:D,MATCH(A31,'作品'!A:A,0),0),"error")} -> GLOW | C31: memory | D31: 00002 | E31: =C31&"_"&A31&"_"&D31 -> memory_glo_00002 | F31: =E31 -> memory_glo_00002 | G31: ="item_icon_"&F31 -> item_icon_memory_glo_00002 | H31: カラーメモリー・レッド | I31: UR | J31: 999999999 | K31: 999999999 | L31: 赤属性キャラのLv.上限開放に使用するアイテム | N31: 2024-01-01 00:00:00 | O31: 202509010 | P31: 14.4
A32: glo | B32: {=iferror(INDEX('作品'!D:D,MATCH(A32,'作品'!A:A,0),0),"error")} -> GLOW | C32: memory | D32: 00003 | E32: =C32&"_"&A32&"_"&D32 -> memory_glo_00003 | F32: =E32 -> memory_glo_00003 | G32: ="item_icon_"&F32 -> item_icon_memory_glo_00003 | H32: カラーメモリー・ブルー | I32: UR | J32: 999999999 | K32: 999999999 | L32: 青属性キャラのLv.上限開放に使用するアイテム | N32: 2024-01-01 00:00:00 | O32: 202509010 | P32: 14.4
A33: glo | B33: {=iferror(INDEX('作品'!D:D,MATCH(A33,'作品'!A:A,0),0),"error")} -> GLOW | C33: memory | D33: 00004 | E33: =C33&"_"&A33&"_"&D33 -> memory_glo_00004 | F33: =E33 -> memory_glo_00004 | G33: ="item_icon_"&F33 -> item_icon_memory_glo_00004 | H33: カラーメモリー・イエロー | I33: UR | J33: 999999999 | K33: 999999999 | L33: 黄属性キャラのLv.上限開放に使用するアイテム | N33: 2024-01-01 00:00:00 | O33: 202509010 | P33: 14.4
A34: glo | B34: {=iferror(INDEX('作品'!D:D,MATCH(A34,'作品'!A:A,0),0),"error")} -> GLOW | C34: memory | D34: 00005 | E34: =C34&"_"&A34&"_"&D34 -> memory_glo_00005 | F34: =E34 -> memory_glo_00005 | G34: ="item_icon_"&F34 -> item_icon_memory_glo_00005 | H34: カラーメモリー・グリーン | I34: UR | J34: 999999999 | K34: 999999999 | L34: 緑属性キャラのLv.上限開放に使用するアイテム | N34: 2024-01-01 00:00:00 | O34: 202509010 | P34: 14.4
A35: glo | B35: {=iferror(INDEX('作品'!D:D,MATCH(A35,'作品'!A:A,0),0),"error")} -> GLOW | C35: memoryfragment | D35: 00001 | E35: =C35&"_"&A35&"_"&D35 -> memoryfragment_glo_00001 | F35: =E35 -> memoryfragment_glo_00001 | G35: ="item_icon_"&F35 -> item_icon_memoryfragment_glo_00001 | H35: メモリーフラグメント・初級 | I35: SR | J35: 999999999 | K35: 999999999 | L35: キャラのLv.上限開放に使用するアイテム | N35: 2024-01-01 00:00:00 | O35: 202509010 | P35: 33
A36: glo | B36: {=iferror(INDEX('作品'!D:D,MATCH(A36,'作品'!A:A,0),0),"error")} -> GLOW | C36: memoryfragment | D36: 00002 | E36: =C36&"_"&A36&"_"&D36 -> memoryfragment_glo_00002 | F36: =E36 -> memoryfragment_glo_00002 | G36: ="item_icon_"&F36 -> item_icon_memoryfragment_glo_00002 | H36: メモリーフラグメント・中級 | I36: SSR | J36: 999999999 | K36: 999999999 | L36: キャラのLv.上限開放に使用するアイテム | N36: 2024-01-01 00:00:00 | O36: 202509010 | P36: 66
A37: glo | B37: {=iferror(INDEX('作品'!D:D,MATCH(A37,'作品'!A:A,0),0),"error")} -> GLOW | C37: memoryfragment | D37: 00003 | E37: =C37&"_"&A37&"_"&D37 -> memoryfragment_glo_00003 | F37: =E37 -> memoryfragment_glo_00003 | G37: ="item_icon_"&F37 -> item_icon_memoryfragment_glo_00003 | H37: メモリーフラグメント・上級 | I37: UR | J37: 999999999 | K37: 999999999 | L37: キャラのLv.上限開放に使用するアイテム | N37: 2024-01-01 00:00:00 | O37: 202509010 | P37: 99
A40: glo | B40: {=iferror(INDEX('作品'!D:D,MATCH(A40,'作品'!A:A,0),0),"error")} -> GLOW | C40: box | D40: 00001 | E40: =C40&"_"&A40&"_"&D40 -> box_glo_00001 | F40: =E40 -> box_glo_00001 | G40: ="item_icon_"&F40 -> item_icon_box_glo_00001 | H40: ランダムRキャラのかけらBOX | I40: R | J40: 999999999 | K40: 999999999 | L40: Rのキャラのかけらがランダムで獲得できるアイテムBOX | N40: 2024-01-01 00:00:00 | O40: 202509010
A41: glo | B41: {=iferror(INDEX('作品'!D:D,MATCH(A41,'作品'!A:A,0),0),"error")} -> GLOW | C41: box | D41: 00002 | E41: =C41&"_"&A41&"_"&D41 -> box_glo_00002 | F41: =E41 -> box_glo_00002 | G41: ="item_icon_"&F41 -> item_icon_box_glo_00002 | H41: ランダムSRキャラのかけらBOX | I41: SR | J41: 999999999 | K41: 999999999 | L41: SRのキャラのかけらがランダムで獲得できるアイテムBOX | N41: 2024-01-01 00:00:00 | O41: 202509010
A42: glo | B42: {=iferror(INDEX('作品'!D:D,MATCH(A42,'作品'!A:A,0),0),"error")} -> GLOW | C42: box | D42: 00003 | E42: =C42&"_"&A42&"_"&D42 -> box_glo_00003 | F42: =E42 -> box_glo_00003 | G42: ="item_icon_"&F42 -> item_icon_box_glo_00003 | H42: ランダムSSRキャラのかけらBOX | I42: SSR | J42: 999999999 | K42: 999999999 | L42: SSRのキャラのかけらがランダムで獲得できるアイテムBOX | N42: 2024-01-01 00:00:00 | O42: 202509010
A43: glo | B43: {=iferror(INDEX('作品'!D:D,MATCH(A43,'作品'!A:A,0),0),"error")} -> GLOW | C43: box | D43: 00004 | E43: =C43&"_"&A43&"_"&D43 -> box_glo_00004 | F43: =E43 -> box_glo_00004 | G43: ="item_icon_"&F43 -> item_icon_box_glo_00004 | H43: ランダムURキャラのかけらBOX | I43: UR | J43: 999999999 | K43: 999999999 | L43: URのキャラのかけらがランダムで獲得できるアイテムBOX | N43: 2024-01-01 00:00:00 | O43: 202509010
A44: glo | B44: {=iferror(INDEX('作品'!D:D,MATCH(A44,'作品'!A:A,0),0),"error")} -> GLOW | C44: box | D44: 00005 | E44: =C44&"_"&A44&"_"&D44 -> box_glo_00005 | F44: =E44 -> box_glo_00005 | G44: ="item_icon_"&F44 -> item_icon_box_glo_00005 | H44: 選べるRキャラのかけらBOX | I44: R | J44: 999999999 | K44: 999999999 | L44: Rのキャラのかけらを選択して獲得できるアイテムBOX | N44: 2024-01-01 00:00:00 | O44: 202509010
A45: glo | B45: {=iferror(INDEX('作品'!D:D,MATCH(A45,'作品'!A:A,0),0),"error")} -> GLOW | C45: box | D45: 00006 | E45: =C45&"_"&A45&"_"&D45 -> box_glo_00006 | F45: =E45 -> box_glo_00006 | G45: ="item_icon_"&F45 -> item_icon_box_glo_00006 | H45: 選べるSRキャラのかけらBOX | I45: SR | J45: 999999999 | K45: 999999999 | L45: SRのキャラのかけらを選択して獲得できるアイテムBOX | N45: 2024-01-01 00:00:00 | O45: 202509010
A46: glo | B46: {=iferror(INDEX('作品'!D:D,MATCH(A46,'作品'!A:A,0),0),"error")} -> GLOW | C46: box | D46: 00007 | E46: =C46&"_"&A46&"_"&D46 -> box_glo_00007 | F46: =E46 -> box_glo_00007 | G46: ="item_icon_"&F46 -> item_icon_box_glo_00007 | H46: 選べるSSRキャラのかけらBOX | I46: SSR | J46: 999999999 | K46: 999999999 | L46: SSRのキャラのかけらを選択して獲得できるアイテムBOX | N46: 2024-01-01 00:00:00 | O46: 202509010
A47: glo | B47: {=iferror(INDEX('作品'!D:D,MATCH(A47,'作品'!A:A,0),0),"error")} -> GLOW | C47: box | D47: 00008 | E47: =C47&"_"&A47&"_"&D47 -> box_glo_00008 | F47: =E47 -> box_glo_00008 | G47: ="item_icon_"&F47 -> item_icon_box_glo_00008 | H47: 選べるURキャラのかけらBOX | I47: UR | J47: 999999999 | K47: 999999999 | L47: URのキャラのかけらを選択して獲得できるアイテムBOX | N47: 2024-01-01 00:00:00 | O47: 202509010
A55: glo | B55: {=iferror(INDEX('作品'!D:D,MATCH(A55,'作品'!A:A,0),0),"error")} -> GLOW | C55: tool | D55: 00001 | E55: =C55&"_"&A55&"_"&D55 -> tool_glo_00001 | F55: =E55 -> tool_glo_00001 | G55: ="item_icon_"&F55 -> item_icon_tool_glo_00001 | H55: 探索N時間分コイン | I55: SR | J55: - | K55: - | M55: リリースしない。 削除すると危ないので、使用できない状態でIDは残しておく。 「探索」N時間分で獲得できる同量のコインが獲得できるアイテム。獲得時に自動的に使用される。 | N55: リリース無し
A56: glo | B56: {=iferror(INDEX('作品'!D:D,MATCH(A56,'作品'!A:A,0),0),"error")} -> GLOW | C56: tool | D56: 00002 | E56: =C56&"_"&A56&"_"&D56 -> tool_glo_00002 | F56: =E56 -> tool_glo_00002 | G56: ="item_icon_"&F56 -> item_icon_tool_glo_00002 | H56: 探索N時間分リミテッドメモリー | I56: SR | J56: - | K56: - | M56: リリースしない。 削除すると危ないので、使用できない状態でIDは残しておく。 「探索」N時間分で獲得できる同量のリミテッドメモリーが獲得できるアイテム。獲得時に自動的に使用される。 | N56: リリース無し
A59: glo | B59: GLOW | C59: piece | D59: 000001 | E59: =C59&"_"&A59&"_"&D59 -> piece_glo_000001 | F59: =E59 -> piece_glo_000001 | G59: ="item_icon_"&F59 -> item_icon_piece_glo_000001 | H59: キャラの結晶 | I59: UR | J59: 999999999 | K59: 999999999 | M59: 余ったキャラのかけらを交換して、グレードアップのワイルドカードとして使える。 ※仕様どうなるか検討中 10/11記載 | N59: 未設定 | O59: 未設定
A60: spy | B60: {=iferror(INDEX('作品'!D:D,MATCH(A60,'作品'!A:A,0),0),"error")} -> SPY×FAMILY | C60: piece | D60: 00001 | E60: =C60&"_"&A60&"_"&D60 -> piece_spy_00001 | F60: =E60 -> piece_spy_00001 | G60: ="item_icon_"&F60 -> item_icon_piece_spy_00001 | H60: わくわく アーニャのかけら | I60: UR | J60: 999999999 | K60: 999999999 | L60: わくわく アーニャのグレードアップに使用するアイテム | N60: 2024-01-01 00:00:00 | O60: 202509010
A61: spy | B61: {=iferror(INDEX('作品'!D:D,MATCH(A61,'作品'!A:A,0),0),"error")} -> SPY×FAMILY | C61: piece | D61: 00101 | E61: =C61&"_"&A61&"_"&D61 -> piece_spy_00101 | F61: =E61 -> piece_spy_00101 | G61: ="item_icon_"&F61 -> item_icon_piece_spy_00101 | H61: ＜黄昏＞ ロイドのかけら | I61: UR | J61: 999999999 | K61: 999999999 | L61: ＜黄昏＞ ロイドのグレードアップに使用するアイテム | N61: 2024-01-01 00:00:00 | O61: 202509010
A62: spy | B62: {=iferror(INDEX('作品'!D:D,MATCH(A62,'作品'!A:A,0),0),"error")} -> SPY×FAMILY | C62: piece | D62: 00201 | E62: =C62&"_"&A62&"_"&D62 -> piece_spy_00201 | F62: =E62 -> piece_spy_00201 | G62: ="item_icon_"&F62 -> item_icon_piece_spy_00201 | H62: ＜いばら姫＞ ヨルのかけら | I62: UR | J62: 999999999 | K62: 999999999 | L62: ＜いばら姫＞ ヨルのグレードアップに使用するアイテム | N62: 2024-01-01 00:00:00 | O62: 202509010
A63: spy | B63: {=iferror(INDEX('作品'!D:D,MATCH(A63,'作品'!A:A,0),0),"error")} -> SPY×FAMILY | C63: piece | D63: 00301 | E63: =C63&"_"&A63&"_"&D63 -> piece_spy_00301 | F63: =E63 -> piece_spy_00301 | G63: ="item_icon_"&F63 -> item_icon_piece_spy_00301 | H63: ダミアン・デズモンドのかけら | I63: SR | J63: 999999999 | K63: 999999999 | L63: ダミアン・デズモンドのグレードアップに使用するアイテム | N63: 45936.625 | O63: 202510010
A64: spy | B64: {=iferror(INDEX('作品'!D:D,MATCH(A64,'作品'!A:A,0),0),"error")} -> SPY×FAMILY | C64: piece | D64: 00401 | E64: =C64&"_"&A64&"_"&D64 -> piece_spy_00401 | F64: =E64 -> piece_spy_00401 | G64: ="item_icon_"&F64 -> item_icon_piece_spy_00401 | H64: フランキー・フランクリンのかけら | I64: SR | J64: 999999999 | K64: 999999999 | L64: フランキー・フランクリンのグレードアップに使用するアイテム | N64: 45936.625 | O64: 202510010
A65: spy | B65: {=iferror(INDEX('作品'!D:D,MATCH(A65,'作品'!A:A,0),0),"error")} -> SPY×FAMILY | C65: piece | D65: 00501 | E65: =C65&"_"&A65&"_"&D65 -> piece_spy_00501 | F65: =E65 -> piece_spy_00501 | G65: ="item_icon_"&F65 -> item_icon_piece_spy_00501 | H65: 姉を想う盲愛 ユーリ・ブライアのかけら | I65: UR | J65: 999999999 | K65: 999999999 | L65: 姉を想う盲愛 ユーリ・ブライアのグレードアップに使用するアイテム | N65: 45936.625 | O65: 202510010
A66: aka | B66: {=iferror(INDEX('作品'!D:D,MATCH(A66,'作品'!A:A,0),0),"error")} -> ラーメン赤猫 | C66: piece | D66: 00001 | E66: =C66&"_"&A66&"_"&D66 -> piece_aka_00001 | F66: =E66 -> piece_aka_00001 | G66: ="item_icon_"&F66 -> item_icon_piece_aka_00001 | H66: 佐々木のかけら | I66: R | J66: 999999999 | K66: 999999999 | L66: 佐々木のグレードアップに使用するアイテム | N66: 2024-01-01 00:00:00 | O66: 202509010
A67: aka | B67: {=iferror(INDEX('作品'!D:D,MATCH(A67,'作品'!A:A,0),0),"error")} -> ラーメン赤猫 | C67: piece | D67: 00101 | E67: =C67&"_"&A67&"_"&D67 -> piece_aka_00101 | F67: =E67 -> piece_aka_00101 | G67: ="item_icon_"&F67 -> item_icon_piece_aka_00101 | H67: 文蔵のかけら | I67: R | J67: 999999999 | K67: 999999999 | L67: 文蔵のグレードアップに使用するアイテム | N67: 2024-01-01 00:00:00 | O67: 202509010
A68: rik | B68: {=iferror(INDEX('作品'!D:D,MATCH(A68,'作品'!A:A,0),0),"error")} -> トマトイプーのリコピン | C68: piece | D68: 00001 | E68: =C68&"_"&A68&"_"&D68 -> piece_rik_00001 | F68: =E68 -> piece_rik_00001 | G68: ="item_icon_"&F68 -> item_icon_piece_rik_00001 | H68: リコピンのかけら | I68: R | J68: 999999999 | K68: 999999999 | L68: リコピンのグレードアップに使用するアイテム | N68: 2024-01-01 00:00:00 | O68: 202509010
A69: rik | B69: {=iferror(INDEX('作品'!D:D,MATCH(A69,'作品'!A:A,0),0),"error")} -> トマトイプーのリコピン | C69: piece | D69: 00101 | E69: =C69&"_"&A69&"_"&D69 -> piece_rik_00101 | F69: =E69 -> piece_rik_00101 | G69: ="item_icon_"&F69 -> item_icon_piece_rik_00101 | H69: 甘戸 めめのかけら | I69: R | J69: 999999999 | K69: 999999999 | L69: 甘戸 めめのグレードアップに使用するアイテム | N69: 2024-01-01 00:00:00 | O69: 202509010
A70: dan | B70: {=iferror(INDEX('作品'!D:D,MATCH(A70,'作品'!A:A,0),0),"error")} -> ダンダダン | C70: piece | D70: 00001 | E70: =C70&"_"&A70&"_"&D70 -> piece_dan_00001 | F70: =E70 -> piece_dan_00001 | G70: ="item_icon_"&F70 -> item_icon_piece_dan_00001 | H70: オカルンのかけら | I70: R | J70: 999999999 | K70: 999999999 | L70: オカルンのグレードアップに使用するアイテム | N70: 2024-01-01 00:00:00 | O70: 202509010
A71: dan | B71: {=iferror(INDEX('作品'!D:D,MATCH(A71,'作品'!A:A,0),0),"error")} -> ダンダダン | C71: piece | D71: 00002 | E71: =C71&"_"&A71&"_"&D71 -> piece_dan_00002 | F71: =E71 -> piece_dan_00002 | G71: ="item_icon_"&F71 -> item_icon_piece_dan_00002 | H71: ターボババアの霊力 オカルンのかけら | I71: UR | J71: 999999999 | K71: 999999999 | L71: ターボババアの霊力 オカルンのグレードアップに使用するアイテム | N71: 2024-01-01 00:00:00 | O71: 202509010
A72: dan | B72: {=iferror(INDEX('作品'!D:D,MATCH(A72,'作品'!A:A,0),0),"error")} -> ダンダダン | C72: piece | D72: 00101 | E72: =C72&"_"&A72&"_"&D72 -> piece_dan_00101 | F72: =E72 -> piece_dan_00101 | G72: ="item_icon_"&F72 -> item_icon_piece_dan_00101 | H72: モモのかけら | I72: SSR | J72: 999999999 | K72: 999999999 | L72: モモのグレードアップに使用するアイテム | N72: 2024-01-01 00:00:00 | O72: 202509010
A73: dan | B73: {=iferror(INDEX('作品'!D:D,MATCH(A73,'作品'!A:A,0),0),"error")} -> ダンダダン | C73: piece | D73: 00201 | E73: =C73&"_"&A73&"_"&D73 -> piece_dan_00201 | F73: =E73 -> piece_dan_00201 | G73: ="item_icon_"&F73 -> item_icon_piece_dan_00201 | H73: アイラのかけら | I73: SR | J73: 999999999 | K73: 999999999 | L73: アイラのグレードアップに使用するアイテム | N73: 45952.625 | O73: 202510020
A74: dan | B74: {=iferror(INDEX('作品'!D:D,MATCH(A74,'作品'!A:A,0),0),"error")} -> ダンダダン | C74: piece | D74: 00202 | E74: =C74&"_"&A74&"_"&D74 -> piece_dan_00202 | F74: =E74 -> piece_dan_00202 | G74: ="item_icon_"&F74 -> item_icon_piece_dan_00202 | H74: アクさらの愛 アイラ のかけら | I74: UR | J74: 999999999 | K74: 999999999 | L74: アクさらの愛 アイラのグレードアップに使用するアイテム | N74: 45952.625 | O74: 202510020
A75: dan | B75: {=iferror(INDEX('作品'!D:D,MATCH(A75,'作品'!A:A,0),0),"error")} -> ダンダダン | C75: piece | D75: 00301 | E75: =C75&"_"&A75&"_"&D75 -> piece_dan_00301 | F75: =E75 -> piece_dan_00301 | G75: ="item_icon_"&F75 -> item_icon_piece_dan_00301 | H75: 招き猫 ターボババアのかけら | I75: SR | J75: 999999999 | K75: 999999999 | L75: 招き猫 ターボババアのグレードアップに使用するアイテム | N75: 45952.625 | O75: 202510020
A76: gom | B76: {=iferror(INDEX('作品'!D:D,MATCH(A76,'作品'!A:A,0),0),"error")} -> 姫様“拷問”の時間です | C76: piece | D76: 00001 | E76: =C76&"_"&A76&"_"&D76 -> piece_gom_00001 | F76: =E76 -> piece_gom_00001 | G76: ="item_icon_"&F76 -> item_icon_piece_gom_00001 | H76: 囚われの王女 姫様のかけら | I76: UR | J76: 999999999 | K76: 999999999 | L76: 囚われの王女 姫様のグレードアップに使用するアイテム | N76: 2024-01-01 00:00:00 | O76: 202509010
A77: gom | B77: {=iferror(INDEX('作品'!D:D,MATCH(A77,'作品'!A:A,0),0),"error")} -> 姫様“拷問”の時間です | C77: piece | D77: 00101 | E77: =C77&"_"&A77&"_"&D77 -> piece_gom_00101 | F77: =E77 -> piece_gom_00101 | G77: ="item_icon_"&F77 -> item_icon_piece_gom_00101 | H77: トーチャー・トルチュールのかけら | I77: SR | J77: 999999999 | K77: 999999999 | L77: トーチャー・トルチュールのグレードアップに使用するアイテム | N77: 2024-01-01 00:00:00 | O77: 202509010
A78: gom | B78: {=iferror(INDEX('作品'!D:D,MATCH(A78,'作品'!A:A,0),0),"error")} -> 姫様“拷問”の時間です | C78: piece | D78: 00201 | E78: =C78&"_"&A78&"_"&D78 -> piece_gom_00201 | F78: =E78 -> piece_gom_00201 | G78: ="item_icon_"&F78 -> item_icon_piece_gom_00201 | H78: クロルのかけら | I78: R | J78: 999999999 | K78: 999999999 | L78: クロルのグレードアップに使用するアイテム | N78: 2024-01-01 00:00:00 | O78: 202509010
A79: chi | B79: {=iferror(INDEX('作品'!D:D,MATCH(A79,'作品'!A:A,0),0),"error")} -> チェンソーマン | C79: piece | D79: 00001 | E79: =C79&"_"&A79&"_"&D79 -> piece_chi_00001 | F79: =E79 -> piece_chi_00001 | G79: ="item_icon_"&F79 -> item_icon_piece_chi_00001 | H79: デンジのかけら | I79: R | J79: 999999999 | K79: 999999999 | L79: デンジのグレードアップに使用するアイテム | N79: 2024-01-01 00:00:00 | O79: 202509010
A80: chi | B80: {=iferror(INDEX('作品'!D:D,MATCH(A80,'作品'!A:A,0),0),"error")} -> チェンソーマン | C80: piece | D80: 00002 | E80: =C80&"_"&A80&"_"&D80 -> piece_chi_00002 | F80: =E80 -> piece_chi_00002 | G80: ="item_icon_"&F80 -> item_icon_piece_chi_00002 | H80: 悪魔が恐れる悪魔 チェンソーマンのかけら | I80: UR | J80: 999999999 | K80: 999999999 | L80: 悪魔が恐れる悪魔 チェンソーマンのグレードアップに使用するアイテム | N80: 2024-01-01 00:00:00 | O80: 202509010
A81: chi | B81: {=iferror(INDEX('作品'!D:D,MATCH(A81,'作品'!A:A,0),0),"error")} -> チェンソーマン | C81: piece | D81: 00201 | E81: =C81&"_"&A81&"_"&D81 -> piece_chi_00201 | F81: =E81 -> piece_chi_00201 | G81: ="item_icon_"&F81 -> item_icon_piece_chi_00201 | H81: 早川 アキのかけら | I81: SSR | J81: 999999999 | K81: 999999999 | L81: 早川 アキのグレードアップに使用するアイテム | N81: 2024-01-01 00:00:00 | O81: 202509010
A82: chi | B82: {=iferror(INDEX('作品'!D:D,MATCH(A82,'作品'!A:A,0),0),"error")} -> チェンソーマン | C82: piece | D82: 00301 | E82: =C82&"_"&A82&"_"&D82 -> piece_chi_00301 | F82: =E82 -> piece_chi_00301 | G82: ="item_icon_"&F82 -> item_icon_piece_chi_00301 | H82: パワーのかけら | I82: SSR | J82: 999999999 | K82: 999999999 | L82: パワーのグレードアップに使用するアイテム | N82: 2024-01-01 00:00:00 | O82: 202509010
A83: bat | B83: {=iferror(INDEX('作品'!D:D,MATCH(A83,'作品'!A:A,0),0),"error")} -> 忘却バッテリー | C83: piece | D83: 00001 | E83: =C83&"_"&A83&"_"&D83 -> piece_bat_00001 | F83: =E83 -> piece_bat_00001 | G83: ="item_icon_"&F83 -> item_icon_piece_bat_00001 | H83: 清峰 葉流火のかけら | I83: SR | J83: 999999999 | K83: 999999999 | L83: 清峰 葉流火のグレードアップに使用するアイテム | N83: 2024-01-01 00:00:00 | O83: 202509010
A84: bat | B84: {=iferror(INDEX('作品'!D:D,MATCH(A84,'作品'!A:A,0),0),"error")} -> 忘却バッテリー | C84: piece | D84: 00101 | E84: =C84&"_"&A84&"_"&D84 -> piece_bat_00101 | F84: =E84 -> piece_bat_00101 | G84: ="item_icon_"&F84 -> item_icon_piece_bat_00101 | H84: 要 圭のかけら | I84: SR | J84: 999999999 | K84: 999999999 | L84: 要 圭のグレードアップに使用するアイテム | N84: 2024-01-01 00:00:00 | O84: 202509010
A85: kai | B85: {=iferror(INDEX('作品'!D:D,MATCH(A85,'作品'!A:A,0),0),"error")} -> 怪獣８号 | C85: piece | D85: 00001 | E85: =C85&"_"&A85&"_"&D85 -> piece_kai_00001 | F85: =E85 -> piece_kai_00001 | G85: ="item_icon_"&F85 -> item_icon_piece_kai_00001 | H85: 日比野 カフカのかけら | I85: R | J85: 999999999 | K85: 999999999 | L85: 日比野 カフカのグレードアップに使用するアイテム | N85: 2024-01-01 00:00:00 | O85: 202509010
A86: kai | B86: {=iferror(INDEX('作品'!D:D,MATCH(A86,'作品'!A:A,0),0),"error")} -> 怪獣８号 | C86: piece | D86: 00002 | E86: =C86&"_"&A86&"_"&D86 -> piece_kai_00002 | F86: =E86 -> piece_kai_00002 | G86: ="item_icon_"&F86 -> item_icon_piece_kai_00002 | H86: 隠された英雄の姿 怪獣８号のかけら | I86: UR | J86: 999999999 | K86: 999999999 | L86: 隠された英雄の姿 怪獣８号のグレードアップに使用するアイテム | N86: 2024-01-01 00:00:00 | O86: 202509010
A87: kai | B87: {=iferror(INDEX('作品'!D:D,MATCH(A87,'作品'!A:A,0),0),"error")} -> 怪獣８号 | C87: piece | D87: 00101 | E87: =C87&"_"&A87&"_"&D87 -> piece_kai_00101 | F87: =E87 -> piece_kai_00101 | G87: ="item_icon_"&F87 -> item_icon_piece_kai_00101 | H87: 市川 レノのかけら | I87: SR | J87: 999999999 | K87: 999999999 | L87: 市川 レノのグレードアップに使用するアイテム | N87: 2024-01-01 00:00:00 | O87: 202509010
... A120: mag | B120: {=iferror(INDEX('作品'!D:D,MATCH(A120,'作品'!A:A,0),0),"error")} -> 株式会社マジルミエ | C120: piece | D120: 00101 | E120: =C120&"_"&A120&"_"&D120 -> piece_mag_00101 | F120: =E120 -> piece_mag_00101 | G120: ="item_icon_"&F120 -> item_icon_piece_mag_00101 | H120: 越谷 仁美のかけら | I120: SR | J120: 999999999 | K120: 999999999 | L120: 越谷 仁美のグレードアップに使用するアイテム | N120: 2024-01-01 00:00:00 | O120: 202509010
A121: mag | B121: {=iferror(INDEX('作品'!D:D,MATCH(A121,'作品'!A:A,0),0),"error")} -> 株式会社マジルミエ | C121: piece | D121: 00201 | E121: =C121&"_"&A121&"_"&D121 -> piece_mag_00201 | F121: =E121 -> piece_mag_00201 | G121: ="item_icon_"&F121 -> item_icon_piece_mag_00201 | H121: 絶対効率の体現者 土刃 メイのかけら | I121: UR | J121: 999999999 | K121: 999999999 | L121: 絶対効率の体現者 土刃 メイのグレードアップに使用するアイテム | N121: 45967.625 | O121: 202511010
A122: mag | B122: {=iferror(INDEX('作品'!D:D,MATCH(A122,'作品'!A:A,0),0),"error")} -> 株式会社マジルミエ | C122: piece | D122: 00301 | E122: =C122&"_"&A122&"_"&D122 -> piece_mag_00301 | F122: =E122 -> piece_mag_00301 | G122: ="item_icon_"&F122 -> item_icon_piece_mag_00301 | H122: 葵 リリーのかけら | I122: SSR | J122: 999999999 | K122: 999999999 | L122: 葵 リリーのグレードアップに使用するアイテム | N122: 45967.625 | O122: 202511010
A123: mag | B123: {=iferror(INDEX('作品'!D:D,MATCH(A123,'作品'!A:A,0),0),"error")} -> 株式会社マジルミエ | C123: piece | D123: 00401 | E123: =C123&"_"&A123&"_"&D123 -> piece_mag_00401 | F123: =E123 -> piece_mag_00401 | G123: ="item_icon_"&F123 -> item_icon_piece_mag_00401 | H123: 槇野 あかねのかけら | I123: SR | J123: 999999999 | K123: 999999999 | L123: 槇野 あかねのグレードアップに使用するアイテム | N123: 45967.625 | O123: 202511010
A124: mag | B124: {=iferror(INDEX('作品'!D:D,MATCH(A124,'作品'!A:A,0),0),"error")} -> 株式会社マジルミエ | C124: piece | D124: 00501 | E124: =C124&"_"&A124&"_"&D124 -> piece_mag_00501 | F124: =E124 -> piece_mag_00501 | G124: ="item_icon_"&F124 -> item_icon_piece_mag_00501 | H124: 重本 浩司のかけら | I124: SR | J124: 999999999 | K124: 999999999 | L124: 重本 浩司のグレードアップに使用するアイテム | N124: 45967.625 | O124: 202511010
A125: dos | B125: {=iferror(INDEX('作品'!D:D,MATCH(A125,'作品'!A:A,0),0),"error")} -> 道産子ギャルはなまらめんこい | C125: piece | D125: 00001 | E125: =C125&"_"&A125&"_"&D125 -> piece_dos_00001 | F125: =E125 -> piece_dos_00001 | G125: ="item_icon_"&F125 -> item_icon_piece_dos_00001 | H125: 冬木 美波のかけら | I125: SSR | J125: 999999999 | K125: 999999999 | L125: 冬木 美波のグレードアップに使用するアイテム | N125: 2024-01-01 00:00:00 | O125: 202509010
A126: dos | B126: {=iferror(INDEX('作品'!D:D,MATCH(A126,'作品'!A:A,0),0),"error")} -> 道産子ギャルはなまらめんこい | C126: piece | D126: 00101 | E126: =C126&"_"&A126&"_"&D126 -> piece_dos_00101 | F126: =E126 -> piece_dos_00101 | G126: ="item_icon_"&F126 -> item_icon_piece_dos_00101 | H126: 秋野 沙友理のかけら | I126: SSR | J126: 999999999 | K126: 999999999 | L126: 秋野 沙友理のグレードアップに使用するアイテム | N126: 2024-01-01 00:00:00 | O126: 202509010
A127: sum | B127: {=iferror(INDEX('作品'!D:D,MATCH(A127,'作品'!A:A,0),0),"error")} -> サマータイムレンダ | C127: piece | D127: 00001 | E127: =C127&"_"&A127&"_"&D127 -> piece_sum_00001 | F127: =E127 -> piece_sum_00001 | G127: ="item_icon_"&F127 -> item_icon_piece_sum_00001 | H127: 網代 慎平のかけら | I127: R | J127: 999999999 | K127: 999999999 | L127: 網代 慎平のグレードアップに使用するアイテム | N127: 2024-01-01 00:00:00 | O127: 202509010
A128: sum | B128: {=iferror(INDEX('作品'!D:D,MATCH(A128,'作品'!A:A,0),0),"error")} -> サマータイムレンダ | C128: piece | D128: 00101 | E128: =C128&"_"&A128&"_"&D128 -> piece_sum_00101 | F128: =E128 -> piece_sum_00101 | G128: ="item_icon_"&F128 -> item_icon_piece_sum_00101 | H128: 影のウシオ 小舟 潮のかけら | I128: UR | J128: 999999999 | K128: 999999999 | L128: 影のウシオ 小舟 潮のグレードアップに使用するアイテム | N128: 2024-01-01 00:00:00 | O128: 202509010
A129: sum | B129: {=iferror(INDEX('作品'!D:D,MATCH(A129,'作品'!A:A,0),0),"error")} -> サマータイムレンダ | C129: piece | D129: 00201 | E129: =C129&"_"&A129&"_"&D129 -> piece_sum_00201 | F129: =E129 -> piece_sum_00201 | G129: ="item_icon_"&F129 -> item_icon_piece_sum_00201 | H129: 小舟 澪のかけら | I129: SR | J129: 999999999 | K129: 999999999 | L129: 小舟 澪のグレードアップに使用するアイテム | N129: 2024-01-01 00:00:00 | O129: 202509010
A130: sum | B130: {=iferror(INDEX('作品'!D:D,MATCH(A130,'作品'!A:A,0),0),"error")} -> サマータイムレンダ | C130: piece | D130: 00301 | E130: =C130&"_"&A130&"_"&D130 -> piece_sum_00301 | F130: =E130 -> piece_sum_00301 | G130: ="item_icon_"&F130 -> item_icon_piece_sum_00301 | H130: 南方 竜之介のかけら | I130: SSR | J130: 999999999 | K130: 999999999 | N130: 未設定
A131: osh | B131: {=iferror(INDEX('作品'!D:D,MATCH(A131,'作品'!A:A,0),0),"error")} -> 【推しの子】 | C131: piece | D131: 00001 | E131: =C131&"_"&A131&"_"&D131 -> piece_osh_00001 | F131: =E131 -> piece_osh_00001 | G131: ="item_icon_"&F131 -> item_icon_piece_osh_00001 | H131: B小町不動のセンター アイのかけら | I131: UR | J131: 999999999 | K131: 999999999 | L131: B小町不動のセンター アイのグレードアップに使用するアイテム | N131: 2026-01-01 00:00:00 | O131: 202512020
A132: osh | B132: {=iferror(INDEX('作品'!D:D,MATCH(A132,'作品'!A:A,0),0),"error")} -> 【推しの子】 | C132: piece | D132: 00101 | E132: =C132&"_"&A132&"_"&D132 -> piece_osh_00101 | F132: =E132 -> piece_osh_00101 | G132: ="item_icon_"&F132 -> item_icon_piece_osh_00101 | H132: 復讐を誓う片星 星野 アクアのかけら | I132: UR | J132: 999999999 | K132: 999999999 | L132: 復讐を誓う片星 星野 アクアのグレードアップに使用するアイテム | N132: 2026-01-01 00:00:00 | O132: 202512020
A133: osh | B133: {=iferror(INDEX('作品'!D:D,MATCH(A133,'作品'!A:A,0),0),"error")} -> 【推しの子】 | C133: piece | D133: 00201 | E133: =C133&"_"&A133&"_"&D133 -> piece_osh_00201 | F133: =E133 -> piece_osh_00201 | G133: ="item_icon_"&F133 -> item_icon_piece_osh_00201 | H133: 星野 ルビーのかけら | I133: SSR | J133: 999999999 | K133: 999999999 | L133: 星野 ルビーのグレードアップに使用するアイテム | N133: 2026-01-01 00:00:00 | O133: 202512020
A134: osh | B134: {=iferror(INDEX('作品'!D:D,MATCH(A134,'作品'!A:A,0),0),"error")} -> 【推しの子】 | C134: piece | D134: 00301 | E134: =C134&"_"&A134&"_"&D134 -> piece_osh_00301 | F134: =E134 -> piece_osh_00301 | G134: ="item_icon_"&F134 -> item_icon_piece_osh_00301 | H134: MEMちょのかけら | I134: SSR | J134: 999999999 | K134: 999999999 | L134: MEMちょのグレードアップに使用するアイテム | N134: 2026-01-01 00:00:00 | O134: 202512020
A135: osh | B135: {=iferror(INDEX('作品'!D:D,MATCH(A135,'作品'!A:A,0),0),"error")} -> 【推しの子】 | C135: piece | D135: 00401 | E135: =C135&"_"&A135&"_"&D135 -> piece_osh_00401 | F135: =E135 -> piece_osh_00401 | G135: ="item_icon_"&F135 -> item_icon_piece_osh_00401 | H135: 有馬 かなのかけら | I135: SSR | J135: 999999999 | K135: 999999999 | L135: 有馬 かなのグレードアップに使用するアイテム | N135: 2026-01-01 00:00:00 | O135: 202512020
A136: osh | B136: {=iferror(INDEX('作品'!D:D,MATCH(A136,'作品'!A:A,0),0),"error")} -> 【推しの子】 | C136: piece | D136: 00501 | E136: =C136&"_"&A136&"_"&D136 -> piece_osh_00501 | F136: =E136 -> piece_osh_00501 | G136: ="item_icon_"&F136 -> item_icon_piece_osh_00501 | H136: 黒川 あかねのかけら | I136: SSR | J136: 999999999 | K136: 999999999 | L136: 黒川 あかねのグレードアップに使用するアイテム | N136: 2026-01-01 00:00:00 | O136: 202512020
A137: osh | B137: {=iferror(INDEX('作品'!D:D,MATCH(A137,'作品'!A:A,0),0),"error")} -> 【推しの子】 | C137: piece | D137: 00601 | E137: =C137&"_"&A137&"_"&D137 -> piece_osh_00601 | F137: =E137 -> piece_osh_00601 | G137: ="item_icon_"&F137 -> item_icon_piece_osh_00601 | H137: ぴえヨンのかけら | I137: SR | J137: 999999999 | K137: 999999999 | L137: ぴえヨンのグレードアップに使用するアイテム | N137: 2026-01-01 00:00:00 | O137: 202512020
A138: jig | B138: {=iferror(INDEX('作品'!D:D,MATCH(A138,'作品'!A:A,0),0),"error")} -> 地獄楽 | C138: piece | D138: 00401 | E138: =C138&"_"&A138&"_"&D138 -> piece_jig_00401 | F138: =E138 -> piece_jig_00401 | G138: ="item_icon_"&F138 -> item_icon_piece_jig_00401 | H138: 賊王 亜左 弔兵衛のかけら | I138: UR | J138: 999999999 | K138: 999999999 | L138: 賊王 亜左 弔兵衛のグレードアップに使用するアイテム | N138: 2026-01-16 15:00:00 | O138: 202601010
A139: jig | B139: {=iferror(INDEX('作品'!D:D,MATCH(A139,'作品'!A:A,0),0),"error")} -> 地獄楽 | C139: piece | D139: 00501 | E139: =C139&"_"&A139&"_"&D139 -> piece_jig_00501 | F139: =E139 -> piece_jig_00501 | G139: ="item_icon_"&F139 -> item_icon_piece_jig_00501 | H139: 山田浅ェ門 桐馬のかけら | I139: SSR | J139: 999999999 | K139: 999999999 | L139: 山田浅ェ門 桐馬のグレードアップに使用するアイテム | N139: 2026-01-16 15:00:00 | O139: 202601010
A140: jig | B140: {=iferror(INDEX('作品'!D:D,MATCH(A140,'作品'!A:A,0),0),"error")} -> 地獄楽 | C140: piece | D140: 00601 | E140: =C140&"_"&A140&"_"&D140 -> piece_jig_00601 | F140: =E140 -> piece_jig_00601 | G140: ="item_icon_"&F140 -> item_icon_piece_jig_00601 | H140: 民谷 巌鉄斎のかけら | I140: SR | J140: 999999999 | K140: 999999999 | L140: 民谷 巌鉄斎のグレードアップに使用するアイテム | N140: 2026-01-16 15:00:00 | O140: 202601010
A141: jig | B141: {=iferror(INDEX('作品'!D:D,MATCH(A141,'作品'!A:A,0),0),"error")} -> 地獄楽 | C141: piece | D141: 00701 | E141: =C141&"_"&A141&"_"&D141 -> piece_jig_00701 | F141: =E141 -> piece_jig_00701 | G141: ="item_icon_"&F141 -> item_icon_piece_jig_00701 | H141: メイのかけら | I141: SR | J141: 999999999 | K141: 999999999 | L141: メイのグレードアップに使用するアイテム | N141: 2026-01-16 15:00:00 | O141: 202601010
A142: you | B142: {=iferror(INDEX('作品'!D:D,MATCH(A142,'作品'!A:A,0),0),"error")} -> 幼稚園WARS | C142: piece | D142: 00001 | E142: =C142&"_"&A142&"_"&D142 -> piece_you_00001 | F142: =E142 -> piece_you_00001 | G142: ="item_icon_"&F142 -> item_icon_piece_you_00001 | H142: 元殺し屋の新人教諭 リタのかけら | I142: UR | J142: 999999999 | K142: 999999999 | L142: 元殺し屋の新人教諭 リタのグレードアップに使用するアイテム | N142: 2026-02-02 15:00:00 | O142: 202602010
... A145: you | B145: {=iferror(INDEX('作品'!D:D,MATCH(A145,'作品'!A:A,0),0),"error")} -> 幼稚園WARS | C145: piece | D145: 00301 | E145: =C145&"_"&A145&"_"&D145 -> piece_you_00301 | F145: =E145 -> piece_you_00301 | G145: ="item_icon_"&F145 -> item_icon_piece_you_00301 | H145: ハナのかけら | I145: SR | J145: 999999999 | K145: 999999999 | L145: ハナのグレードアップに使用するアイテム | N145: 2026-02-02 15:00:00 | O145: 202602010
A146: kim | B146: {=iferror(INDEX('作品'!D:D,MATCH(A146,'作品'!A:A,0),0),"error")} -> 君のことが大大大大大好きな100人の彼女 | C146: piece | D146: 00001 | E146: =C146&"_"&A146&"_"&D146 -> piece_kim_00001 | F146: =E146 -> piece_kim_00001 | G146: ="item_icon_"&F146 -> item_icon_piece_kim_00001 | H146: 溢れる母性 花園 羽々里のかけら | I146: UR | J146: 999999999 | K146: 999999999 | L146: 溢れる母性 花園 羽々里のグレードアップに使用するアイテム | N146: 2026-02-16 15:00:00
A147: kim | B147: {=iferror(INDEX('作品'!D:D,MATCH(A147,'作品'!A:A,0),0),"error")} -> 君のことが大大大大大好きな100人の彼女 | C147: piece | D147: 00101 | E147: =C147&"_"&A147&"_"&D147 -> piece_kim_00101 | F147: =E147 -> piece_kim_00101 | G147: ="item_icon_"&F147 -> item_icon_piece_kim_00101 | H147: 花園 羽香里のかけら | I147: SSR | J147: 999999999 | K147: 999999999 | L147: 花園 羽香里のグレードアップに使用するアイテム | N147: 2026-02-16 15:00:00
A148: kim | B148: {=iferror(INDEX('作品'!D:D,MATCH(A148,'作品'!A:A,0),0),"error")} -> 君のことが大大大大大好きな100人の彼女 | C148: piece | D148: 00201 | E148: =C148&"_"&A148&"_"&D148 -> piece_kim_00201 | F148: =E148 -> piece_kim_00201 | G148: ="item_icon_"&F148 -> item_icon_piece_kim_00201 | H148: 院田 唐音のかけら | I148: SSR | J148: 999999999 | K148: 999999999 | L148: 院田 唐音のグレードアップに使用するアイテム | N148: 2026-02-16 15:00:00
A149: kim | B149: {=iferror(INDEX('作品'!D:D,MATCH(A149,'作品'!A:A,0),0),"error")} -> 君のことが大大大大大好きな100人の彼女 | C149: piece | D149: 00301 | E149: =C149&"_"&A149&"_"&D149 -> piece_kim_00301 | F149: =E149 -> piece_kim_00301 | G149: ="item_icon_"&F149 -> item_icon_piece_kim_00301 | H149: 好本 静のかけら | I149: SSR | J149: 999999999 | K149: 999999999 | L149: 好本 静のグレードアップに使用するアイテム | N149: 2026-02-16 15:00:00
...

Sheet クエストカテゴリー
A1: クエストカテゴリー(意味) | B1: クエストカテゴリー | D1: クエスト難易度 | E1: クエスト難易度
A2: メインクエスト | B2: main | D2: 1日1回(イベント) | E2: 1day
A3: 強化/素材入手 | B3: training | D3: キャラ獲得 | E3: charaget
A4: 降臨バトル | B4: raid | D4: ストーリー | E4: story
A5: イベント | B5: event | D5: 原画獲得 | E5: artwork
D6: スピードチャレンジ | E6: challenge
D7: 高難易度 | E7: savage
D8: 降臨バトル | E8: raid

Sheet アバターアイコン
A1: 作品_ID | B1: 作品名 | C1: 識別ID | D1: アバターアイコン_ID | E1: キャラ_ID | F1: キャラ名（仮） | G1: キャラ名（監修FIX） | H1: valid_start_date | I1: valid_end_date | J1: デプロイ
A2: spy | B2: {=iferror(INDEX('作品'!D:D,MATCH(A2,'作品'!A:A,0),0),"error")} -> SPY×FAMILY | C2: 00001 | D2: ="unit_icon_chara"&"_"&A2&"_"&C2 -> unit_icon_chara_spy_00001 | E2: chara_spy_00001 | F2: イーデン校の生徒 アーニャ | G2: イーデン校の生徒 アーニャ | H2: 45658 | I2: 390812.5
A3: spy | B3: {=iferror(INDEX('作品'!D:D,MATCH(A3,'作品'!A:A,0),0),"error")} -> SPY×FAMILY | C3: 00002 | D3: ="unit_icon_chara"&"_"&A3&"_"&C3 -> unit_icon_chara_spy_00002 | E3: chara_spy_00002 | F3: アーニャ・フォージャー | G3: アーニャ・フォージャー | H3: 45658 | I3: 390812.5
A4: spy | B4: {=iferror(INDEX('作品'!D:D,MATCH(A4,'作品'!A:A,0),0),"error")} -> SPY×FAMILY | C4: 00101 | D4: ="unit_icon_chara"&"_"&A4&"_"&C4 -> unit_icon_chara_spy_00101 | E4: chara_spy_00101 | F4: ロイド・フォージャー | H4: 45658 | I4: 390812.5
A5: spy | B5: {=iferror(INDEX('作品'!D:D,MATCH(A5,'作品'!A:A,0),0),"error")} -> SPY×FAMILY | C5: 00201 | D5: ="unit_icon_chara"&"_"&A5&"_"&C5 -> unit_icon_chara_spy_00201 | E5: chara_spy_00201 | F5: ヨル・フォージャー | H5: 45658 | I5: 390812.5
A6: spy | B6: {=iferror(INDEX('作品'!D:D,MATCH(A6,'作品'!A:A,0),0),"error")} -> SPY×FAMILY | C6: 00301 | D6: ="unit_icon_chara"&"_"&A6&"_"&C6 -> unit_icon_chara_spy_00301 | E6: chara_spy_00301 | F6: ダミアン・デズモンド | H6: 45658 | I6: 390812.5
A7: spy | B7: {=iferror(INDEX('作品'!D:D,MATCH(A7,'作品'!A:A,0),0),"error")} -> SPY×FAMILY | C7: 00401 | D7: ="unit_icon_chara"&"_"&A7&"_"&C7 -> unit_icon_chara_spy_00401 | E7: chara_spy_00401 | F7: フランキー・フランクリン | H7: 45658 | I7: 390812.5
A8: aka | B8: {=iferror(INDEX('作品'!D:D,MATCH(A8,'作品'!A:A,0),0),"error")} -> ラーメン赤猫 | C8: 00001 | D8: ="unit_icon_chara"&"_"&A8&"_"&C8 -> unit_icon_chara_aka_00001 | E8: chara_aka_00001 | F8: 佐々木 | H8: 45658 | I8: 390812.5
A9: aka | B9: {=iferror(INDEX('作品'!D:D,MATCH(A9,'作品'!A:A,0),0),"error")} -> ラーメン赤猫 | C9: 00101 | D9: ="unit_icon_chara"&"_"&A9&"_"&C9 -> unit_icon_chara_aka_00101 | E9: chara_aka_00101 | F9: 文蔵 | H9: 45658 | I9: 390812.5
A10: rik | B10: {=iferror(INDEX('作品'!D:D,MATCH(A10,'作品'!A:A,0),0),"error")} -> トマトイプーのリコピン | C10: 00001 | D10: ="unit_icon_chara"&"_"&A10&"_"&C10 -> unit_icon_chara_rik_00001 | E10: chara_rik_00001 | F10: リコピン | H10: 45658 | I10: 390812.5
A11: rik | B11: {=iferror(INDEX('作品'!D:D,MATCH(A11,'作品'!A:A,0),0),"error")} -> トマトイプーのリコピン | C11: 00101 | D11: ="unit_icon_chara"&"_"&A11&"_"&C11 -> unit_icon_chara_rik_00101 | E11: chara_rik_00101 | F11: 甘戸 めめ | H11: 45658 | I11: 390812.5
A12: rik | B12: {=iferror(INDEX('作品'!D:D,MATCH(A12,'作品'!A:A,0),0),"error")} -> トマトイプーのリコピン | C12: 00201 | D12: ="unit_icon_chara"&"_"&A12&"_"&C12 -> unit_icon_chara_rik_00201 | E12: chara_rik_00201 | F12: チアミン | H12: 45658 | I12: 390812.5
A13: dan | B13: {=iferror(INDEX('作品'!D:D,MATCH(A13,'作品'!A:A,0),0),"error")} -> ダンダダン | C13: 00001 | D13: ="unit_icon_chara"&"_"&A13&"_"&C13 -> unit_icon_chara_dan_00001 | E13: chara_dan_00001 | F13: 綾瀬桃 | H13: 45658 | I13: 390812.5
A14: dan | B14: {=iferror(INDEX('作品'!D:D,MATCH(A14,'作品'!A:A,0),0),"error")} -> ダンダダン | C14: 00002 | D14: ="unit_icon_chara"&"_"&A14&"_"&C14 -> unit_icon_chara_dan_00002 | E14: chara_dan_00002 | F14: オカルン（高倉 健） （ターボババア憑依状態） | H14: 45658 | I14: 390812.5
A15: dan | B15: {=iferror(INDEX('作品'!D:D,MATCH(A15,'作品'!A:A,0),0),"error")} -> ダンダダン | C15: 00101 | D15: ="unit_icon_chara"&"_"&A15&"_"&C15 -> unit_icon_chara_dan_00101 | E15: chara_dan_00101 | F15: オカルン （制服着用） | H15: 45658 | I15: 390812.5
... A50: sum | B50: {=iferror(INDEX('作品'!D:D,MATCH(A50,'作品'!A:A,0),0),"error")} -> サマータイムレンダ | C50: 00201 | D50: ="unit_icon_chara"&"_"&A50&"_"&C50 -> unit_icon_chara_sum_00201 | E50: chara_sum_00201 | F50: 小舟 澪 | H50: 45658 | I50: 390812.5

Sheet クエスト
A1: 作品_ID | B1: 作品名 | C1: クエスト難易度 | D1: クエストカテゴリー | E1: クエストカテゴリー(意味) | F1: クエスト_id | G1: クエスト名 | H1: ステージ_id | I1: Stage_id | J1: ステージアイコン画像ID | K1: ステージ名 | L1: コマ段数 | M1: BGM_id | N1: BOSS_BGM_id | O1: 原画group_id | P1: デプロイ | Q1: 備考
A2: spy | B2: {=iferror(INDEX('作品'!D:D,MATCH(left(A2,3),'作品'!A:A,0),0),"error")} -> SPY×FAMILY | C2: normal | D2: main | E2: メインクエスト | F2: =IFERROR(__xludf.DUMMYFUNCTION("CONCATENATE(""quest_"",D2,""_"",A2,""_"",C2,""_"")&IFERROR(REGEXEXTRACT(G2,""[0-9]{2}""),REGEXEXTRACT(G2,""[0-9]{1}""))"),"quest_main_spy_normal_1") -> quest_main_spy_normal_1 | G2: 1.SPY FAMILY | H2: 01 | I2: =CONCATENATE(C2,"_",A2,"_","000",H2,) -> normal_spy_00001 | J2: ="stage_icon_"&A2&"_"&C2&"_"&H2 -> stage_icon_spy_normal_01
A3: spy | B3: {=iferror(INDEX('作品'!D:D,MATCH(left(A3,3),'作品'!A:A,0),0),"error")} -> SPY×FAMILY | C3: normal | D3: main | E3: メインクエスト | F3: =IFERROR(__xludf.DUMMYFUNCTION("CONCATENATE(""quest_"",D3,""_"",A3,""_"",C3,""_"")&IFERROR(REGEXEXTRACT(G3,""[0-9]{2}""),REGEXEXTRACT(G3,""[0-9]{1}""))"),"quest_main_spy_normal_1") -> quest_main_spy_normal_1 | G3: 1.SPY FAMILY | H3: 02 | I3: =CONCATENATE(C3,"_",A3,"_","000",H3,) -> normal_spy_00002 | J3: ="stage_icon_"&A3&"_"&C3&"_"&H3 -> stage_icon_spy_normal_02
A4: spy | B4: {=iferror(INDEX('作品'!D:D,MATCH(left(A4,3),'作品'!A:A,0),0),"error")} -> SPY×FAMILY | C4: normal | D4: main | E4: メインクエスト | F4: =IFERROR(__xludf.DUMMYFUNCTION("CONCATENATE(""quest_"",D4,""_"",A4,""_"",C4,""_"")&IFERROR(REGEXEXTRACT(G4,""[0-9]{2}""),REGEXEXTRACT(G4,""[0-9]{1}""))"),"quest_main_spy_normal_1") -> quest_main_spy_normal_1 | G4: 1.SPY FAMILY | H4: 03 | I4: =CONCATENATE(C4,"_",A4,"_","000",H4,) -> normal_spy_00003 | J4: ="stage_icon_"&A4&"_"&C4&"_"&H4 -> stage_icon_spy_normal_03
A5: spy | B5: {=iferror(INDEX('作品'!D:D,MATCH(left(A5,3),'作品'!A:A,0),0),"error")} -> SPY×FAMILY | C5: normal | D5: main | E5: メインクエスト | F5: =IFERROR(__xludf.DUMMYFUNCTION("CONCATENATE(""quest_"",D5,""_"",A5,""_"",C5,""_"")&IFERROR(REGEXEXTRACT(G5,""[0-9]{2}""),REGEXEXTRACT(G5,""[0-9]{1}""))"),"quest_main_spy_normal_1") -> quest_main_spy_normal_1 | G5: 1.SPY FAMILY | H5: 04 | I5: =CONCATENATE(C5,"_",A5,"_","000",H5,) -> normal_spy_00004 | J5: ="stage_icon_"&A5&"_"&C5&"_"&H5 -> stage_icon_spy_normal_04
A6: spy | B6: {=iferror(INDEX('作品'!D:D,MATCH(left(A6,3),'作品'!A:A,0),0),"error")} -> SPY×FAMILY | C6: normal | D6: main | E6: メインクエスト | F6: =IFERROR(__xludf.DUMMYFUNCTION("CONCATENATE(""quest_"",D6,""_"",A6,""_"",C6,""_"")&IFERROR(REGEXEXTRACT(G6,""[0-9]{2}""),REGEXEXTRACT(G6,""[0-9]{1}""))"),"quest_main_spy_normal_1") -> quest_main_spy_normal_1 | G6: 1.SPY FAMILY | H6: 05 | I6: =CONCATENATE(C6,"_",A6,"_","000",H6,) -> normal_spy_00005 | J6: ="stage_icon_"&A6&"_"&C6&"_"&H6 -> stage_icon_spy_normal_05
A7: spy | B7: {=iferror(INDEX('作品'!D:D,MATCH(left(A7,3),'作品'!A:A,0),0),"error")} -> SPY×FAMILY | C7: normal | D7: main | E7: メインクエスト | F7: =IFERROR(__xludf.DUMMYFUNCTION("CONCATENATE(""quest_"",D7,""_"",A7,""_"",C7,""_"")&IFERROR(REGEXEXTRACT(G7,""[0-9]{2}""),REGEXEXTRACT(G7,""[0-9]{1}""))"),"quest_main_spy_normal_1") -> quest_main_spy_normal_1 | G7: 1.SPY FAMILY | H7: 06 | I7: =CONCATENATE(C7,"_",A7,"_","000",H7,) -> normal_spy_00006 | J7: ="stage_icon_"&A7&"_"&C7&"_"&H7 -> stage_icon_spy_normal_06
A8: gom | B8: {=iferror(INDEX('作品'!D:D,MATCH(left(A8,3),'作品'!A:A,0),0),"error")} -> 姫様“拷問”の時間です | C8: normal | D8: main | E8: メインクエスト | F8: =IFERROR(__xludf.DUMMYFUNCTION("CONCATENATE(""quest_"",D8,""_"",A8,""_"",C8,""_"")&IFERROR(REGEXEXTRACT(G8,""[0-9]{2}""),REGEXEXTRACT(G8,""[0-9]{1}""))"),"quest_main_gom_normal_2") -> quest_main_gom_normal_2 | G8: 2.姫様“拷問”の時間です | H8: 01 | I8: =CONCATENATE(C8,"_",A8,"_","000",H8,) -> normal_gom_00001 | J8: ="stage_icon_"&A8&"_"&C8&"_"&H8 -> stage_icon_gom_normal_01
A9: gom | B9: {=iferror(INDEX('作品'!D:D,MATCH(left(A9,3),'作品'!A:A,0),0),"error")} -> 姫様“拷問”の時間です | C9: normal | D9: main | E9: メインクエスト | F9: =IFERROR(__xludf.DUMMYFUNCTION("CONCATENATE(""quest_"",D9,""_"",A9,""_"",C9,""_"")&IFERROR(REGEXEXTRACT(G9,""[0-9]{2}""),REGEXEXTRACT(G9,""[0-9]{1}""))"),"quest_main_gom_normal_2") -> quest_main_gom_normal_2 | G9: 2.姫様“拷問”の時間です | H9: 02 | I9: =CONCATENATE(C9,"_",A9,"_","000",H9,) -> normal_gom_00002 | J9: ="stage_icon_"&A9&"_"&C9&"_"&H9 -> stage_icon_gom_normal_02
A10: gom | B10: {=iferror(INDEX('作品'!D:D,MATCH(left(A10,3),'作品'!A:A,0),0),"error")} -> 姫様“拷問”の時間です | C10: normal | D10: main | E10: メインクエスト | F10: =IFERROR(__xludf.DUMMYFUNCTION("CONCATENATE(""quest_"",D10,""_"",A10,""_"",C10,""_"")&IFERROR(REGEXEXTRACT(G10,""[0-9]{2}""),REGEXEXTRACT(G10,""[0-9]{1}""))"),"quest_main_gom_normal_2") -> quest_main_gom_normal_2 | G10: 2.姫様“拷問”の時間です | H10: 03 | I10: =CONCATENATE(C10,"_",A10,"_","000",H10,) -> normal_gom_00003 | J10: ="stage_icon_"&A10&"_"&C10&"_"&H10 -> stage_icon_gom_normal_03
A11: gom | B11: {=iferror(INDEX('作品'!D:D,MATCH(left(A11,3),'作品'!A:A,0),0),"error")} -> 姫様“拷問”の時間です | C11: normal | D11: main | E11: メインクエスト | F11: =IFERROR(__xludf.DUMMYFUNCTION("CONCATENATE(""quest_"",D11,""_"",A11,""_"",C11,""_"")&IFERROR(REGEXEXTRACT(G11,""[0-9]{2}""),REGEXEXTRACT(G11,""[0-9]{1}""))"),"quest_main_gom_normal_2") -> quest_main_gom_normal_2 | G11: 2.姫様“拷問”の時間です | H11: 04 | I11: =CONCATENATE(C11,"_",A11,"_","000",H11,) -> normal_gom_00004 | J11: ="stage_icon_"&A11&"_"&C11&"_"&H11 -> stage_icon_gom_normal_04
A12: gom | B12: {=iferror(INDEX('作品'!D:D,MATCH(left(A12,3),'作品'!A:A,0),0),"error")} -> 姫様“拷問”の時間です | C12: normal | D12: main | E12: メインクエスト | F12: =IFERROR(__xludf.DUMMYFUNCTION("CONCATENATE(""quest_"",D12,""_"",A12,""_"",C12,""_"")&IFERROR(REGEXEXTRACT(G12,""[0-9]{2}""),REGEXEXTRACT(G12,""[0-9]{1}""))"),"quest_main_gom_normal_2") -> quest_main_gom_normal_2 | G12: 2.姫様“拷問”の時間です | H12: 05 | I12: =CONCATENATE(C12,"_",A12,"_","000",H12,) -> normal_gom_00005 | J12: ="stage_icon_"&A12&"_"&C12&"_"&H12 -> stage_icon_gom_normal_05
A13: gom | B13: {=iferror(INDEX('作品'!D:D,MATCH(left(A13,3),'作品'!A:A,0),0),"error")} -> 姫様“拷問”の時間です | C13: normal | D13: main | E13: メインクエスト | F13: =IFERROR(__xludf.DUMMYFUNCTION("CONCATENATE(""quest_"",D13,""_"",A13,""_"",C13,""_"")&IFERROR(REGEXEXTRACT(G13,""[0-9]{2}""),REGEXEXTRACT(G13,""[0-9]{1}""))"),"quest_main_gom_normal_2") -> quest_main_gom_normal_2 | G13: 2.姫様“拷問”の時間です | H13: 06 | I13: =CONCATENATE(C13,"_",A13,"_","000",H13,) -> normal_gom_00006 | J13: ="stage_icon_"&A13&"_"&C13&"_"&H13 -> stage_icon_gom_normal_06
A14: aka | B14: {=iferror(INDEX('作品'!D:D,MATCH(left(A14,3),'作品'!A:A,0),0),"error")} -> ラーメン赤猫 | C14: normal | D14: main | E14: メインクエスト | F14: =IFERROR(__xludf.DUMMYFUNCTION("CONCATENATE(""quest_"",D14,""_"",A14,""_"",C14,""_"")&IFERROR(REGEXEXTRACT(G14,""[0-9]{2}""),REGEXEXTRACT(G14,""[0-9]{1}""))"),"quest_main_aka_normal_3") -> quest_main_aka_normal_3 | G14: 3.ラーメン赤猫 | H14: 01 | I14: =CONCATENATE(C14,"_",A14,"_","000",H14,) -> normal_aka_00001 | J14: ="stage_icon_"&A14&"_"&C14&"_"&H14 -> stage_icon_aka_normal_01
A15: aka | B15: {=iferror(INDEX('作品'!D:D,MATCH(left(A15,3),'作品'!A:A,0),0),"error")} -> ラーメン赤猫 | C15: normal | D15: main | E15: メインクエスト | F15: =IFERROR(__xludf.DUMMYFUNCTION("CONCATENATE(""quest_"",D15,""_"",A15,""_"",C15,""_"")&IFERROR(REGEXEXTRACT(G15,""[0-9]{2}""),REGEXEXTRACT(G15,""[0-9]{1}""))"),"quest_main_aka_normal_3") -> quest_main_aka_normal_3 | G15: 3.ラーメン赤猫 | H15: 02 | I15: =CONCATENATE(C15,"_",A15,"_","000",H15,) -> normal_aka_00002 | J15: ="stage_icon_"&A15&"_"&C15&"_"&H15 -> stage_icon_aka_normal_02
A16: aka | B16: {=iferror(INDEX('作品'!D:D,MATCH(left(A16,3),'作品'!A:A,0),0),"error")} -> ラーメン赤猫 | C16: normal | D16: main | E16: メインクエスト | F16: =IFERROR(__xludf.DUMMYFUNCTION("CONCATENATE(""quest_"",D16,""_"",A16,""_"",C16,""_"")&IFERROR(REGEXEXTRACT(G16,""[0-9]{2}""),REGEXEXTRACT(G16,""[0-9]{1}""))"),"quest_main_aka_normal_3") -> quest_main_aka_normal_3 | G16: 3.ラーメン赤猫 | H16: 03 | I16: =CONCATENATE(C16,"_",A16,"_","000",H16,) -> normal_aka_00003 | J16: ="stage_icon_"&A16&"_"&C16&"_"&H16 -> stage_icon_aka_normal_03
A17: glo1 | B17: {=iferror(INDEX('作品'!D:D,MATCH(left(A17,3),'作品'!A:A,0),0),"error")} -> GLOW | C17: normal | D17: main | E17: メインクエスト | F17: =IFERROR(__xludf.DUMMYFUNCTION("CONCATENATE(""quest_"",D17,""_"",A17,""_"",C17,""_"")&IFERROR(REGEXEXTRACT(G17,""[0-9]{2}""),REGEXEXTRACT(G17,""[0-9]{1}""))"),"quest_main_glo1_normal_4") -> quest_main_glo1_normal_4 | G17: 4.リミックスクエスト Vol.1 | H17: 01 | I17: =CONCATENATE(C17,"_",A17,"_","000",H17,) -> normal_glo1_00001 | J17: ="stage_icon_"&A17&"_"&C17&"_"&H17 -> stage_icon_glo1_normal_01
A18: glo1 | B18: {=iferror(INDEX('作品'!D:D,MATCH(left(A18,3),'作品'!A:A,0),0),"error")} -> GLOW | C18: normal | D18: main | E18: メインクエスト | F18: =IFERROR(__xludf.DUMMYFUNCTION("CONCATENATE(""quest_"",D18,""_"",A18,""_"",C18,""_"")&IFERROR(REGEXEXTRACT(G18,""[0-9]{2}""),REGEXEXTRACT(G18,""[0-9]{1}""))"),"quest_main_glo1_normal_4") -> quest_main_glo1_normal_4 | G18: 4.リミックスクエスト Vol.1 | H18: 02 | I18: =CONCATENATE(C18,"_",A18,"_","000",H18,) -> normal_glo1_00002 | J18: ="stage_icon_"&A18&"_"&C18&"_"&H18 -> stage_icon_glo1_normal_02
A19: glo1 | B19: {=iferror(INDEX('作品'!D:D,MATCH(left(A19,3),'作品'!A:A,0),0),"error")} -> GLOW | C19: normal | D19: main | E19: メインクエスト | F19: =IFERROR(__xludf.DUMMYFUNCTION("CONCATENATE(""quest_"",D19,""_"",A19,""_"",C19,""_"")&IFERROR(REGEXEXTRACT(G19,""[0-9]{2}""),REGEXEXTRACT(G19,""[0-9]{1}""))"),"quest_main_glo1_normal_4") -> quest_main_glo1_normal_4 | G19: 4.リミックスクエスト Vol.1 | H19: 03 | I19: =CONCATENATE(C19,"_",A19,"_","000",H19,) -> normal_glo1_00003 | J19: ="stage_icon_"&A19&"_"&C19&"_"&H19 -> stage_icon_glo1_normal_03
A20: glo1 | B20: {=iferror(INDEX('作品'!D:D,MATCH(left(A20,3),'作品'!A:A,0),0),"error")} -> GLOW | C20: normal | D20: main | E20: メインクエスト | F20: =IFERROR(__xludf.DUMMYFUNCTION("CONCATENATE(""quest_"",D20,""_"",A20,""_"",C20,""_"")&IFERROR(REGEXEXTRACT(G20,""[0-9]{2}""),REGEXEXTRACT(G20,""[0-9]{1}""))"),"quest_main_glo1_normal_4") -> quest_main_glo1_normal_4 | G20: 4.リミックスクエスト Vol.1 | H20: 04 | I20: =CONCATENATE(C20,"_",A20,"_","000",H20,) -> normal_glo1_00004 | J20: ="stage_icon_"&A20&"_"&C20&"_"&H20 -> stage_icon_glo1_normal_04
A21: glo1 | B21: {=iferror(INDEX('作品'!D:D,MATCH(left(A21,3),'作品'!A:A,0),0),"error")} -> GLOW | C21: normal | D21: main | E21: メインクエスト | F21: =IFERROR(__xludf.DUMMYFUNCTION("CONCATENATE(""quest_"",D21,""_"",A21,""_"",C21,""_"")&IFERROR(REGEXEXTRACT(G21,""[0-9]{2}""),REGEXEXTRACT(G21,""[0-9]{1}""))"),"quest_main_glo1_normal_4") -> quest_main_glo1_normal_4 | G21: 4.リミックスクエスト Vol.1 | H21: 05 | I21: =CONCATENATE(C21,"_",A21,"_","000",H21,) -> normal_glo1_00005 | J21: ="stage_icon_"&A21&"_"&C21&"_"&H21 -> stage_icon_glo1_normal_05
A22: glo1 | B22: {=iferror(INDEX('作品'!D:D,MATCH(left(A22,3),'作品'!A:A,0),0),"error")} -> GLOW | C22: normal | D22: main | E22: メインクエスト | F22: =IFERROR(__xludf.DUMMYFUNCTION("CONCATENATE(""quest_"",D22,""_"",A22,""_"",C22,""_"")&IFERROR(REGEXEXTRACT(G22,""[0-9]{2}""),REGEXEXTRACT(G22,""[0-9]{1}""))"),"quest_main_glo1_normal_4") -> quest_main_glo1_normal_4 | G22: 4.リミックスクエスト Vol.1 | H22: 06 | I22: =CONCATENATE(C22,"_",A22,"_","000",H22,) -> normal_glo1_00006 | J22: ="stage_icon_"&A22&"_"&C22&"_"&H22 -> stage_icon_glo1_normal_06
A23: dan | B23: {=iferror(INDEX('作品'!D:D,MATCH(left(A23,3),'作品'!A:A,0),0),"error")} -> ダンダダン | C23: normal | D23: main | E23: メインクエスト | F23: =IFERROR(__xludf.DUMMYFUNCTION("CONCATENATE(""quest_"",D23,""_"",A23,""_"",C23,""_"")&IFERROR(REGEXEXTRACT(G23,""[0-9]{2}""),REGEXEXTRACT(G23,""[0-9]{1}""))"),"quest_main_dan_normal_5") -> quest_main_dan_normal_5 | G23: 5.ダンダダン | H23: 01 | I23: =CONCATENATE(C23,"_",A23,"_","000",H23,) -> normal_dan_00001 | J23: ="stage_icon_"&A23&"_"&C23&"_"&H23 -> stage_icon_dan_normal_01
A24: dan | B24: {=iferror(INDEX('作品'!D:D,MATCH(left(A24,3),'作品'!A:A,0),0),"error")} -> ダンダダン | C24: normal | D24: main | E24: メインクエスト | F24: =IFERROR(__xludf.DUMMYFUNCTION("CONCATENATE(""quest_"",D24,""_"",A24,""_"",C24,""_"")&IFERROR(REGEXEXTRACT(G24,""[0-9]{2}""),REGEXEXTRACT(G24,""[0-9]{1}""))"),"quest_main_dan_normal_5") -> quest_main_dan_normal_5 | G24: 5.ダンダダン | H24: 02 | I24: =CONCATENATE(C24,"_",A24,"_","000",H24,) -> normal_dan_00002 | J24: ="stage_icon_"&A24&"_"&C24&"_"&H24 -> stage_icon_dan_normal_02
A25: dan | B25: {=iferror(INDEX('作品'!D:D,MATCH(left(A25,3),'作品'!A:A,0),0),"error")} -> ダンダダン | C25: normal | D25: main | E25: メインクエスト | F25: =IFERROR(__xludf.DUMMYFUNCTION("CONCATENATE(""quest_"",D25,""_"",A25,""_"",C25,""_"")&IFERROR(REGEXEXTRACT(G25,""[0-9]{2}""),REGEXEXTRACT(G25,""[0-9]{1}""))"),"quest_main_dan_normal_5") -> quest_main_dan_normal_5 | G25: 5.ダンダダン | H25: 03 | I25: =CONCATENATE(C25,"_",A25,"_","000",H25,) -> normal_dan_00003 | J25: ="stage_icon_"&A25&"_"&C25&"_"&H25 -> stage_icon_dan_normal_03
A26: dan | B26: {=iferror(INDEX('作品'!D:D,MATCH(left(A26,3),'作品'!A:A,0),0),"error")} -> ダンダダン | C26: normal | D26: main | E26: メインクエスト | F26: =IFERROR(__xludf.DUMMYFUNCTION("CONCATENATE(""quest_"",D26,""_"",A26,""_"",C26,""_"")&IFERROR(REGEXEXTRACT(G26,""[0-9]{2}""),REGEXEXTRACT(G26,""[0-9]{1}""))"),"quest_main_dan_normal_5") -> quest_main_dan_normal_5 | G26: 5.ダンダダン | H26: 04 | I26: =CONCATENATE(C26,"_",A26,"_","000",H26,) -> normal_dan_00004 | J26: ="stage_icon_"&A26&"_"&C26&"_"&H26 -> stage_icon_dan_normal_04
A27: dan | B27: {=iferror(INDEX('作品'!D:D,MATCH(left(A27,3),'作品'!A:A,0),0),"error")} -> ダンダダン | C27: normal | D27: main | E27: メインクエスト | F27: =IFERROR(__xludf.DUMMYFUNCTION("CONCATENATE(""quest_"",D27,""_"",A27,""_"",C27,""_"")&IFERROR(REGEXEXTRACT(G27,""[0-9]{2}""),REGEXEXTRACT(G27,""[0-9]{1}""))"),"quest_main_dan_normal_5") -> quest_main_dan_normal_5 | G27: 5.ダンダダン | H27: 05 | I27: =CONCATENATE(C27,"_",A27,"_","000",H27,) -> normal_dan_00005 | J27: ="stage_icon_"&A27&"_"&C27&"_"&H27 -> stage_icon_dan_normal_05
A28: dan | B28: {=iferror(INDEX('作品'!D:D,MATCH(left(A28,3),'作品'!A:A,0),0),"error")} -> ダンダダン | C28: normal | D28: main | E28: メインクエスト | F28: =IFERROR(__xludf.DUMMYFUNCTION("CONCATENATE(""quest_"",D28,""_"",A28,""_"",C28,""_"")&IFERROR(REGEXEXTRACT(G28,""[0-9]{2}""),REGEXEXTRACT(G28,""[0-9]{1}""))"),"quest_main_dan_normal_5") -> quest_main_dan_normal_5 | G28: 5.ダンダダン | H28: 06 | I28: =CONCATENATE(C28,"_",A28,"_","000",H28,) -> normal_dan_00006 | J28: ="stage_icon_"&A28&"_"&C28&"_"&H28 -> stage_icon_dan_normal_06
A29: jig | B29: {=iferror(INDEX('作品'!D:D,MATCH(left(A29,3),'作品'!A:A,0),0),"error")} -> 地獄楽 | C29: normal | D29: main | E29: メインクエスト | F29: =IFERROR(__xludf.DUMMYFUNCTION("CONCATENATE(""quest_"",D29,""_"",A29,""_"",C29,""_"")&IFERROR(REGEXEXTRACT(G29,""[0-9]{2}""),REGEXEXTRACT(G29,""[0-9]{1}""))"),"quest_main_jig_normal_6") -> quest_main_jig_normal_6 | G29: 6.地獄楽 | H29: 01 | I29: =CONCATENATE(C29,"_",A29,"_","000",H29,) -> normal_jig_00001 | J29: ="stage_icon_"&A29&"_"&C29&"_"&H29 -> stage_icon_jig_normal_01
A30: jig | B30: {=iferror(INDEX('作品'!D:D,MATCH(left(A30,3),'作品'!A:A,0),0),"error")} -> 地獄楽 | C30: normal | D30: main | E30: メインクエスト | F30: =IFERROR(__xludf.DUMMYFUNCTION("CONCATENATE(""quest_"",D30,""_"",A30,""_"",C30,""_"")&IFERROR(REGEXEXTRACT(G30,""[0-9]{2}""),REGEXEXTRACT(G30,""[0-9]{1}""))"),"quest_main_jig_normal_6") -> quest_main_jig_normal_6 | G30: 6.地獄楽 | H30: 02 | I30: =CONCATENATE(C30,"_",A30,"_","000",H30,) -> normal_jig_00002 | J30: ="stage_icon_"&A30&"_"&C30&"_"&H30 -> stage_icon_jig_normal_02
A31: jig | B31: {=iferror(INDEX('作品'!D:D,MATCH(left(A31,3),'作品'!A:A,0),0),"error")} -> 地獄楽 | C31: normal | D31: main | E31: メインクエスト | F31: =IFERROR(__xludf.DUMMYFUNCTION("CONCATENATE(""quest_"",D31,""_"",A31,""_"",C31,""_"")&IFERROR(REGEXEXTRACT(G31,""[0-9]{2}""),REGEXEXTRACT(G31,""[0-9]{1}""))"),"quest_main_jig_normal_6") -> quest_main_jig_normal_6 | G31: 6.地獄楽 | H31: 03 | I31: =CONCATENATE(C31,"_",A31,"_","000",H31,) -> normal_jig_00003 | J31: ="stage_icon_"&A31&"_"&C31&"_"&H31 -> stage_icon_jig_normal_03
A32: jig | B32: {=iferror(INDEX('作品'!D:D,MATCH(left(A32,3),'作品'!A:A,0),0),"error")} -> 地獄楽 | C32: normal | D32: main | E32: メインクエスト | F32: =IFERROR(__xludf.DUMMYFUNCTION("CONCATENATE(""quest_"",D32,""_"",A32,""_"",C32,""_"")&IFERROR(REGEXEXTRACT(G32,""[0-9]{2}""),REGEXEXTRACT(G32,""[0-9]{1}""))"),"quest_main_jig_normal_6") -> quest_main_jig_normal_6 | G32: 6.地獄楽 | H32: 04 | I32: =CONCATENATE(C32,"_",A32,"_","000",H32,) -> normal_jig_00004 | J32: ="stage_icon_"&A32&"_"&C32&"_"&H32 -> stage_icon_jig_normal_04
A33: jig | B33: {=iferror(INDEX('作品'!D:D,MATCH(left(A33,3),'作品'!A:A,0),0),"error")} -> 地獄楽 | C33: normal | D33: main | E33: メインクエスト | F33: =IFERROR(__xludf.DUMMYFUNCTION("CONCATENATE(""quest_"",D33,""_"",A33,""_"",C33,""_"")&IFERROR(REGEXEXTRACT(G33,""[0-9]{2}""),REGEXEXTRACT(G33,""[0-9]{1}""))"),"quest_main_jig_normal_6") -> quest_main_jig_normal_6 | G33: 6.地獄楽 | H33: 05 | I33: =CONCATENATE(C33,"_",A33,"_","000",H33,) -> normal_jig_00005 | J33: ="stage_icon_"&A33&"_"&C33&"_"&H33 -> stage_icon_jig_normal_05
A34: jig | B34: {=iferror(INDEX('作品'!D:D,MATCH(left(A34,3),'作品'!A:A,0),0),"error")} -> 地獄楽 | C34: normal | D34: main | E34: メインクエスト | F34: =IFERROR(__xludf.DUMMYFUNCTION("CONCATENATE(""quest_"",D34,""_"",A34,""_"",C34,""_"")&IFERROR(REGEXEXTRACT(G34,""[0-9]{2}""),REGEXEXTRACT(G34,""[0-9]{1}""))"),"quest_main_jig_normal_6") -> quest_main_jig_normal_6 | G34: 6.地獄楽 | H34: 06 | I34: =CONCATENATE(C34,"_",A34,"_","000",H34,) -> normal_jig_00006 | J34: ="stage_icon_"&A34&"_"&C34&"_"&H34 -> stage_icon_jig_normal_06
A35: tak | B35: {=iferror(INDEX('作品'!D:D,MATCH(left(A35,3),'作品'!A:A,0),0),"error")} -> タコピーの原罪 | C35: normal | D35: main | E35: メインクエスト | F35: =IFERROR(__xludf.DUMMYFUNCTION("CONCATENATE(""quest_"",D35,""_"",A35,""_"",C35,""_"")&IFERROR(REGEXEXTRACT(G35,""[0-9]{2}""),REGEXEXTRACT(G35,""[0-9]{1}""))"),"quest_main_tak_normal_7") -> quest_main_tak_normal_7 | G35: 7.タコピーの原罪 | H35: 01 | I35: =CONCATENATE(C35,"_",A35,"_","000",H35,) -> normal_tak_00001 | J35: ="stage_icon_"&A35&"_"&C35&"_"&H35 -> stage_icon_tak_normal_01
A36: tak | B36: {=iferror(INDEX('作品'!D:D,MATCH(left(A36,3),'作品'!A:A,0),0),"error")} -> タコピーの原罪 | C36: normal | D36: main | E36: メインクエスト | F36: =IFERROR(__xludf.DUMMYFUNCTION("CONCATENATE(""quest_"",D36,""_"",A36,""_"",C36,""_"")&IFERROR(REGEXEXTRACT(G36,""[0-9]{2}""),REGEXEXTRACT(G36,""[0-9]{1}""))"),"quest_main_tak_normal_7") -> quest_main_tak_normal_7 | G36: 7.タコピーの原罪 | H36: 02 | I36: =CONCATENATE(C36,"_",A36,"_","000",H36,) -> normal_tak_00002 | J36: ="stage_icon_"&A36&"_"&C36&"_"&H36 -> stage_icon_tak_normal_02
A37: tak | B37: {=iferror(INDEX('作品'!D:D,MATCH(left(A37,3),'作品'!A:A,0),0),"error")} -> タコピーの原罪 | C37: normal | D37: main | E37: メインクエスト | F37: =IFERROR(__xludf.DUMMYFUNCTION("CONCATENATE(""quest_"",D37,""_"",A37,""_"",C37,""_"")&IFERROR(REGEXEXTRACT(G37,""[0-9]{2}""),REGEXEXTRACT(G37,""[0-9]{1}""))"),"quest_main_tak_normal_7") -> quest_main_tak_normal_7 | G37: 7.タコピーの原罪 | H37: 03 | I37: =CONCATENATE(C37,"_",A37,"_","000",H37,) -> normal_tak_00003 | J37: ="stage_icon_"&A37&"_"&C37&"_"&H37 -> stage_icon_tak_normal_03
A38: glo2 | B38: {=iferror(INDEX('作品'!D:D,MATCH(left(A38,3),'作品'!A:A,0),0),"error")} -> GLOW | C38: normal | D38: main | E38: メインクエスト | F38: =IFERROR(__xludf.DUMMYFUNCTION("CONCATENATE(""quest_"",D38,""_"",A38,""_"",C38,""_"")&IFERROR(REGEXEXTRACT(G38,""[0-9]{2}""),REGEXEXTRACT(G38,""[0-9]{1}""))"),"quest_main_glo2_normal_8") -> quest_main_glo2_normal_8 | G38: 8.リミックスクエスト Vol.2 | H38: 01 | I38: =CONCATENATE(C38,"_",A38,"_","000",H38,) -> normal_glo2_00001 | J38: ="stage_icon_"&A38&"_"&C38&"_"&H38 -> stage_icon_glo2_normal_01
A39: glo2 | B39: {=iferror(INDEX('作品'!D:D,MATCH(left(A39,3),'作品'!A:A,0),0),"error")} -> GLOW | C39: normal | D39: main | E39: メインクエスト | F39: =IFERROR(__xludf.DUMMYFUNCTION("CONCATENATE(""quest_"",D39,""_"",A39,""_"",C39,""_"")&IFERROR(REGEXEXTRACT(G39,""[0-9]{2}""),REGEXEXTRACT(G39,""[0-9]{1}""))"),"quest_main_glo2_normal_8") -> quest_main_glo2_normal_8 | G39: 8.リミックスクエスト Vol.2 | H39: 02 | I39: =CONCATENATE(C39,"_",A39,"_","000",H39,) -> normal_glo2_00002 | J39: ="stage_icon_"&A39&"_"&C39&"_"&H39 -> stage_icon_glo2_normal_02
A40: glo2 | B40: {=iferror(INDEX('作品'!D:D,MATCH(left(A40,3),'作品'!A:A,0),0),"error")} -> GLOW | C40: normal | D40: main | E40: メインクエスト | F40: =IFERROR(__xludf.DUMMYFUNCTION("CONCATENATE(""quest_"",D40,""_"",A40,""_"",C40,""_"")&IFERROR(REGEXEXTRACT(G40,""[0-9]{2}""),REGEXEXTRACT(G40,""[0-9]{1}""))"),"quest_main_glo2_normal_8") -> quest_main_glo2_normal_8 | G40: 8.リミックスクエスト Vol.2 | H40: 03 | I40: =CONCATENATE(C40,"_",A40,"_","000",H40,) -> normal_glo2_00003 | J40: ="stage_icon_"&A40&"_"&C40&"_"&H40 -> stage_icon_glo2_normal_03
A41: glo2 | B41: {=iferror(INDEX('作品'!D:D,MATCH(left(A41,3),'作品'!A:A,0),0),"error")} -> GLOW | C41: normal | D41: main | E41: メインクエスト | F41: =IFERROR(__xludf.DUMMYFUNCTION("CONCATENATE(""quest_"",D41,""_"",A41,""_"",C41,""_"")&IFERROR(REGEXEXTRACT(G41,""[0-9]{2}""),REGEXEXTRACT(G41,""[0-9]{1}""))"),"quest_main_glo2_normal_8") -> quest_main_glo2_normal_8 | G41: 8.リミックスクエスト Vol.2 | H41: 04 | I41: =CONCATENATE(C41,"_",A41,"_","000",H41,) -> normal_glo2_00004 | J41: ="stage_icon_"&A41&"_"&C41&"_"&H41 -> stage_icon_glo2_normal_04
A42: glo2 | B42: {=iferror(INDEX('作品'!D:D,MATCH(left(A42,3),'作品'!A:A,0),0),"error")} -> GLOW | C42: normal | D42: main | E42: メインクエスト | F42: =IFERROR(__xludf.DUMMYFUNCTION("CONCATENATE(""quest_"",D42,""_"",A42,""_"",C42,""_"")&IFERROR(REGEXEXTRACT(G42,""[0-9]{2}""),REGEXEXTRACT(G42,""[0-9]{1}""))"),"quest_main_glo2_normal_8") -> quest_main_glo2_normal_8 | G42: 8.リミックスクエスト Vol.2 | H42: 05 | I42: =CONCATENATE(C42,"_",A42,"_","000",H42,) -> normal_glo2_00005 | J42: ="stage_icon_"&A42&"_"&C42&"_"&H42 -> stage_icon_glo2_normal_05
A43: glo2 | B43: {=iferror(INDEX('作品'!D:D,MATCH(left(A43,3),'作品'!A:A,0),0),"error")} -> GLOW | C43: normal | D43: main | E43: メインクエスト | F43: =IFERROR(__xludf.DUMMYFUNCTION("CONCATENATE(""quest_"",D43,""_"",A43,""_"",C43,""_"")&IFERROR(REGEXEXTRACT(G43,""[0-9]{2}""),REGEXEXTRACT(G43,""[0-9]{1}""))"),"quest_main_glo2_normal_8") -> quest_main_glo2_normal_8 | G43: 8.リミックスクエスト Vol.2 | H43: 06 | I43: =CONCATENATE(C43,"_",A43,"_","000",H43,) -> normal_glo2_00006 | J43: ="stage_icon_"&A43&"_"&C43&"_"&H43 -> stage_icon_glo2_normal_06
A44: chi | B44: {=iferror(INDEX('作品'!D:D,MATCH(left(A44,3),'作品'!A:A,0),0),"error")} -> チェンソーマン | C44: normal | D44: main | E44: メインクエスト | F44: =IFERROR(__xludf.DUMMYFUNCTION("CONCATENATE(""quest_"",D44,""_"",A44,""_"",C44,""_"")&IFERROR(REGEXEXTRACT(G44,""[0-9]{2}""),REGEXEXTRACT(G44,""[0-9]{1}""))"),"quest_main_chi_normal_9") -> quest_main_chi_normal_9 | G44: 9.チェンソーマン | H44: 01 | I44: =CONCATENATE(C44,"_",A44,"_","000",H44,) -> normal_chi_00001 | J44: ="stage_icon_"&A44&"_"&C44&"_"&H44 -> stage_icon_chi_normal_01
A45: chi | B45: {=iferror(INDEX('作品'!D:D,MATCH(left(A45,3),'作品'!A:A,0),0),"error")} -> チェンソーマン | C45: normal | D45: main | E45: メインクエスト | F45: =IFERROR(__xludf.DUMMYFUNCTION("CONCATENATE(""quest_"",D45,""_"",A45,""_"",C45,""_"")&IFERROR(REGEXEXTRACT(G45,""[0-9]{2}""),REGEXEXTRACT(G45,""[0-9]{1}""))"),"quest_main_chi_normal_9") -> quest_main_chi_normal_9 | G45: 9.チェンソーマン | H45: 02 | I45: =CONCATENATE(C45,"_",A45,"_","000",H45,) -> normal_chi_00002 | J45: ="stage_icon_"&A45&"_"&C45&"_"&H45 -> stage_icon_chi_normal_02
A46: chi | B46: {=iferror(INDEX('作品'!D:D,MATCH(left(A46,3),'作品'!A:A,0),0),"error")} -> チェンソーマン | C46: normal | D46: main | E46: メインクエスト | F46: =IFERROR(__xludf.DUMMYFUNCTION("CONCATENATE(""quest_"",D46,""_"",A46,""_"",C46,""_"")&IFERROR(REGEXEXTRACT(G46,""[0-9]{2}""),REGEXEXTRACT(G46,""[0-9]{1}""))"),"quest_main_chi_normal_9") -> quest_main_chi_normal_9 | G46: 9.チェンソーマン | H46: 03 | I46: =CONCATENATE(C46,"_",A46,"_","000",H46,) -> normal_chi_00003 | J46: ="stage_icon_"&A46&"_"&C46&"_"&H46 -> stage_icon_chi_normal_03
A47: chi | B47: {=iferror(INDEX('作品'!D:D,MATCH(left(A47,3),'作品'!A:A,0),0),"error")} -> チェンソーマン | C47: normal | D47: main | E47: メインクエスト | F47: =IFERROR(__xludf.DUMMYFUNCTION("CONCATENATE(""quest_"",D47,""_"",A47,""_"",C47,""_"")&IFERROR(REGEXEXTRACT(G47,""[0-9]{2}""),REGEXEXTRACT(G47,""[0-9]{1}""))"),"quest_main_chi_normal_9") -> quest_main_chi_normal_9 | G47: 9.チェンソーマン | H47: 04 | I47: =CONCATENATE(C47,"_",A47,"_","000",H47,) -> normal_chi_00004 | J47: ="stage_icon_"&A47&"_"&C47&"_"&H47 -> stage_icon_chi_normal_04
A48: chi | B48: {=iferror(INDEX('作品'!D:D,MATCH(left(A48,3),'作品'!A:A,0),0),"error")} -> チェンソーマン | C48: normal | D48: main | E48: メインクエスト | F48: =IFERROR(__xludf.DUMMYFUNCTION("CONCATENATE(""quest_"",D48,""_"",A48,""_"",C48,""_"")&IFERROR(REGEXEXTRACT(G48,""[0-9]{2}""),REGEXEXTRACT(G48,""[0-9]{1}""))"),"quest_main_chi_normal_9") -> quest_main_chi_normal_9 | G48: 9.チェンソーマン | H48: 05 | I48: =CONCATENATE(C48,"_",A48,"_","000",H48,) -> normal_chi_00005 | J48: ="stage_icon_"&A48&"_"&C48&"_"&H48 -> stage_icon_chi_normal_05
A49: chi | B49: {=iferror(INDEX('作品'!D:D,MATCH(left(A49,3),'作品'!A:A,0),0),"error")} -> チェンソーマン | C49: normal | D49: main | E49: メインクエスト | F49: =IFERROR(__xludf.DUMMYFUNCTION("CONCATENATE(""quest_"",D49,""_"",A49,""_"",C49,""_"")&IFERROR(REGEXEXTRACT(G49,""[0-9]{2}""),REGEXEXTRACT(G49,""[0-9]{1}""))"),"quest_main_chi_normal_9") -> quest_main_chi_normal_9 | G49: 9.チェンソーマン | H49: 06 | I49: =CONCATENATE(C49,"_",A49,"_","000",H49,) -> normal_chi_00006 | J49: ="stage_icon_"&A49&"_"&C49&"_"&H49 -> stage_icon_chi_normal_06
A50: sur | B50: {=iferror(INDEX('作品'!D:D,MATCH(left(A50,3),'作品'!A:A,0),0),"error")} -> 魔都精兵のスレイブ | C50: normal | D50: main | E50: メインクエスト | F50: =IFERROR(__xludf.DUMMYFUNCTION("CONCATENATE(""quest_"",D50,""_"",A50,""_"",C50,""_"")&IFERROR(REGEXEXTRACT(G50,""[0-9]{2}""),REGEXEXTRACT(G50,""[0-9]{1}""))"),"quest_main_sur_normal_10") -> quest_main_sur_normal_10 | G50: 10.魔都精兵のスレイブ | H50: 01 | I50: =CONCATENATE(C50,"_",A50,"_","000",H50,) -> normal_sur_00001 | J50: ="stage_icon_"&A50&"_"&C50&"_"&H50 -> stage_icon_sur_normal_01
A51: sur | B51: {=iferror(INDEX('作品'!D:D,MATCH(left(A51,3),'作品'!A:A,0),0),"error")} -> 魔都精兵のスレイブ | C51: normal | D51: main | E51: メインクエスト | F51: =IFERROR(__xludf.DUMMYFUNCTION("CONCATENATE(""quest_"",D51,""_"",A51,""_"",C51,""_"")&IFERROR(REGEXEXTRACT(G51,""[0-9]{2}""),REGEXEXTRACT(G51,""[0-9]{1}""))"),"quest_main_sur_normal_10") -> quest_main_sur_normal_10 | G51: 10.魔都精兵のスレイブ | H51: 02 | I51: =CONCATENATE(C51,"_",A51,"_","000",H51,) -> normal_sur_00002 | J51: ="stage_icon_"&A51&"_"&C51&"_"&H51 -> stage_icon_sur_normal_02
A52: sur | B52: {=iferror(INDEX('作品'!D:D,MATCH(left(A52,3),'作品'!A:A,0),0),"error")} -> 魔都精兵のスレイブ | C52: normal | D52: main | E52: メインクエスト | F52: =IFERROR(__xludf.DUMMYFUNCTION("CONCATENATE(""quest_"",D52,""_"",A52,""_"",C52,""_"")&IFERROR(REGEXEXTRACT(G52,""[0-9]{2}""),REGEXEXTRACT(G52,""[0-9]{1}""))"),"quest_main_sur_normal_10") -> quest_main_sur_normal_10 | G52: 10.魔都精兵のスレイブ | H52: 03 | I52: =CONCATENATE(C52,"_",A52,"_","000",H52,) -> normal_sur_00003 | J52: ="stage_icon_"&A52&"_"&C52&"_"&H52 -> stage_icon_sur_normal_03
A53: sur | B53: {=iferror(INDEX('作品'!D:D,MATCH(left(A53,3),'作品'!A:A,0),0),"error")} -> 魔都精兵のスレイブ | C53: normal | D53: main | E53: メインクエスト | F53: =IFERROR(__xludf.DUMMYFUNCTION("CONCATENATE(""quest_"",D53,""_"",A53,""_"",C53,""_"")&IFERROR(REGEXEXTRACT(G53,""[0-9]{2}""),REGEXEXTRACT(G53,""[0-9]{1}""))"),"quest_main_sur_normal_10") -> quest_main_sur_normal_10 | G53: 10.魔都精兵のスレイブ | H53: 04 | I53: =CONCATENATE(C53,"_",A53,"_","000",H53,) -> normal_sur_00004 | J53: ="stage_icon_"&A53&"_"&C53&"_"&H53 -> stage_icon_sur_normal_04
A54: sur | B54: {=iferror(INDEX('作品'!D:D,MATCH(left(A54,3),'作品'!A:A,0),0),"error")} -> 魔都精兵のスレイブ | C54: normal | D54: main | E54: メインクエスト | F54: =IFERROR(__xludf.DUMMYFUNCTION("CONCATENATE(""quest_"",D54,""_"",A54,""_"",C54,""_"")&IFERROR(REGEXEXTRACT(G54,""[0-9]{2}""),REGEXEXTRACT(G54,""[0-9]{1}""))"),"quest_main_sur_normal_10") -> quest_main_sur_normal_10 | G54: 10.魔都精兵のスレイブ | H54: 05 | I54: =CONCATENATE(C54,"_",A54,"_","000",H54,) -> normal_sur_00005 | J54: ="stage_icon_"&A54&"_"&C54&"_"&H54 -> stage_icon_sur_normal_05
A55: sur | B55: {=iferror(INDEX('作品'!D:D,MATCH(left(A55,3),'作品'!A:A,0),0),"error")} -> 魔都精兵のスレイブ | C55: normal | D55: main | E55: メインクエスト | F55: =IFERROR(__xludf.DUMMYFUNCTION("CONCATENATE(""quest_"",D55,""_"",A55,""_"",C55,""_"")&IFERROR(REGEXEXTRACT(G55,""[0-9]{2}""),REGEXEXTRACT(G55,""[0-9]{1}""))"),"quest_main_sur_normal_10") -> quest_main_sur_normal_10 | G55: 10.魔都精兵のスレイブ | H55: 06 | I55: =CONCATENATE(C55,"_",A55,"_","000",H55,) -> normal_sur_00006 | J55: ="stage_icon_"&A55&"_"&C55&"_"&H55 -> stage_icon_sur_normal_06
A56: rik | B56: {=iferror(INDEX('作品'!D:D,MATCH(left(A56,3),'作品'!A:A,0),0),"error")} -> トマトイプーのリコピン | C56: normal | D56: main | E56: メインクエスト | F56: =IFERROR(__xludf.DUMMYFUNCTION("CONCATENATE(""quest_"",D56,""_"",A56,""_"",C56,""_"")&IFERROR(REGEXEXTRACT(G56,""[0-9]{2}""),REGEXEXTRACT(G56,""[0-9]{1}""))"),"quest_main_rik_normal_11") -> quest_main_rik_normal_11 | G56: 11.トマトイプーのリコピン | H56: 01 | I56: =CONCATENATE(C56,"_",A56,"_","000",H56,) -> normal_rik_00001 | J56: ="stage_icon_"&A56&"_"&C56&"_"&H56 -> stage_icon_rik_normal_01
A57: rik | B57: {=iferror(INDEX('作品'!D:D,MATCH(left(A57,3),'作品'!A:A,0),0),"error")} -> トマトイプーのリコピン | C57: normal | D57: main | E57: メインクエスト | F57: =IFERROR(__xludf.DUMMYFUNCTION("CONCATENATE(""quest_"",D57,""_"",A57,""_"",C57,""_"")&IFERROR(REGEXEXTRACT(G57,""[0-9]{2}""),REGEXEXTRACT(G57,""[0-9]{1}""))"),"quest_main_rik_normal_11") -> quest_main_rik_normal_11 | G57: 11.トマトイプーのリコピン | H57: 02 | I57: =CONCATENATE(C57,"_",A57,"_","000",H57,) -> normal_rik_00002 | J57: ="stage_icon_"&A57&"_"&C57&"_"&H57 -> stage_icon_rik_normal_02
A58: rik | B58: {=iferror(INDEX('作品'!D:D,MATCH(left(A58,3),'作品'!A:A,0),0),"error")} -> トマトイプーのリコピン | C58: normal | D58: main | E58: メインクエスト | F58: =IFERROR(__xludf.DUMMYFUNCTION("CONCATENATE(""quest_"",D58,""_"",A58,""_"",C58,""_"")&IFERROR(REGEXEXTRACT(G58,""[0-9]{2}""),REGEXEXTRACT(G58,""[0-9]{1}""))"),"quest_main_rik_normal_11") -> quest_main_rik_normal_11 | G58: 11.トマトイプーのリコピン | H58: 03 | I58: =CONCATENATE(C58,"_",A58,"_","000",H58,) -> normal_rik_00003 | J58: ="stage_icon_"&A58&"_"&C58&"_"&H58 -> stage_icon_rik_normal_03
A59: glo3 | B59: {=iferror(INDEX('作品'!D:D,MATCH(left(A59,3),'作品'!A:A,0),0),"error")} -> GLOW | C59: normal | D59: main | E59: メインクエスト | F59: =IFERROR(__xludf.DUMMYFUNCTION("CONCATENATE(""quest_"",D59,""_"",A59,""_"",C59,""_"")&IFERROR(REGEXEXTRACT(G59,""[0-9]{2}""),REGEXEXTRACT(G59,""[0-9]{1}""))"),"quest_main_glo3_normal_12") -> quest_main_glo3_normal_12 | G59: 12.リミックスクエスト Vol.3 | H59: 01 | I59: =CONCATENATE(C59,"_",A59,"_","000",H59,) -> normal_glo3_00001 | J59: ="stage_icon_"&A59&"_"&C59&"_"&H59 -> stage_icon_glo3_normal_01
A60: glo3 | B60: {=iferror(INDEX('作品'!D:D,MATCH(left(A60,3),'作品'!A:A,0),0),"error")} -> GLOW | C60: normal | D60: main | E60: メインクエスト | F60: =IFERROR(__xludf.DUMMYFUNCTION("CONCATENATE(""quest_"",D60,""_"",A60,""_"",C60,""_"")&IFERROR(REGEXEXTRACT(G60,""[0-9]{2}""),REGEXEXTRACT(G60,""[0-9]{1}""))"),"quest_main_glo3_normal_12") -> quest_main_glo3_normal_12 | G60: 12.リミックスクエスト Vol.3 | H60: 02 | I60: =CONCATENATE(C60,"_",A60,"_","000",H60,) -> normal_glo3_00002 | J60: ="stage_icon_"&A60&"_"&C60&"_"&H60 -> stage_icon_glo3_normal_02
A61: glo3 | B61: {=iferror(INDEX('作品'!D:D,MATCH(left(A61,3),'作品'!A:A,0),0),"error")} -> GLOW | C61: normal | D61: main | E61: メインクエスト | F61: =IFERROR(__xludf.DUMMYFUNCTION("CONCATENATE(""quest_"",D61,""_"",A61,""_"",C61,""_"")&IFERROR(REGEXEXTRACT(G61,""[0-9]{2}""),REGEXEXTRACT(G61,""[0-9]{1}""))"),"quest_main_glo3_normal_12") -> quest_main_glo3_normal_12 | G61: 12.リミックスクエスト Vol.3 | H61: 03 | I61: =CONCATENATE(C61,"_",A61,"_","000",H61,) -> normal_glo3_00003 | J61: ="stage_icon_"&A61&"_"&C61&"_"&H61 -> stage_icon_glo3_normal_03
A62: glo3 | B62: {=iferror(INDEX('作品'!D:D,MATCH(left(A62,3),'作品'!A:A,0),0),"error")} -> GLOW | C62: normal | D62: main | E62: メインクエスト | F62: =IFERROR(__xludf.DUMMYFUNCTION("CONCATENATE(""quest_"",D62,""_"",A62,""_"",C62,""_"")&IFERROR(REGEXEXTRACT(G62,""[0-9]{2}""),REGEXEXTRACT(G62,""[0-9]{1}""))"),"quest_main_glo3_normal_12") -> quest_main_glo3_normal_12 | G62: 12.リミックスクエスト Vol.3 | H62: 04 | I62: =CONCATENATE(C62,"_",A62,"_","000",H62,) -> normal_glo3_00004 | J62: ="stage_icon_"&A62&"_"&C62&"_"&H62 -> stage_icon_glo3_normal_04
A63: glo3 | B63: {=iferror(INDEX('作品'!D:D,MATCH(left(A63,3),'作品'!A:A,0),0),"error")} -> GLOW | C63: normal | D63: main | E63: メインクエスト | F63: =IFERROR(__xludf.DUMMYFUNCTION("CONCATENATE(""quest_"",D63,""_"",A63,""_"",C63,""_"")&IFERROR(REGEXEXTRACT(G63,""[0-9]{2}""),REGEXEXTRACT(G63,""[0-9]{1}""))"),"quest_main_glo3_normal_12") -> quest_main_glo3_normal_12 | G63: 12.リミックスクエスト Vol.3 | H63: 05 | I63: =CONCATENATE(C63,"_",A63,"_","000",H63,) -> normal_glo3_00005 | J63: ="stage_icon_"&A63&"_"&C63&"_"&H63 -> stage_icon_glo3_normal_05
