Workbook

Sheet キャラ基礎設計
B2: ■基礎設計 | AU2: ■シミュレーション
AU3: 検索用
B4: 特筆事項 | R4: 実装日 | AU4: Lv | AW4: 基礎HP | AX4: 基礎ATK | AY4: Rnk込星1HP | AZ4: Rnk込星1ATK | BA4: 星2HP | BB4: 星3HP | BC4: 星4HP | BD4: 星5HP | BE4: 星6HP | BF4: 星7HP | BG4: 星8HP | BH4: 星9HP | BI4: 星10HP | BJ4: 星2ATK | BK4: 星3ATK | BL4: 星4ATK | BM4: 星5ATK | BN4: 星6ATK | BO4: 星7ATK | BP4: 星8ATK | BQ4: 星9ATK | BR4: 星10ATK
B5: リリース時キャラ | R5: =IFERROR(__xludf.DUMMYFUNCTION("IFERROR( INDEX( IMPORTRANGE(""https://docs.google.com/spreadsheets/d/1oJmkDK37Qizzdaxn4KCwh1BMwdNWuHCx3AGH8BC9yu0/edit?gid=781951868#gid=781951868"", ""キャラ!U:U""), MATCH(B11, IMPORTRANGE(""https://docs.google.com/spreadsheets/d/1oJmkDK37Qizzdaxn"&"4KCwh1BMwdNWuHCx3AGH8BC9yu0/edit?gid=781951868#gid=781951868"", ""キャラ!D:D""), 0) ), ""該当なし"" ) "),45922.458333333336) -> 45922.458 | AU5: 1 | AW5: =VLOOKUP($AU$5,$AU$7:$BR$117,3,false) -> 1490 | AX5: =VLOOKUP($AU$5,$AU$7:$BR$117,4,false) -> 1740 | AY5: =VLOOKUP($AU$5,$AU$7:$BR$117,5,false) -> 1490 | AZ5: =VLOOKUP($AU$5,$AU$7:$BR$117,6,false) -> 1740 | BA5: =VLOOKUP($AU$5,$AU$7:$BR$117,7,false) -> 1668 | BB5: =VLOOKUP($AU$5,$AU$7:$BR$117,8,false) -> 1773 | BC5: =VLOOKUP($AU$5,$AU$7:$BR$117,9,false) -> 1832 | BD5: =VLOOKUP($AU$5,$AU$7:$BR$117,10,false) -> 1862 | BE5: =VLOOKUP($AU$5,$AU$7:$BR$117,11,false) -> 1862 | BF5: =VLOOKUP($AU$5,$AU$7:$BR$117,12,false) -> 1862 | BG5: =VLOOKUP($AU$5,$AU$7:$BR$117,13,false) -> 1862 | BH5: =VLOOKUP($AU$5,$AU$7:$BR$117,14,false) -> 1862 | BI5: =VLOOKUP($AU$5,$AU$7:$BR$117,15,false) -> 1862 | BJ5: =VLOOKUP($AU$5,$AU$7:$BR$117,16,false) -> 1948 | BK5: =VLOOKUP($AU$5,$AU$7:$BR$117,17,false) -> 2070 | BL5: =VLOOKUP($AU$5,$AU$7:$BR$117,18,false) -> 2140 | BM5: =VLOOKUP($AU$5,$AU$7:$BR$117,19,false) -> 2175 | BN5: =VLOOKUP($AU$5,$AU$7:$BR$117,20,false) -> 2175 | BO5: =VLOOKUP($AU$5,$AU$7:$BR$117,21,false) -> 2175 | BP5: =VLOOKUP($AU$5,$AU$7:$BR$117,22,false) -> 2175 | BQ5: =VLOOKUP($AU$5,$AU$7:$BR$117,23,false) -> 2175 | BR5: =VLOOKUP($AU$5,$AU$7:$BR$117,24,false) -> 2175
R6: デプロイ | AU6: ※少数切り上げ
R7: =IFERROR(__xludf.DUMMYFUNCTION("IFERROR( INDEX( IMPORTRANGE(""https://docs.google.com/spreadsheets/d/1oJmkDK37Qizzdaxn4KCwh1BMwdNWuHCx3AGH8BC9yu0/edit?gid=781951868#gid=781951868"", ""キャラ!AB:AB""), MATCH(B11, IMPORTRANGE(""https://docs.google.com/spreadsheets/d/1oJmkDK37Qizzda"&"xn4KCwh1BMwdNWuHCx3AGH8BC9yu0/edit?gid=781951868#gid=781951868"", ""キャラ!D:D""), 0) ), ""該当なし"" ) "),"リリース時") -> リリース時 | AU7: Lv | AV7: Rnk | AW7: 基礎HP | AX7: 基礎ATK | AY7: Rnk込星1HP | AZ7: Rnk込星1ATK | BA7: 星2HP | BB7: 星3HP | BC7: 星4HP | BD7: 星5HP | BE7: 星6HP | BF7: 星7HP | BG7: 星8HP | BH7: 星9HP | BI7: 星10HP | BJ7: 星2ATK | BK7: 星3ATK | BL7: 星4ATK | BM7: 星5ATK | BN7: 星6ATK | BO7: 星7ATK | BP7: 星8ATK | BQ7: 星9ATK | BR7: 星10ATK
AU8: 0 | AV8: 0 | AW8: 0 | AX8: 0 | AY8: 0 | AZ8: 0 | BA8: 0 | BB8: 0 | BC8: 0 | BD8: 0 | BE8: 0 | BF8: 0 | BG8: 0 | BH8: 0 | BI8: 0 | BJ8: 0 | BK8: 0 | BL8: 0 | BM8: 0 | BN8: 0 | BO8: 0 | BP8: 0 | BQ8: 0 | BR8: 0
B9: 基礎情報 | AP9: 消さないで | AU9: 1 | AV9: 0 | AW9: =B21 -> 1490 | AX9: =H21 -> 1740 | AY9: =VLOOKUP(AV9,$AU$191:$AY$205,4,FALSE)+AW9 -> 1490 | AZ9: =VLOOKUP(AV9,$AU$191:$AY$205,5,FALSE)+AX9 -> 1740 | BA9: =rounddown(($AW9*VLOOKUP($B$13,$AU$177:$AW$185,3,false))+VLOOKUP(AV9,$AU$191:$AY$205,4,false),0) -> 1668 | BB9: =rounddown(($AW9*VLOOKUP($B$13,$AU$177:$AX$185,4,false))+VLOOKUP(AV9,$AU$191:$AY$205,4,false),0) -> 1773 | BC9: =rounddown(($AW9*VLOOKUP($B$13,$AU$177:$AY$185,5,false))+VLOOKUP(AV9,$AU$191:$AY$205,4,false),0) -> 1832 | BD9: =rounddown(($AW9*VLOOKUP($B$13,$AU$177:$AZ$185,6,false))+VLOOKUP(AV9,$AU$191:$AY$205,4,false),0) -> 1862 | BE9: =rounddown(($AW9*VLOOKUP($B$13,$AU$177:$BE$185,7,false))+VLOOKUP(AV9,$AU$191:$AY$205,4,false),0) -> 1862 | BF9: =rounddown(($AW9*VLOOKUP($B$13,$AU$177:$BE$185,8,false))+VLOOKUP(AV9,$AU$191:$AY$205,4,false),0) -> 1862 | BG9: =rounddown(($AW9*VLOOKUP($B$13,$AU$177:$BE$185,9,false))+VLOOKUP(AV9,$AU$191:$AY$205,4,false),0) -> 1862 | BH9: =rounddown(($AW9*VLOOKUP($B$13,$AU$177:$BE$185,10,false))+VLOOKUP(AV9,$AU$191:$AY$205,4,false),0) -> 1862 | BI9: =rounddown(($AW9*VLOOKUP($B$13,$AU$177:$BE$185,11,false))+VLOOKUP(AV9,$AU$191:$AY$205,4,false),0) -> 1862 | BJ9: =rounddown(($AX9*VLOOKUP($B$13,$AU$177:$AW$185,3,false))+VLOOKUP(AV9,$AU$191:$AY$205,5,false),0) -> 1948 | BK9: =rounddown(($AX9*VLOOKUP($B$13,$AU$177:$AX$185,4,false))+VLOOKUP(AV9,$AU$191:$AY$205,5,false),0) -> 2070 | BL9: =rounddown(($AX9*VLOOKUP($B$13,$AU$177:$AY$185,5,false))+VLOOKUP(AV9,$AU$191:$AY$205,5,false),0) -> 2140 | BM9: =rounddown(($AX9*VLOOKUP($B$13,$AU$177:$AZ$185,6,false))+VLOOKUP(AV9,$AU$191:$AY$205,5,false),0) -> 2175 | BN9: =rounddown(($AX9*VLOOKUP($B$13,$AU$177:$BE$185,7,false))+VLOOKUP(AV9,$AU$191:$AY$205,5,false),0) -> 2175 | BO9: =rounddown(($AX9*VLOOKUP($B$13,$AU$177:$BE$185,8,false))+VLOOKUP(AV9,$AU$191:$AY$205,5,false),0) -> 2175 | BP9: =rounddown(($AX9*VLOOKUP($B$13,$AU$177:$BE$185,9,false))+VLOOKUP(AV9,$AU$191:$AY$205,5,false),0) -> 2175 | BQ9: =rounddown(($AX9*VLOOKUP($B$13,$AU$177:$BE$185,10,false))+VLOOKUP(AV9,$AU$191:$AY$205,5,false),0) -> 2175 | BR9: =rounddown(($AX9*VLOOKUP($B$13,$AU$177:$BE$185,11,false))+VLOOKUP(AV9,$AU$191:$AY$205,5,false),0) -> 2175
B10: キャラ_ID | F10: キャラクター名 | N10: 作品名 | AP10: {=INDEX('キャラクターID管理'!I:I,MATCH(F11,'キャラクターID管理'!E:E,0),0)} -> PremiumSSR | AU10: 2 | AV10: 0 | AW10: =Floor( $AW$9+($AW$171-$AW$9) * Pow( (AU10-1) / ($AU$171-1),$AU$189) ,1) -> 1544 | AX10: =Floor( $AX$9+($AX$171-$AX$9) * Pow( (AU10-1) / ($AU$171-1),$AU$189) ,1) -> 1803 | AY10: =VLOOKUP(AV10,$AU$191:$AY$205,4,FALSE)+AW10 -> 1544 | AZ10: =VLOOKUP(AV10,$AU$191:$AY$205,5,FALSE)+AX10 -> 1803 | BA10: =rounddown(($AW10*VLOOKUP($B$13,$AU$177:$AW$185,3,false))+VLOOKUP(AV10,$AU$191:$AY$205,4,false),0) -> 1729 | BB10: =rounddown(($AW10*VLOOKUP($B$13,$AU$177:$AX$185,4,false))+VLOOKUP(AV10,$AU$191:$AY$205,4,false),0) -> 1837 | BC10: =rounddown(($AW10*VLOOKUP($B$13,$AU$177:$AY$185,5,false))+VLOOKUP(AV10,$AU$191:$AY$205,4,false),0) -> 1899 | BD10: =rounddown(($AW10*VLOOKUP($B$13,$AU$177:$AZ$185,6,false))+VLOOKUP(AV10,$AU$191:$AY$205,4,false),0) -> 1930 | BE10: =rounddown(($AW10*VLOOKUP($B$13,$AU$177:$BE$185,7,false))+VLOOKUP(AV10,$AU$191:$AY$205,4,false),0) -> 1930 | BF10: =rounddown(($AW10*VLOOKUP($B$13,$AU$177:$BE$185,8,false))+VLOOKUP(AV10,$AU$191:$AY$205,4,false),0) -> 1930 | BG10: =rounddown(($AW10*VLOOKUP($B$13,$AU$177:$BE$185,9,false))+VLOOKUP(AV10,$AU$191:$AY$205,4,false),0) -> 1930 | BH10: =rounddown(($AW10*VLOOKUP($B$13,$AU$177:$BE$185,10,false))+VLOOKUP(AV10,$AU$191:$AY$205,4,false),0) -> 1930 | BI10: =rounddown(($AW10*VLOOKUP($B$13,$AU$177:$BE$185,11,false))+VLOOKUP(AV10,$AU$191:$AY$205,4,false),0) -> 1930 | BJ10: =rounddown(($AX10*VLOOKUP($B$13,$AU$177:$AW$185,3,false))+VLOOKUP(AV10,$AU$191:$AY$205,5,false),0) -> 2019 | BK10: =rounddown(($AX10*VLOOKUP($B$13,$AU$177:$AX$185,4,false))+VLOOKUP(AV10,$AU$191:$AY$205,5,false),0) -> 2145 | BL10: =rounddown(($AX10*VLOOKUP($B$13,$AU$177:$AY$185,5,false))+VLOOKUP(AV10,$AU$191:$AY$205,5,false),0) -> 2217 | BM10: =rounddown(($AX10*VLOOKUP($B$13,$AU$177:$AZ$185,6,false))+VLOOKUP(AV10,$AU$191:$AY$205,5,false),0) -> 2253 | BN10: =rounddown(($AX10*VLOOKUP($B$13,$AU$177:$BE$185,7,false))+VLOOKUP(AV10,$AU$191:$AY$205,5,false),0) -> 2253 | BO10: =rounddown(($AX10*VLOOKUP($B$13,$AU$177:$BE$185,8,false))+VLOOKUP(AV10,$AU$191:$AY$205,5,false),0) -> 2253 | BP10: =rounddown(($AX10*VLOOKUP($B$13,$AU$177:$BE$185,9,false))+VLOOKUP(AV10,$AU$191:$AY$205,5,false),0) -> 2253 | BQ10: =rounddown(($AX10*VLOOKUP($B$13,$AU$177:$BE$185,10,false))+VLOOKUP(AV10,$AU$191:$AY$205,5,false),0) -> 2253 | BR10: =rounddown(($AX10*VLOOKUP($B$13,$AU$177:$BE$185,11,false))+VLOOKUP(AV10,$AU$191:$AY$205,5,false),0) -> 2253
B11: chara_jig_00101 | F11: =IFERROR(__xludf.DUMMYFUNCTION("IFERROR( IF( INDEX(IMPORTRANGE(""https://docs.google.com/spreadsheets/d/1oJmkDK37Qizzdaxn4KCwh1BMwdNWuHCx3AGH8BC9yu0/edit?gid=781951868#gid=781951868"", ""キャラ!F:F""), MATCH(B11, IMPORTRANGE(""https://docs.google.com/spreadsheets/d/1oJmkDK3"&"7Qizzdaxn4KCwh1BMwdNWuHCx3AGH8BC9yu0/edit?gid=781951868#gid=781951868"", ""キャラ!D:D""), 0) ) <> """", INDEX(IMPORTRANGE(""https://docs.google.com/spreadsheets/d/1oJmkDK37Qizzdaxn4KCwh1BMwdNWuHCx3AGH8BC9yu0/edit?gid=781951868#gid=781951868"", ""キャラ!"&"F:F""), MATCH(B11, IMPORTRANGE(""https://docs.google.com/spreadsheets/d/1oJmkDK37Qizzdaxn4KCwh1BMwdNWuHCx3AGH8BC9yu0/edit?gid=781951868#gid=781951868"", ""キャラ!D:D""), 0) ), IF( INDEX(IMPORTRANGE(""https://docs.google.com/spreadshee"&"ts/d/1oJmkDK37Qizzdaxn4KCwh1BMwdNWuHCx3AGH8BC9yu0/edit?gid=781951868#gid=781951868"", ""キャラ!E:E""), MATCH(B11, IMPORTRANGE(""https://docs.google.com/spreadsheets/d/1oJmkDK37Qizzdaxn4KCwh1BMwdNWuHCx3AGH8BC9yu0/edit?gid=781951868#gid=781951868"""&", ""キャラ!D:D""), 0) ) <> """", ""(仮)"" & INDEX(IMPORTRANGE(""https://docs.google.com/spreadsheets/d/1oJmkDK37Qizzdaxn4KCwh1BMwdNWuHCx3AGH8BC9yu0/edit?gid=781951868#gid=781951868"", ""キャラ!E:E""), MATCH(B11, IMPORTRANGE(""htt"&"ps://docs.google.com/spreadsheets/d/1oJmkDK37Qizzdaxn4KCwh1BMwdNWuHCx3AGH8BC9yu0/edit?gid=781951868#gid=781951868"", ""キャラ!D:D""), 0) ), ""該当なし"" ) ), ""該当なし"" ) "),"山田浅ェ門 佐切") -> 山田浅ェ門 佐切 | N11: =IFERROR(__xludf.DUMMYFUNCTION("IFERROR( INDEX( IMPORTRANGE(""https://docs.google.com/spreadsheets/d/1oJmkDK37Qizzdaxn4KCwh1BMwdNWuHCx3AGH8BC9yu0/edit?gid=781951868#gid=781951868"", ""キャラ!B:B""), MATCH(B11, IMPORTRANGE(""https://docs.google.com/spreadsheets/d/1oJmkDK37Qizzdaxn"&"4KCwh1BMwdNWuHCx3AGH8BC9yu0/edit?gid=781951868#gid=781951868"", ""キャラ!D:D""), 0) ), ""該当なし"" ) "),"地獄楽") -> 地獄楽 | AU11: 3 | AV11: 0 | AW11: =Floor( $AW$9+($AW$171-$AW$9) * Pow( (AU11-1) / ($AU$171-1),$AU$189) ,1) -> 1606 | AX11: =Floor( $AX$9+($AX$171-$AX$9) * Pow( (AU11-1) / ($AU$171-1),$AU$189) ,1) -> 1876 | AY11: =VLOOKUP(AV11,$AU$191:$AY$205,4,FALSE)+AW11 -> 1606 | AZ11: =VLOOKUP(AV11,$AU$191:$AY$205,5,FALSE)+AX11 -> 1876 | BA11: =rounddown(($AW11*VLOOKUP($B$13,$AU$177:$AW$185,3,false))+VLOOKUP(AV11,$AU$191:$AY$205,4,false),0) -> 1798 | BB11: =rounddown(($AW11*VLOOKUP($B$13,$AU$177:$AX$185,4,false))+VLOOKUP(AV11,$AU$191:$AY$205,4,false),0) -> 1911 | BC11: =rounddown(($AW11*VLOOKUP($B$13,$AU$177:$AY$185,5,false))+VLOOKUP(AV11,$AU$191:$AY$205,4,false),0) -> 1975 | BD11: =rounddown(($AW11*VLOOKUP($B$13,$AU$177:$AZ$185,6,false))+VLOOKUP(AV11,$AU$191:$AY$205,4,false),0) -> 2007 | BE11: =rounddown(($AW11*VLOOKUP($B$13,$AU$177:$BE$185,7,false))+VLOOKUP(AV11,$AU$191:$AY$205,4,false),0) -> 2007 | BF11: =rounddown(($AW11*VLOOKUP($B$13,$AU$177:$BE$185,8,false))+VLOOKUP(AV11,$AU$191:$AY$205,4,false),0) -> 2007 | BG11: =rounddown(($AW11*VLOOKUP($B$13,$AU$177:$BE$185,9,false))+VLOOKUP(AV11,$AU$191:$AY$205,4,false),0) -> 2007 | BH11: =rounddown(($AW11*VLOOKUP($B$13,$AU$177:$BE$185,10,false))+VLOOKUP(AV11,$AU$191:$AY$205,4,false),0) -> 2007 | BI11: =rounddown(($AW11*VLOOKUP($B$13,$AU$177:$BE$185,11,false))+VLOOKUP(AV11,$AU$191:$AY$205,4,false),0) -> 2007 | BJ11: =rounddown(($AX11*VLOOKUP($B$13,$AU$177:$AW$185,3,false))+VLOOKUP(AV11,$AU$191:$AY$205,5,false),0) -> 2101 | BK11: =rounddown(($AX11*VLOOKUP($B$13,$AU$177:$AX$185,4,false))+VLOOKUP(AV11,$AU$191:$AY$205,5,false),0) -> 2232 | BL11: =rounddown(($AX11*VLOOKUP($B$13,$AU$177:$AY$185,5,false))+VLOOKUP(AV11,$AU$191:$AY$205,5,false),0) -> 2307 | BM11: =rounddown(($AX11*VLOOKUP($B$13,$AU$177:$AZ$185,6,false))+VLOOKUP(AV11,$AU$191:$AY$205,5,false),0) -> 2345 | BN11: =rounddown(($AX11*VLOOKUP($B$13,$AU$177:$BE$185,7,false))+VLOOKUP(AV11,$AU$191:$AY$205,5,false),0) -> 2345 | BO11: =rounddown(($AX11*VLOOKUP($B$13,$AU$177:$BE$185,8,false))+VLOOKUP(AV11,$AU$191:$AY$205,5,false),0) -> 2345 | BP11: =rounddown(($AX11*VLOOKUP($B$13,$AU$177:$BE$185,9,false))+VLOOKUP(AV11,$AU$191:$AY$205,5,false),0) -> 2345 | BQ11: =rounddown(($AX11*VLOOKUP($B$13,$AU$177:$BE$185,10,false))+VLOOKUP(AV11,$AU$191:$AY$205,5,false),0) -> 2345 | BR11: =rounddown(($AX11*VLOOKUP($B$13,$AU$177:$BE$185,11,false))+VLOOKUP(AV11,$AU$191:$AY$205,5,false),0) -> 2345
B12: ラベル | E12: ロール | H12: 属性 | K12: 攻撃射程 | AU12: 4 | AV12: 0 | AW12: =Floor( $AW$9+($AW$171-$AW$9) * Pow( (AU12-1) / ($AU$171-1),$AU$189) ,1) -> 1672 | AX12: =Floor( $AX$9+($AX$171-$AX$9) * Pow( (AU12-1) / ($AU$171-1),$AU$189) ,1) -> 1953 | AY12: =VLOOKUP(AV12,$AU$191:$AY$205,4,FALSE)+AW12 -> 1672 | AZ12: =VLOOKUP(AV12,$AU$191:$AY$205,5,FALSE)+AX12 -> 1953 | BA12: =rounddown(($AW12*VLOOKUP($B$13,$AU$177:$AW$185,3,false))+VLOOKUP(AV12,$AU$191:$AY$205,4,false),0) -> 1872 | BB12: =rounddown(($AW12*VLOOKUP($B$13,$AU$177:$AX$185,4,false))+VLOOKUP(AV12,$AU$191:$AY$205,4,false),0) -> 1989 | BC12: =rounddown(($AW12*VLOOKUP($B$13,$AU$177:$AY$185,5,false))+VLOOKUP(AV12,$AU$191:$AY$205,4,false),0) -> 2056 | BD12: =rounddown(($AW12*VLOOKUP($B$13,$AU$177:$AZ$185,6,false))+VLOOKUP(AV12,$AU$191:$AY$205,4,false),0) -> 2090 | BE12: =rounddown(($AW12*VLOOKUP($B$13,$AU$177:$BE$185,7,false))+VLOOKUP(AV12,$AU$191:$AY$205,4,false),0) -> 2090 | BF12: =rounddown(($AW12*VLOOKUP($B$13,$AU$177:$BE$185,8,false))+VLOOKUP(AV12,$AU$191:$AY$205,4,false),0) -> 2090 | BG12: =rounddown(($AW12*VLOOKUP($B$13,$AU$177:$BE$185,9,false))+VLOOKUP(AV12,$AU$191:$AY$205,4,false),0) -> 2090 | BH12: =rounddown(($AW12*VLOOKUP($B$13,$AU$177:$BE$185,10,false))+VLOOKUP(AV12,$AU$191:$AY$205,4,false),0) -> 2090 | BI12: =rounddown(($AW12*VLOOKUP($B$13,$AU$177:$BE$185,11,false))+VLOOKUP(AV12,$AU$191:$AY$205,4,false),0) -> 2090 | BJ12: =rounddown(($AX12*VLOOKUP($B$13,$AU$177:$AW$185,3,false))+VLOOKUP(AV12,$AU$191:$AY$205,5,false),0) -> 2187 | BK12: =rounddown(($AX12*VLOOKUP($B$13,$AU$177:$AX$185,4,false))+VLOOKUP(AV12,$AU$191:$AY$205,5,false),0) -> 2324 | BL12: =rounddown(($AX12*VLOOKUP($B$13,$AU$177:$AY$185,5,false))+VLOOKUP(AV12,$AU$191:$AY$205,5,false),0) -> 2402 | BM12: =rounddown(($AX12*VLOOKUP($B$13,$AU$177:$AZ$185,6,false))+VLOOKUP(AV12,$AU$191:$AY$205,5,false),0) -> 2441 | BN12: =rounddown(($AX12*VLOOKUP($B$13,$AU$177:$BE$185,7,false))+VLOOKUP(AV12,$AU$191:$AY$205,5,false),0) -> 2441 | BO12: =rounddown(($AX12*VLOOKUP($B$13,$AU$177:$BE$185,8,false))+VLOOKUP(AV12,$AU$191:$AY$205,5,false),0) -> 2441 | BP12: =rounddown(($AX12*VLOOKUP($B$13,$AU$177:$BE$185,9,false))+VLOOKUP(AV12,$AU$191:$AY$205,5,false),0) -> 2441 | BQ12: =rounddown(($AX12*VLOOKUP($B$13,$AU$177:$BE$185,10,false))+VLOOKUP(AV12,$AU$191:$AY$205,5,false),0) -> 2441 | BR12: =rounddown(($AX12*VLOOKUP($B$13,$AU$177:$BE$185,11,false))+VLOOKUP(AV12,$AU$191:$AY$205,5,false),0) -> 2441
B13: =IFERROR(__xludf.DUMMYFUNCTION("IFERROR( INDEX( IMPORTRANGE(""https://docs.google.com/spreadsheets/d/1oJmkDK37Qizzdaxn4KCwh1BMwdNWuHCx3AGH8BC9yu0/edit?gid=781951868#gid=781951868"", ""キャラ!I:I""), MATCH(B11, IMPORTRANGE(""https://docs.google.com/spreadsheets/d/1oJmkDK37Qizzdaxn"&"4KCwh1BMwdNWuHCx3AGH8BC9yu0/edit?gid=781951868#gid=781951868"", ""キャラ!D:D""), 0) ), ""該当なし"" ) "),"PremiumSSR") -> PremiumSSR | E13: =IFERROR(__xludf.DUMMYFUNCTION("IFERROR( INDEX( IMPORTRANGE(""https://docs.google.com/spreadsheets/d/1oJmkDK37Qizzdaxn4KCwh1BMwdNWuHCx3AGH8BC9yu0/edit?gid=781951868#gid=781951868"", ""キャラ!L:L""), MATCH(B11, IMPORTRANGE(""https://docs.google.com/spreadsheets/d/1oJmkDK37Qizzdaxn"&"4KCwh1BMwdNWuHCx3AGH8BC9yu0/edit?gid=781951868#gid=781951868"", ""キャラ!D:D""), 0) ), ""該当なし"" ) "),"アタック") -> アタック | H13: =IFERROR(__xludf.DUMMYFUNCTION("IFERROR( INDEX( IMPORTRANGE(""https://docs.google.com/spreadsheets/d/1oJmkDK37Qizzdaxn4KCwh1BMwdNWuHCx3AGH8BC9yu0/edit?gid=781951868#gid=781951868"", ""キャラ!J:J""), MATCH(B11, IMPORTRANGE(""https://docs.google.com/spreadsheets/d/1oJmkDK37Qizzdaxn"&"4KCwh1BMwdNWuHCx3AGH8BC9yu0/edit?gid=781951868#gid=781951868"", ""キャラ!D:D""), 0) ), ""該当なし"" ) "),"赤") -> 赤 | K13: =IFERROR(__xludf.DUMMYFUNCTION("IFERROR( INDEX( IMPORTRANGE(""https://docs.google.com/spreadsheets/d/1oJmkDK37Qizzdaxn4KCwh1BMwdNWuHCx3AGH8BC9yu0/edit?gid=781951868#gid=781951868"", ""キャラ!N:N""), MATCH(B11, IMPORTRANGE(""https://docs.google.com/spreadsheets/d/1oJmkDK37Qizzdaxn"&"4KCwh1BMwdNWuHCx3AGH8BC9yu0/edit?gid=781951868#gid=781951868"", ""キャラ!D:D""), 0) ), ""該当なし"" ) "),"Short") -> Short | AP13: 消さないで | AU13: 5 | AV13: 0 | AW13: =Floor( $AW$9+($AW$171-$AW$9) * Pow( (AU13-1) / ($AU$171-1),$AU$189) ,1) -> 1740 | AX13: =Floor( $AX$9+($AX$171-$AX$9) * Pow( (AU13-1) / ($AU$171-1),$AU$189) ,1) -> 2032 | AY13: =VLOOKUP(AV13,$AU$191:$AY$205,4,FALSE)+AW13 -> 1740 | AZ13: =VLOOKUP(AV13,$AU$191:$AY$205,5,FALSE)+AX13 -> 2032 | BA13: =rounddown(($AW13*VLOOKUP($B$13,$AU$177:$AW$185,3,false))+VLOOKUP(AV13,$AU$191:$AY$205,4,false),0) -> 1948 | BB13: =rounddown(($AW13*VLOOKUP($B$13,$AU$177:$AX$185,4,false))+VLOOKUP(AV13,$AU$191:$AY$205,4,false),0) -> 2070 | BC13: =rounddown(($AW13*VLOOKUP($B$13,$AU$177:$AY$185,5,false))+VLOOKUP(AV13,$AU$191:$AY$205,4,false),0) -> 2140 | BD13: =rounddown(($AW13*VLOOKUP($B$13,$AU$177:$AZ$185,6,false))+VLOOKUP(AV13,$AU$191:$AY$205,4,false),0) -> 2175 | BE13: =rounddown(($AW13*VLOOKUP($B$13,$AU$177:$BE$185,7,false))+VLOOKUP(AV13,$AU$191:$AY$205,4,false),0) -> 2175 | BF13: =rounddown(($AW13*VLOOKUP($B$13,$AU$177:$BE$185,8,false))+VLOOKUP(AV13,$AU$191:$AY$205,4,false),0) -> 2175 | BG13: =rounddown(($AW13*VLOOKUP($B$13,$AU$177:$BE$185,9,false))+VLOOKUP(AV13,$AU$191:$AY$205,4,false),0) -> 2175 | BH13: =rounddown(($AW13*VLOOKUP($B$13,$AU$177:$BE$185,10,false))+VLOOKUP(AV13,$AU$191:$AY$205,4,false),0) -> 2175 | BI13: =rounddown(($AW13*VLOOKUP($B$13,$AU$177:$BE$185,11,false))+VLOOKUP(AV13,$AU$191:$AY$205,4,false),0) -> 2175 | BJ13: =rounddown(($AX13*VLOOKUP($B$13,$AU$177:$AW$185,3,false))+VLOOKUP(AV13,$AU$191:$AY$205,5,false),0) -> 2275 | BK13: =rounddown(($AX13*VLOOKUP($B$13,$AU$177:$AX$185,4,false))+VLOOKUP(AV13,$AU$191:$AY$205,5,false),0) -> 2418 | BL13: =rounddown(($AX13*VLOOKUP($B$13,$AU$177:$AY$185,5,false))+VLOOKUP(AV13,$AU$191:$AY$205,5,false),0) -> 2499 | BM13: =rounddown(($AX13*VLOOKUP($B$13,$AU$177:$AZ$185,6,false))+VLOOKUP(AV13,$AU$191:$AY$205,5,false),0) -> 2540 | BN13: =rounddown(($AX13*VLOOKUP($B$13,$AU$177:$BE$185,7,false))+VLOOKUP(AV13,$AU$191:$AY$205,5,false),0) -> 2540 | BO13: =rounddown(($AX13*VLOOKUP($B$13,$AU$177:$BE$185,8,false))+VLOOKUP(AV13,$AU$191:$AY$205,5,false),0) -> 2540 | BP13: =rounddown(($AX13*VLOOKUP($B$13,$AU$177:$BE$185,9,false))+VLOOKUP(AV13,$AU$191:$AY$205,5,false),0) -> 2540 | BQ13: =rounddown(($AX13*VLOOKUP($B$13,$AU$177:$BE$185,10,false))+VLOOKUP(AV13,$AU$191:$AY$205,5,false),0) -> 2540 | BR13: =rounddown(($AX13*VLOOKUP($B$13,$AU$177:$BE$185,11,false))+VLOOKUP(AV13,$AU$191:$AY$205,5,false),0) -> 2540
B14: ※キャラクター名：Glow_ID_管理のFIX名称を参照。未記入の場合(仮)名称を参照。 | AP14: =IFS(and(E13="ディフェンス",G17<=0.59),"遠距離以外",and(E13="アタック",G17<=0.59),"遠距離以外",and(E13="サポート",G17<=0.59),"遠距離以外",and(E13="テクニカル",G17<=0.59),"遠距離以外",TRUE,"遠距離") -> 遠距離以外 | AU14: 6 | AV14: 0 | AW14: =Floor( $AW$9+($AW$171-$AW$9) * Pow( (AU14-1) / ($AU$171-1),$AU$189) ,1) -> 1810 | AX14: =Floor( $AX$9+($AX$171-$AX$9) * Pow( (AU14-1) / ($AU$171-1),$AU$189) ,1) -> 2114 | AY14: =VLOOKUP(AV14,$AU$191:$AY$205,4,FALSE)+AW14 -> 1810 | AZ14: =VLOOKUP(AV14,$AU$191:$AY$205,5,FALSE)+AX14 -> 2114 | BA14: =rounddown(($AW14*VLOOKUP($B$13,$AU$177:$AW$185,3,false))+VLOOKUP(AV14,$AU$191:$AY$205,4,false),0) -> 2027 | BB14: =rounddown(($AW14*VLOOKUP($B$13,$AU$177:$AX$185,4,false))+VLOOKUP(AV14,$AU$191:$AY$205,4,false),0) -> 2153 | BC14: =rounddown(($AW14*VLOOKUP($B$13,$AU$177:$AY$185,5,false))+VLOOKUP(AV14,$AU$191:$AY$205,4,false),0) -> 2226 | BD14: =rounddown(($AW14*VLOOKUP($B$13,$AU$177:$AZ$185,6,false))+VLOOKUP(AV14,$AU$191:$AY$205,4,false),0) -> 2262 | BE14: =rounddown(($AW14*VLOOKUP($B$13,$AU$177:$BE$185,7,false))+VLOOKUP(AV14,$AU$191:$AY$205,4,false),0) -> 2262 | BF14: =rounddown(($AW14*VLOOKUP($B$13,$AU$177:$BE$185,8,false))+VLOOKUP(AV14,$AU$191:$AY$205,4,false),0) -> 2262 | BG14: =rounddown(($AW14*VLOOKUP($B$13,$AU$177:$BE$185,9,false))+VLOOKUP(AV14,$AU$191:$AY$205,4,false),0) -> 2262 | BH14: =rounddown(($AW14*VLOOKUP($B$13,$AU$177:$BE$185,10,false))+VLOOKUP(AV14,$AU$191:$AY$205,4,false),0) -> 2262 | BI14: =rounddown(($AW14*VLOOKUP($B$13,$AU$177:$BE$185,11,false))+VLOOKUP(AV14,$AU$191:$AY$205,4,false),0) -> 2262 | BJ14: =rounddown(($AX14*VLOOKUP($B$13,$AU$177:$AW$185,3,false))+VLOOKUP(AV14,$AU$191:$AY$205,5,false),0) -> 2367 | BK14: =rounddown(($AX14*VLOOKUP($B$13,$AU$177:$AX$185,4,false))+VLOOKUP(AV14,$AU$191:$AY$205,5,false),0) -> 2515 | BL14: =rounddown(($AX14*VLOOKUP($B$13,$AU$177:$AY$185,5,false))+VLOOKUP(AV14,$AU$191:$AY$205,5,false),0) -> 2600 | BM14: =rounddown(($AX14*VLOOKUP($B$13,$AU$177:$AZ$185,6,false))+VLOOKUP(AV14,$AU$191:$AY$205,5,false),0) -> 2642 | BN14: =rounddown(($AX14*VLOOKUP($B$13,$AU$177:$BE$185,7,false))+VLOOKUP(AV14,$AU$191:$AY$205,5,false),0) -> 2642 | BO14: =rounddown(($AX14*VLOOKUP($B$13,$AU$177:$BE$185,8,false))+VLOOKUP(AV14,$AU$191:$AY$205,5,false),0) -> 2642 | BP14: =rounddown(($AX14*VLOOKUP($B$13,$AU$177:$BE$185,9,false))+VLOOKUP(AV14,$AU$191:$AY$205,5,false),0) -> 2642 | BQ14: =rounddown(($AX14*VLOOKUP($B$13,$AU$177:$BE$185,10,false))+VLOOKUP(AV14,$AU$191:$AY$205,5,false),0) -> 2642 | BR14: =rounddown(($AX14*VLOOKUP($B$13,$AU$177:$BE$185,11,false))+VLOOKUP(AV14,$AU$191:$AY$205,5,false),0) -> 2642
B15: 基本ステータス | AU15: 7 | AV15: 0 | AW15: =Floor( $AW$9+($AW$171-$AW$9) * Pow( (AU15-1) / ($AU$171-1),$AU$189) ,1) -> 1881 | AX15: =Floor( $AX$9+($AX$171-$AX$9) * Pow( (AU15-1) / ($AU$171-1),$AU$189) ,1) -> 2197 | AY15: =VLOOKUP(AV15,$AU$191:$AY$205,4,FALSE)+AW15 -> 1881 | AZ15: =VLOOKUP(AV15,$AU$191:$AY$205,5,FALSE)+AX15 -> 2197 | BA15: =rounddown(($AW15*VLOOKUP($B$13,$AU$177:$AW$185,3,false))+VLOOKUP(AV15,$AU$191:$AY$205,4,false),0) -> 2106 | BB15: =rounddown(($AW15*VLOOKUP($B$13,$AU$177:$AX$185,4,false))+VLOOKUP(AV15,$AU$191:$AY$205,4,false),0) -> 2238 | BC15: =rounddown(($AW15*VLOOKUP($B$13,$AU$177:$AY$185,5,false))+VLOOKUP(AV15,$AU$191:$AY$205,4,false),0) -> 2313 | BD15: =rounddown(($AW15*VLOOKUP($B$13,$AU$177:$AZ$185,6,false))+VLOOKUP(AV15,$AU$191:$AY$205,4,false),0) -> 2351 | BE15: =rounddown(($AW15*VLOOKUP($B$13,$AU$177:$BE$185,7,false))+VLOOKUP(AV15,$AU$191:$AY$205,4,false),0) -> 2351 | BF15: =rounddown(($AW15*VLOOKUP($B$13,$AU$177:$BE$185,8,false))+VLOOKUP(AV15,$AU$191:$AY$205,4,false),0) -> 2351 | BG15: =rounddown(($AW15*VLOOKUP($B$13,$AU$177:$BE$185,9,false))+VLOOKUP(AV15,$AU$191:$AY$205,4,false),0) -> 2351 | BH15: =rounddown(($AW15*VLOOKUP($B$13,$AU$177:$BE$185,10,false))+VLOOKUP(AV15,$AU$191:$AY$205,4,false),0) -> 2351 | BI15: =rounddown(($AW15*VLOOKUP($B$13,$AU$177:$BE$185,11,false))+VLOOKUP(AV15,$AU$191:$AY$205,4,false),0) -> 2351 | BJ15: =rounddown(($AX15*VLOOKUP($B$13,$AU$177:$AW$185,3,false))+VLOOKUP(AV15,$AU$191:$AY$205,5,false),0) -> 2460 | BK15: =rounddown(($AX15*VLOOKUP($B$13,$AU$177:$AX$185,4,false))+VLOOKUP(AV15,$AU$191:$AY$205,5,false),0) -> 2614 | BL15: =rounddown(($AX15*VLOOKUP($B$13,$AU$177:$AY$185,5,false))+VLOOKUP(AV15,$AU$191:$AY$205,5,false),0) -> 2702 | BM15: =rounddown(($AX15*VLOOKUP($B$13,$AU$177:$AZ$185,6,false))+VLOOKUP(AV15,$AU$191:$AY$205,5,false),0) -> 2746 | BN15: =rounddown(($AX15*VLOOKUP($B$13,$AU$177:$BE$185,7,false))+VLOOKUP(AV15,$AU$191:$AY$205,5,false),0) -> 2746 | BO15: =rounddown(($AX15*VLOOKUP($B$13,$AU$177:$BE$185,8,false))+VLOOKUP(AV15,$AU$191:$AY$205,5,false),0) -> 2746 | BP15: =rounddown(($AX15*VLOOKUP($B$13,$AU$177:$BE$185,9,false))+VLOOKUP(AV15,$AU$191:$AY$205,5,false),0) -> 2746 | BQ15: =rounddown(($AX15*VLOOKUP($B$13,$AU$177:$BE$185,10,false))+VLOOKUP(AV15,$AU$191:$AY$205,5,false),0) -> 2746 | BR15: =rounddown(($AX15*VLOOKUP($B$13,$AU$177:$BE$185,11,false))+VLOOKUP(AV15,$AU$191:$AY$205,5,false),0) -> 2746
B16: 召喚コスト | D16: 再召喚時間F | G16: well_distace | J16: 移動速度 | M16: KB回数 | AU16: 8 | AV16: 0 | AW16: =Floor( $AW$9+($AW$171-$AW$9) * Pow( (AU16-1) / ($AU$171-1),$AU$189) ,1) -> 1954 | AX16: =Floor( $AX$9+($AX$171-$AX$9) * Pow( (AU16-1) / ($AU$171-1),$AU$189) ,1) -> 2281 | AY16: =VLOOKUP(AV16,$AU$191:$AY$205,4,FALSE)+AW16 -> 1954 | AZ16: =VLOOKUP(AV16,$AU$191:$AY$205,5,FALSE)+AX16 -> 2281 | BA16: =rounddown(($AW16*VLOOKUP($B$13,$AU$177:$AW$185,3,false))+VLOOKUP(AV16,$AU$191:$AY$205,4,false),0) -> 2188 | BB16: =rounddown(($AW16*VLOOKUP($B$13,$AU$177:$AX$185,4,false))+VLOOKUP(AV16,$AU$191:$AY$205,4,false),0) -> 2325 | BC16: =rounddown(($AW16*VLOOKUP($B$13,$AU$177:$AY$185,5,false))+VLOOKUP(AV16,$AU$191:$AY$205,4,false),0) -> 2403 | BD16: =rounddown(($AW16*VLOOKUP($B$13,$AU$177:$AZ$185,6,false))+VLOOKUP(AV16,$AU$191:$AY$205,4,false),0) -> 2442 | BE16: =rounddown(($AW16*VLOOKUP($B$13,$AU$177:$BE$185,7,false))+VLOOKUP(AV16,$AU$191:$AY$205,4,false),0) -> 2442 | BF16: =rounddown(($AW16*VLOOKUP($B$13,$AU$177:$BE$185,8,false))+VLOOKUP(AV16,$AU$191:$AY$205,4,false),0) -> 2442 | BG16: =rounddown(($AW16*VLOOKUP($B$13,$AU$177:$BE$185,9,false))+VLOOKUP(AV16,$AU$191:$AY$205,4,false),0) -> 2442 | BH16: =rounddown(($AW16*VLOOKUP($B$13,$AU$177:$BE$185,10,false))+VLOOKUP(AV16,$AU$191:$AY$205,4,false),0) -> 2442 | BI16: =rounddown(($AW16*VLOOKUP($B$13,$AU$177:$BE$185,11,false))+VLOOKUP(AV16,$AU$191:$AY$205,4,false),0) -> 2442 | BJ16: =rounddown(($AX16*VLOOKUP($B$13,$AU$177:$AW$185,3,false))+VLOOKUP(AV16,$AU$191:$AY$205,5,false),0) -> 2554 | BK16: =rounddown(($AX16*VLOOKUP($B$13,$AU$177:$AX$185,4,false))+VLOOKUP(AV16,$AU$191:$AY$205,5,false),0) -> 2714 | BL16: =rounddown(($AX16*VLOOKUP($B$13,$AU$177:$AY$185,5,false))+VLOOKUP(AV16,$AU$191:$AY$205,5,false),0) -> 2805 | BM16: =rounddown(($AX16*VLOOKUP($B$13,$AU$177:$AZ$185,6,false))+VLOOKUP(AV16,$AU$191:$AY$205,5,false),0) -> 2851 | BN16: =rounddown(($AX16*VLOOKUP($B$13,$AU$177:$BE$185,7,false))+VLOOKUP(AV16,$AU$191:$AY$205,5,false),0) -> 2851 | BO16: =rounddown(($AX16*VLOOKUP($B$13,$AU$177:$BE$185,8,false))+VLOOKUP(AV16,$AU$191:$AY$205,5,false),0) -> 2851 | BP16: =rounddown(($AX16*VLOOKUP($B$13,$AU$177:$BE$185,9,false))+VLOOKUP(AV16,$AU$191:$AY$205,5,false),0) -> 2851 | BQ16: =rounddown(($AX16*VLOOKUP($B$13,$AU$177:$BE$185,10,false))+VLOOKUP(AV16,$AU$191:$AY$205,5,false),0) -> 2851 | BR16: =rounddown(($AX16*VLOOKUP($B$13,$AU$177:$BE$185,11,false))+VLOOKUP(AV16,$AU$191:$AY$205,5,false),0) -> 2851
B17: =IFERROR(__xludf.DUMMYFUNCTION("IFERROR( INDEX( IMPORTRANGE(""https://docs.google.com/spreadsheets/d/1tAaChe98Zh7vhMfGMK5Y4_ijmNb40fr519GtdZkkDUY/edit?gid=1369914306#gid=1369914306"", ""キャラ基礎数値!M:M""), MATCH(B11, IMPORTRANGE(""https://docs.google.com/spreadsheets/d/1tAaChe98Zh"&"7vhMfGMK5Y4_ijmNb40fr519GtdZkkDUY/edit?gid=1369914306#gid=1369914306"", ""キャラ基礎数値!C:C""), 0) ), ""該当なし"" ) "),620.0) -> 620 | D17: =IFERROR(__xludf.DUMMYFUNCTION("IF( E13 = ""スペシャル"", ""-"", IFERROR( INDEX( IMPORTRANGE(""https://docs.google.com/spreadsheets/d/1tAaChe98Zh7vhMfGMK5Y4_ijmNb40fr519GtdZkkDUY/edit#gid=1369914306"", ""キャラ基礎数値!T:T""), MATCH(B11, IMPORTRANGE(""https://docs.google.com/s"&"preadsheets/d/1tAaChe98Zh7vhMfGMK5Y4_ijmNb40fr519GtdZkkDUY/edit#gid=1369914306"", ""キャラ基礎数値!C:C""), 0) ), ""該当なし"" ) ) "),545.0) -> 545 | G17: =IFERROR(__xludf.DUMMYFUNCTION("IFERROR( INDEX( IMPORTRANGE(""https://docs.google.com/spreadsheets/d/1tAaChe98Zh7vhMfGMK5Y4_ijmNb40fr519GtdZkkDUY/edit#gid=1369914306"", ""キャラ基礎数値!BT:BT""), MATCH(B11, IMPORTRANGE(""https://docs.google.com/spreadsheets/d/1tAaChe98Zh7vhMfGMK5Y4_i"&"jmNb40fr519GtdZkkDUY/edit#gid=1369914306"", ""キャラ基礎数値!C:C""), 0) ), ""該当なし"" ) "),0.29) -> 0.29 | J17: =IFERROR(__xludf.DUMMYFUNCTION("IFERROR( INDEX( IMPORTRANGE(""https://docs.google.com/spreadsheets/d/1tAaChe98Zh7vhMfGMK5Y4_ijmNb40fr519GtdZkkDUY/edit#gid=1369914306"", ""キャラ基礎数値!BS:BS""), MATCH(B11, IMPORTRANGE(""https://docs.google.com/spreadsheets/d/1tAaChe98Zh7vhMfGMK5Y4_i"&"jmNb40fr519GtdZkkDUY/edit#gid=1369914306"", ""キャラ基礎数値!C:C""), 0) ), ""該当なし"" ) "),40.0) -> 40 | M17: =IFERROR(__xludf.DUMMYFUNCTION("IFERROR( INDEX( IMPORTRANGE(""https://docs.google.com/spreadsheets/d/1tAaChe98Zh7vhMfGMK5Y4_ijmNb40fr519GtdZkkDUY/edit#gid=1369914306"", ""キャラ基礎数値!BR:BR""), MATCH(B11, IMPORTRANGE(""https://docs.google.com/spreadsheets/d/1tAaChe98Zh7vhMfGMK5Y4_i"&"jmNb40fr519GtdZkkDUY/edit#gid=1369914306"", ""キャラ基礎数値!C:C""), 0) ), ""該当なし"" ) "),2.0) -> 2 | AU17: 9 | AV17: 0 | AW17: =Floor( $AW$9+($AW$171-$AW$9) * Pow( (AU17-1) / ($AU$171-1),$AU$189) ,1) -> 2027 | AX17: =Floor( $AX$9+($AX$171-$AX$9) * Pow( (AU17-1) / ($AU$171-1),$AU$189) ,1) -> 2367 | AY17: =VLOOKUP(AV17,$AU$191:$AY$205,4,FALSE)+AW17 -> 2027 | AZ17: =VLOOKUP(AV17,$AU$191:$AY$205,5,FALSE)+AX17 -> 2367 | BA17: =rounddown(($AW17*VLOOKUP($B$13,$AU$177:$AW$185,3,false))+VLOOKUP(AV17,$AU$191:$AY$205,4,false),0) -> 2270 | BB17: =rounddown(($AW17*VLOOKUP($B$13,$AU$177:$AX$185,4,false))+VLOOKUP(AV17,$AU$191:$AY$205,4,false),0) -> 2412 | BC17: =rounddown(($AW17*VLOOKUP($B$13,$AU$177:$AY$185,5,false))+VLOOKUP(AV17,$AU$191:$AY$205,4,false),0) -> 2493 | BD17: =rounddown(($AW17*VLOOKUP($B$13,$AU$177:$AZ$185,6,false))+VLOOKUP(AV17,$AU$191:$AY$205,4,false),0) -> 2533 | BE17: =rounddown(($AW17*VLOOKUP($B$13,$AU$177:$BE$185,7,false))+VLOOKUP(AV17,$AU$191:$AY$205,4,false),0) -> 2533 | BF17: =rounddown(($AW17*VLOOKUP($B$13,$AU$177:$BE$185,8,false))+VLOOKUP(AV17,$AU$191:$AY$205,4,false),0) -> 2533 | BG17: =rounddown(($AW17*VLOOKUP($B$13,$AU$177:$BE$185,9,false))+VLOOKUP(AV17,$AU$191:$AY$205,4,false),0) -> 2533 | BH17: =rounddown(($AW17*VLOOKUP($B$13,$AU$177:$BE$185,10,false))+VLOOKUP(AV17,$AU$191:$AY$205,4,false),0) -> 2533 | BI17: =rounddown(($AW17*VLOOKUP($B$13,$AU$177:$BE$185,11,false))+VLOOKUP(AV17,$AU$191:$AY$205,4,false),0) -> 2533 | BJ17: =rounddown(($AX17*VLOOKUP($B$13,$AU$177:$AW$185,3,false))+VLOOKUP(AV17,$AU$191:$AY$205,5,false),0) -> 2651 | BK17: =rounddown(($AX17*VLOOKUP($B$13,$AU$177:$AX$185,4,false))+VLOOKUP(AV17,$AU$191:$AY$205,5,false),0) -> 2816 | BL17: =rounddown(($AX17*VLOOKUP($B$13,$AU$177:$AY$185,5,false))+VLOOKUP(AV17,$AU$191:$AY$205,5,false),0) -> 2911 | BM17: =rounddown(($AX17*VLOOKUP($B$13,$AU$177:$AZ$185,6,false))+VLOOKUP(AV17,$AU$191:$AY$205,5,false),0) -> 2958 | BN17: =rounddown(($AX17*VLOOKUP($B$13,$AU$177:$BE$185,7,false))+VLOOKUP(AV17,$AU$191:$AY$205,5,false),0) -> 2958 | BO17: =rounddown(($AX17*VLOOKUP($B$13,$AU$177:$BE$185,8,false))+VLOOKUP(AV17,$AU$191:$AY$205,5,false),0) -> 2958 | BP17: =rounddown(($AX17*VLOOKUP($B$13,$AU$177:$BE$185,9,false))+VLOOKUP(AV17,$AU$191:$AY$205,5,false),0) -> 2958 | BQ17: =rounddown(($AX17*VLOOKUP($B$13,$AU$177:$BE$185,10,false))+VLOOKUP(AV17,$AU$191:$AY$205,5,false),0) -> 2958 | BR17: =rounddown(($AX17*VLOOKUP($B$13,$AU$177:$BE$185,11,false))+VLOOKUP(AV17,$AU$191:$AY$205,5,false),0) -> 2958
AU18: 10 | AV18: 0 | AW18: =Floor( $AW$9+($AW$171-$AW$9) * Pow( (AU18-1) / ($AU$171-1),$AU$189) ,1) -> 2101 | AX18: =Floor( $AX$9+($AX$171-$AX$9) * Pow( (AU18-1) / ($AU$171-1),$AU$189) ,1) -> 2454 | AY18: =VLOOKUP(AV18,$AU$191:$AY$205,4,FALSE)+AW18 -> 2101 | AZ18: =VLOOKUP(AV18,$AU$191:$AY$205,5,FALSE)+AX18 -> 2454 | BA18: =rounddown(($AW18*VLOOKUP($B$13,$AU$177:$AW$185,3,false))+VLOOKUP(AV18,$AU$191:$AY$205,4,false),0) -> 2353 | BB18: =rounddown(($AW18*VLOOKUP($B$13,$AU$177:$AX$185,4,false))+VLOOKUP(AV18,$AU$191:$AY$205,4,false),0) -> 2500 | BC18: =rounddown(($AW18*VLOOKUP($B$13,$AU$177:$AY$185,5,false))+VLOOKUP(AV18,$AU$191:$AY$205,4,false),0) -> 2584 | BD18: =rounddown(($AW18*VLOOKUP($B$13,$AU$177:$AZ$185,6,false))+VLOOKUP(AV18,$AU$191:$AY$205,4,false),0) -> 2626 | BE18: =rounddown(($AW18*VLOOKUP($B$13,$AU$177:$BE$185,7,false))+VLOOKUP(AV18,$AU$191:$AY$205,4,false),0) -> 2626 | BF18: =rounddown(($AW18*VLOOKUP($B$13,$AU$177:$BE$185,8,false))+VLOOKUP(AV18,$AU$191:$AY$205,4,false),0) -> 2626 | BG18: =rounddown(($AW18*VLOOKUP($B$13,$AU$177:$BE$185,9,false))+VLOOKUP(AV18,$AU$191:$AY$205,4,false),0) -> 2626 | BH18: =rounddown(($AW18*VLOOKUP($B$13,$AU$177:$BE$185,10,false))+VLOOKUP(AV18,$AU$191:$AY$205,4,false),0) -> 2626 | BI18: =rounddown(($AW18*VLOOKUP($B$13,$AU$177:$BE$185,11,false))+VLOOKUP(AV18,$AU$191:$AY$205,4,false),0) -> 2626 | BJ18: =rounddown(($AX18*VLOOKUP($B$13,$AU$177:$AW$185,3,false))+VLOOKUP(AV18,$AU$191:$AY$205,5,false),0) -> 2748 | BK18: =rounddown(($AX18*VLOOKUP($B$13,$AU$177:$AX$185,4,false))+VLOOKUP(AV18,$AU$191:$AY$205,5,false),0) -> 2920 | BL18: =rounddown(($AX18*VLOOKUP($B$13,$AU$177:$AY$185,5,false))+VLOOKUP(AV18,$AU$191:$AY$205,5,false),0) -> 3018 | BM18: =rounddown(($AX18*VLOOKUP($B$13,$AU$177:$AZ$185,6,false))+VLOOKUP(AV18,$AU$191:$AY$205,5,false),0) -> 3067 | BN18: =rounddown(($AX18*VLOOKUP($B$13,$AU$177:$BE$185,7,false))+VLOOKUP(AV18,$AU$191:$AY$205,5,false),0) -> 3067 | BO18: =rounddown(($AX18*VLOOKUP($B$13,$AU$177:$BE$185,8,false))+VLOOKUP(AV18,$AU$191:$AY$205,5,false),0) -> 3067 | BP18: =rounddown(($AX18*VLOOKUP($B$13,$AU$177:$BE$185,9,false))+VLOOKUP(AV18,$AU$191:$AY$205,5,false),0) -> 3067 | BQ18: =rounddown(($AX18*VLOOKUP($B$13,$AU$177:$BE$185,10,false))+VLOOKUP(AV18,$AU$191:$AY$205,5,false),0) -> 3067 | BR18: =rounddown(($AX18*VLOOKUP($B$13,$AU$177:$BE$185,11,false))+VLOOKUP(AV18,$AU$191:$AY$205,5,false),0) -> 3067
B19: Lvステータス | AU19: 10 | AV19: 0 | AW19: =Floor( $AW$9+($AW$171-$AW$9) * Pow( (AU19-1) / ($AU$171-1),$AU$189) ,1) -> 2101 | AX19: =Floor( $AX$9+($AX$171-$AX$9) * Pow( (AU19-1) / ($AU$171-1),$AU$189) ,1) -> 2454 | AY19: =VLOOKUP(AV19,$AU$191:$AY$205,4,FALSE)+AW19 -> 2101 | AZ19: =VLOOKUP(AV19,$AU$191:$AY$205,5,FALSE)+AX19 -> 2454 | BA19: =rounddown(($AW19*VLOOKUP($B$13,$AU$177:$AW$185,3,false))+VLOOKUP(AV19,$AU$191:$AY$205,4,false),0) -> 2353 | BB19: =rounddown(($AW19*VLOOKUP($B$13,$AU$177:$AX$185,4,false))+VLOOKUP(AV19,$AU$191:$AY$205,4,false),0) -> 2500 | BC19: =rounddown(($AW19*VLOOKUP($B$13,$AU$177:$AY$185,5,false))+VLOOKUP(AV19,$AU$191:$AY$205,4,false),0) -> 2584 | BD19: =rounddown(($AW19*VLOOKUP($B$13,$AU$177:$AZ$185,6,false))+VLOOKUP(AV19,$AU$191:$AY$205,4,false),0) -> 2626 | BE19: =rounddown(($AW19*VLOOKUP($B$13,$AU$177:$BE$185,7,false))+VLOOKUP(AV19,$AU$191:$AY$205,4,false),0) -> 2626 | BF19: =rounddown(($AW19*VLOOKUP($B$13,$AU$177:$BE$185,8,false))+VLOOKUP(AV19,$AU$191:$AY$205,4,false),0) -> 2626 | BG19: =rounddown(($AW19*VLOOKUP($B$13,$AU$177:$BE$185,9,false))+VLOOKUP(AV19,$AU$191:$AY$205,4,false),0) -> 2626 | BH19: =rounddown(($AW19*VLOOKUP($B$13,$AU$177:$BE$185,10,false))+VLOOKUP(AV19,$AU$191:$AY$205,4,false),0) -> 2626 | BI19: =rounddown(($AW19*VLOOKUP($B$13,$AU$177:$BE$185,11,false))+VLOOKUP(AV19,$AU$191:$AY$205,4,false),0) -> 2626 | BJ19: =rounddown(($AX19*VLOOKUP($B$13,$AU$177:$AW$185,3,false))+VLOOKUP(AV19,$AU$191:$AY$205,5,false),0) -> 2748 | BK19: =rounddown(($AX19*VLOOKUP($B$13,$AU$177:$AX$185,4,false))+VLOOKUP(AV19,$AU$191:$AY$205,5,false),0) -> 2920 | BL19: =rounddown(($AX19*VLOOKUP($B$13,$AU$177:$AY$185,5,false))+VLOOKUP(AV19,$AU$191:$AY$205,5,false),0) -> 3018 | BM19: =rounddown(($AX19*VLOOKUP($B$13,$AU$177:$AZ$185,6,false))+VLOOKUP(AV19,$AU$191:$AY$205,5,false),0) -> 3067 | BN19: =rounddown(($AX19*VLOOKUP($B$13,$AU$177:$BE$185,7,false))+VLOOKUP(AV19,$AU$191:$AY$205,5,false),0) -> 3067 | BO19: =rounddown(($AX19*VLOOKUP($B$13,$AU$177:$BE$185,8,false))+VLOOKUP(AV19,$AU$191:$AY$205,5,false),0) -> 3067 | BP19: =rounddown(($AX19*VLOOKUP($B$13,$AU$177:$BE$185,9,false))+VLOOKUP(AV19,$AU$191:$AY$205,5,false),0) -> 3067 | BQ19: =rounddown(($AX19*VLOOKUP($B$13,$AU$177:$BE$185,10,false))+VLOOKUP(AV19,$AU$191:$AY$205,5,false),0) -> 3067 | BR19: =rounddown(($AX19*VLOOKUP($B$13,$AU$177:$BE$185,11,false))+VLOOKUP(AV19,$AU$191:$AY$205,5,false),0) -> 3067
B20: 体力Lv1 | E20: 体力Lv150 | H20: 攻撃力Lv1 | K20: 攻撃力Lv150 | AU20: 11 | AV20: 0 | AW20: =Floor( $AW$9+($AW$171-$AW$9) * Pow( (AU20-1) / ($AU$171-1),$AU$189) ,1) -> 2176 | AX20: =Floor( $AX$9+($AX$171-$AX$9) * Pow( (AU20-1) / ($AU$171-1),$AU$189) ,1) -> 2542 | AY20: =VLOOKUP(AV20,$AU$191:$AY$205,4,FALSE)+AW20 -> 2176 | AZ20: =VLOOKUP(AV20,$AU$191:$AY$205,5,FALSE)+AX20 -> 2542 | BA20: =rounddown(($AW20*VLOOKUP($B$13,$AU$177:$AW$185,3,false))+VLOOKUP(AV20,$AU$191:$AY$205,4,false),0) -> 2437 | BB20: =rounddown(($AW20*VLOOKUP($B$13,$AU$177:$AX$185,4,false))+VLOOKUP(AV20,$AU$191:$AY$205,4,false),0) -> 2589 | BC20: =rounddown(($AW20*VLOOKUP($B$13,$AU$177:$AY$185,5,false))+VLOOKUP(AV20,$AU$191:$AY$205,4,false),0) -> 2676 | BD20: =rounddown(($AW20*VLOOKUP($B$13,$AU$177:$AZ$185,6,false))+VLOOKUP(AV20,$AU$191:$AY$205,4,false),0) -> 2720 | BE20: =rounddown(($AW20*VLOOKUP($B$13,$AU$177:$BE$185,7,false))+VLOOKUP(AV20,$AU$191:$AY$205,4,false),0) -> 2720 | BF20: =rounddown(($AW20*VLOOKUP($B$13,$AU$177:$BE$185,8,false))+VLOOKUP(AV20,$AU$191:$AY$205,4,false),0) -> 2720 | BG20: =rounddown(($AW20*VLOOKUP($B$13,$AU$177:$BE$185,9,false))+VLOOKUP(AV20,$AU$191:$AY$205,4,false),0) -> 2720 | BH20: =rounddown(($AW20*VLOOKUP($B$13,$AU$177:$BE$185,10,false))+VLOOKUP(AV20,$AU$191:$AY$205,4,false),0) -> 2720 | BI20: =rounddown(($AW20*VLOOKUP($B$13,$AU$177:$BE$185,11,false))+VLOOKUP(AV20,$AU$191:$AY$205,4,false),0) -> 2720 | BJ20: =rounddown(($AX20*VLOOKUP($B$13,$AU$177:$AW$185,3,false))+VLOOKUP(AV20,$AU$191:$AY$205,5,false),0) -> 2847 | BK20: =rounddown(($AX20*VLOOKUP($B$13,$AU$177:$AX$185,4,false))+VLOOKUP(AV20,$AU$191:$AY$205,5,false),0) -> 3024 | BL20: =rounddown(($AX20*VLOOKUP($B$13,$AU$177:$AY$185,5,false))+VLOOKUP(AV20,$AU$191:$AY$205,5,false),0) -> 3126 | BM20: =rounddown(($AX20*VLOOKUP($B$13,$AU$177:$AZ$185,6,false))+VLOOKUP(AV20,$AU$191:$AY$205,5,false),0) -> 3177 | BN20: =rounddown(($AX20*VLOOKUP($B$13,$AU$177:$BE$185,7,false))+VLOOKUP(AV20,$AU$191:$AY$205,5,false),0) -> 3177 | BO20: =rounddown(($AX20*VLOOKUP($B$13,$AU$177:$BE$185,8,false))+VLOOKUP(AV20,$AU$191:$AY$205,5,false),0) -> 3177 | BP20: =rounddown(($AX20*VLOOKUP($B$13,$AU$177:$BE$185,9,false))+VLOOKUP(AV20,$AU$191:$AY$205,5,false),0) -> 3177 | BQ20: =rounddown(($AX20*VLOOKUP($B$13,$AU$177:$BE$185,10,false))+VLOOKUP(AV20,$AU$191:$AY$205,5,false),0) -> 3177 | BR20: =rounddown(($AX20*VLOOKUP($B$13,$AU$177:$BE$185,11,false))+VLOOKUP(AV20,$AU$191:$AY$205,5,false),0) -> 3177
B21: =IFERROR(__xludf.DUMMYFUNCTION("IF( E13 = ""スペシャル"", ""-"", IFERROR( INDEX( IMPORTRANGE(""https://docs.google.com/spreadsheets/d/1tAaChe98Zh7vhMfGMK5Y4_ijmNb40fr519GtdZkkDUY/edit#gid=1369914306"", ""キャラ基礎数値!AL:AL""), MATCH(B11, IMPORTRANGE(""https://docs.google.com"&"/spreadsheets/d/1tAaChe98Zh7vhMfGMK5Y4_ijmNb40fr519GtdZkkDUY/edit#gid=1369914306"", ""キャラ基礎数値!C:C""), 0) ), ""該当なし"" ) ) "),1490.0) -> 1490 | E21: =IF(E13 = "スペシャル", "-", B21 * 10) -> 14900 | H21: =IFERROR(__xludf.DUMMYFUNCTION("IF( E13 = ""スペシャル"", ""-"", IFERROR( INDEX( IMPORTRANGE(""https://docs.google.com/spreadsheets/d/1tAaChe98Zh7vhMfGMK5Y4_ijmNb40fr519GtdZkkDUY/edit#gid=1369914306"", ""キャラ基礎数値!AX:AX""), MATCH(B11, IMPORTRANGE(""https://docs.google.com"&"/spreadsheets/d/1tAaChe98Zh7vhMfGMK5Y4_ijmNb40fr519GtdZkkDUY/edit#gid=1369914306"", ""キャラ基礎数値!C:C""), 0) ), ""該当なし"" ) ) "),1740.0) -> 1740 | K21: =IF(E13 = "スペシャル", "-", H21 * 10) -> 17400 | AU21: 12 | AV21: 0 | AW21: =Floor( $AW$9+($AW$171-$AW$9) * Pow( (AU21-1) / ($AU$171-1),$AU$189) ,1) -> 2252 | AX21: =Floor( $AX$9+($AX$171-$AX$9) * Pow( (AU21-1) / ($AU$171-1),$AU$189) ,1) -> 2630 | AY21: =VLOOKUP(AV21,$AU$191:$AY$205,4,FALSE)+AW21 -> 2252 | AZ21: =VLOOKUP(AV21,$AU$191:$AY$205,5,FALSE)+AX21 -> 2630 | BA21: =rounddown(($AW21*VLOOKUP($B$13,$AU$177:$AW$185,3,false))+VLOOKUP(AV21,$AU$191:$AY$205,4,false),0) -> 2522 | BB21: =rounddown(($AW21*VLOOKUP($B$13,$AU$177:$AX$185,4,false))+VLOOKUP(AV21,$AU$191:$AY$205,4,false),0) -> 2679 | BC21: =rounddown(($AW21*VLOOKUP($B$13,$AU$177:$AY$185,5,false))+VLOOKUP(AV21,$AU$191:$AY$205,4,false),0) -> 2769 | BD21: =rounddown(($AW21*VLOOKUP($B$13,$AU$177:$AZ$185,6,false))+VLOOKUP(AV21,$AU$191:$AY$205,4,false),0) -> 2815 | BE21: =rounddown(($AW21*VLOOKUP($B$13,$AU$177:$BE$185,7,false))+VLOOKUP(AV21,$AU$191:$AY$205,4,false),0) -> 2815 | BF21: =rounddown(($AW21*VLOOKUP($B$13,$AU$177:$BE$185,8,false))+VLOOKUP(AV21,$AU$191:$AY$205,4,false),0) -> 2815 | BG21: =rounddown(($AW21*VLOOKUP($B$13,$AU$177:$BE$185,9,false))+VLOOKUP(AV21,$AU$191:$AY$205,4,false),0) -> 2815 | BH21: =rounddown(($AW21*VLOOKUP($B$13,$AU$177:$BE$185,10,false))+VLOOKUP(AV21,$AU$191:$AY$205,4,false),0) -> 2815 | BI21: =rounddown(($AW21*VLOOKUP($B$13,$AU$177:$BE$185,11,false))+VLOOKUP(AV21,$AU$191:$AY$205,4,false),0) -> 2815 | BJ21: =rounddown(($AX21*VLOOKUP($B$13,$AU$177:$AW$185,3,false))+VLOOKUP(AV21,$AU$191:$AY$205,5,false),0) -> 2945 | BK21: =rounddown(($AX21*VLOOKUP($B$13,$AU$177:$AX$185,4,false))+VLOOKUP(AV21,$AU$191:$AY$205,5,false),0) -> 3129 | BL21: =rounddown(($AX21*VLOOKUP($B$13,$AU$177:$AY$185,5,false))+VLOOKUP(AV21,$AU$191:$AY$205,5,false),0) -> 3234 | BM21: =rounddown(($AX21*VLOOKUP($B$13,$AU$177:$AZ$185,6,false))+VLOOKUP(AV21,$AU$191:$AY$205,5,false),0) -> 3287 | BN21: =rounddown(($AX21*VLOOKUP($B$13,$AU$177:$BE$185,7,false))+VLOOKUP(AV21,$AU$191:$AY$205,5,false),0) -> 3287 | BO21: =rounddown(($AX21*VLOOKUP($B$13,$AU$177:$BE$185,8,false))+VLOOKUP(AV21,$AU$191:$AY$205,5,false),0) -> 3287 | BP21: =rounddown(($AX21*VLOOKUP($B$13,$AU$177:$BE$185,9,false))+VLOOKUP(AV21,$AU$191:$AY$205,5,false),0) -> 3287 | BQ21: =rounddown(($AX21*VLOOKUP($B$13,$AU$177:$BE$185,10,false))+VLOOKUP(AV21,$AU$191:$AY$205,5,false),0) -> 3287 | BR21: =rounddown(($AX21*VLOOKUP($B$13,$AU$177:$BE$185,11,false))+VLOOKUP(AV21,$AU$191:$AY$205,5,false),0) -> 3287
AU22: 13 | AV22: 0 | AW22: =Floor( $AW$9+($AW$171-$AW$9) * Pow( (AU22-1) / ($AU$171-1),$AU$189) ,1) -> 2329 | AX22: =Floor( $AX$9+($AX$171-$AX$9) * Pow( (AU22-1) / ($AU$171-1),$AU$189) ,1) -> 2720 | AY22: =VLOOKUP(AV22,$AU$191:$AY$205,4,FALSE)+AW22 -> 2329 | AZ22: =VLOOKUP(AV22,$AU$191:$AY$205,5,FALSE)+AX22 -> 2720 | BA22: =rounddown(($AW22*VLOOKUP($B$13,$AU$177:$AW$185,3,false))+VLOOKUP(AV22,$AU$191:$AY$205,4,false),0) -> 2608 | BB22: =rounddown(($AW22*VLOOKUP($B$13,$AU$177:$AX$185,4,false))+VLOOKUP(AV22,$AU$191:$AY$205,4,false),0) -> 2771 | BC22: =rounddown(($AW22*VLOOKUP($B$13,$AU$177:$AY$185,5,false))+VLOOKUP(AV22,$AU$191:$AY$205,4,false),0) -> 2864 | BD22: =rounddown(($AW22*VLOOKUP($B$13,$AU$177:$AZ$185,6,false))+VLOOKUP(AV22,$AU$191:$AY$205,4,false),0) -> 2911 | BE22: =rounddown(($AW22*VLOOKUP($B$13,$AU$177:$BE$185,7,false))+VLOOKUP(AV22,$AU$191:$AY$205,4,false),0) -> 2911 | BF22: =rounddown(($AW22*VLOOKUP($B$13,$AU$177:$BE$185,8,false))+VLOOKUP(AV22,$AU$191:$AY$205,4,false),0) -> 2911 | BG22: =rounddown(($AW22*VLOOKUP($B$13,$AU$177:$BE$185,9,false))+VLOOKUP(AV22,$AU$191:$AY$205,4,false),0) -> 2911 | BH22: =rounddown(($AW22*VLOOKUP($B$13,$AU$177:$BE$185,10,false))+VLOOKUP(AV22,$AU$191:$AY$205,4,false),0) -> 2911 | BI22: =rounddown(($AW22*VLOOKUP($B$13,$AU$177:$BE$185,11,false))+VLOOKUP(AV22,$AU$191:$AY$205,4,false),0) -> 2911 | BJ22: =rounddown(($AX22*VLOOKUP($B$13,$AU$177:$AW$185,3,false))+VLOOKUP(AV22,$AU$191:$AY$205,5,false),0) -> 3046 | BK22: =rounddown(($AX22*VLOOKUP($B$13,$AU$177:$AX$185,4,false))+VLOOKUP(AV22,$AU$191:$AY$205,5,false),0) -> 3236 | BL22: =rounddown(($AX22*VLOOKUP($B$13,$AU$177:$AY$185,5,false))+VLOOKUP(AV22,$AU$191:$AY$205,5,false),0) -> 3345 | BM22: =rounddown(($AX22*VLOOKUP($B$13,$AU$177:$AZ$185,6,false))+VLOOKUP(AV22,$AU$191:$AY$205,5,false),0) -> 3400 | BN22: =rounddown(($AX22*VLOOKUP($B$13,$AU$177:$BE$185,7,false))+VLOOKUP(AV22,$AU$191:$AY$205,5,false),0) -> 3400 | BO22: =rounddown(($AX22*VLOOKUP($B$13,$AU$177:$BE$185,8,false))+VLOOKUP(AV22,$AU$191:$AY$205,5,false),0) -> 3400 | BP22: =rounddown(($AX22*VLOOKUP($B$13,$AU$177:$BE$185,9,false))+VLOOKUP(AV22,$AU$191:$AY$205,5,false),0) -> 3400 | BQ22: =rounddown(($AX22*VLOOKUP($B$13,$AU$177:$BE$185,10,false))+VLOOKUP(AV22,$AU$191:$AY$205,5,false),0) -> 3400 | BR22: =rounddown(($AX22*VLOOKUP($B$13,$AU$177:$BE$185,11,false))+VLOOKUP(AV22,$AU$191:$AY$205,5,false),0) -> 3400
B23: 特性 | I23: 効果値 | K23: 解放ランク | M23: 解放レベル | AU23: 14 | AV23: 0 | AW23: =Floor( $AW$9+($AW$171-$AW$9) * Pow( (AU23-1) / ($AU$171-1),$AU$189) ,1) -> 2406 | AX23: =Floor( $AX$9+($AX$171-$AX$9) * Pow( (AU23-1) / ($AU$171-1),$AU$189) ,1) -> 2810 | AY23: =VLOOKUP(AV23,$AU$191:$AY$205,4,FALSE)+AW23 -> 2406 | AZ23: =VLOOKUP(AV23,$AU$191:$AY$205,5,FALSE)+AX23 -> 2810 | BA23: =rounddown(($AW23*VLOOKUP($B$13,$AU$177:$AW$185,3,false))+VLOOKUP(AV23,$AU$191:$AY$205,4,false),0) -> 2694 | BB23: =rounddown(($AW23*VLOOKUP($B$13,$AU$177:$AX$185,4,false))+VLOOKUP(AV23,$AU$191:$AY$205,4,false),0) -> 2863 | BC23: =rounddown(($AW23*VLOOKUP($B$13,$AU$177:$AY$185,5,false))+VLOOKUP(AV23,$AU$191:$AY$205,4,false),0) -> 2959 | BD23: =rounddown(($AW23*VLOOKUP($B$13,$AU$177:$AZ$185,6,false))+VLOOKUP(AV23,$AU$191:$AY$205,4,false),0) -> 3007 | BE23: =rounddown(($AW23*VLOOKUP($B$13,$AU$177:$BE$185,7,false))+VLOOKUP(AV23,$AU$191:$AY$205,4,false),0) -> 3007 | BF23: =rounddown(($AW23*VLOOKUP($B$13,$AU$177:$BE$185,8,false))+VLOOKUP(AV23,$AU$191:$AY$205,4,false),0) -> 3007 | BG23: =rounddown(($AW23*VLOOKUP($B$13,$AU$177:$BE$185,9,false))+VLOOKUP(AV23,$AU$191:$AY$205,4,false),0) -> 3007 | BH23: =rounddown(($AW23*VLOOKUP($B$13,$AU$177:$BE$185,10,false))+VLOOKUP(AV23,$AU$191:$AY$205,4,false),0) -> 3007 | BI23: =rounddown(($AW23*VLOOKUP($B$13,$AU$177:$BE$185,11,false))+VLOOKUP(AV23,$AU$191:$AY$205,4,false),0) -> 3007 | BJ23: =rounddown(($AX23*VLOOKUP($B$13,$AU$177:$AW$185,3,false))+VLOOKUP(AV23,$AU$191:$AY$205,5,false),0) -> 3147 | BK23: =rounddown(($AX23*VLOOKUP($B$13,$AU$177:$AX$185,4,false))+VLOOKUP(AV23,$AU$191:$AY$205,5,false),0) -> 3343 | BL23: =rounddown(($AX23*VLOOKUP($B$13,$AU$177:$AY$185,5,false))+VLOOKUP(AV23,$AU$191:$AY$205,5,false),0) -> 3456 | BM23: =rounddown(($AX23*VLOOKUP($B$13,$AU$177:$AZ$185,6,false))+VLOOKUP(AV23,$AU$191:$AY$205,5,false),0) -> 3512 | BN23: =rounddown(($AX23*VLOOKUP($B$13,$AU$177:$BE$185,7,false))+VLOOKUP(AV23,$AU$191:$AY$205,5,false),0) -> 3512 | BO23: =rounddown(($AX23*VLOOKUP($B$13,$AU$177:$BE$185,8,false))+VLOOKUP(AV23,$AU$191:$AY$205,5,false),0) -> 3512 | BP23: =rounddown(($AX23*VLOOKUP($B$13,$AU$177:$BE$185,9,false))+VLOOKUP(AV23,$AU$191:$AY$205,5,false),0) -> 3512 | BQ23: =rounddown(($AX23*VLOOKUP($B$13,$AU$177:$BE$185,10,false))+VLOOKUP(AV23,$AU$191:$AY$205,5,false),0) -> 3512 | BR23: =rounddown(($AX23*VLOOKUP($B$13,$AU$177:$BE$185,11,false))+VLOOKUP(AV23,$AU$191:$AY$205,5,false),0) -> 3512
B24: 1 | C24: =IFERROR(__xludf.DUMMYFUNCTION("IFERROR( INDEX( IMPORTRANGE(""https://docs.google.com/spreadsheets/d/1tAaChe98Zh7vhMfGMK5Y4_ijmNb40fr519GtdZkkDUY/edit#gid=1369914306"", ""キャラ基礎数値!BW:BW""), MATCH(B11, IMPORTRANGE(""https://docs.google.com/spreadsheets/d/1tAaChe98Zh7vhMfGMK5Y4_i"&"jmNb40fr519GtdZkkDUY/edit#gid=1369914306"", ""キャラ基礎数値!C:C""), 0) ), ""該当なし"" ) "),"攻撃UPコマ効果UP") -> 攻撃UPコマ効果UP | I24: =IFERROR(__xludf.DUMMYFUNCTION("IFERROR( INDEX( IMPORTRANGE(""https://docs.google.com/spreadsheets/d/1tAaChe98Zh7vhMfGMK5Y4_ijmNb40fr519GtdZkkDUY/edit#gid=1369914306"", ""キャラ基礎数値!BX:BX""), MATCH($B$11, IMPORTRANGE(""https://docs.google.com/spreadsheets/d/1tAaChe98Zh7vhMfGMK5Y4"&"_ijmNb40fr519GtdZkkDUY/edit#gid=1369914306"", ""キャラ基礎数値!C:C""), 0) ), ""該当なし"" ) "),20.0) -> 20 | K24: =IFERROR(__xludf.DUMMYFUNCTION("IFERROR( INDEX( IMPORTRANGE(""https://docs.google.com/spreadsheets/d/1tAaChe98Zh7vhMfGMK5Y4_ijmNb40fr519GtdZkkDUY/edit#gid=1369914306"", ""キャラ基礎数値!BY:BY""), MATCH($B$11, IMPORTRANGE(""https://docs.google.com/spreadsheets/d/1tAaChe98Zh7vhMfGMK5Y4"&"_ijmNb40fr519GtdZkkDUY/edit#gid=1369914306"", ""キャラ基礎数値!C:C""), 0) ), ""該当なし"" ) "),0.0) -> 0 | M24: {=INDEX('参照ランク'!C2:C9,MATCH(K24,'参照ランク'!B2:B9))} -> 0 | AU24: 15 | AV24: 0 | AW24: =Floor( $AW$9+($AW$171-$AW$9) * Pow( (AU24-1) / ($AU$171-1),$AU$189) ,1) -> 2484 | AX24: =Floor( $AX$9+($AX$171-$AX$9) * Pow( (AU24-1) / ($AU$171-1),$AU$189) ,1) -> 2901 | AY24: =VLOOKUP(AV24,$AU$191:$AY$205,4,FALSE)+AW24 -> 2484 | AZ24: =VLOOKUP(AV24,$AU$191:$AY$205,5,FALSE)+AX24 -> 2901 | BA24: =rounddown(($AW24*VLOOKUP($B$13,$AU$177:$AW$185,3,false))+VLOOKUP(AV24,$AU$191:$AY$205,4,false),0) -> 2782 | BB24: =rounddown(($AW24*VLOOKUP($B$13,$AU$177:$AX$185,4,false))+VLOOKUP(AV24,$AU$191:$AY$205,4,false),0) -> 2955 | BC24: =rounddown(($AW24*VLOOKUP($B$13,$AU$177:$AY$185,5,false))+VLOOKUP(AV24,$AU$191:$AY$205,4,false),0) -> 3055 | BD24: =rounddown(($AW24*VLOOKUP($B$13,$AU$177:$AZ$185,6,false))+VLOOKUP(AV24,$AU$191:$AY$205,4,false),0) -> 3105 | BE24: =rounddown(($AW24*VLOOKUP($B$13,$AU$177:$BE$185,7,false))+VLOOKUP(AV24,$AU$191:$AY$205,4,false),0) -> 3105 | BF24: =rounddown(($AW24*VLOOKUP($B$13,$AU$177:$BE$185,8,false))+VLOOKUP(AV24,$AU$191:$AY$205,4,false),0) -> 3105 | BG24: =rounddown(($AW24*VLOOKUP($B$13,$AU$177:$BE$185,9,false))+VLOOKUP(AV24,$AU$191:$AY$205,4,false),0) -> 3105 | BH24: =rounddown(($AW24*VLOOKUP($B$13,$AU$177:$BE$185,10,false))+VLOOKUP(AV24,$AU$191:$AY$205,4,false),0) -> 3105 | BI24: =rounddown(($AW24*VLOOKUP($B$13,$AU$177:$BE$185,11,false))+VLOOKUP(AV24,$AU$191:$AY$205,4,false),0) -> 3105 | BJ24: =rounddown(($AX24*VLOOKUP($B$13,$AU$177:$AW$185,3,false))+VLOOKUP(AV24,$AU$191:$AY$205,5,false),0) -> 3249 | BK24: =rounddown(($AX24*VLOOKUP($B$13,$AU$177:$AX$185,4,false))+VLOOKUP(AV24,$AU$191:$AY$205,5,false),0) -> 3452 | BL24: =rounddown(($AX24*VLOOKUP($B$13,$AU$177:$AY$185,5,false))+VLOOKUP(AV24,$AU$191:$AY$205,5,false),0) -> 3568 | BM24: =rounddown(($AX24*VLOOKUP($B$13,$AU$177:$AZ$185,6,false))+VLOOKUP(AV24,$AU$191:$AY$205,5,false),0) -> 3626 | BN24: =rounddown(($AX24*VLOOKUP($B$13,$AU$177:$BE$185,7,false))+VLOOKUP(AV24,$AU$191:$AY$205,5,false),0) -> 3626 | BO24: =rounddown(($AX24*VLOOKUP($B$13,$AU$177:$BE$185,8,false))+VLOOKUP(AV24,$AU$191:$AY$205,5,false),0) -> 3626 | BP24: =rounddown(($AX24*VLOOKUP($B$13,$AU$177:$BE$185,9,false))+VLOOKUP(AV24,$AU$191:$AY$205,5,false),0) -> 3626 | BQ24: =rounddown(($AX24*VLOOKUP($B$13,$AU$177:$BE$185,10,false))+VLOOKUP(AV24,$AU$191:$AY$205,5,false),0) -> 3626 | BR24: =rounddown(($AX24*VLOOKUP($B$13,$AU$177:$BE$185,11,false))+VLOOKUP(AV24,$AU$191:$AY$205,5,false),0) -> 3626
B25: 2 | C25: =IFERROR(__xludf.DUMMYFUNCTION("IFERROR( INDEX( IMPORTRANGE(""https://docs.google.com/spreadsheets/d/1tAaChe98Zh7vhMfGMK5Y4_ijmNb40fr519GtdZkkDUY/edit#gid=1369914306"", ""キャラ基礎数値!BZ:BZ""), MATCH(B11, IMPORTRANGE(""https://docs.google.com/spreadsheets/d/1tAaChe98Zh7vhMfGMK5Y4_i"&"jmNb40fr519GtdZkkDUY/edit#gid=1369914306"", ""キャラ基礎数値!C:C""), 0) ), ""該当なし"" ) "),"-") -> - | I25: =IFERROR(__xludf.DUMMYFUNCTION("IFERROR( INDEX( IMPORTRANGE(""https://docs.google.com/spreadsheets/d/1tAaChe98Zh7vhMfGMK5Y4_ijmNb40fr519GtdZkkDUY/edit#gid=1369914306"", ""キャラ基礎数値!CA:CA""), MATCH($B$11, IMPORTRANGE(""https://docs.google.com/spreadsheets/d/1tAaChe98Zh7vhMfGMK5Y4"&"_ijmNb40fr519GtdZkkDUY/edit#gid=1369914306"", ""キャラ基礎数値!C:C""), 0) ), ""該当なし"" ) "),"-") -> - | K25: =IFERROR(__xludf.DUMMYFUNCTION("IFERROR( INDEX( IMPORTRANGE(""https://docs.google.com/spreadsheets/d/1tAaChe98Zh7vhMfGMK5Y4_ijmNb40fr519GtdZkkDUY/edit#gid=1369914306"", ""キャラ基礎数値!CB:CB""), MATCH($B$11, IMPORTRANGE(""https://docs.google.com/spreadsheets/d/1tAaChe98Zh7vhMfGMK5Y4"&"_ijmNb40fr519GtdZkkDUY/edit#gid=1369914306"", ""キャラ基礎数値!C:C""), 0) ), ""該当なし"" ) "),"-") -> - | M25: {=INDEX('参照ランク'!C3:C10,MATCH(K25,'参照ランク'!B3:B10))} -> #N/A | AU25: 16 | AV25: 0 | AW25: =Floor( $AW$9+($AW$171-$AW$9) * Pow( (AU25-1) / ($AU$171-1),$AU$189) ,1) -> 2563 | AX25: =Floor( $AX$9+($AX$171-$AX$9) * Pow( (AU25-1) / ($AU$171-1),$AU$189) ,1) -> 2993 | AY25: =VLOOKUP(AV25,$AU$191:$AY$205,4,FALSE)+AW25 -> 2563 | AZ25: =VLOOKUP(AV25,$AU$191:$AY$205,5,FALSE)+AX25 -> 2993 | BA25: =rounddown(($AW25*VLOOKUP($B$13,$AU$177:$AW$185,3,false))+VLOOKUP(AV25,$AU$191:$AY$205,4,false),0) -> 2870 | BB25: =rounddown(($AW25*VLOOKUP($B$13,$AU$177:$AX$185,4,false))+VLOOKUP(AV25,$AU$191:$AY$205,4,false),0) -> 3049 | BC25: =rounddown(($AW25*VLOOKUP($B$13,$AU$177:$AY$185,5,false))+VLOOKUP(AV25,$AU$191:$AY$205,4,false),0) -> 3152 | BD25: =rounddown(($AW25*VLOOKUP($B$13,$AU$177:$AZ$185,6,false))+VLOOKUP(AV25,$AU$191:$AY$205,4,false),0) -> 3203 | BE25: =rounddown(($AW25*VLOOKUP($B$13,$AU$177:$BE$185,7,false))+VLOOKUP(AV25,$AU$191:$AY$205,4,false),0) -> 3203 | BF25: =rounddown(($AW25*VLOOKUP($B$13,$AU$177:$BE$185,8,false))+VLOOKUP(AV25,$AU$191:$AY$205,4,false),0) -> 3203 | BG25: =rounddown(($AW25*VLOOKUP($B$13,$AU$177:$BE$185,9,false))+VLOOKUP(AV25,$AU$191:$AY$205,4,false),0) -> 3203 | BH25: =rounddown(($AW25*VLOOKUP($B$13,$AU$177:$BE$185,10,false))+VLOOKUP(AV25,$AU$191:$AY$205,4,false),0) -> 3203 | BI25: =rounddown(($AW25*VLOOKUP($B$13,$AU$177:$BE$185,11,false))+VLOOKUP(AV25,$AU$191:$AY$205,4,false),0) -> 3203 | BJ25: =rounddown(($AX25*VLOOKUP($B$13,$AU$177:$AW$185,3,false))+VLOOKUP(AV25,$AU$191:$AY$205,5,false),0) -> 3352 | BK25: =rounddown(($AX25*VLOOKUP($B$13,$AU$177:$AX$185,4,false))+VLOOKUP(AV25,$AU$191:$AY$205,5,false),0) -> 3561 | BL25: =rounddown(($AX25*VLOOKUP($B$13,$AU$177:$AY$185,5,false))+VLOOKUP(AV25,$AU$191:$AY$205,5,false),0) -> 3681 | BM25: =rounddown(($AX25*VLOOKUP($B$13,$AU$177:$AZ$185,6,false))+VLOOKUP(AV25,$AU$191:$AY$205,5,false),0) -> 3741 | BN25: =rounddown(($AX25*VLOOKUP($B$13,$AU$177:$BE$185,7,false))+VLOOKUP(AV25,$AU$191:$AY$205,5,false),0) -> 3741 | BO25: =rounddown(($AX25*VLOOKUP($B$13,$AU$177:$BE$185,8,false))+VLOOKUP(AV25,$AU$191:$AY$205,5,false),0) -> 3741 | BP25: =rounddown(($AX25*VLOOKUP($B$13,$AU$177:$BE$185,9,false))+VLOOKUP(AV25,$AU$191:$AY$205,5,false),0) -> 3741 | BQ25: =rounddown(($AX25*VLOOKUP($B$13,$AU$177:$BE$185,10,false))+VLOOKUP(AV25,$AU$191:$AY$205,5,false),0) -> 3741 | BR25: =rounddown(($AX25*VLOOKUP($B$13,$AU$177:$BE$185,11,false))+VLOOKUP(AV25,$AU$191:$AY$205,5,false),0) -> 3741
B26: 3 | C26: - | I26: - | K26: - | M26: {=INDEX('参照ランク'!C4:C11,MATCH(K26,'参照ランク'!B4:B11))} -> #N/A | AU26: 17 | AV26: 0 | AW26: =Floor( $AW$9+($AW$171-$AW$9) * Pow( (AU26-1) / ($AU$171-1),$AU$189) ,1) -> 2642 | AX26: =Floor( $AX$9+($AX$171-$AX$9) * Pow( (AU26-1) / ($AU$171-1),$AU$189) ,1) -> 3085 | AY26: =VLOOKUP(AV26,$AU$191:$AY$205,4,FALSE)+AW26 -> 2642 | AZ26: =VLOOKUP(AV26,$AU$191:$AY$205,5,FALSE)+AX26 -> 3085 | BA26: =rounddown(($AW26*VLOOKUP($B$13,$AU$177:$AW$185,3,false))+VLOOKUP(AV26,$AU$191:$AY$205,4,false),0) -> 2959 | BB26: =rounddown(($AW26*VLOOKUP($B$13,$AU$177:$AX$185,4,false))+VLOOKUP(AV26,$AU$191:$AY$205,4,false),0) -> 3143 | BC26: =rounddown(($AW26*VLOOKUP($B$13,$AU$177:$AY$185,5,false))+VLOOKUP(AV26,$AU$191:$AY$205,4,false),0) -> 3249 | BD26: =rounddown(($AW26*VLOOKUP($B$13,$AU$177:$AZ$185,6,false))+VLOOKUP(AV26,$AU$191:$AY$205,4,false),0) -> 3302 | BE26: =rounddown(($AW26*VLOOKUP($B$13,$AU$177:$BE$185,7,false))+VLOOKUP(AV26,$AU$191:$AY$205,4,false),0) -> 3302 | BF26: =rounddown(($AW26*VLOOKUP($B$13,$AU$177:$BE$185,8,false))+VLOOKUP(AV26,$AU$191:$AY$205,4,false),0) -> 3302 | BG26: =rounddown(($AW26*VLOOKUP($B$13,$AU$177:$BE$185,9,false))+VLOOKUP(AV26,$AU$191:$AY$205,4,false),0) -> 3302 | BH26: =rounddown(($AW26*VLOOKUP($B$13,$AU$177:$BE$185,10,false))+VLOOKUP(AV26,$AU$191:$AY$205,4,false),0) -> 3302 | BI26: =rounddown(($AW26*VLOOKUP($B$13,$AU$177:$BE$185,11,false))+VLOOKUP(AV26,$AU$191:$AY$205,4,false),0) -> 3302 | BJ26: =rounddown(($AX26*VLOOKUP($B$13,$AU$177:$AW$185,3,false))+VLOOKUP(AV26,$AU$191:$AY$205,5,false),0) -> 3455 | BK26: =rounddown(($AX26*VLOOKUP($B$13,$AU$177:$AX$185,4,false))+VLOOKUP(AV26,$AU$191:$AY$205,5,false),0) -> 3671 | BL26: =rounddown(($AX26*VLOOKUP($B$13,$AU$177:$AY$185,5,false))+VLOOKUP(AV26,$AU$191:$AY$205,5,false),0) -> 3794 | BM26: =rounddown(($AX26*VLOOKUP($B$13,$AU$177:$AZ$185,6,false))+VLOOKUP(AV26,$AU$191:$AY$205,5,false),0) -> 3856 | BN26: =rounddown(($AX26*VLOOKUP($B$13,$AU$177:$BE$185,7,false))+VLOOKUP(AV26,$AU$191:$AY$205,5,false),0) -> 3856 | BO26: =rounddown(($AX26*VLOOKUP($B$13,$AU$177:$BE$185,8,false))+VLOOKUP(AV26,$AU$191:$AY$205,5,false),0) -> 3856 | BP26: =rounddown(($AX26*VLOOKUP($B$13,$AU$177:$BE$185,9,false))+VLOOKUP(AV26,$AU$191:$AY$205,5,false),0) -> 3856 | BQ26: =rounddown(($AX26*VLOOKUP($B$13,$AU$177:$BE$185,10,false))+VLOOKUP(AV26,$AU$191:$AY$205,5,false),0) -> 3856 | BR26: =rounddown(($AX26*VLOOKUP($B$13,$AU$177:$BE$185,11,false))+VLOOKUP(AV26,$AU$191:$AY$205,5,false),0) -> 3856
O27: ※解放ランク1=Lv20,ランク2=Lv30。以降同様。 | AU27: 18 | AV27: 0 | AW27: =Floor( $AW$9+($AW$171-$AW$9) * Pow( (AU27-1) / ($AU$171-1),$AU$189) ,1) -> 2721 | AX27: =Floor( $AX$9+($AX$171-$AX$9) * Pow( (AU27-1) / ($AU$171-1),$AU$189) ,1) -> 3178 | AY27: =VLOOKUP(AV27,$AU$191:$AY$205,4,FALSE)+AW27 -> 2721 | AZ27: =VLOOKUP(AV27,$AU$191:$AY$205,5,FALSE)+AX27 -> 3178 | BA27: =rounddown(($AW27*VLOOKUP($B$13,$AU$177:$AW$185,3,false))+VLOOKUP(AV27,$AU$191:$AY$205,4,false),0) -> 3047 | BB27: =rounddown(($AW27*VLOOKUP($B$13,$AU$177:$AX$185,4,false))+VLOOKUP(AV27,$AU$191:$AY$205,4,false),0) -> 3237 | BC27: =rounddown(($AW27*VLOOKUP($B$13,$AU$177:$AY$185,5,false))+VLOOKUP(AV27,$AU$191:$AY$205,4,false),0) -> 3346 | BD27: =rounddown(($AW27*VLOOKUP($B$13,$AU$177:$AZ$185,6,false))+VLOOKUP(AV27,$AU$191:$AY$205,4,false),0) -> 3401 | BE27: =rounddown(($AW27*VLOOKUP($B$13,$AU$177:$BE$185,7,false))+VLOOKUP(AV27,$AU$191:$AY$205,4,false),0) -> 3401 | BF27: =rounddown(($AW27*VLOOKUP($B$13,$AU$177:$BE$185,8,false))+VLOOKUP(AV27,$AU$191:$AY$205,4,false),0) -> 3401 | BG27: =rounddown(($AW27*VLOOKUP($B$13,$AU$177:$BE$185,9,false))+VLOOKUP(AV27,$AU$191:$AY$205,4,false),0) -> 3401 | BH27: =rounddown(($AW27*VLOOKUP($B$13,$AU$177:$BE$185,10,false))+VLOOKUP(AV27,$AU$191:$AY$205,4,false),0) -> 3401 | BI27: =rounddown(($AW27*VLOOKUP($B$13,$AU$177:$BE$185,11,false))+VLOOKUP(AV27,$AU$191:$AY$205,4,false),0) -> 3401 | BJ27: =rounddown(($AX27*VLOOKUP($B$13,$AU$177:$AW$185,3,false))+VLOOKUP(AV27,$AU$191:$AY$205,5,false),0) -> 3559 | BK27: =rounddown(($AX27*VLOOKUP($B$13,$AU$177:$AX$185,4,false))+VLOOKUP(AV27,$AU$191:$AY$205,5,false),0) -> 3781 | BL27: =rounddown(($AX27*VLOOKUP($B$13,$AU$177:$AY$185,5,false))+VLOOKUP(AV27,$AU$191:$AY$205,5,false),0) -> 3908 | BM27: =rounddown(($AX27*VLOOKUP($B$13,$AU$177:$AZ$185,6,false))+VLOOKUP(AV27,$AU$191:$AY$205,5,false),0) -> 3972 | BN27: =rounddown(($AX27*VLOOKUP($B$13,$AU$177:$BE$185,7,false))+VLOOKUP(AV27,$AU$191:$AY$205,5,false),0) -> 3972 | BO27: =rounddown(($AX27*VLOOKUP($B$13,$AU$177:$BE$185,8,false))+VLOOKUP(AV27,$AU$191:$AY$205,5,false),0) -> 3972 | BP27: =rounddown(($AX27*VLOOKUP($B$13,$AU$177:$BE$185,9,false))+VLOOKUP(AV27,$AU$191:$AY$205,5,false),0) -> 3972 | BQ27: =rounddown(($AX27*VLOOKUP($B$13,$AU$177:$BE$185,10,false))+VLOOKUP(AV27,$AU$191:$AY$205,5,false),0) -> 3972 | BR27: =rounddown(($AX27*VLOOKUP($B$13,$AU$177:$BE$185,11,false))+VLOOKUP(AV27,$AU$191:$AY$205,5,false),0) -> 3972
B28: 通常攻撃ステータス | AU28: 19 | AV28: 0 | AW28: =Floor( $AW$9+($AW$171-$AW$9) * Pow( (AU28-1) / ($AU$171-1),$AU$189) ,1) -> 2801 | AX28: =Floor( $AX$9+($AX$171-$AX$9) * Pow( (AU28-1) / ($AU$171-1),$AU$189) ,1) -> 3271 | AY28: =VLOOKUP(AV28,$AU$191:$AY$205,4,FALSE)+AW28 -> 2801 | AZ28: =VLOOKUP(AV28,$AU$191:$AY$205,5,FALSE)+AX28 -> 3271 | BA28: =rounddown(($AW28*VLOOKUP($B$13,$AU$177:$AW$185,3,false))+VLOOKUP(AV28,$AU$191:$AY$205,4,false),0) -> 3137 | BB28: =rounddown(($AW28*VLOOKUP($B$13,$AU$177:$AX$185,4,false))+VLOOKUP(AV28,$AU$191:$AY$205,4,false),0) -> 3333 | BC28: =rounddown(($AW28*VLOOKUP($B$13,$AU$177:$AY$185,5,false))+VLOOKUP(AV28,$AU$191:$AY$205,4,false),0) -> 3445 | BD28: =rounddown(($AW28*VLOOKUP($B$13,$AU$177:$AZ$185,6,false))+VLOOKUP(AV28,$AU$191:$AY$205,4,false),0) -> 3501 | BE28: =rounddown(($AW28*VLOOKUP($B$13,$AU$177:$BE$185,7,false))+VLOOKUP(AV28,$AU$191:$AY$205,4,false),0) -> 3501 | BF28: =rounddown(($AW28*VLOOKUP($B$13,$AU$177:$BE$185,8,false))+VLOOKUP(AV28,$AU$191:$AY$205,4,false),0) -> 3501 | BG28: =rounddown(($AW28*VLOOKUP($B$13,$AU$177:$BE$185,9,false))+VLOOKUP(AV28,$AU$191:$AY$205,4,false),0) -> 3501 | BH28: =rounddown(($AW28*VLOOKUP($B$13,$AU$177:$BE$185,10,false))+VLOOKUP(AV28,$AU$191:$AY$205,4,false),0) -> 3501 | BI28: =rounddown(($AW28*VLOOKUP($B$13,$AU$177:$BE$185,11,false))+VLOOKUP(AV28,$AU$191:$AY$205,4,false),0) -> 3501 | BJ28: =rounddown(($AX28*VLOOKUP($B$13,$AU$177:$AW$185,3,false))+VLOOKUP(AV28,$AU$191:$AY$205,5,false),0) -> 3663 | BK28: =rounddown(($AX28*VLOOKUP($B$13,$AU$177:$AX$185,4,false))+VLOOKUP(AV28,$AU$191:$AY$205,5,false),0) -> 3892 | BL28: =rounddown(($AX28*VLOOKUP($B$13,$AU$177:$AY$185,5,false))+VLOOKUP(AV28,$AU$191:$AY$205,5,false),0) -> 4023 | BM28: =rounddown(($AX28*VLOOKUP($B$13,$AU$177:$AZ$185,6,false))+VLOOKUP(AV28,$AU$191:$AY$205,5,false),0) -> 4088 | BN28: =rounddown(($AX28*VLOOKUP($B$13,$AU$177:$BE$185,7,false))+VLOOKUP(AV28,$AU$191:$AY$205,5,false),0) -> 4088 | BO28: =rounddown(($AX28*VLOOKUP($B$13,$AU$177:$BE$185,8,false))+VLOOKUP(AV28,$AU$191:$AY$205,5,false),0) -> 4088 | BP28: =rounddown(($AX28*VLOOKUP($B$13,$AU$177:$BE$185,9,false))+VLOOKUP(AV28,$AU$191:$AY$205,5,false),0) -> 4088 | BQ28: =rounddown(($AX28*VLOOKUP($B$13,$AU$177:$BE$185,10,false))+VLOOKUP(AV28,$AU$191:$AY$205,5,false),0) -> 4088 | BR28: =rounddown(($AX28*VLOOKUP($B$13,$AU$177:$BE$185,11,false))+VLOOKUP(AV28,$AU$191:$AY$205,5,false),0) -> 4088
B29: オノマトペ | E29: 通常攻撃発生F | H29: 攻撃ヒットF | L29: 攻撃CDF | O29: 攻撃距離 | R29: 射程 | T29: 攻撃範囲 | W29: 攻撃倍率 | AU29: 20 | AV29: 0 | AW29: =Floor( $AW$9+($AW$171-$AW$9) * Pow( (AU29-1) / ($AU$171-1),$AU$189) ,1) -> 2881 | AX29: =Floor( $AX$9+($AX$171-$AX$9) * Pow( (AU29-1) / ($AU$171-1),$AU$189) ,1) -> 3365 | AY29: =VLOOKUP(AV29,$AU$191:$AY$205,4,FALSE)+AW29 -> 2881 | AZ29: =VLOOKUP(AV29,$AU$191:$AY$205,5,FALSE)+AX29 -> 3365 | BA29: =rounddown(($AW29*VLOOKUP($B$13,$AU$177:$AW$185,3,false))+VLOOKUP(AV29,$AU$191:$AY$205,4,false),0) -> 3226 | BB29: =rounddown(($AW29*VLOOKUP($B$13,$AU$177:$AX$185,4,false))+VLOOKUP(AV29,$AU$191:$AY$205,4,false),0) -> 3428 | BC29: =rounddown(($AW29*VLOOKUP($B$13,$AU$177:$AY$185,5,false))+VLOOKUP(AV29,$AU$191:$AY$205,4,false),0) -> 3543 | BD29: =rounddown(($AW29*VLOOKUP($B$13,$AU$177:$AZ$185,6,false))+VLOOKUP(AV29,$AU$191:$AY$205,4,false),0) -> 3601 | BE29: =rounddown(($AW29*VLOOKUP($B$13,$AU$177:$BE$185,7,false))+VLOOKUP(AV29,$AU$191:$AY$205,4,false),0) -> 3601 | BF29: =rounddown(($AW29*VLOOKUP($B$13,$AU$177:$BE$185,8,false))+VLOOKUP(AV29,$AU$191:$AY$205,4,false),0) -> 3601 | BG29: =rounddown(($AW29*VLOOKUP($B$13,$AU$177:$BE$185,9,false))+VLOOKUP(AV29,$AU$191:$AY$205,4,false),0) -> 3601 | BH29: =rounddown(($AW29*VLOOKUP($B$13,$AU$177:$BE$185,10,false))+VLOOKUP(AV29,$AU$191:$AY$205,4,false),0) -> 3601 | BI29: =rounddown(($AW29*VLOOKUP($B$13,$AU$177:$BE$185,11,false))+VLOOKUP(AV29,$AU$191:$AY$205,4,false),0) -> 3601 | BJ29: =rounddown(($AX29*VLOOKUP($B$13,$AU$177:$AW$185,3,false))+VLOOKUP(AV29,$AU$191:$AY$205,5,false),0) -> 3768 | BK29: =rounddown(($AX29*VLOOKUP($B$13,$AU$177:$AX$185,4,false))+VLOOKUP(AV29,$AU$191:$AY$205,5,false),0) -> 4004 | BL29: =rounddown(($AX29*VLOOKUP($B$13,$AU$177:$AY$185,5,false))+VLOOKUP(AV29,$AU$191:$AY$205,5,false),0) -> 4138 | BM29: =rounddown(($AX29*VLOOKUP($B$13,$AU$177:$AZ$185,6,false))+VLOOKUP(AV29,$AU$191:$AY$205,5,false),0) -> 4206 | BN29: =rounddown(($AX29*VLOOKUP($B$13,$AU$177:$BE$185,7,false))+VLOOKUP(AV29,$AU$191:$AY$205,5,false),0) -> 4206 | BO29: =rounddown(($AX29*VLOOKUP($B$13,$AU$177:$BE$185,8,false))+VLOOKUP(AV29,$AU$191:$AY$205,5,false),0) -> 4206 | BP29: =rounddown(($AX29*VLOOKUP($B$13,$AU$177:$BE$185,9,false))+VLOOKUP(AV29,$AU$191:$AY$205,5,false),0) -> 4206 | BQ29: =rounddown(($AX29*VLOOKUP($B$13,$AU$177:$BE$185,10,false))+VLOOKUP(AV29,$AU$191:$AY$205,5,false),0) -> 4206 | BR29: =rounddown(($AX29*VLOOKUP($B$13,$AU$177:$BE$185,11,false))+VLOOKUP(AV29,$AU$191:$AY$205,5,false),0) -> 4206
B30: =IFERROR(__xludf.DUMMYFUNCTION("IFERROR( INDEX( IMPORTRANGE(""https://docs.google.com/spreadsheets/d/1oJmkDK37Qizzdaxn4KCwh1BMwdNWuHCx3AGH8BC9yu0/edit?gid=781951868#gid=781951868"", ""キャラ!M:M""), MATCH(B11, IMPORTRANGE(""https://docs.google.com/spreadsheets/d/1oJmkDK37Qizzdaxn"&"4KCwh1BMwdNWuHCx3AGH8BC9yu0/edit?gid=781951868#gid=781951868"", ""キャラ!D:D""), 0) ), ""該当なし"" ) "),"zangeki_1") -> zangeki_1 | E30: =IFERROR(__xludf.DUMMYFUNCTION("IFERROR( INDEX( IMPORTRANGE(""https://docs.google.com/spreadsheets/d/1oJmkDK37Qizzdaxn4KCwh1BMwdNWuHCx3AGH8BC9yu0/edit?gid=781951868#gid=781951868"", ""キャラ!Q:Q""), MATCH(B11, IMPORTRANGE(""https://docs.google.com/spreadsheets/d/1oJmkDK37Qizzdaxn"&"4KCwh1BMwdNWuHCx3AGH8BC9yu0/edit?gid=781951868#gid=781951868"", ""キャラ!D:D""), 0) ), ""該当なし"" ) "),"1.5") -> 1.5 | H30: =IFERROR(__xludf.DUMMYFUNCTION("IFERROR( INDEX( IMPORTRANGE(""https://docs.google.com/spreadsheets/d/1oJmkDK37Qizzdaxn4KCwh1BMwdNWuHCx3AGH8BC9yu0/edit?gid=781951868#gid=781951868"", ""キャラ!R:R""), MATCH(B11, IMPORTRANGE(""https://docs.google.com/spreadsheets/d/1oJmkDK37Qizzdaxn"&"4KCwh1BMwdNWuHCx3AGH8BC9yu0/edit?gid=781951868#gid=781951868"", ""キャラ!D:D""), 0) ), ""該当なし"" ) "),"0.50") -> 0.50 | L30: =IFERROR(__xludf.DUMMYFUNCTION("IFERROR( INDEX( IMPORTRANGE(""https://docs.google.com/spreadsheets/d/1tAaChe98Zh7vhMfGMK5Y4_ijmNb40fr519GtdZkkDUY/edit#gid=1369914306"", ""キャラ基礎数値!BN:BN""), MATCH(B11, IMPORTRANGE(""https://docs.google.com/spreadsheets/d/1tAaChe98Zh7vhMfGMK5Y4_i"&"jmNb40fr519GtdZkkDUY/edit#gid=1369914306"", ""キャラ基礎数値!C:C""), 0) ), ""該当なし"" ) "),50.0) -> 50 | O30: =IFERROR(__xludf.DUMMYFUNCTION("IFERROR( INDEX( IMPORTRANGE(""https://docs.google.com/spreadsheets/d/1tAaChe98Zh7vhMfGMK5Y4_ijmNb40fr519GtdZkkDUY/edit#gid=1369914306"", ""キャラ基礎数値!CC:CC""), MATCH(B11, IMPORTRANGE(""https://docs.google.com/spreadsheets/d/1tAaChe98Zh7vhMfGMK5Y4_i"&"jmNb40fr519GtdZkkDUY/edit#gid=1369914306"", ""キャラ基礎数値!C:C""), 0) ), ""該当なし"" ) "),"近距離") -> 近距離 | R30: =IFERROR(__xludf.DUMMYFUNCTION("IFERROR( INDEX( IMPORTRANGE(""https://docs.google.com/spreadsheets/d/1tAaChe98Zh7vhMfGMK5Y4_ijmNb40fr519GtdZkkDUY/edit#gid=1369914306"", ""キャラ基礎数値!CF:CF""), MATCH(B11, IMPORTRANGE(""https://docs.google.com/spreadsheets/d/1tAaChe98Zh7vhMfGMK5Y4_i"&"jmNb40fr519GtdZkkDUY/edit#gid=1369914306"", ""キャラ基礎数値!C:C""), 0) ), ""該当なし"" ) "),0.4) -> 0.4 | T30: =IFERROR(__xludf.DUMMYFUNCTION("IFERROR( INDEX( IMPORTRANGE(""https://docs.google.com/spreadsheets/d/1tAaChe98Zh7vhMfGMK5Y4_ijmNb40fr519GtdZkkDUY/edit#gid=1369914306"", ""キャラ基礎数値!CD:CD""), MATCH(B11, IMPORTRANGE(""https://docs.google.com/spreadsheets/d/1tAaChe98Zh7vhMfGMK5Y4_i"&"jmNb40fr519GtdZkkDUY/edit#gid=1369914306"", ""キャラ基礎数値!C:C""), 0) ), ""該当なし"" ) "),"単体") -> 単体 | W30: =IFERROR(__xludf.DUMMYFUNCTION("IFERROR( INDEX( IMPORTRANGE(""https://docs.google.com/spreadsheets/d/1tAaChe98Zh7vhMfGMK5Y4_ijmNb40fr519GtdZkkDUY/edit#gid=1369914306"", ""キャラ基礎数値!CE:CE""), MATCH(B11, IMPORTRANGE(""https://docs.google.com/spreadsheets/d/1tAaChe98Zh7vhMfGMK5Y4_i"&"jmNb40fr519GtdZkkDUY/edit#gid=1369914306"", ""キャラ基礎数値!C:C""), 0) ), ""該当なし"" ) "),1.0) -> 1 | AU30: 20 | AV30: 1 | AW30: =Floor( $AW$9+($AW$171-$AW$9) * Pow( (AU30-1) / ($AU$171-1),$AU$189) ,1) -> 2881 | AX30: =Floor( $AX$9+($AX$171-$AX$9) * Pow( (AU30-1) / ($AU$171-1),$AU$189) ,1) -> 3365 | AY30: =VLOOKUP(AV30,$AU$191:$AY$205,4,FALSE)+AW30 -> 3053 | AZ30: =VLOOKUP(AV30,$AU$191:$AY$205,5,FALSE)+AX30 -> 3566 | BA30: =rounddown(($AW30*VLOOKUP($B$13,$AU$177:$AW$185,3,false))+VLOOKUP(AV30,$AU$191:$AY$205,4,false),0) -> 3398 | BB30: =rounddown(($AW30*VLOOKUP($B$13,$AU$177:$AX$185,4,false))+VLOOKUP(AV30,$AU$191:$AY$205,4,false),0) -> 3600 | BC30: =rounddown(($AW30*VLOOKUP($B$13,$AU$177:$AY$185,5,false))+VLOOKUP(AV30,$AU$191:$AY$205,4,false),0) -> 3715 | BD30: =rounddown(($AW30*VLOOKUP($B$13,$AU$177:$AZ$185,6,false))+VLOOKUP(AV30,$AU$191:$AY$205,4,false),0) -> 3773 | BE30: =rounddown(($AW30*VLOOKUP($B$13,$AU$177:$BE$185,7,false))+VLOOKUP(AV30,$AU$191:$AY$205,4,false),0) -> 3773 | BF30: =rounddown(($AW30*VLOOKUP($B$13,$AU$177:$BE$185,8,false))+VLOOKUP(AV30,$AU$191:$AY$205,4,false),0) -> 3773 | BG30: =rounddown(($AW30*VLOOKUP($B$13,$AU$177:$BE$185,9,false))+VLOOKUP(AV30,$AU$191:$AY$205,4,false),0) -> 3773 | BH30: =rounddown(($AW30*VLOOKUP($B$13,$AU$177:$BE$185,10,false))+VLOOKUP(AV30,$AU$191:$AY$205,4,false),0) -> 3773 | BI30: =rounddown(($AW30*VLOOKUP($B$13,$AU$177:$BE$185,11,false))+VLOOKUP(AV30,$AU$191:$AY$205,4,false),0) -> 3773 | BJ30: =rounddown(($AX30*VLOOKUP($B$13,$AU$177:$AW$185,3,false))+VLOOKUP(AV30,$AU$191:$AY$205,5,false),0) -> 3969 | BK30: =rounddown(($AX30*VLOOKUP($B$13,$AU$177:$AX$185,4,false))+VLOOKUP(AV30,$AU$191:$AY$205,5,false),0) -> 4205 | BL30: =rounddown(($AX30*VLOOKUP($B$13,$AU$177:$AY$185,5,false))+VLOOKUP(AV30,$AU$191:$AY$205,5,false),0) -> 4339 | BM30: =rounddown(($AX30*VLOOKUP($B$13,$AU$177:$AZ$185,6,false))+VLOOKUP(AV30,$AU$191:$AY$205,5,false),0) -> 4407 | BN30: =rounddown(($AX30*VLOOKUP($B$13,$AU$177:$BE$185,7,false))+VLOOKUP(AV30,$AU$191:$AY$205,5,false),0) -> 4407 | BO30: =rounddown(($AX30*VLOOKUP($B$13,$AU$177:$BE$185,8,false))+VLOOKUP(AV30,$AU$191:$AY$205,5,false),0) -> 4407 | BP30: =rounddown(($AX30*VLOOKUP($B$13,$AU$177:$BE$185,9,false))+VLOOKUP(AV30,$AU$191:$AY$205,5,false),0) -> 4407 | BQ30: =rounddown(($AX30*VLOOKUP($B$13,$AU$177:$BE$185,10,false))+VLOOKUP(AV30,$AU$191:$AY$205,5,false),0) -> 4407 | BR30: =rounddown(($AX30*VLOOKUP($B$13,$AU$177:$BE$185,11,false))+VLOOKUP(AV30,$AU$191:$AY$205,5,false),0) -> 4407
B31: range_start_type | E31: range_start_parameter | I31: range_end_type | L31: range_end_parameter | P31: 対象 | R31: 対象属性 | U31: 対象ロール | AU31: 21 | AV31: 1 | AW31: =Floor( $AW$9+($AW$171-$AW$9) * Pow( (AU31-1) / ($AU$171-1),$AU$189) ,1) -> 2962 | AX31: =Floor( $AX$9+($AX$171-$AX$9) * Pow( (AU31-1) / ($AU$171-1),$AU$189) ,1) -> 3459 | AY31: =VLOOKUP(AV31,$AU$191:$AY$205,4,FALSE)+AW31 -> 3134 | AZ31: =VLOOKUP(AV31,$AU$191:$AY$205,5,FALSE)+AX31 -> 3660 | BA31: =rounddown(($AW31*VLOOKUP($B$13,$AU$177:$AW$185,3,false))+VLOOKUP(AV31,$AU$191:$AY$205,4,false),0) -> 3489 | BB31: =rounddown(($AW31*VLOOKUP($B$13,$AU$177:$AX$185,4,false))+VLOOKUP(AV31,$AU$191:$AY$205,4,false),0) -> 3696 | BC31: =rounddown(($AW31*VLOOKUP($B$13,$AU$177:$AY$185,5,false))+VLOOKUP(AV31,$AU$191:$AY$205,4,false),0) -> 3815 | BD31: =rounddown(($AW31*VLOOKUP($B$13,$AU$177:$AZ$185,6,false))+VLOOKUP(AV31,$AU$191:$AY$205,4,false),0) -> 3874 | BE31: =rounddown(($AW31*VLOOKUP($B$13,$AU$177:$BE$185,7,false))+VLOOKUP(AV31,$AU$191:$AY$205,4,false),0) -> 3874 | BF31: =rounddown(($AW31*VLOOKUP($B$13,$AU$177:$BE$185,8,false))+VLOOKUP(AV31,$AU$191:$AY$205,4,false),0) -> 3874 | BG31: =rounddown(($AW31*VLOOKUP($B$13,$AU$177:$BE$185,9,false))+VLOOKUP(AV31,$AU$191:$AY$205,4,false),0) -> 3874 | BH31: =rounddown(($AW31*VLOOKUP($B$13,$AU$177:$BE$185,10,false))+VLOOKUP(AV31,$AU$191:$AY$205,4,false),0) -> 3874 | BI31: =rounddown(($AW31*VLOOKUP($B$13,$AU$177:$BE$185,11,false))+VLOOKUP(AV31,$AU$191:$AY$205,4,false),0) -> 3874 | BJ31: =rounddown(($AX31*VLOOKUP($B$13,$AU$177:$AW$185,3,false))+VLOOKUP(AV31,$AU$191:$AY$205,5,false),0) -> 4075 | BK31: =rounddown(($AX31*VLOOKUP($B$13,$AU$177:$AX$185,4,false))+VLOOKUP(AV31,$AU$191:$AY$205,5,false),0) -> 4317 | BL31: =rounddown(($AX31*VLOOKUP($B$13,$AU$177:$AY$185,5,false))+VLOOKUP(AV31,$AU$191:$AY$205,5,false),0) -> 4455 | BM31: =rounddown(($AX31*VLOOKUP($B$13,$AU$177:$AZ$185,6,false))+VLOOKUP(AV31,$AU$191:$AY$205,5,false),0) -> 4524 | BN31: =rounddown(($AX31*VLOOKUP($B$13,$AU$177:$BE$185,7,false))+VLOOKUP(AV31,$AU$191:$AY$205,5,false),0) -> 4524 | BO31: =rounddown(($AX31*VLOOKUP($B$13,$AU$177:$BE$185,8,false))+VLOOKUP(AV31,$AU$191:$AY$205,5,false),0) -> 4524 | BP31: =rounddown(($AX31*VLOOKUP($B$13,$AU$177:$BE$185,9,false))+VLOOKUP(AV31,$AU$191:$AY$205,5,false),0) -> 4524 | BQ31: =rounddown(($AX31*VLOOKUP($B$13,$AU$177:$BE$185,10,false))+VLOOKUP(AV31,$AU$191:$AY$205,5,false),0) -> 4524 | BR31: =rounddown(($AX31*VLOOKUP($B$13,$AU$177:$BE$185,11,false))+VLOOKUP(AV31,$AU$191:$AY$205,5,false),0) -> 4524
B32: Distance | E32: 0 | I32: Distance | L32: =IFERROR(__xludf.DUMMYFUNCTION("IFERROR( INDEX( IMPORTRANGE(""https://docs.google.com/spreadsheets/d/1tAaChe98Zh7vhMfGMK5Y4_ijmNb40fr519GtdZkkDUY/edit#gid=1369914306"", ""キャラ基礎数値!CF:CF""), MATCH(B11, IMPORTRANGE(""https://docs.google.com/spreadsheets/d/1tAaChe98Zh7vhMfGMK5Y4_i"&"jmNb40fr519GtdZkkDUY/edit#gid=1369914306"", ""キャラ基礎数値!C:C""), 0) ), ""該当なし"" ) "),0.4) -> 0.4 | P32: 敵 | R32: All | U32: All | AU32: 22 | AV32: 1 | AW32: =Floor( $AW$9+($AW$171-$AW$9) * Pow( (AU32-1) / ($AU$171-1),$AU$189) ,1) -> 3043 | AX32: =Floor( $AX$9+($AX$171-$AX$9) * Pow( (AU32-1) / ($AU$171-1),$AU$189) ,1) -> 3554 | AY32: =VLOOKUP(AV32,$AU$191:$AY$205,4,FALSE)+AW32 -> 3215 | AZ32: =VLOOKUP(AV32,$AU$191:$AY$205,5,FALSE)+AX32 -> 3755 | BA32: =rounddown(($AW32*VLOOKUP($B$13,$AU$177:$AW$185,3,false))+VLOOKUP(AV32,$AU$191:$AY$205,4,false),0) -> 3580 | BB32: =rounddown(($AW32*VLOOKUP($B$13,$AU$177:$AX$185,4,false))+VLOOKUP(AV32,$AU$191:$AY$205,4,false),0) -> 3793 | BC32: =rounddown(($AW32*VLOOKUP($B$13,$AU$177:$AY$185,5,false))+VLOOKUP(AV32,$AU$191:$AY$205,4,false),0) -> 3914 | BD32: =rounddown(($AW32*VLOOKUP($B$13,$AU$177:$AZ$185,6,false))+VLOOKUP(AV32,$AU$191:$AY$205,4,false),0) -> 3975 | BE32: =rounddown(($AW32*VLOOKUP($B$13,$AU$177:$BE$185,7,false))+VLOOKUP(AV32,$AU$191:$AY$205,4,false),0) -> 3975 | BF32: =rounddown(($AW32*VLOOKUP($B$13,$AU$177:$BE$185,8,false))+VLOOKUP(AV32,$AU$191:$AY$205,4,false),0) -> 3975 | BG32: =rounddown(($AW32*VLOOKUP($B$13,$AU$177:$BE$185,9,false))+VLOOKUP(AV32,$AU$191:$AY$205,4,false),0) -> 3975 | BH32: =rounddown(($AW32*VLOOKUP($B$13,$AU$177:$BE$185,10,false))+VLOOKUP(AV32,$AU$191:$AY$205,4,false),0) -> 3975 | BI32: =rounddown(($AW32*VLOOKUP($B$13,$AU$177:$BE$185,11,false))+VLOOKUP(AV32,$AU$191:$AY$205,4,false),0) -> 3975 | BJ32: =rounddown(($AX32*VLOOKUP($B$13,$AU$177:$AW$185,3,false))+VLOOKUP(AV32,$AU$191:$AY$205,5,false),0) -> 4181 | BK32: =rounddown(($AX32*VLOOKUP($B$13,$AU$177:$AX$185,4,false))+VLOOKUP(AV32,$AU$191:$AY$205,5,false),0) -> 4430 | BL32: =rounddown(($AX32*VLOOKUP($B$13,$AU$177:$AY$185,5,false))+VLOOKUP(AV32,$AU$191:$AY$205,5,false),0) -> 4572 | BM32: =rounddown(($AX32*VLOOKUP($B$13,$AU$177:$AZ$185,6,false))+VLOOKUP(AV32,$AU$191:$AY$205,5,false),0) -> 4643 | BN32: =rounddown(($AX32*VLOOKUP($B$13,$AU$177:$BE$185,7,false))+VLOOKUP(AV32,$AU$191:$AY$205,5,false),0) -> 4643 | BO32: =rounddown(($AX32*VLOOKUP($B$13,$AU$177:$BE$185,8,false))+VLOOKUP(AV32,$AU$191:$AY$205,5,false),0) -> 4643 | BP32: =rounddown(($AX32*VLOOKUP($B$13,$AU$177:$BE$185,9,false))+VLOOKUP(AV32,$AU$191:$AY$205,5,false),0) -> 4643 | BQ32: =rounddown(($AX32*VLOOKUP($B$13,$AU$177:$BE$185,10,false))+VLOOKUP(AV32,$AU$191:$AY$205,5,false),0) -> 4643 | BR32: =rounddown(($AX32*VLOOKUP($B$13,$AU$177:$BE$185,11,false))+VLOOKUP(AV32,$AU$191:$AY$205,5,false),0) -> 4643
B33: → | C33: 攻撃発生Fと攻撃ヒットFは各数値に *50。その他攻撃CDFは/50。 | AU33: 23 | AV33: 1 | AW33: =Floor( $AW$9+($AW$171-$AW$9) * Pow( (AU33-1) / ($AU$171-1),$AU$189) ,1) -> 3125 | AX33: =Floor( $AX$9+($AX$171-$AX$9) * Pow( (AU33-1) / ($AU$171-1),$AU$189) ,1) -> 3649 | AY33: =VLOOKUP(AV33,$AU$191:$AY$205,4,FALSE)+AW33 -> 3297 | AZ33: =VLOOKUP(AV33,$AU$191:$AY$205,5,FALSE)+AX33 -> 3850 | BA33: =rounddown(($AW33*VLOOKUP($B$13,$AU$177:$AW$185,3,false))+VLOOKUP(AV33,$AU$191:$AY$205,4,false),0) -> 3672 | BB33: =rounddown(($AW33*VLOOKUP($B$13,$AU$177:$AX$185,4,false))+VLOOKUP(AV33,$AU$191:$AY$205,4,false),0) -> 3890 | BC33: =rounddown(($AW33*VLOOKUP($B$13,$AU$177:$AY$185,5,false))+VLOOKUP(AV33,$AU$191:$AY$205,4,false),0) -> 4015 | BD33: =rounddown(($AW33*VLOOKUP($B$13,$AU$177:$AZ$185,6,false))+VLOOKUP(AV33,$AU$191:$AY$205,4,false),0) -> 4078 | BE33: =rounddown(($AW33*VLOOKUP($B$13,$AU$177:$BE$185,7,false))+VLOOKUP(AV33,$AU$191:$AY$205,4,false),0) -> 4078 | BF33: =rounddown(($AW33*VLOOKUP($B$13,$AU$177:$BE$185,8,false))+VLOOKUP(AV33,$AU$191:$AY$205,4,false),0) -> 4078 | BG33: =rounddown(($AW33*VLOOKUP($B$13,$AU$177:$BE$185,9,false))+VLOOKUP(AV33,$AU$191:$AY$205,4,false),0) -> 4078 | BH33: =rounddown(($AW33*VLOOKUP($B$13,$AU$177:$BE$185,10,false))+VLOOKUP(AV33,$AU$191:$AY$205,4,false),0) -> 4078 | BI33: =rounddown(($AW33*VLOOKUP($B$13,$AU$177:$BE$185,11,false))+VLOOKUP(AV33,$AU$191:$AY$205,4,false),0) -> 4078 | BJ33: =rounddown(($AX33*VLOOKUP($B$13,$AU$177:$AW$185,3,false))+VLOOKUP(AV33,$AU$191:$AY$205,5,false),0) -> 4287 | BK33: =rounddown(($AX33*VLOOKUP($B$13,$AU$177:$AX$185,4,false))+VLOOKUP(AV33,$AU$191:$AY$205,5,false),0) -> 4543 | BL33: =rounddown(($AX33*VLOOKUP($B$13,$AU$177:$AY$185,5,false))+VLOOKUP(AV33,$AU$191:$AY$205,5,false),0) -> 4689 | BM33: =rounddown(($AX33*VLOOKUP($B$13,$AU$177:$AZ$185,6,false))+VLOOKUP(AV33,$AU$191:$AY$205,5,false),0) -> 4762 | BN33: =rounddown(($AX33*VLOOKUP($B$13,$AU$177:$BE$185,7,false))+VLOOKUP(AV33,$AU$191:$AY$205,5,false),0) -> 4762 | BO33: =rounddown(($AX33*VLOOKUP($B$13,$AU$177:$BE$185,8,false))+VLOOKUP(AV33,$AU$191:$AY$205,5,false),0) -> 4762 | BP33: =rounddown(($AX33*VLOOKUP($B$13,$AU$177:$BE$185,9,false))+VLOOKUP(AV33,$AU$191:$AY$205,5,false),0) -> 4762 | BQ33: =rounddown(($AX33*VLOOKUP($B$13,$AU$177:$BE$185,10,false))+VLOOKUP(AV33,$AU$191:$AY$205,5,false),0) -> 4762 | BR33: =rounddown(($AX33*VLOOKUP($B$13,$AU$177:$BE$185,11,false))+VLOOKUP(AV33,$AU$191:$AY$205,5,false),0) -> 4762
B34: 必殺ワザステータス | AP34: ※数式参照用 | AU34: 24 | AV34: 1 | AW34: =Floor( $AW$9+($AW$171-$AW$9) * Pow( (AU34-1) / ($AU$171-1),$AU$189) ,1) -> 3207 | AX34: =Floor( $AX$9+($AX$171-$AX$9) * Pow( (AU34-1) / ($AU$171-1),$AU$189) ,1) -> 3745 | AY34: =VLOOKUP(AV34,$AU$191:$AY$205,4,FALSE)+AW34 -> 3379 | AZ34: =VLOOKUP(AV34,$AU$191:$AY$205,5,FALSE)+AX34 -> 3946 | BA34: =rounddown(($AW34*VLOOKUP($B$13,$AU$177:$AW$185,3,false))+VLOOKUP(AV34,$AU$191:$AY$205,4,false),0) -> 3763 | BB34: =rounddown(($AW34*VLOOKUP($B$13,$AU$177:$AX$185,4,false))+VLOOKUP(AV34,$AU$191:$AY$205,4,false),0) -> 3988 | BC34: =rounddown(($AW34*VLOOKUP($B$13,$AU$177:$AY$185,5,false))+VLOOKUP(AV34,$AU$191:$AY$205,4,false),0) -> 4116 | BD34: =rounddown(($AW34*VLOOKUP($B$13,$AU$177:$AZ$185,6,false))+VLOOKUP(AV34,$AU$191:$AY$205,4,false),0) -> 4180 | BE34: =rounddown(($AW34*VLOOKUP($B$13,$AU$177:$BE$185,7,false))+VLOOKUP(AV34,$AU$191:$AY$205,4,false),0) -> 4180 | BF34: =rounddown(($AW34*VLOOKUP($B$13,$AU$177:$BE$185,8,false))+VLOOKUP(AV34,$AU$191:$AY$205,4,false),0) -> 4180 | BG34: =rounddown(($AW34*VLOOKUP($B$13,$AU$177:$BE$185,9,false))+VLOOKUP(AV34,$AU$191:$AY$205,4,false),0) -> 4180 | BH34: =rounddown(($AW34*VLOOKUP($B$13,$AU$177:$BE$185,10,false))+VLOOKUP(AV34,$AU$191:$AY$205,4,false),0) -> 4180 | BI34: =rounddown(($AW34*VLOOKUP($B$13,$AU$177:$BE$185,11,false))+VLOOKUP(AV34,$AU$191:$AY$205,4,false),0) -> 4180 | BJ34: =rounddown(($AX34*VLOOKUP($B$13,$AU$177:$AW$185,3,false))+VLOOKUP(AV34,$AU$191:$AY$205,5,false),0) -> 4395 | BK34: =rounddown(($AX34*VLOOKUP($B$13,$AU$177:$AX$185,4,false))+VLOOKUP(AV34,$AU$191:$AY$205,5,false),0) -> 4657 | BL34: =rounddown(($AX34*VLOOKUP($B$13,$AU$177:$AY$185,5,false))+VLOOKUP(AV34,$AU$191:$AY$205,5,false),0) -> 4807 | BM34: =rounddown(($AX34*VLOOKUP($B$13,$AU$177:$AZ$185,6,false))+VLOOKUP(AV34,$AU$191:$AY$205,5,false),0) -> 4882 | BN34: =rounddown(($AX34*VLOOKUP($B$13,$AU$177:$BE$185,7,false))+VLOOKUP(AV34,$AU$191:$AY$205,5,false),0) -> 4882 | BO34: =rounddown(($AX34*VLOOKUP($B$13,$AU$177:$BE$185,8,false))+VLOOKUP(AV34,$AU$191:$AY$205,5,false),0) -> 4882 | BP34: =rounddown(($AX34*VLOOKUP($B$13,$AU$177:$BE$185,9,false))+VLOOKUP(AV34,$AU$191:$AY$205,5,false),0) -> 4882 | BQ34: =rounddown(($AX34*VLOOKUP($B$13,$AU$177:$BE$185,10,false))+VLOOKUP(AV34,$AU$191:$AY$205,5,false),0) -> 4882 | BR34: =rounddown(($AX34*VLOOKUP($B$13,$AU$177:$BE$185,11,false))+VLOOKUP(AV34,$AU$191:$AY$205,5,false),0) -> 4882
B35: 必殺攻撃_ オノマトペ | E35: 必殺攻撃F | H35: 必殺攻撃ヒットF | L35: 初回必殺CDF | O35: 2回目以降必殺CDF | R35: 攻撃距離 | X35: 射程 | Z35: 攻撃範囲 | AC35: 攻撃倍率 | AP35: バフ・デバフ効果型 | AU35: 25 | AV35: 1 | AW35: =Floor( $AW$9+($AW$171-$AW$9) * Pow( (AU35-1) / ($AU$171-1),$AU$189) ,1) -> 3289 | AX35: =Floor( $AX$9+($AX$171-$AX$9) * Pow( (AU35-1) / ($AU$171-1),$AU$189) ,1) -> 3841 | AY35: =VLOOKUP(AV35,$AU$191:$AY$205,4,FALSE)+AW35 -> 3461 | AZ35: =VLOOKUP(AV35,$AU$191:$AY$205,5,FALSE)+AX35 -> 4042 | BA35: =rounddown(($AW35*VLOOKUP($B$13,$AU$177:$AW$185,3,false))+VLOOKUP(AV35,$AU$191:$AY$205,4,false),0) -> 3855 | BB35: =rounddown(($AW35*VLOOKUP($B$13,$AU$177:$AX$185,4,false))+VLOOKUP(AV35,$AU$191:$AY$205,4,false),0) -> 4085 | BC35: =rounddown(($AW35*VLOOKUP($B$13,$AU$177:$AY$185,5,false))+VLOOKUP(AV35,$AU$191:$AY$205,4,false),0) -> 4217 | BD35: =rounddown(($AW35*VLOOKUP($B$13,$AU$177:$AZ$185,6,false))+VLOOKUP(AV35,$AU$191:$AY$205,4,false),0) -> 4283 | BE35: =rounddown(($AW35*VLOOKUP($B$13,$AU$177:$BE$185,7,false))+VLOOKUP(AV35,$AU$191:$AY$205,4,false),0) -> 4283 | BF35: =rounddown(($AW35*VLOOKUP($B$13,$AU$177:$BE$185,8,false))+VLOOKUP(AV35,$AU$191:$AY$205,4,false),0) -> 4283 | BG35: =rounddown(($AW35*VLOOKUP($B$13,$AU$177:$BE$185,9,false))+VLOOKUP(AV35,$AU$191:$AY$205,4,false),0) -> 4283 | BH35: =rounddown(($AW35*VLOOKUP($B$13,$AU$177:$BE$185,10,false))+VLOOKUP(AV35,$AU$191:$AY$205,4,false),0) -> 4283 | BI35: =rounddown(($AW35*VLOOKUP($B$13,$AU$177:$BE$185,11,false))+VLOOKUP(AV35,$AU$191:$AY$205,4,false),0) -> 4283 | BJ35: =rounddown(($AX35*VLOOKUP($B$13,$AU$177:$AW$185,3,false))+VLOOKUP(AV35,$AU$191:$AY$205,5,false),0) -> 4502 | BK35: =rounddown(($AX35*VLOOKUP($B$13,$AU$177:$AX$185,4,false))+VLOOKUP(AV35,$AU$191:$AY$205,5,false),0) -> 4771 | BL35: =rounddown(($AX35*VLOOKUP($B$13,$AU$177:$AY$185,5,false))+VLOOKUP(AV35,$AU$191:$AY$205,5,false),0) -> 4925 | BM35: =rounddown(($AX35*VLOOKUP($B$13,$AU$177:$AZ$185,6,false))+VLOOKUP(AV35,$AU$191:$AY$205,5,false),0) -> 5002 | BN35: =rounddown(($AX35*VLOOKUP($B$13,$AU$177:$BE$185,7,false))+VLOOKUP(AV35,$AU$191:$AY$205,5,false),0) -> 5002 | BO35: =rounddown(($AX35*VLOOKUP($B$13,$AU$177:$BE$185,8,false))+VLOOKUP(AV35,$AU$191:$AY$205,5,false),0) -> 5002 | BP35: =rounddown(($AX35*VLOOKUP($B$13,$AU$177:$BE$185,9,false))+VLOOKUP(AV35,$AU$191:$AY$205,5,false),0) -> 5002 | BQ35: =rounddown(($AX35*VLOOKUP($B$13,$AU$177:$BE$185,10,false))+VLOOKUP(AV35,$AU$191:$AY$205,5,false),0) -> 5002 | BR35: =rounddown(($AX35*VLOOKUP($B$13,$AU$177:$BE$185,11,false))+VLOOKUP(AV35,$AU$191:$AY$205,5,false),0) -> 5002
B36: =IFERROR(__xludf.DUMMYFUNCTION("IFERROR( INDEX( IMPORTRANGE(""https://docs.google.com/spreadsheets/d/1oJmkDK37Qizzdaxn4KCwh1BMwdNWuHCx3AGH8BC9yu0/edit?gid=781951868#gid=781951868"", ""キャラ!O:O""), MATCH(B11, IMPORTRANGE(""https://docs.google.com/spreadsheets/d/1oJmkDK37Qizzdaxn"&"4KCwh1BMwdNWuHCx3AGH8BC9yu0/edit?gid=781951868#gid=781951868"", ""キャラ!D:D""), 0) ), ""該当なし"" ) "),"zangeki_1") -> zangeki_1 | E36: =IFERROR(__xludf.DUMMYFUNCTION("IFERROR( INDEX( IMPORTRANGE(""https://docs.google.com/spreadsheets/d/1oJmkDK37Qizzdaxn4KCwh1BMwdNWuHCx3AGH8BC9yu0/edit?gid=781951868#gid=781951868"", ""キャラ!S:S""), MATCH(B11, IMPORTRANGE(""https://docs.google.com/spreadsheets/d/1oJmkDK37Qizzdaxn"&"4KCwh1BMwdNWuHCx3AGH8BC9yu0/edit?gid=781951868#gid=781951868"", ""キャラ!D:D""), 0) ), ""該当なし"" ) "),"2.50") -> 2.50 | H36: =IFERROR(__xludf.DUMMYFUNCTION("IFERROR( INDEX( IMPORTRANGE(""https://docs.google.com/spreadsheets/d/1oJmkDK37Qizzdaxn4KCwh1BMwdNWuHCx3AGH8BC9yu0/edit?gid=781951868#gid=781951868"", ""キャラ!T:T""), MATCH(B11, IMPORTRANGE(""https://docs.google.com/spreadsheets/d/1oJmkDK37Qizzdaxn"&"4KCwh1BMwdNWuHCx3AGH8BC9yu0/edit?gid=781951868#gid=781951868"", ""キャラ!D:D""), 0) ), ""該当なし"" ) "),"1.20") -> 1.20 | L36: =IFERROR(__xludf.DUMMYFUNCTION("IFERROR( INDEX( IMPORTRANGE(""https://docs.google.com/spreadsheets/d/1tAaChe98Zh7vhMfGMK5Y4_ijmNb40fr519GtdZkkDUY/edit#gid=1369914306"", ""キャラ基礎数値!Y:Y""), MATCH(B11, IMPORTRANGE(""https://docs.google.com/spreadsheets/d/1tAaChe98Zh7vhMfGMK5Y4_ijm"&"Nb40fr519GtdZkkDUY/edit#gid=1369914306"", ""キャラ基礎数値!C:C""), 0) ), ""該当なし"" ) "),260.0) -> 260 | O36: =IFERROR(__xludf.DUMMYFUNCTION("IFERROR( INDEX( IMPORTRANGE(""https://docs.google.com/spreadsheets/d/1tAaChe98Zh7vhMfGMK5Y4_ijmNb40fr519GtdZkkDUY/edit#gid=1369914306"", ""キャラ基礎数値!AD:AD""), MATCH(B11, IMPORTRANGE(""https://docs.google.com/spreadsheets/d/1tAaChe98Zh7vhMfGMK5Y4_i"&"jmNb40fr519GtdZkkDUY/edit#gid=1369914306"", ""キャラ基礎数値!C:C""), 0) ), ""該当なし"" ) "),615.0) -> 615 | R36: =IFERROR(__xludf.DUMMYFUNCTION("IFERROR( INDEX( IMPORTRANGE(""https://docs.google.com/spreadsheets/d/1tAaChe98Zh7vhMfGMK5Y4_ijmNb40fr519GtdZkkDUY/edit#gid=1369914306"", ""キャラ基礎数値!CG:CG""), MATCH(B11, IMPORTRANGE(""https://docs.google.com/spreadsheets/d/1tAaChe98Zh7vhMfGMK5Y4_i"&"jmNb40fr519GtdZkkDUY/edit#gid=1369914306"", ""キャラ基礎数値!C:C""), 0) ), ""該当なし"" ) "),"中距離") -> 中距離 | X36: =IFERROR(__xludf.DUMMYFUNCTION("IFERROR( INDEX( IMPORTRANGE(""https://docs.google.com/spreadsheets/d/1tAaChe98Zh7vhMfGMK5Y4_ijmNb40fr519GtdZkkDUY/edit#gid=1369914306"", ""キャラ基礎数値!CJ:CJ""), MATCH(B11, IMPORTRANGE(""https://docs.google.com/spreadsheets/d/1tAaChe98Zh7vhMfGMK5Y4_i"&"jmNb40fr519GtdZkkDUY/edit#gid=1369914306"", ""キャラ基礎数値!C:C""), 0) ), ""該当なし"" ) "),0.3) -> 0.3 | Z36: =IFERROR(__xludf.DUMMYFUNCTION("IFERROR( INDEX( IMPORTRANGE(""https://docs.google.com/spreadsheets/d/1tAaChe98Zh7vhMfGMK5Y4_ijmNb40fr519GtdZkkDUY/edit#gid=1369914306"", ""キャラ基礎数値!CH:CH""), MATCH(B11, IMPORTRANGE(""https://docs.google.com/spreadsheets/d/1tAaChe98Zh7vhMfGMK5Y4_i"&"jmNb40fr519GtdZkkDUY/edit#gid=1369914306"", ""キャラ基礎数値!C:C""), 0) ), ""該当なし"" ) "),"単体") -> 単体 | AC36: =IFERROR(__xludf.DUMMYFUNCTION("IFERROR( INDEX( IMPORTRANGE(""https://docs.google.com/spreadsheets/d/1tAaChe98Zh7vhMfGMK5Y4_ijmNb40fr519GtdZkkDUY/edit#gid=1369914306"", ""キャラ基礎数値!CI:CI""), MATCH(B11, IMPORTRANGE(""https://docs.google.com/spreadsheets/d/1tAaChe98Zh7vhMfGMK5Y4_i"&"jmNb40fr519GtdZkkDUY/edit#gid=1369914306"", ""キャラ基礎数値!C:C""), 0) ), ""該当なし"" ) "),1.0) -> 1 | AP36: =IFERROR(__xludf.DUMMYFUNCTION("IFERROR( INDEX( IMPORTRANGE(""https://docs.google.com/spreadsheets/d/1tAaChe98Zh7vhMfGMK5Y4_ijmNb40fr519GtdZkkDUY/edit#gid=1369914306"", ""キャラ基礎数値!CR:CR""), MATCH(B11, IMPORTRANGE(""https://docs.google.com/spreadsheets/d/1tAaChe98Zh7vhMfGMK5Y4_i"&"jmNb40fr519GtdZkkDUY/edit#gid=1369914306"", ""キャラ基礎数値!C:C""), 0) ), ""該当なし"" ) "),"-") -> - | AU36: 26 | AV36: 1 | AW36: =Floor( $AW$9+($AW$171-$AW$9) * Pow( (AU36-1) / ($AU$171-1),$AU$189) ,1) -> 3372 | AX36: =Floor( $AX$9+($AX$171-$AX$9) * Pow( (AU36-1) / ($AU$171-1),$AU$189) ,1) -> 3937 | AY36: =VLOOKUP(AV36,$AU$191:$AY$205,4,FALSE)+AW36 -> 3544 | AZ36: =VLOOKUP(AV36,$AU$191:$AY$205,5,FALSE)+AX36 -> 4138 | BA36: =rounddown(($AW36*VLOOKUP($B$13,$AU$177:$AW$185,3,false))+VLOOKUP(AV36,$AU$191:$AY$205,4,false),0) -> 3948 | BB36: =rounddown(($AW36*VLOOKUP($B$13,$AU$177:$AX$185,4,false))+VLOOKUP(AV36,$AU$191:$AY$205,4,false),0) -> 4184 | BC36: =rounddown(($AW36*VLOOKUP($B$13,$AU$177:$AY$185,5,false))+VLOOKUP(AV36,$AU$191:$AY$205,4,false),0) -> 4319 | BD36: =rounddown(($AW36*VLOOKUP($B$13,$AU$177:$AZ$185,6,false))+VLOOKUP(AV36,$AU$191:$AY$205,4,false),0) -> 4387 | BE36: =rounddown(($AW36*VLOOKUP($B$13,$AU$177:$BE$185,7,false))+VLOOKUP(AV36,$AU$191:$AY$205,4,false),0) -> 4387 | BF36: =rounddown(($AW36*VLOOKUP($B$13,$AU$177:$BE$185,8,false))+VLOOKUP(AV36,$AU$191:$AY$205,4,false),0) -> 4387 | BG36: =rounddown(($AW36*VLOOKUP($B$13,$AU$177:$BE$185,9,false))+VLOOKUP(AV36,$AU$191:$AY$205,4,false),0) -> 4387 | BH36: =rounddown(($AW36*VLOOKUP($B$13,$AU$177:$BE$185,10,false))+VLOOKUP(AV36,$AU$191:$AY$205,4,false),0) -> 4387 | BI36: =rounddown(($AW36*VLOOKUP($B$13,$AU$177:$BE$185,11,false))+VLOOKUP(AV36,$AU$191:$AY$205,4,false),0) -> 4387 | BJ36: =rounddown(($AX36*VLOOKUP($B$13,$AU$177:$AW$185,3,false))+VLOOKUP(AV36,$AU$191:$AY$205,5,false),0) -> 4610 | BK36: =rounddown(($AX36*VLOOKUP($B$13,$AU$177:$AX$185,4,false))+VLOOKUP(AV36,$AU$191:$AY$205,5,false),0) -> 4886 | BL36: =rounddown(($AX36*VLOOKUP($B$13,$AU$177:$AY$185,5,false))+VLOOKUP(AV36,$AU$191:$AY$205,5,false),0) -> 5043 | BM36: =rounddown(($AX36*VLOOKUP($B$13,$AU$177:$AZ$185,6,false))+VLOOKUP(AV36,$AU$191:$AY$205,5,false),0) -> 5122 | BN36: =rounddown(($AX36*VLOOKUP($B$13,$AU$177:$BE$185,7,false))+VLOOKUP(AV36,$AU$191:$AY$205,5,false),0) -> 5122 | BO36: =rounddown(($AX36*VLOOKUP($B$13,$AU$177:$BE$185,8,false))+VLOOKUP(AV36,$AU$191:$AY$205,5,false),0) -> 5122 | BP36: =rounddown(($AX36*VLOOKUP($B$13,$AU$177:$BE$185,9,false))+VLOOKUP(AV36,$AU$191:$AY$205,5,false),0) -> 5122 | BQ36: =rounddown(($AX36*VLOOKUP($B$13,$AU$177:$BE$185,10,false))+VLOOKUP(AV36,$AU$191:$AY$205,5,false),0) -> 5122 | BR36: =rounddown(($AX36*VLOOKUP($B$13,$AU$177:$BE$185,11,false))+VLOOKUP(AV36,$AU$191:$AY$205,5,false),0) -> 5122
B37: range_start_type | E37: range_start_parameter | I37: range_end_type | L37: range_end_parameter | P37: 対象 | R37: 対象属性 | U37: 対象ロール | W37: バフ・デバフ効果型 | AC37: ※攻撃系以外の必殺ワザは攻撃倍率「無」 | AU37: 27 | AV37: 1 | AW37: =Floor( $AW$9+($AW$171-$AW$9) * Pow( (AU37-1) / ($AU$171-1),$AU$189) ,1) -> 3455 | AX37: =Floor( $AX$9+($AX$171-$AX$9) * Pow( (AU37-1) / ($AU$171-1),$AU$189) ,1) -> 4034 | AY37: =VLOOKUP(AV37,$AU$191:$AY$205,4,FALSE)+AW37 -> 3627 | AZ37: =VLOOKUP(AV37,$AU$191:$AY$205,5,FALSE)+AX37 -> 4235 | BA37: =rounddown(($AW37*VLOOKUP($B$13,$AU$177:$AW$185,3,false))+VLOOKUP(AV37,$AU$191:$AY$205,4,false),0) -> 4041 | BB37: =rounddown(($AW37*VLOOKUP($B$13,$AU$177:$AX$185,4,false))+VLOOKUP(AV37,$AU$191:$AY$205,4,false),0) -> 4283 | BC37: =rounddown(($AW37*VLOOKUP($B$13,$AU$177:$AY$185,5,false))+VLOOKUP(AV37,$AU$191:$AY$205,4,false),0) -> 4421 | BD37: =rounddown(($AW37*VLOOKUP($B$13,$AU$177:$AZ$185,6,false))+VLOOKUP(AV37,$AU$191:$AY$205,4,false),0) -> 4490 | BE37: =rounddown(($AW37*VLOOKUP($B$13,$AU$177:$BE$185,7,false))+VLOOKUP(AV37,$AU$191:$AY$205,4,false),0) -> 4490 | BF37: =rounddown(($AW37*VLOOKUP($B$13,$AU$177:$BE$185,8,false))+VLOOKUP(AV37,$AU$191:$AY$205,4,false),0) -> 4490 | BG37: =rounddown(($AW37*VLOOKUP($B$13,$AU$177:$BE$185,9,false))+VLOOKUP(AV37,$AU$191:$AY$205,4,false),0) -> 4490 | BH37: =rounddown(($AW37*VLOOKUP($B$13,$AU$177:$BE$185,10,false))+VLOOKUP(AV37,$AU$191:$AY$205,4,false),0) -> 4490 | BI37: =rounddown(($AW37*VLOOKUP($B$13,$AU$177:$BE$185,11,false))+VLOOKUP(AV37,$AU$191:$AY$205,4,false),0) -> 4490 | BJ37: =rounddown(($AX37*VLOOKUP($B$13,$AU$177:$AW$185,3,false))+VLOOKUP(AV37,$AU$191:$AY$205,5,false),0) -> 4719 | BK37: =rounddown(($AX37*VLOOKUP($B$13,$AU$177:$AX$185,4,false))+VLOOKUP(AV37,$AU$191:$AY$205,5,false),0) -> 5001 | BL37: =rounddown(($AX37*VLOOKUP($B$13,$AU$177:$AY$185,5,false))+VLOOKUP(AV37,$AU$191:$AY$205,5,false),0) -> 5162 | BM37: =rounddown(($AX37*VLOOKUP($B$13,$AU$177:$AZ$185,6,false))+VLOOKUP(AV37,$AU$191:$AY$205,5,false),0) -> 5243 | BN37: =rounddown(($AX37*VLOOKUP($B$13,$AU$177:$BE$185,7,false))+VLOOKUP(AV37,$AU$191:$AY$205,5,false),0) -> 5243 | BO37: =rounddown(($AX37*VLOOKUP($B$13,$AU$177:$BE$185,8,false))+VLOOKUP(AV37,$AU$191:$AY$205,5,false),0) -> 5243 | BP37: =rounddown(($AX37*VLOOKUP($B$13,$AU$177:$BE$185,9,false))+VLOOKUP(AV37,$AU$191:$AY$205,5,false),0) -> 5243 | BQ37: =rounddown(($AX37*VLOOKUP($B$13,$AU$177:$BE$185,10,false))+VLOOKUP(AV37,$AU$191:$AY$205,5,false),0) -> 5243 | BR37: =rounddown(($AX37*VLOOKUP($B$13,$AU$177:$BE$185,11,false))+VLOOKUP(AV37,$AU$191:$AY$205,5,false),0) -> 5243
B38: =IFERROR(__xludf.DUMMYFUNCTION("IF(REGEXMATCH(Z36, ""全体""), ""Deck"", IF(REGEXMATCH(Z36, ""コマ""), ""Koma"", ""Distance"")) "),"Distance") -> Distance | E38: 0 | I38: =IFERROR(__xludf.DUMMYFUNCTION("IF(REGEXMATCH(Z36, ""全体""), ""Deck"", IF(REGEXMATCH(Z36, ""コマ""), ""Koma"", ""Distance"")) "),"Distance") -> Distance | L38: =IFERROR(__xludf.DUMMYFUNCTION("IFERROR( INDEX( IMPORTRANGE(""https://docs.google.com/spreadsheets/d/1tAaChe98Zh7vhMfGMK5Y4_ijmNb40fr519GtdZkkDUY/edit#gid=1369914306"", ""キャラ基礎数値!CJ:CJ""), MATCH(B11, IMPORTRANGE(""https://docs.google.com/spreadsheets/d/1tAaChe98Zh7vhMfGMK5Y4_i"&"jmNb40fr519GtdZkkDUY/edit#gid=1369914306"", ""キャラ基礎数値!C:C""), 0) ), ""該当なし"" ) "),0.3) -> 0.3 | P38: =IFERROR(__xludf.DUMMYFUNCTION("IFERROR( INDEX( IMPORTRANGE(""https://docs.google.com/spreadsheets/d/1tAaChe98Zh7vhMfGMK5Y4_ijmNb40fr519GtdZkkDUY/edit#gid=1369914306"", ""キャラ基礎数値!CK:CK""), MATCH(B11, IMPORTRANGE(""https://docs.google.com/spreadsheets/d/1tAaChe98Zh7vhMfGMK5Y4_i"&"jmNb40fr519GtdZkkDUY/edit#gid=1369914306"", ""キャラ基礎数値!C:C""), 0) ), ""該当なし"" ) "),"敵") -> 敵 | R38: =IFERROR(__xludf.DUMMYFUNCTION("IFERROR( INDEX( IMPORTRANGE(""https://docs.google.com/spreadsheets/d/1tAaChe98Zh7vhMfGMK5Y4_ijmNb40fr519GtdZkkDUY/edit#gid=1369914306"", ""キャラ基礎数値!CL:CL""), MATCH(B11, IMPORTRANGE(""https://docs.google.com/spreadsheets/d/1tAaChe98Zh7vhMfGMK5Y4_i"&"jmNb40fr519GtdZkkDUY/edit#gid=1369914306"", ""キャラ基礎数値!C:C""), 0) ), ""該当なし"" ) "),"緑") -> 緑 | U38: =IFERROR(__xludf.DUMMYFUNCTION("IFERROR( INDEX( IMPORTRANGE(""https://docs.google.com/spreadsheets/d/1tAaChe98Zh7vhMfGMK5Y4_ijmNb40fr519GtdZkkDUY/edit#gid=1369914306"", ""キャラ基礎数値!CM:CM""), MATCH(B11, IMPORTRANGE(""https://docs.google.com/spreadsheets/d/1tAaChe98Zh7vhMfGMK5Y4_i"&"jmNb40fr519GtdZkkDUY/edit#gid=1369914306"", ""キャラ基礎数値!C:C""), 0) ), ""該当なし"" ) "),"All") -> All | W38: =AP36 -> - | AU38: 28 | AV38: 1 | AW38: =Floor( $AW$9+($AW$171-$AW$9) * Pow( (AU38-1) / ($AU$171-1),$AU$189) ,1) -> 3538 | AX38: =Floor( $AX$9+($AX$171-$AX$9) * Pow( (AU38-1) / ($AU$171-1),$AU$189) ,1) -> 4132 | AY38: =VLOOKUP(AV38,$AU$191:$AY$205,4,FALSE)+AW38 -> 3710 | AZ38: =VLOOKUP(AV38,$AU$191:$AY$205,5,FALSE)+AX38 -> 4333 | BA38: =rounddown(($AW38*VLOOKUP($B$13,$AU$177:$AW$185,3,false))+VLOOKUP(AV38,$AU$191:$AY$205,4,false),0) -> 4134 | BB38: =rounddown(($AW38*VLOOKUP($B$13,$AU$177:$AX$185,4,false))+VLOOKUP(AV38,$AU$191:$AY$205,4,false),0) -> 4382 | BC38: =rounddown(($AW38*VLOOKUP($B$13,$AU$177:$AY$185,5,false))+VLOOKUP(AV38,$AU$191:$AY$205,4,false),0) -> 4523 | BD38: =rounddown(($AW38*VLOOKUP($B$13,$AU$177:$AZ$185,6,false))+VLOOKUP(AV38,$AU$191:$AY$205,4,false),0) -> 4594 | BE38: =rounddown(($AW38*VLOOKUP($B$13,$AU$177:$BE$185,7,false))+VLOOKUP(AV38,$AU$191:$AY$205,4,false),0) -> 4594 | BF38: =rounddown(($AW38*VLOOKUP($B$13,$AU$177:$BE$185,8,false))+VLOOKUP(AV38,$AU$191:$AY$205,4,false),0) -> 4594 | BG38: =rounddown(($AW38*VLOOKUP($B$13,$AU$177:$BE$185,9,false))+VLOOKUP(AV38,$AU$191:$AY$205,4,false),0) -> 4594 | BH38: =rounddown(($AW38*VLOOKUP($B$13,$AU$177:$BE$185,10,false))+VLOOKUP(AV38,$AU$191:$AY$205,4,false),0) -> 4594 | BI38: =rounddown(($AW38*VLOOKUP($B$13,$AU$177:$BE$185,11,false))+VLOOKUP(AV38,$AU$191:$AY$205,4,false),0) -> 4594 | BJ38: =rounddown(($AX38*VLOOKUP($B$13,$AU$177:$AW$185,3,false))+VLOOKUP(AV38,$AU$191:$AY$205,5,false),0) -> 4828 | BK38: =rounddown(($AX38*VLOOKUP($B$13,$AU$177:$AX$185,4,false))+VLOOKUP(AV38,$AU$191:$AY$205,5,false),0) -> 5118 | BL38: =rounddown(($AX38*VLOOKUP($B$13,$AU$177:$AY$185,5,false))+VLOOKUP(AV38,$AU$191:$AY$205,5,false),0) -> 5283 | BM38: =rounddown(($AX38*VLOOKUP($B$13,$AU$177:$AZ$185,6,false))+VLOOKUP(AV38,$AU$191:$AY$205,5,false),0) -> 5366 | BN38: =rounddown(($AX38*VLOOKUP($B$13,$AU$177:$BE$185,7,false))+VLOOKUP(AV38,$AU$191:$AY$205,5,false),0) -> 5366 | BO38: =rounddown(($AX38*VLOOKUP($B$13,$AU$177:$BE$185,8,false))+VLOOKUP(AV38,$AU$191:$AY$205,5,false),0) -> 5366 | BP38: =rounddown(($AX38*VLOOKUP($B$13,$AU$177:$BE$185,9,false))+VLOOKUP(AV38,$AU$191:$AY$205,5,false),0) -> 5366 | BQ38: =rounddown(($AX38*VLOOKUP($B$13,$AU$177:$BE$185,10,false))+VLOOKUP(AV38,$AU$191:$AY$205,5,false),0) -> 5366 | BR38: =rounddown(($AX38*VLOOKUP($B$13,$AU$177:$BE$185,11,false))+VLOOKUP(AV38,$AU$191:$AY$205,5,false),0) -> 5366
B39: → | C39: 攻撃発生Fと攻撃ヒットFは各数値に *50。その他攻撃CDFは/50。 | AU39: 29 | AV39: 1 | AW39: =Floor( $AW$9+($AW$171-$AW$9) * Pow( (AU39-1) / ($AU$171-1),$AU$189) ,1) -> 3622 | AX39: =Floor( $AX$9+($AX$171-$AX$9) * Pow( (AU39-1) / ($AU$171-1),$AU$189) ,1) -> 4229 | AY39: =VLOOKUP(AV39,$AU$191:$AY$205,4,FALSE)+AW39 -> 3794 | AZ39: =VLOOKUP(AV39,$AU$191:$AY$205,5,FALSE)+AX39 -> 4430 | BA39: =rounddown(($AW39*VLOOKUP($B$13,$AU$177:$AW$185,3,false))+VLOOKUP(AV39,$AU$191:$AY$205,4,false),0) -> 4228 | BB39: =rounddown(($AW39*VLOOKUP($B$13,$AU$177:$AX$185,4,false))+VLOOKUP(AV39,$AU$191:$AY$205,4,false),0) -> 4482 | BC39: =rounddown(($AW39*VLOOKUP($B$13,$AU$177:$AY$185,5,false))+VLOOKUP(AV39,$AU$191:$AY$205,4,false),0) -> 4627 | BD39: =rounddown(($AW39*VLOOKUP($B$13,$AU$177:$AZ$185,6,false))+VLOOKUP(AV39,$AU$191:$AY$205,4,false),0) -> 4699 | BE39: =rounddown(($AW39*VLOOKUP($B$13,$AU$177:$BE$185,7,false))+VLOOKUP(AV39,$AU$191:$AY$205,4,false),0) -> 4699 | BF39: =rounddown(($AW39*VLOOKUP($B$13,$AU$177:$BE$185,8,false))+VLOOKUP(AV39,$AU$191:$AY$205,4,false),0) -> 4699 | BG39: =rounddown(($AW39*VLOOKUP($B$13,$AU$177:$BE$185,9,false))+VLOOKUP(AV39,$AU$191:$AY$205,4,false),0) -> 4699 | BH39: =rounddown(($AW39*VLOOKUP($B$13,$AU$177:$BE$185,10,false))+VLOOKUP(AV39,$AU$191:$AY$205,4,false),0) -> 4699 | BI39: =rounddown(($AW39*VLOOKUP($B$13,$AU$177:$BE$185,11,false))+VLOOKUP(AV39,$AU$191:$AY$205,4,false),0) -> 4699 | BJ39: =rounddown(($AX39*VLOOKUP($B$13,$AU$177:$AW$185,3,false))+VLOOKUP(AV39,$AU$191:$AY$205,5,false),0) -> 4937 | BK39: =rounddown(($AX39*VLOOKUP($B$13,$AU$177:$AX$185,4,false))+VLOOKUP(AV39,$AU$191:$AY$205,5,false),0) -> 5233 | BL39: =rounddown(($AX39*VLOOKUP($B$13,$AU$177:$AY$185,5,false))+VLOOKUP(AV39,$AU$191:$AY$205,5,false),0) -> 5402 | BM39: =rounddown(($AX39*VLOOKUP($B$13,$AU$177:$AZ$185,6,false))+VLOOKUP(AV39,$AU$191:$AY$205,5,false),0) -> 5487 | BN39: =rounddown(($AX39*VLOOKUP($B$13,$AU$177:$BE$185,7,false))+VLOOKUP(AV39,$AU$191:$AY$205,5,false),0) -> 5487 | BO39: =rounddown(($AX39*VLOOKUP($B$13,$AU$177:$BE$185,8,false))+VLOOKUP(AV39,$AU$191:$AY$205,5,false),0) -> 5487 | BP39: =rounddown(($AX39*VLOOKUP($B$13,$AU$177:$BE$185,9,false))+VLOOKUP(AV39,$AU$191:$AY$205,5,false),0) -> 5487 | BQ39: =rounddown(($AX39*VLOOKUP($B$13,$AU$177:$BE$185,10,false))+VLOOKUP(AV39,$AU$191:$AY$205,5,false),0) -> 5487 | BR39: =rounddown(($AX39*VLOOKUP($B$13,$AU$177:$BE$185,11,false))+VLOOKUP(AV39,$AU$191:$AY$205,5,false),0) -> 5487
B40: 必殺ワザ詳細 | E40: 必殺ワザ1 | Q40: 必殺ワザ2 | AC40: 必殺ワザ3 | AU40: 30 | AV40: 1 | AW40: =Floor( $AW$9+($AW$171-$AW$9) * Pow( (AU40-1) / ($AU$171-1),$AU$189) ,1) -> 3705 | AX40: =Floor( $AX$9+($AX$171-$AX$9) * Pow( (AU40-1) / ($AU$171-1),$AU$189) ,1) -> 4327 | AY40: =VLOOKUP(AV40,$AU$191:$AY$205,4,FALSE)+AW40 -> 3877 | AZ40: =VLOOKUP(AV40,$AU$191:$AY$205,5,FALSE)+AX40 -> 4528 | BA40: =rounddown(($AW40*VLOOKUP($B$13,$AU$177:$AW$185,3,false))+VLOOKUP(AV40,$AU$191:$AY$205,4,false),0) -> 4321 | BB40: =rounddown(($AW40*VLOOKUP($B$13,$AU$177:$AX$185,4,false))+VLOOKUP(AV40,$AU$191:$AY$205,4,false),0) -> 4580 | BC40: =rounddown(($AW40*VLOOKUP($B$13,$AU$177:$AY$185,5,false))+VLOOKUP(AV40,$AU$191:$AY$205,4,false),0) -> 4729 | BD40: =rounddown(($AW40*VLOOKUP($B$13,$AU$177:$AZ$185,6,false))+VLOOKUP(AV40,$AU$191:$AY$205,4,false),0) -> 4803 | BE40: =rounddown(($AW40*VLOOKUP($B$13,$AU$177:$BE$185,7,false))+VLOOKUP(AV40,$AU$191:$AY$205,4,false),0) -> 4803 | BF40: =rounddown(($AW40*VLOOKUP($B$13,$AU$177:$BE$185,8,false))+VLOOKUP(AV40,$AU$191:$AY$205,4,false),0) -> 4803 | BG40: =rounddown(($AW40*VLOOKUP($B$13,$AU$177:$BE$185,9,false))+VLOOKUP(AV40,$AU$191:$AY$205,4,false),0) -> 4803 | BH40: =rounddown(($AW40*VLOOKUP($B$13,$AU$177:$BE$185,10,false))+VLOOKUP(AV40,$AU$191:$AY$205,4,false),0) -> 4803 | BI40: =rounddown(($AW40*VLOOKUP($B$13,$AU$177:$BE$185,11,false))+VLOOKUP(AV40,$AU$191:$AY$205,4,false),0) -> 4803 | BJ40: =rounddown(($AX40*VLOOKUP($B$13,$AU$177:$AW$185,3,false))+VLOOKUP(AV40,$AU$191:$AY$205,5,false),0) -> 5047 | BK40: =rounddown(($AX40*VLOOKUP($B$13,$AU$177:$AX$185,4,false))+VLOOKUP(AV40,$AU$191:$AY$205,5,false),0) -> 5350 | BL40: =rounddown(($AX40*VLOOKUP($B$13,$AU$177:$AY$185,5,false))+VLOOKUP(AV40,$AU$191:$AY$205,5,false),0) -> 5523 | BM40: =rounddown(($AX40*VLOOKUP($B$13,$AU$177:$AZ$185,6,false))+VLOOKUP(AV40,$AU$191:$AY$205,5,false),0) -> 5609 | BN40: =rounddown(($AX40*VLOOKUP($B$13,$AU$177:$BE$185,7,false))+VLOOKUP(AV40,$AU$191:$AY$205,5,false),0) -> 5609 | BO40: =rounddown(($AX40*VLOOKUP($B$13,$AU$177:$BE$185,8,false))+VLOOKUP(AV40,$AU$191:$AY$205,5,false),0) -> 5609 | BP40: =rounddown(($AX40*VLOOKUP($B$13,$AU$177:$BE$185,9,false))+VLOOKUP(AV40,$AU$191:$AY$205,5,false),0) -> 5609 | BQ40: =rounddown(($AX40*VLOOKUP($B$13,$AU$177:$BE$185,10,false))+VLOOKUP(AV40,$AU$191:$AY$205,5,false),0) -> 5609 | BR40: =rounddown(($AX40*VLOOKUP($B$13,$AU$177:$BE$185,11,false))+VLOOKUP(AV40,$AU$191:$AY$205,5,false),0) -> 5609
E41: =IFERROR(__xludf.DUMMYFUNCTION("IFERROR( INDEX( IMPORTRANGE(""https://docs.google.com/spreadsheets/d/1tAaChe98Zh7vhMfGMK5Y4_ijmNb40fr519GtdZkkDUY/edit#gid=1369914306"", ""キャラ基礎数値!CS:CS""), MATCH(B11, IMPORTRANGE(""https://docs.google.com/spreadsheets/d/1tAaChe98Zh7vhMfGMK5Y4_i"&"jmNb40fr519GtdZkkDUY/edit#gid=1369914306"", ""キャラ基礎数値!C:C""), 0) ), ""該当なし"" ) "),"キラー攻撃(緑)") -> キラー攻撃(緑) | Q41: =IFERROR(__xludf.DUMMYFUNCTION("IFERROR( INDEX( IMPORTRANGE(""https://docs.google.com/spreadsheets/d/1tAaChe98Zh7vhMfGMK5Y4_ijmNb40fr519GtdZkkDUY/edit#gid=1369914306"", ""キャラ基礎数値!CY:CY""), MATCH(B11, IMPORTRANGE(""https://docs.google.com/spreadsheets/d/1tAaChe98Zh7vhMfGMK5Y4_i"&"jmNb40fr519GtdZkkDUY/edit#gid=1369914306"", ""キャラ基礎数値!C:C""), 0) ), ""該当なし"" ) "),"-") -> - | AC41: =IFERROR(__xludf.DUMMYFUNCTION("IFERROR( INDEX( IMPORTRANGE(""https://docs.google.com/spreadsheets/d/1tAaChe98Zh7vhMfGMK5Y4_ijmNb40fr519GtdZkkDUY/edit#gid=1369914306"", ""キャラ基礎数値!DE:DE""), MATCH(B11, IMPORTRANGE(""https://docs.google.com/spreadsheets/d/1tAaChe98Zh7vhMfGMK5Y4_i"&"jmNb40fr519GtdZkkDUY/edit#gid=1369914306"", ""キャラ基礎数値!C:C""), 0) ), ""該当なし"" ) "),"-") -> - | AU41: 30 | AV41: 2 | AW41: =Floor( $AW$9+($AW$171-$AW$9) * Pow( (AU41-1) / ($AU$171-1),$AU$189) ,1) -> 3705 | AX41: =Floor( $AX$9+($AX$171-$AX$9) * Pow( (AU41-1) / ($AU$171-1),$AU$189) ,1) -> 4327 | AY41: =VLOOKUP(AV41,$AU$191:$AY$205,4,FALSE)+AW41 -> 4038 | AZ41: =VLOOKUP(AV41,$AU$191:$AY$205,5,FALSE)+AX41 -> 4716 | BA41: =rounddown(($AW41*VLOOKUP($B$13,$AU$177:$AW$185,3,false))+VLOOKUP(AV41,$AU$191:$AY$205,4,false),0) -> 4482 | BB41: =rounddown(($AW41*VLOOKUP($B$13,$AU$177:$AX$185,4,false))+VLOOKUP(AV41,$AU$191:$AY$205,4,false),0) -> 4741 | BC41: =rounddown(($AW41*VLOOKUP($B$13,$AU$177:$AY$185,5,false))+VLOOKUP(AV41,$AU$191:$AY$205,4,false),0) -> 4890 | BD41: =rounddown(($AW41*VLOOKUP($B$13,$AU$177:$AZ$185,6,false))+VLOOKUP(AV41,$AU$191:$AY$205,4,false),0) -> 4964 | BE41: =rounddown(($AW41*VLOOKUP($B$13,$AU$177:$BE$185,7,false))+VLOOKUP(AV41,$AU$191:$AY$205,4,false),0) -> 4964 | BF41: =rounddown(($AW41*VLOOKUP($B$13,$AU$177:$BE$185,8,false))+VLOOKUP(AV41,$AU$191:$AY$205,4,false),0) -> 4964 | BG41: =rounddown(($AW41*VLOOKUP($B$13,$AU$177:$BE$185,9,false))+VLOOKUP(AV41,$AU$191:$AY$205,4,false),0) -> 4964 | BH41: =rounddown(($AW41*VLOOKUP($B$13,$AU$177:$BE$185,10,false))+VLOOKUP(AV41,$AU$191:$AY$205,4,false),0) -> 4964 | BI41: =rounddown(($AW41*VLOOKUP($B$13,$AU$177:$BE$185,11,false))+VLOOKUP(AV41,$AU$191:$AY$205,4,false),0) -> 4964 | BJ41: =rounddown(($AX41*VLOOKUP($B$13,$AU$177:$AW$185,3,false))+VLOOKUP(AV41,$AU$191:$AY$205,5,false),0) -> 5235 | BK41: =rounddown(($AX41*VLOOKUP($B$13,$AU$177:$AX$185,4,false))+VLOOKUP(AV41,$AU$191:$AY$205,5,false),0) -> 5538 | BL41: =rounddown(($AX41*VLOOKUP($B$13,$AU$177:$AY$185,5,false))+VLOOKUP(AV41,$AU$191:$AY$205,5,false),0) -> 5711 | BM41: =rounddown(($AX41*VLOOKUP($B$13,$AU$177:$AZ$185,6,false))+VLOOKUP(AV41,$AU$191:$AY$205,5,false),0) -> 5797 | BN41: =rounddown(($AX41*VLOOKUP($B$13,$AU$177:$BE$185,7,false))+VLOOKUP(AV41,$AU$191:$AY$205,5,false),0) -> 5797 | BO41: =rounddown(($AX41*VLOOKUP($B$13,$AU$177:$BE$185,8,false))+VLOOKUP(AV41,$AU$191:$AY$205,5,false),0) -> 5797 | BP41: =rounddown(($AX41*VLOOKUP($B$13,$AU$177:$BE$185,9,false))+VLOOKUP(AV41,$AU$191:$AY$205,5,false),0) -> 5797 | BQ41: =rounddown(($AX41*VLOOKUP($B$13,$AU$177:$BE$185,10,false))+VLOOKUP(AV41,$AU$191:$AY$205,5,false),0) -> 5797 | BR41: =rounddown(($AX41*VLOOKUP($B$13,$AU$177:$BE$185,11,false))+VLOOKUP(AV41,$AU$191:$AY$205,5,false),0) -> 5797
E42: 攻撃・特殊系効果 | K42: バフ・デバフ系効果 | Q42: 攻撃・特殊系効果 | W42: バフ・デバフ系効果 | AC42: 攻撃・特殊系効果 | AI42: バフ・デバフ系効果 | AU42: 31 | AV42: 2 | AW42: =Floor( $AW$9+($AW$171-$AW$9) * Pow( (AU42-1) / ($AU$171-1),$AU$189) ,1) -> 3790 | AX42: =Floor( $AX$9+($AX$171-$AX$9) * Pow( (AU42-1) / ($AU$171-1),$AU$189) ,1) -> 4426 | AY42: =VLOOKUP(AV42,$AU$191:$AY$205,4,FALSE)+AW42 -> 4123 | AZ42: =VLOOKUP(AV42,$AU$191:$AY$205,5,FALSE)+AX42 -> 4815 | BA42: =rounddown(($AW42*VLOOKUP($B$13,$AU$177:$AW$185,3,false))+VLOOKUP(AV42,$AU$191:$AY$205,4,false),0) -> 4577 | BB42: =rounddown(($AW42*VLOOKUP($B$13,$AU$177:$AX$185,4,false))+VLOOKUP(AV42,$AU$191:$AY$205,4,false),0) -> 4843 | BC42: =rounddown(($AW42*VLOOKUP($B$13,$AU$177:$AY$185,5,false))+VLOOKUP(AV42,$AU$191:$AY$205,4,false),0) -> 4994 | BD42: =rounddown(($AW42*VLOOKUP($B$13,$AU$177:$AZ$185,6,false))+VLOOKUP(AV42,$AU$191:$AY$205,4,false),0) -> 5070 | BE42: =rounddown(($AW42*VLOOKUP($B$13,$AU$177:$BE$185,7,false))+VLOOKUP(AV42,$AU$191:$AY$205,4,false),0) -> 5070 | BF42: =rounddown(($AW42*VLOOKUP($B$13,$AU$177:$BE$185,8,false))+VLOOKUP(AV42,$AU$191:$AY$205,4,false),0) -> 5070 | BG42: =rounddown(($AW42*VLOOKUP($B$13,$AU$177:$BE$185,9,false))+VLOOKUP(AV42,$AU$191:$AY$205,4,false),0) -> 5070 | BH42: =rounddown(($AW42*VLOOKUP($B$13,$AU$177:$BE$185,10,false))+VLOOKUP(AV42,$AU$191:$AY$205,4,false),0) -> 5070 | BI42: =rounddown(($AW42*VLOOKUP($B$13,$AU$177:$BE$185,11,false))+VLOOKUP(AV42,$AU$191:$AY$205,4,false),0) -> 5070 | BJ42: =rounddown(($AX42*VLOOKUP($B$13,$AU$177:$AW$185,3,false))+VLOOKUP(AV42,$AU$191:$AY$205,5,false),0) -> 5346 | BK42: =rounddown(($AX42*VLOOKUP($B$13,$AU$177:$AX$185,4,false))+VLOOKUP(AV42,$AU$191:$AY$205,5,false),0) -> 5655 | BL42: =rounddown(($AX42*VLOOKUP($B$13,$AU$177:$AY$185,5,false))+VLOOKUP(AV42,$AU$191:$AY$205,5,false),0) -> 5832 | BM42: =rounddown(($AX42*VLOOKUP($B$13,$AU$177:$AZ$185,6,false))+VLOOKUP(AV42,$AU$191:$AY$205,5,false),0) -> 5921 | BN42: =rounddown(($AX42*VLOOKUP($B$13,$AU$177:$BE$185,7,false))+VLOOKUP(AV42,$AU$191:$AY$205,5,false),0) -> 5921 | BO42: =rounddown(($AX42*VLOOKUP($B$13,$AU$177:$BE$185,8,false))+VLOOKUP(AV42,$AU$191:$AY$205,5,false),0) -> 5921 | BP42: =rounddown(($AX42*VLOOKUP($B$13,$AU$177:$BE$185,9,false))+VLOOKUP(AV42,$AU$191:$AY$205,5,false),0) -> 5921 | BQ42: =rounddown(($AX42*VLOOKUP($B$13,$AU$177:$BE$185,10,false))+VLOOKUP(AV42,$AU$191:$AY$205,5,false),0) -> 5921 | BR42: =rounddown(($AX42*VLOOKUP($B$13,$AU$177:$BE$185,11,false))+VLOOKUP(AV42,$AU$191:$AY$205,5,false),0) -> 5921
B43: グレード | E43: 効果値 | G43: 効果時間 | I43: 発動確率 | K43: 効果値 | M43: 効果時間 | O43: 発動確率 | Q43: 効果値 | S43: 効果時間 | U43: 発動確率 | W43: 効果値 | Y43: 効果時間 | AA43: 発動確率 | AC43: 効果値 | AE43: 効果時間 | AG43: 発動確率 | AI43: 効果値 | AK43: 効果時間 | AM43: 発動確率 | AU43: 32 | AV43: 2 | AW43: =Floor( $AW$9+($AW$171-$AW$9) * Pow( (AU43-1) / ($AU$171-1),$AU$189) ,1) -> 3874 | AX43: =Floor( $AX$9+($AX$171-$AX$9) * Pow( (AU43-1) / ($AU$171-1),$AU$189) ,1) -> 4524 | AY43: =VLOOKUP(AV43,$AU$191:$AY$205,4,FALSE)+AW43 -> 4207 | AZ43: =VLOOKUP(AV43,$AU$191:$AY$205,5,FALSE)+AX43 -> 4913 | BA43: =rounddown(($AW43*VLOOKUP($B$13,$AU$177:$AW$185,3,false))+VLOOKUP(AV43,$AU$191:$AY$205,4,false),0) -> 4671 | BB43: =rounddown(($AW43*VLOOKUP($B$13,$AU$177:$AX$185,4,false))+VLOOKUP(AV43,$AU$191:$AY$205,4,false),0) -> 4943 | BC43: =rounddown(($AW43*VLOOKUP($B$13,$AU$177:$AY$185,5,false))+VLOOKUP(AV43,$AU$191:$AY$205,4,false),0) -> 5098 | BD43: =rounddown(($AW43*VLOOKUP($B$13,$AU$177:$AZ$185,6,false))+VLOOKUP(AV43,$AU$191:$AY$205,4,false),0) -> 5175 | BE43: =rounddown(($AW43*VLOOKUP($B$13,$AU$177:$BE$185,7,false))+VLOOKUP(AV43,$AU$191:$AY$205,4,false),0) -> 5175 | BF43: =rounddown(($AW43*VLOOKUP($B$13,$AU$177:$BE$185,8,false))+VLOOKUP(AV43,$AU$191:$AY$205,4,false),0) -> 5175 | BG43: =rounddown(($AW43*VLOOKUP($B$13,$AU$177:$BE$185,9,false))+VLOOKUP(AV43,$AU$191:$AY$205,4,false),0) -> 5175 | BH43: =rounddown(($AW43*VLOOKUP($B$13,$AU$177:$BE$185,10,false))+VLOOKUP(AV43,$AU$191:$AY$205,4,false),0) -> 5175 | BI43: =rounddown(($AW43*VLOOKUP($B$13,$AU$177:$BE$185,11,false))+VLOOKUP(AV43,$AU$191:$AY$205,4,false),0) -> 5175 | BJ43: =rounddown(($AX43*VLOOKUP($B$13,$AU$177:$AW$185,3,false))+VLOOKUP(AV43,$AU$191:$AY$205,5,false),0) -> 5455 | BK43: =rounddown(($AX43*VLOOKUP($B$13,$AU$177:$AX$185,4,false))+VLOOKUP(AV43,$AU$191:$AY$205,5,false),0) -> 5772 | BL43: =rounddown(($AX43*VLOOKUP($B$13,$AU$177:$AY$185,5,false))+VLOOKUP(AV43,$AU$191:$AY$205,5,false),0) -> 5953 | BM43: =rounddown(($AX43*VLOOKUP($B$13,$AU$177:$AZ$185,6,false))+VLOOKUP(AV43,$AU$191:$AY$205,5,false),0) -> 6044 | BN43: =rounddown(($AX43*VLOOKUP($B$13,$AU$177:$BE$185,7,false))+VLOOKUP(AV43,$AU$191:$AY$205,5,false),0) -> 6044 | BO43: =rounddown(($AX43*VLOOKUP($B$13,$AU$177:$BE$185,8,false))+VLOOKUP(AV43,$AU$191:$AY$205,5,false),0) -> 6044 | BP43: =rounddown(($AX43*VLOOKUP($B$13,$AU$177:$BE$185,9,false))+VLOOKUP(AV43,$AU$191:$AY$205,5,false),0) -> 6044 | BQ43: =rounddown(($AX43*VLOOKUP($B$13,$AU$177:$BE$185,10,false))+VLOOKUP(AV43,$AU$191:$AY$205,5,false),0) -> 6044 | BR43: =rounddown(($AX43*VLOOKUP($B$13,$AU$177:$BE$185,11,false))+VLOOKUP(AV43,$AU$191:$AY$205,5,false),0) -> 6044
